Workbook
Name _____I2: {"PVGraph2",#N/A,FALSE,"PV Data"}
Name _____I2: {"PVGraph2",#N/A,FALSE,"PV Data"}
Name _____I2: {"PVGraph2",#N/A,FALSE,"PV Data"}
Name _____I3: {"PVGraph2",#N/A,FALSE,"PV Data"}
Name _____I3: {"PVGraph2",#N/A,FALSE,"PV Data"}
Name _____I3: {"PVGraph2",#N/A,FALSE,"PV Data"}
Name _____w1: {"PVGraph2",#N/A,FALSE,"PV Data"}
Name _____w1: {"PVGraph2",#N/A,FALSE,"PV Data"}
Name _____w1: {"PVGraph2",#N/A,FALSE,"PV Data"}
Name _____w2: {"PVGraph2",#N/A,FALSE,"PV Data"}
Name _____w2: {"PVGraph2",#N/A,FALSE,"PV Data"}
Name _____w2: {"PVGraph2",#N/A,FALSE,"PV Data"}
Name _____w3: {"PVGraph2",#N/A,FALSE,"PV Data"}
Name _____w3: {"PVGraph2",#N/A,FALSE,"PV Data"}
Name _____w3: {"PVGraph2",#N/A,FALSE,"PV Data"}
Name _____y2: {"PVGraph2",#N/A,FALSE,"PV Data"}
Name _____y2: {"PVGraph2",#N/A,FALSE,"PV Data"}
Name _____y2: {"PVGraph2",#N/A,FALSE,"PV Data"}
Name ___I2: {"PVGraph2",#N/A,FALSE,"PV Data"}
Name ___I2: {"PVGraph2",#N/A,FALSE,"PV Data"}
Name ___I2: {"PVGraph2",#N/A,FALSE,"PV Data"}
Name ___I3: {"PVGraph2",#N/A,FALSE,"PV Data"}
Name ___I3: {"PVGraph2",#N/A,FALSE,"PV Data"}
Name ___I3: {"PVGraph2",#N/A,FALSE,"PV Data"}
Name ___s1: #REF!
Name ___s2: #REF!
Name ___s3: #REF!
Name ___s4: #REF!
Name ___s5: #REF!
Name ___s6: #REF!
Name ___w1: {"PVGraph2",#N/A,FALSE,"PV Data"}
Name ___w1: {"PVGraph2",#N/A,FALSE,"PV Data"}
Name ___w1: {"PVGraph2",#N/A,FALSE,"PV Data"}
Name ___w2: {"PVGraph2",#N/A,FALSE,"PV Data"}
Name ___w2: {"PVGraph2",#N/A,FALSE,"PV Data"}
Name ___w2: {"PVGraph2",#N/A,FALSE,"PV Data"}
Name ___w3: {"PVGraph2",#N/A,FALSE,"PV Data"}
Name ___w3: {"PVGraph2",#N/A,FALSE,"PV Data"}
Name ___w3: {"PVGraph2",#N/A,FALSE,"PV Data"}
Name ___y2: {"PVGraph2",#N/A,FALSE,"PV Data"}
Name ___y2: {"PVGraph2",#N/A,FALSE,"PV Data"}
Name ___y2: {"PVGraph2",#N/A,FALSE,"PV Data"}
Name __123Graph_A: #REF!
Name __123gRAPH_achart: #REF!
Name __123Graph_AChart1: #REF!
Name __123Graph_ACurrent: #REF!
Name __123Graph_AGRPH_EXPIRE: #REF!
Name __123Graph_AHMCISALES: #REF!
Name __123Graph_APRINCIPAL: #REF!
Name __123Graph_B: #REF!
Name __123Graph_BChart1: #REF!
Name __123Graph_BCurrent: #REF!
Name __123Graph_BFUEL: #REF!
Name __123Graph_BHMCISALES: #REF!
Name __123Graph_C: #REF!
Name __123Graph_CChart1: #REF!
Name __123Graph_CCurrent: #REF!
Name __123Graph_D: #REF!
Name __123Graph_DChart1: #REF!
Name __123Graph_DCurrent: #REF!

Sheet M&A Reporting Slide - Old
A1: Pro Forma Estimates | B1: Leads | C1: Events | D1: Total $ / Event | E1: Catering Attach. | F1: Beverage Attach. | G1: Non-Ancillary | H1: F&B | I1: Other Ancillary | J1: Total Revenue | K1: F&B | L1: Total COGS | M1: Staffing / Labor | N1: Other Opex | O1: EBITDA
A2: Firefly Lane | Q2: rev check | R2: EBITDA Check
A3: PF Y1 Estimate | B3: ='Adj. P&L'!$CD$11 -> 1506 | C3: ='Adj. P&L'!CD35+'Adj. P&L'!CD40 -> 190 | D3: =J3/C3 -> 10.333762 | E3: =('Revenue Analysis - Total'!G44+'Revenue Analysis - Total'!G30)/('Revenue Analysis - Total'!G43+'Revenue Analysis - Total'!G29) -> 0.3 | F3: =('Revenue Analysis - Total'!G31+'Revenue Analysis - Total'!G45)/('Revenue Analysis - Total'!G43+'Revenue Analysis - Total'!G29) -> 0 | G3: =SUM('Adj. P&L'!CD43:CD44,'Adj. P&L'!CD50:CD53) -> 1200.1098 | H3: ='Adj. P&L'!CD46+'Adj. P&L'!CD117 -> 241.85 | I3: =SUM('Adj. P&L'!CD47:CD49,'Adj. P&L'!CD118) -> 521.45487 | J3: =SUM(G3:I3) -> 1963.4147 | K3: =-('Adj. P&L'!CD58+'Adj. P&L'!CD60) -> 161.50825 | L3: =-('Adj. P&L'!CD65) -> 646.64875 | M3: =-'Adj. P&L'!CD80 -> 419.07763 | N3: =-'Adj. P&L'!CD99 -> 304.64108 | O3: =J3-SUM(L3:N3) -> 593.04724 | Q3: ='Adj. P&L'!CD55-J3 -> 0 | R3: ='Adj. P&L'!CD101-O3 -> 0
A4: PF Y2 Estimate | B4: ='Adj. P&L'!$CE$11 -> 1581 | C4: ='Adj. P&L'!CE35+'Adj. P&L'!CE40 -> 200 | D4: =J4/C4 -> 13.355365 | E4: =('Revenue Analysis - Total'!H44+'Revenue Analysis - Total'!H30)/('Revenue Analysis - Total'!H43+'Revenue Analysis - Total'!H29) -> 0.659375 | F4: =('Revenue Analysis - Total'!H31+'Revenue Analysis - Total'!H45)/('Revenue Analysis - Total'!H43+'Revenue Analysis - Total'!H29) -> 0.203125 | G4: =SUM('Adj. P&L'!CE43:CE44,'Adj. P&L'!CE50:CE53) -> 1335.1458 | H4: ='Adj. P&L'!CE46+'Adj. P&L'!CE117 -> 491.10833 | I4: =SUM('Adj. P&L'!CE47:CE49,'Adj. P&L'!CE118) -> 844.8189 | J4: =SUM(G4:I4) -> 2671.073 | K4: =-('Adj. P&L'!CE58+'Adj. P&L'!CE60) -> 389.58441 | L4: =-('Adj. P&L'!CE65) -> 1029.6084 | M4: =-'Adj. P&L'!CE80 -> 456.73697 | N4: =-'Adj. P&L'!CE99 -> 376.89088 | O4: =J4-SUM(L4:N4) -> 807.83677 | Q4: ='Adj. P&L'!CE55-J4 -> 0 | R4: ='Adj. P&L'!CE101-O4 -> 0
A5: PF Y3 Estimate | B5: ='Adj. P&L'!$CF$11 -> 1660 | C5: ='Adj. P&L'!CF35+'Adj. P&L'!CF40 -> 210 | D5: =J5/C5 -> 18.092088 | E5: =('Revenue Analysis - Total'!I44+'Revenue Analysis - Total'!I30)/('Revenue Analysis - Total'!I43+'Revenue Analysis - Total'!I29) -> 1 | F5: =('Revenue Analysis - Total'!I31+'Revenue Analysis - Total'!I45)/('Revenue Analysis - Total'!I43+'Revenue Analysis - Total'!I29) -> 1 | G5: =SUM('Adj. P&L'!CF43:CF44,'Adj. P&L'!CF50:CF53) -> 1399.0112 | H5: ='Adj. P&L'!CF46+'Adj. P&L'!CF117 -> 767.83333 | I5: =SUM('Adj. P&L'!CF47:CF49,'Adj. P&L'!CF118) -> 1632.4939 | J5: =SUM(G5:I5) -> 3799.3385 | K5: =-('Adj. P&L'!CF58+'Adj. P&L'!CF60) -> 667.3527 | L5: =-('Adj. P&L'!CF65) -> 1592.4943 | M5: =-'Adj. P&L'!CF80 -> 497.67151 | N5: =-'Adj. P&L'!CF99 -> 488.89979 | O5: =J5-SUM(L5:N5) -> 1220.2729 | Q5: ='Adj. P&L'!CF55-J5 -> 0 | R5: ='Adj. P&L'!CF101-O5 -> 0

Sheet M&A Reporting - New
D1: 46203 | E1: 46234 | F1: 46265 | G1: 46295 | H1: 46326 | I1: 46356 | J1: 46387 | K1: 46418 | L1: 46446 | M1: 46477 | N1: 46507 | O1: 46538 | Q1: Y1 | R1: Y2 | S1: Y3 | U1: 2026 | V1: 2027 | W1: 2028
C3: =Checks!$C$3 -> Firefly Lane
C4: PF P&L Analysis
D6: Year 1 Pro Forma | Q6: Annual | U6: Annual
D7: 46203 | E7: =EOMONTH(D7,1) -> 46234 | F7: =EOMONTH(E7,1) -> 46265 | G7: =EOMONTH(F7,1) -> 46295 | H7: =EOMONTH(G7,1) -> 46326 | I7: =EOMONTH(H7,1) -> 46356 | J7: =EOMONTH(I7,1) -> 46387 | K7: =EOMONTH(J7,1) -> 46418 | L7: =EOMONTH(K7,1) -> 46446 | ... O7: =EOMONTH(N7,1) -> 46538 | Q7: Y1 | R7: Y2 | S7: Y3 | U7: 2026 | V7: 2027 | W7: 2028
C9: Firefly Lane
A10: Contracts | C10: Contracts | D10: {=INDEX('Adj. P&L'!$D$11:$CX$119,MATCH($A10,'Adj. P&L'!$C$11:$C$119,0),MATCH(D$1,'Adj. P&L'!$D$9:$CX$9,0))} -> 15 | E10: {=INDEX('Adj. P&L'!$D$11:$CX$119,MATCH($A10,'Adj. P&L'!$C$11:$C$119,0),MATCH(E$1,'Adj. P&L'!$D$9:$CX$9,0))} -> 24 | F10: {=INDEX('Adj. P&L'!$D$11:$CX$119,MATCH($A10,'Adj. P&L'!$C$11:$C$119,0),MATCH(F$1,'Adj. P&L'!$D$9:$CX$9,0))} -> 21 | G10: {=INDEX('Adj. P&L'!$D$11:$CX$119,MATCH($A10,'Adj. P&L'!$C$11:$C$119,0),MATCH(G$1,'Adj. P&L'!$D$9:$CX$9,0))} -> 16 | H10: {=INDEX('Adj. P&L'!$D$11:$CX$119,MATCH($A10,'Adj. P&L'!$C$11:$C$119,0),MATCH(H$1,'Adj. P&L'!$D$9:$CX$9,0))} -> 12 | I10: {=INDEX('Adj. P&L'!$D$11:$CX$119,MATCH($A10,'Adj. P&L'!$C$11:$C$119,0),MATCH(I$1,'Adj. P&L'!$D$9:$CX$9,0))} -> 16 | J10: {=INDEX('Adj. P&L'!$D$11:$CX$119,MATCH($A10,'Adj. P&L'!$C$11:$C$119,0),MATCH(J$1,'Adj. P&L'!$D$9:$CX$9,0))} -> 11 | K10: {=INDEX('Adj. P&L'!$D$11:$CX$119,MATCH($A10,'Adj. P&L'!$C$11:$C$119,0),MATCH(K$1,'Adj. P&L'!$D$9:$CX$9,0))} -> 21 | ... O10: {=INDEX('Adj. P&L'!$D$11:$CX$119,MATCH($A10,'Adj. P&L'!$C$11:$C$119,0),MATCH(O$1,'Adj. P&L'!$D$9:$CX$9,0))} -> 13 | Q10: {=INDEX('Adj. P&L'!$D$11:$CX$119,MATCH($A10,'Adj. P&L'!$C$11:$C$119,0),MATCH(Q$1,'Adj. P&L'!$D$9:$CX$9,0))} -> 190 | R10: {=INDEX('Adj. P&L'!$D$11:$CX$119,MATCH($A10,'Adj. P&L'!$C$11:$C$119,0),MATCH(R$1,'Adj. P&L'!$D$9:$CX$9,0))} -> 200 | S10: {=INDEX('Adj. P&L'!$D$11:$CX$119,MATCH($A10,'Adj. P&L'!$C$11:$C$119,0),MATCH(S$1,'Adj. P&L'!$D$9:$CX$9,0))} -> 210 | U10: {=INDEX('Adj. P&L'!$D$11:$CX$119,MATCH($A10,'Adj. P&L'!$C$11:$C$119,0),MATCH(U$1,'Adj. P&L'!$D$9:$CX$9,0))} -> 163 | V10: {=INDEX('Adj. P&L'!$D$11:$CX$119,MATCH($A10,'Adj. P&L'!$C$11:$C$119,0),MATCH(V$1,'Adj. P&L'!$D$9:$CX$9,0))} -> 195 | W10: {=INDEX('Adj. P&L'!$D$11:$CX$119,MATCH($A10,'Adj. P&L'!$C$11:$C$119,0),MATCH(W$1,'Adj. P&L'!$D$9:$CX$9,0))} -> 206
A11: Events - B&C | C11: Events - B&C | D11: {=INDEX('Adj. P&L'!$D$11:$CX$119,MATCH($A11,'Adj. P&L'!$C$11:$C$119,0),MATCH(D$1,'Adj. P&L'!$D$9:$CX$9,0))} -> 12 | E11: {=INDEX('Adj. P&L'!$D$11:$CX$119,MATCH($A11,'Adj. P&L'!$C$11:$C$119,0),MATCH(E$1,'Adj. P&L'!$D$9:$CX$9,0))} -> 10 | F11: {=INDEX('Adj. P&L'!$D$11:$CX$119,MATCH($A11,'Adj. P&L'!$C$11:$C$119,0),MATCH(F$1,'Adj. P&L'!$D$9:$CX$9,0))} -> 15 | G11: {=INDEX('Adj. P&L'!$D$11:$CX$119,MATCH($A11,'Adj. P&L'!$C$11:$C$119,0),MATCH(G$1,'Adj. P&L'!$D$9:$CX$9,0))} -> 19 | H11: {=INDEX('Adj. P&L'!$D$11:$CX$119,MATCH($A11,'Adj. P&L'!$C$11:$C$119,0),MATCH(H$1,'Adj. P&L'!$D$9:$CX$9,0))} -> 24 | I11: {=INDEX('Adj. P&L'!$D$11:$CX$119,MATCH($A11,'Adj. P&L'!$C$11:$C$119,0),MATCH(I$1,'Adj. P&L'!$D$9:$CX$9,0))} -> 12 | J11: {=INDEX('Adj. P&L'!$D$11:$CX$119,MATCH($A11,'Adj. P&L'!$C$11:$C$119,0),MATCH(J$1,'Adj. P&L'!$D$9:$CX$9,0))} -> 5 | K11: {=INDEX('Adj. P&L'!$D$11:$CX$119,MATCH($A11,'Adj. P&L'!$C$11:$C$119,0),MATCH(K$1,'Adj. P&L'!$D$9:$CX$9,0))} -> 0 | ... O11: {=INDEX('Adj. P&L'!$D$11:$CX$119,MATCH($A11,'Adj. P&L'!$C$11:$C$119,0),MATCH(O$1,'Adj. P&L'!$D$9:$CX$9,0))} -> 27 | Q11: {=INDEX('Adj. P&L'!$D$11:$CX$119,MATCH($A11,'Adj. P&L'!$C$11:$C$119,0),MATCH(Q$1,'Adj. P&L'!$D$9:$CX$9,0))} -> 150 | R11: {=INDEX('Adj. P&L'!$D$11:$CX$119,MATCH($A11,'Adj. P&L'!$C$11:$C$119,0),MATCH(R$1,'Adj. P&L'!$D$9:$CX$9,0))} -> 160 | S11: {=INDEX('Adj. P&L'!$D$11:$CX$119,MATCH($A11,'Adj. P&L'!$C$11:$C$119,0),MATCH(S$1,'Adj. P&L'!$D$9:$CX$9,0))} -> 170 | U11: {=INDEX('Adj. P&L'!$D$11:$CX$119,MATCH($A11,'Adj. P&L'!$C$11:$C$119,0),MATCH(U$1,'Adj. P&L'!$D$9:$CX$9,0))} -> 140 | V11: {=INDEX('Adj. P&L'!$D$11:$CX$119,MATCH($A11,'Adj. P&L'!$C$11:$C$119,0),MATCH(V$1,'Adj. P&L'!$D$9:$CX$9,0))} -> 162 | W11: {=INDEX('Adj. P&L'!$D$11:$CX$119,MATCH($A11,'Adj. P&L'!$C$11:$C$119,0),MATCH(W$1,'Adj. P&L'!$D$9:$CX$9,0))} -> 166
A12: Elopements | C12: Elopements | D12: {=INDEX('Adj. P&L'!$D$11:$CX$119,MATCH($A12,'Adj. P&L'!$C$11:$C$119,0),MATCH(D$1,'Adj. P&L'!$D$9:$CX$9,0))} -> 4 | E12: {=INDEX('Adj. P&L'!$D$11:$CX$119,MATCH($A12,'Adj. P&L'!$C$11:$C$119,0),MATCH(E$1,'Adj. P&L'!$D$9:$CX$9,0))} -> 0 | F12: {=INDEX('Adj. P&L'!$D$11:$CX$119,MATCH($A12,'Adj. P&L'!$C$11:$C$119,0),MATCH(F$1,'Adj. P&L'!$D$9:$CX$9,0))} -> 2 | G12: {=INDEX('Adj. P&L'!$D$11:$CX$119,MATCH($A12,'Adj. P&L'!$C$11:$C$119,0),MATCH(G$1,'Adj. P&L'!$D$9:$CX$9,0))} -> 5 | H12: {=INDEX('Adj. P&L'!$D$11:$CX$119,MATCH($A12,'Adj. P&L'!$C$11:$C$119,0),MATCH(H$1,'Adj. P&L'!$D$9:$CX$9,0))} -> 6 | I12: {=INDEX('Adj. P&L'!$D$11:$CX$119,MATCH($A12,'Adj. P&L'!$C$11:$C$119,0),MATCH(I$1,'Adj. P&L'!$D$9:$CX$9,0))} -> 1 | J12: {=INDEX('Adj. P&L'!$D$11:$CX$119,MATCH($A12,'Adj. P&L'!$C$11:$C$119,0),MATCH(J$1,'Adj. P&L'!$D$9:$CX$9,0))} -> 0 | K12: {=INDEX('Adj. P&L'!$D$11:$CX$119,MATCH($A12,'Adj. P&L'!$C$11:$C$119,0),MATCH(K$1,'Adj. P&L'!$D$9:$CX$9,0))} -> 0 | ... O12: {=INDEX('Adj. P&L'!$D$11:$CX$119,MATCH($A12,'Adj. P&L'!$C$11:$C$119,0),MATCH(O$1,'Adj. P&L'!$D$9:$CX$9,0))} -> 12 | Q12: {=INDEX('Adj. P&L'!$D$11:$CX$119,MATCH($A12,'Adj. P&L'!$C$11:$C$119,0),MATCH(Q$1,'Adj. P&L'!$D$9:$CX$9,0))} -> 40 | R12: {=INDEX('Adj. P&L'!$D$11:$CX$119,MATCH($A12,'Adj. P&L'!$C$11:$C$119,0),MATCH(R$1,'Adj. P&L'!$D$9:$CX$9,0))} -> 40 | S12: {=INDEX('Adj. P&L'!$D$11:$CX$119,MATCH($A12,'Adj. P&L'!$C$11:$C$119,0),MATCH(S$1,'Adj. P&L'!$D$9:$CX$9,0))} -> 40 | U12: {=INDEX('Adj. P&L'!$D$11:$CX$119,MATCH($A12,'Adj. P&L'!$C$11:$C$119,0),MATCH(U$1,'Adj. P&L'!$D$9:$CX$9,0))} -> 27 | V12: {=INDEX('Adj. P&L'!$D$11:$CX$119,MATCH($A12,'Adj. P&L'!$C$11:$C$119,0),MATCH(V$1,'Adj. P&L'!$D$9:$CX$9,0))} -> 48 | W12: {=INDEX('Adj. P&L'!$D$11:$CX$119,MATCH($A12,'Adj. P&L'!$C$11:$C$119,0),MATCH(W$1,'Adj. P&L'!$D$9:$CX$9,0))} -> 40
C13: Events | D13: =SUM(D11:D12) -> 16 | E13: =SUM(E11:E12) -> 10 | F13: =SUM(F11:F12) -> 17 | G13: =SUM(G11:G12) -> 24 | H13: =SUM(H11:H12) -> 30 | I13: =SUM(I11:I12) -> 13 | J13: =SUM(J11:J12) -> 5 | K13: =SUM(K11:K12) -> 0 | ... O13: =SUM(O11:O12) -> 39 | Q13: =SUM(Q11:Q12) -> 190 | R13: =SUM(R11:R12) -> 200 | S13: =SUM(S11:S12) -> 210 | U13: =SUM(U11:U12) -> 167 | V13: =SUM(V11:V12) -> 210 | W13: =SUM(W11:W12) -> 206
A14: Total Revenue | C14: Revenue | D14: {=INDEX('Adj. P&L'!$D$11:$CX$119,MATCH($A14,'Adj. P&L'!$C$11:$C$119,0),MATCH(D$1,'Adj. P&L'!$D$9:$CX$9,0))} -> 170.66258 | E14: {=INDEX('Adj. P&L'!$D$11:$CX$119,MATCH($A14,'Adj. P&L'!$C$11:$C$119,0),MATCH(E$1,'Adj. P&L'!$D$9:$CX$9,0))} -> 115.06465 | F14: {=INDEX('Adj. P&L'!$D$11:$CX$119,MATCH($A14,'Adj. P&L'!$C$11:$C$119,0),MATCH(F$1,'Adj. P&L'!$D$9:$CX$9,0))} -> 238.78947 | G14: {=INDEX('Adj. P&L'!$D$11:$CX$119,MATCH($A14,'Adj. P&L'!$C$11:$C$119,0),MATCH(G$1,'Adj. P&L'!$D$9:$CX$9,0))} -> 256.80033 | H14: {=INDEX('Adj. P&L'!$D$11:$CX$119,MATCH($A14,'Adj. P&L'!$C$11:$C$119,0),MATCH(H$1,'Adj. P&L'!$D$9:$CX$9,0))} -> 298.71015 | I14: {=INDEX('Adj. P&L'!$D$11:$CX$119,MATCH($A14,'Adj. P&L'!$C$11:$C$119,0),MATCH(I$1,'Adj. P&L'!$D$9:$CX$9,0))} -> 154.89258 | J14: {=INDEX('Adj. P&L'!$D$11:$CX$119,MATCH($A14,'Adj. P&L'!$C$11:$C$119,0),MATCH(J$1,'Adj. P&L'!$D$9:$CX$9,0))} -> 54.519823 | K14: {=INDEX('Adj. P&L'!$D$11:$CX$119,MATCH($A14,'Adj. P&L'!$C$11:$C$119,0),MATCH(K$1,'Adj. P&L'!$D$9:$CX$9,0))} -> 0 | ... O14: {=INDEX('Adj. P&L'!$D$11:$CX$119,MATCH($A14,'Adj. P&L'!$C$11:$C$119,0),MATCH(O$1,'Adj. P&L'!$D$9:$CX$9,0))} -> 376.71205 | Q14: {=INDEX('Adj. P&L'!$D$11:$CX$119,MATCH($A14,'Adj. P&L'!$C$11:$C$119,0),MATCH(Q$1,'Adj. P&L'!$D$9:$CX$9,0))} -> 1963.4147 | R14: {=INDEX('Adj. P&L'!$D$11:$CX$119,MATCH($A14,'Adj. P&L'!$C$11:$C$119,0),MATCH(R$1,'Adj. P&L'!$D$9:$CX$9,0))} -> 2671.073 | S14: {=INDEX('Adj. P&L'!$D$11:$CX$119,MATCH($A14,'Adj. P&L'!$C$11:$C$119,0),MATCH(S$1,'Adj. P&L'!$D$9:$CX$9,0))} -> 3799.3385 | U14: {=INDEX('Adj. P&L'!$D$11:$CX$119,MATCH($A14,'Adj. P&L'!$C$11:$C$119,0),MATCH(U$1,'Adj. P&L'!$D$9:$CX$9,0))} -> 1689.6162 | V14: {=INDEX('Adj. P&L'!$D$11:$CX$119,MATCH($A14,'Adj. P&L'!$C$11:$C$119,0),MATCH(V$1,'Adj. P&L'!$D$9:$CX$9,0))} -> 2447.7819 | W14: {=INDEX('Adj. P&L'!$D$11:$CX$119,MATCH($A14,'Adj. P&L'!$C$11:$C$119,0),MATCH(W$1,'Adj. P&L'!$D$9:$CX$9,0))} -> 3467.3041
A15: Adjusted EBITDAR | C15: EBITDAR | D15: {=INDEX('Adj. P&L'!$D$11:$CX$119,MATCH($A15,'Adj. P&L'!$C$11:$C$119,0),MATCH(D$1,'Adj. P&L'!$D$9:$CX$9,0))} -> 48.268789 | E15: {=INDEX('Adj. P&L'!$D$11:$CX$119,MATCH($A15,'Adj. P&L'!$C$11:$C$119,0),MATCH(E$1,'Adj. P&L'!$D$9:$CX$9,0))} -> 23.790508 | F15: {=INDEX('Adj. P&L'!$D$11:$CX$119,MATCH($A15,'Adj. P&L'!$C$11:$C$119,0),MATCH(F$1,'Adj. P&L'!$D$9:$CX$9,0))} -> 71.364649 | G15: {=INDEX('Adj. P&L'!$D$11:$CX$119,MATCH($A15,'Adj. P&L'!$C$11:$C$119,0),MATCH(G$1,'Adj. P&L'!$D$9:$CX$9,0))} -> 100.16013 | H15: {=INDEX('Adj. P&L'!$D$11:$CX$119,MATCH($A15,'Adj. P&L'!$C$11:$C$119,0),MATCH(H$1,'Adj. P&L'!$D$9:$CX$9,0))} -> 132.74032 | I15: {=INDEX('Adj. P&L'!$D$11:$CX$119,MATCH($A15,'Adj. P&L'!$C$11:$C$119,0),MATCH(I$1,'Adj. P&L'!$D$9:$CX$9,0))} -> 42.60307 | J15: {=INDEX('Adj. P&L'!$D$11:$CX$119,MATCH($A15,'Adj. P&L'!$C$11:$C$119,0),MATCH(J$1,'Adj. P&L'!$D$9:$CX$9,0))} -> -10.321925 | K15: {=INDEX('Adj. P&L'!$D$11:$CX$119,MATCH($A15,'Adj. P&L'!$C$11:$C$119,0),MATCH(K$1,'Adj. P&L'!$D$9:$CX$9,0))} -> -44.904764 | ... O15: {=INDEX('Adj. P&L'!$D$11:$CX$119,MATCH($A15,'Adj. P&L'!$C$11:$C$119,0),MATCH(O$1,'Adj. P&L'!$D$9:$CX$9,0))} -> 170.72079 | Q15: {=INDEX('Adj. P&L'!$D$11:$CX$119,MATCH($A15,'Adj. P&L'!$C$11:$C$119,0),MATCH(Q$1,'Adj. P&L'!$D$9:$CX$9,0))} -> 593.04724 | R15: {=INDEX('Adj. P&L'!$D$11:$CX$119,MATCH($A15,'Adj. P&L'!$C$11:$C$119,0),MATCH(R$1,'Adj. P&L'!$D$9:$CX$9,0))} -> 807.83677 | S15: {=INDEX('Adj. P&L'!$D$11:$CX$119,MATCH($A15,'Adj. P&L'!$C$11:$C$119,0),MATCH(S$1,'Adj. P&L'!$D$9:$CX$9,0))} -> 1220.2729 | U15: {=INDEX('Adj. P&L'!$D$11:$CX$119,MATCH($A15,'Adj. P&L'!$C$11:$C$119,0),MATCH(U$1,'Adj. P&L'!$D$9:$CX$9,0))} -> 579.92769 | V15: {=INDEX('Adj. P&L'!$D$11:$CX$119,MATCH($A15,'Adj. P&L'!$C$11:$C$119,0),MATCH(V$1,'Adj. P&L'!$D$9:$CX$9,0))} -> 739.2378 | W15: {=INDEX('Adj. P&L'!$D$11:$CX$119,MATCH($A15,'Adj. P&L'!$C$11:$C$119,0),MATCH(W$1,'Adj. P&L'!$D$9:$CX$9,0))} -> 1150.5784

Sheet Valuation
C3: Firefly Lane
C4: Valuation
C6: Inputs
C7: Cap Rate | D7: 0.072
C8: LTM EBITDAR | D8: ='Adj. P&L'!CC111 -> 559.60715
C9: Y1 EBITDAR | D9: ='Adj. P&L'!CD111 -> 593.04724
C10: PF Year 2 EBITDAR | D10: ='Adj. P&L'!CE111 -> 807.83677
C12: $ in thousands | D12: WH Offer
D13: WholeCo | E13: OpCo w/ SLB
C15: Deal Value
C17: Implied Total Value (RE + Business) | D17: =D20 -> 3600 | E17: =E20-E19 -> 3600
C19: (-) Implied Real Estate Value (EPRT) | D19: =D43 -> 0 | E19: -2000
C20: Walters Purchase Price | D20: 3600 | E20: 1600
C22: (-) Seller Financing | D22: =D46 -> 0 | E22: =E46 -> 0
C23: Walters Purchase Price | D23: =D20+D22 -> 3600 | E23: =E20+E22 -> 1600
C25: Transaction Expenses
C26: Broker Fee
C27: Other Transaction Expenses
C28: Deposits not Received
C29: Transaction Value | D29: =D26+D28 -> 0 | E29: =E26+E28 -> 0
C31: Deal Value
C33: LTM EBITDAR | D33: =$D$8 -> 559.60715 | E33: =$D$8 -> 559.60715
C34: Y1 EBITDAR | D34: =$D$9 -> 593.04724 | E34: =$D$9 -> 593.04724
C35: Y2 EBITDAR | D35: =$D$10 -> 807.83677 | E35: =$D$10 -> 807.83677
C37: LTM EBITDA | D37: =D33-D$42 -> 559.60715 | E37: =E33-E$42 -> 415.60715
C38: Y1 EBITDA | D38: =D34-D$42 -> 593.04724 | E38: =E34-E$42 -> 449.04724
C39: Y2 EBITDA | D39: =D35-D$42 -> 807.83677 | E39: =E35-E$42 -> 663.83677
C41: Memo: Real Estate Value
C42: Rent | D42: 0 | E42: =E43*$D$7 -> 144
C43: ="Implied SLB Value ("&TEXT(D7,"0.0%")&" Cap Rate)" -> Implied SLB Value (7.2% Cap Rate) | D43: =D42/$D$7 -> 0 | E43: =-E19 -> 2000
C44: Rent Coverage - Closing EBITDAR | D44: =IFERROR(D33/D42,0) -> 0 | E44: =IFERROR(E33/E42,0) -> 3.8861607
C45: Rent Coverage - PF EBITDAR | D45: =IFERROR(D35/D42,0) -> 0 | E45: =IFERROR(E35/E42,0) -> 5.6099775
C47: Multiples
C49: LTM
C51: Lender Multiple (Upfront / EBITDA) | D51: =D$23/D37 -> 6.4330844 | E51: =E$23/E37 -> 3.8497894
C52: Purchase Multiple (Deal Value / EBITDAR) | D52: =D$17/D33 -> 6.4330844 | E52: =E$17/E33 -> 6.4330844
C54: PF Year 1
C56: Lender Multiple (Upfront / EBITDA) | D56: =D$23/D38 -> 6.0703427 | E56: =E$23/E38 -> 3.5630995
C57: Purchase Multiple (Deal Value / EBITDAR) | D57: =D$17/D34 -> 6.0703427 | E57: =E$17/E34 -> 6.0703427
C59: PF Year 2
C61: Lender Multiple (Upfront / EBITDA) | D61: =D$23/D39 -> 4.4563458 | E61: =E$23/E39 -> 2.4102311
C62: Purchase Multiple (Deal Value / EBITDAR) | D62: =D17/D35 -> 4.4563458 | E62: =E17/E35 -> 4.4563458
C64: ="Returns @"&TEXT('Cash Flow'!D7,"0.0x")&" exit multiple in "&'Cash Flow'!D8&" years" -> Returns @11.0x exit multiple in 6 years
C66: IRR | D66: ='Cash Flow'!D31 -> 0.43138283 | E66: ='Cash Flow'!D52 -> 0.69572582
C67: MOIC | D67: ='Cash Flow'!D32 -> 5.8815908 | E67: ='Cash Flow'!D53 -> 8.5932333

Sheet Sales & Marketing Summary
D3: =Checks!$C$3 -> Firefly Lane
D4: Sales / Marketing Summary
D6: Note: Contracts includes elopement contracts
D7: Month | E7: # Leads | F7: Tours | G7: Contracts | H7: L->T | I7: T->C | J7: L->C
D9: Monthly Average
D10: 1 | E10: =AVERAGEIFS(E$19:E$61,$B$19:$B$61,$D10) -> 125.5 | F10: =AVERAGEIFS(F$19:F$61,$B$19:$B$61,$D10) -> 35.416667 | G10: =AVERAGEIFS(G$19:G$61,$B$19:$B$61,$D10) -> 15.833333 | H10: =F10/E10 -> 0.28220452 | I10: =G10/F10 -> 0.44705882 | J10: =G10/E10 -> 0.12616202
D11: 2 | E11: =AVERAGEIFS(E$19:E$61,$B$19:$B$61,$D11) -> 131.75 | F11: =AVERAGEIFS(F$19:F$61,$B$19:$B$61,$D11) -> 39.583333 | G11: =AVERAGEIFS(G$19:G$61,$B$19:$B$61,$D11) -> 16.666667 | H11: =F11/E11 -> 0.30044276 | I11: =G11/F11 -> 0.42105263 | J11: =G11/E11 -> 0.12650221
D12: 3 | E12: =AVERAGEIFS(E$19:E$61,$B$19:$B$61,$D12) -> 138.33333 | F12: =AVERAGEIFS(F$19:F$61,$B$19:$B$61,$D12) -> 43.75 | G12: =AVERAGEIFS(G$19:G$61,$B$19:$B$61,$D12) -> 17.5 | H12: =F12/E12 -> 0.31626506 | I12: =G12/F12 -> 0.4 | J12: =G12/E12 -> 0.12650602
A14: =YEAR(D14) -> 2026 | D14: 46053
A15: =YEAR(D15) -> 2026 | D15: =EOMONTH(D14,1) -> 46081
A16: =YEAR(D16) -> 2026 | D16: =EOMONTH(D15,1) -> 46112
A17: =YEAR(D17) -> 2026 | D17: =EOMONTH(D16,1) -> 46142
A18: =YEAR(D18) -> 2026 | D18: =EOMONTH(D17,1) -> 46173
A19: =YEAR(D19) -> 2026 | B19: 1 | D19: =EOMONTH(D18,1) -> 46203 | E19: =SUMIFS('Adj. P&L'!$11:$11,'Adj. P&L'!$9:$9,$D19) -> 118.89474 | F19: =SUMIFS('Adj. P&L'!$15:$15,'Adj. P&L'!$9:$9,$D19) -> 33.552632 | G19: =SUMIFS('Adj. P&L'!$22:$22,'Adj. P&L'!$9:$9,$D19) -> 15 | H19: =F19/E19 -> 0.28220452 | I19: =G19/F19 -> 0.44705882 | J19: =G19/E19 -> 0.12616202
A20: =YEAR(D20) -> 2026 | B20: =B19 -> 1 | D20: =EOMONTH(D19,1) -> 46234 | E20: =SUMIFS('Adj. P&L'!$11:$11,'Adj. P&L'!$9:$9,$D20) -> 190.23158 | F20: =SUMIFS('Adj. P&L'!$15:$15,'Adj. P&L'!$9:$9,$D20) -> 53.684211 | G20: =SUMIFS('Adj. P&L'!$22:$22,'Adj. P&L'!$9:$9,$D20) -> 24 | H20: =F20/E20 -> 0.28220452 | I20: =G20/F20 -> 0.44705882 | J20: =G20/E20 -> 0.12616202
A21: =YEAR(D21) -> 2026 | B21: =B20 -> 1 | D21: =EOMONTH(D20,1) -> 46265 | E21: =SUMIFS('Adj. P&L'!$11:$11,'Adj. P&L'!$9:$9,$D21) -> 166.45263 | F21: =SUMIFS('Adj. P&L'!$15:$15,'Adj. P&L'!$9:$9,$D21) -> 46.973684 | G21: =SUMIFS('Adj. P&L'!$22:$22,'Adj. P&L'!$9:$9,$D21) -> 21 | H21: =F21/E21 -> 0.28220452 | I21: =G21/F21 -> 0.44705882 | J21: =G21/E21 -> 0.12616202
A22: =YEAR(D22) -> 2026 | B22: =B21 -> 1 | D22: =EOMONTH(D21,1) -> 46295 | E22: =SUMIFS('Adj. P&L'!$11:$11,'Adj. P&L'!$9:$9,$D22) -> 126.82105 | F22: =SUMIFS('Adj. P&L'!$15:$15,'Adj. P&L'!$9:$9,$D22) -> 35.789474 | G22: =SUMIFS('Adj. P&L'!$22:$22,'Adj. P&L'!$9:$9,$D22) -> 16 | H22: =F22/E22 -> 0.28220452 | I22: =G22/F22 -> 0.44705882 | J22: =G22/E22 -> 0.12616202
A23: =YEAR(D23) -> 2026 | B23: =B22 -> 1 | D23: =EOMONTH(D22,1) -> 46326 | E23: =SUMIFS('Adj. P&L'!$11:$11,'Adj. P&L'!$9:$9,$D23) -> 95.115789 | F23: =SUMIFS('Adj. P&L'!$15:$15,'Adj. P&L'!$9:$9,$D23) -> 26.842105 | G23: =SUMIFS('Adj. P&L'!$22:$22,'Adj. P&L'!$9:$9,$D23) -> 12 | H23: =F23/E23 -> 0.28220452 | I23: =G23/F23 -> 0.44705882 | J23: =G23/E23 -> 0.12616202
A24: =YEAR(D24) -> 2026 | B24: =B23 -> 1 | D24: =EOMONTH(D23,1) -> 46356 | E24: =SUMIFS('Adj. P&L'!$11:$11,'Adj. P&L'!$9:$9,$D24) -> 126.82105 | F24: =SUMIFS('Adj. P&L'!$15:$15,'Adj. P&L'!$9:$9,$D24) -> 35.789474 | G24: =SUMIFS('Adj. P&L'!$22:$22,'Adj. P&L'!$9:$9,$D24) -> 16 | H24: =F24/E24 -> 0.28220452 | I24: =G24/F24 -> 0.44705882 | J24: =G24/E24 -> 0.12616202
A25: =YEAR(D25) -> 2026 | B25: =B24 -> 1 | D25: =EOMONTH(D24,1) -> 46387 | E25: =SUMIFS('Adj. P&L'!$11:$11,'Adj. P&L'!$9:$9,$D25) -> 87.189474 | F25: =SUMIFS('Adj. P&L'!$15:$15,'Adj. P&L'!$9:$9,$D25) -> 24.605263 | G25: =SUMIFS('Adj. P&L'!$22:$22,'Adj. P&L'!$9:$9,$D25) -> 11 | H25: =F25/E25 -> 0.28220452 | I25: =G25/F25 -> 0.44705882 | J25: =G25/E25 -> 0.12616202
A26: =YEAR(D26) -> 2027 | B26: =B25 -> 1 | D26: =EOMONTH(D25,1) -> 46418 | E26: =SUMIFS('Adj. P&L'!$11:$11,'Adj. P&L'!$9:$9,$D26) -> 166.45263 | F26: =SUMIFS('Adj. P&L'!$15:$15,'Adj. P&L'!$9:$9,$D26) -> 46.973684 | G26: =SUMIFS('Adj. P&L'!$22:$22,'Adj. P&L'!$9:$9,$D26) -> 21 | H26: =F26/E26 -> 0.28220452 | I26: =G26/F26 -> 0.44705882 | J26: =G26/E26 -> 0.12616202
A27: =YEAR(D27) -> 2027 | B27: =B26 -> 1 | D27: =EOMONTH(D26,1) -> 46446 | E27: =SUMIFS('Adj. P&L'!$11:$11,'Adj. P&L'!$9:$9,$D27) -> 87.189474 | F27: =SUMIFS('Adj. P&L'!$15:$15,'Adj. P&L'!$9:$9,$D27) -> 24.605263 | G27: =SUMIFS('Adj. P&L'!$22:$22,'Adj. P&L'!$9:$9,$D27) -> 11 | H27: =F27/E27 -> 0.28220452 | I27: =G27/F27 -> 0.44705882 | J27: =G27/E27 -> 0.12616202
A28: =YEAR(D28) -> 2027 | B28: =B27 -> 1 | D28: =EOMONTH(D27,1) -> 46477 | E28: =SUMIFS('Adj. P&L'!$11:$11,'Adj. P&L'!$9:$9,$D28) -> 134.74737 | F28: =SUMIFS('Adj. P&L'!$15:$15,'Adj. P&L'!$9:$9,$D28) -> 38.026316 | G28: =SUMIFS('Adj. P&L'!$22:$22,'Adj. P&L'!$9:$9,$D28) -> 17 | H28: =F28/E28 -> 0.28220452 | I28: =G28/F28 -> 0.44705882 | J28: =G28/E28 -> 0.12616202
A29: =YEAR(D29) -> 2027 | B29: =B28 -> 1 | D29: =EOMONTH(D28,1) -> 46507 | E29: =SUMIFS('Adj. P&L'!$11:$11,'Adj. P&L'!$9:$9,$D29) -> 103.04211 | F29: =SUMIFS('Adj. P&L'!$15:$15,'Adj. P&L'!$9:$9,$D29) -> 29.078947 | G29: =SUMIFS('Adj. P&L'!$22:$22,'Adj. P&L'!$9:$9,$D29) -> 13 | H29: =F29/E29 -> 0.28220452 | I29: =G29/F29 -> 0.44705882 | J29: =G29/E29 -> 0.12616202
A30: =YEAR(D30) -> 2027 | B30: =B29 -> 1 | D30: =EOMONTH(D29,1) -> 46538 | E30: =SUMIFS('Adj. P&L'!$11:$11,'Adj. P&L'!$9:$9,$D30) -> 103.04211 | F30: =SUMIFS('Adj. P&L'!$15:$15,'Adj. P&L'!$9:$9,$D30) -> 29.078947 | G30: =SUMIFS('Adj. P&L'!$22:$22,'Adj. P&L'!$9:$9,$D30) -> 13 | H30: =F30/E30 -> 0.28220452 | I30: =G30/F30 -> 0.44705882 | J30: =G30/E30 -> 0.12616202
A31: =YEAR(D31) -> 2027 | B31: =B19+1 -> 2 | D31: =EOMONTH(D30,1) -> 46568 | E31: =SUMIFS('Adj. P&L'!$11:$11,'Adj. P&L'!$9:$9,$D31) -> 158.1 | F31: =SUMIFS('Adj. P&L'!$15:$15,'Adj. P&L'!$9:$9,$D31) -> 47.5 | G31: =SUMIFS('Adj. P&L'!$22:$22,'Adj. P&L'!$9:$9,$D31) -> 20 | H31: =F31/E31 -> 0.30044276 | I31: =G31/F31 -> 0.42105263 | J31: =G31/E31 -> 0.12650221
A32: =YEAR(D32) -> 2027 | B32: =B20+1 -> 2 | D32: =EOMONTH(D31,1) -> 46599 | E32: =SUMIFS('Adj. P&L'!$11:$11,'Adj. P&L'!$9:$9,$D32) -> 221.34 | F32: =SUMIFS('Adj. P&L'!$15:$15,'Adj. P&L'!$9:$9,$D32) -> 66.5 | G32: =SUMIFS('Adj. P&L'!$22:$22,'Adj. P&L'!$9:$9,$D32) -> 28 | H32: =F32/E32 -> 0.30044276 | I32: =G32/F32 -> 0.42105263 | J32: =G32/E32 -> 0.12650221
A33: =YEAR(D33) -> 2027 | B33: =B21+1 -> 2 | D33: =EOMONTH(D32,1) -> 46630 | E33: =SUMIFS('Adj. P&L'!$11:$11,'Adj. P&L'!$9:$9,$D33) -> 189.72 | F33: =SUMIFS('Adj. P&L'!$15:$15,'Adj. P&L'!$9:$9,$D33) -> 57 | G33: =SUMIFS('Adj. P&L'!$22:$22,'Adj. P&L'!$9:$9,$D33) -> 24 | H33: =F33/E33 -> 0.30044276 | I33: =G33/F33 -> 0.42105263 | J33: =G33/E33 -> 0.12650221
A34: =YEAR(D34) -> 2027 | B34: =B22+1 -> 2 | D34: =EOMONTH(D33,1) -> 46660 | E34: =SUMIFS('Adj. P&L'!$11:$11,'Adj. P&L'!$9:$9,$D34) -> 126.48 | F34: =SUMIFS('Adj. P&L'!$15:$15,'Adj. P&L'!$9:$9,$D34) -> 38 | G34: =SUMIFS('Adj. P&L'!$22:$22,'Adj. P&L'!$9:$9,$D34) -> 16 | H34: =F34/E34 -> 0.30044276 | I34: =G34/F34 -> 0.42105263 | J34: =G34/E34 -> 0.12650221
A35: =YEAR(D35) -> 2027 | B35: =B23+1 -> 2 | D35: =EOMONTH(D34,1) -> 46691 | E35: =SUMIFS('Adj. P&L'!$11:$11,'Adj. P&L'!$9:$9,$D35) -> 94.86 | F35: =SUMIFS('Adj. P&L'!$15:$15,'Adj. P&L'!$9:$9,$D35) -> 28.5 | G35: =SUMIFS('Adj. P&L'!$22:$22,'Adj. P&L'!$9:$9,$D35) -> 12 | H35: =F35/E35 -> 0.30044276 | I35: =G35/F35 -> 0.42105263 | J35: =G35/E35 -> 0.12650221
A36: =YEAR(D36) -> 2027 | B36: =B24+1 -> 2 | D36: =EOMONTH(D35,1) -> 46721 | E36: =SUMIFS('Adj. P&L'!$11:$11,'Adj. P&L'!$9:$9,$D36) -> 110.67 | F36: =SUMIFS('Adj. P&L'!$15:$15,'Adj. P&L'!$9:$9,$D36) -> 33.25 | G36: =SUMIFS('Adj. P&L'!$22:$22,'Adj. P&L'!$9:$9,$D36) -> 14 | H36: =F36/E36 -> 0.30044276 | I36: =G36/F36 -> 0.42105263 | J36: =G36/E36 -> 0.12650221
A37: =YEAR(D37) -> 2027 | B37: =B25+1 -> 2 | D37: =EOMONTH(D36,1) -> 46752 | E37: =SUMIFS('Adj. P&L'!$11:$11,'Adj. P&L'!$9:$9,$D37) -> 47.43 | F37: =SUMIFS('Adj. P&L'!$15:$15,'Adj. P&L'!$9:$9,$D37) -> 14.25 | G37: =SUMIFS('Adj. P&L'!$22:$22,'Adj. P&L'!$9:$9,$D37) -> 6 | H37: =F37/E37 -> 0.30044276 | I37: =G37/F37 -> 0.42105263 | J37: =G37/E37 -> 0.12650221
A38: =YEAR(D38) -> 2028 | B38: =B26+1 -> 2 | D38: =EOMONTH(D37,1) -> 46783 | E38: =SUMIFS('Adj. P&L'!$11:$11,'Adj. P&L'!$9:$9,$D38) -> 173.91 | F38: =SUMIFS('Adj. P&L'!$15:$15,'Adj. P&L'!$9:$9,$D38) -> 52.25 | G38: =SUMIFS('Adj. P&L'!$22:$22,'Adj. P&L'!$9:$9,$D38) -> 22 | H38: =F38/E38 -> 0.30044276 | I38: =G38/F38 -> 0.42105263 | J38: =G38/E38 -> 0.12650221
A39: =YEAR(D39) -> 2028 | B39: =B27+1 -> 2 | D39: =EOMONTH(D38,1) -> 46812 | E39: =SUMIFS('Adj. P&L'!$11:$11,'Adj. P&L'!$9:$9,$D39) -> 94.86 | F39: =SUMIFS('Adj. P&L'!$15:$15,'Adj. P&L'!$9:$9,$D39) -> 28.5 | G39: =SUMIFS('Adj. P&L'!$22:$22,'Adj. P&L'!$9:$9,$D39) -> 12 | H39: =F39/E39 -> 0.30044276 | I39: =G39/F39 -> 0.42105263 | J39: =G39/E39 -> 0.12650221
A40: =YEAR(D40) -> 2028 | B40: =B28+1 -> 2 | D40: =EOMONTH(D39,1) -> 46843 | E40: =SUMIFS('Adj. P&L'!$11:$11,'Adj. P&L'!$9:$9,$D40) -> 142.29 | F40: =SUMIFS('Adj. P&L'!$15:$15,'Adj. P&L'!$9:$9,$D40) -> 42.75 | G40: =SUMIFS('Adj. P&L'!$22:$22,'Adj. P&L'!$9:$9,$D40) -> 18 | H40: =F40/E40 -> 0.30044276 | I40: =G40/F40 -> 0.42105263 | J40: =G40/E40 -> 0.12650221
A41: =YEAR(D41) -> 2028 | B41: =B29+1 -> 2 | D41: =EOMONTH(D40,1) -> 46873 | E41: =SUMIFS('Adj. P&L'!$11:$11,'Adj. P&L'!$9:$9,$D41) -> 110.67 | F41: =SUMIFS('Adj. P&L'!$15:$15,'Adj. P&L'!$9:$9,$D41) -> 33.25 | G41: =SUMIFS('Adj. P&L'!$22:$22,'Adj. P&L'!$9:$9,$D41) -> 14 | H41: =F41/E41 -> 0.30044276 | I41: =G41/F41 -> 0.42105263 | J41: =G41/E41 -> 0.12650221
A42: =YEAR(D42) -> 2028 | B42: =B30+1 -> 2 | D42: =EOMONTH(D41,1) -> 46904 | E42: =SUMIFS('Adj. P&L'!$11:$11,'Adj. P&L'!$9:$9,$D42) -> 110.67 | F42: =SUMIFS('Adj. P&L'!$15:$15,'Adj. P&L'!$9:$9,$D42) -> 33.25 | G42: =SUMIFS('Adj. P&L'!$22:$22,'Adj. P&L'!$9:$9,$D42) -> 14 | H42: =F42/E42 -> 0.30044276 | I42: =G42/F42 -> 0.42105263 | J42: =G42/E42 -> 0.12650221
... A61: =YEAR(D61) -> 2029 | B61: =B49+1 -> 4 | D61: =EOMONTH(D60,1) -> 47483 | E61: =SUMIFS('Adj. P&L'!$11:$11,'Adj. P&L'!$9:$9,$D61) -> 47.428571 | F61: =SUMIFS('Adj. P&L'!$15:$15,'Adj. P&L'!$9:$9,$D61) -> 15 | G61: =SUMIFS('Adj. P&L'!$22:$22,'Adj. P&L'!$9:$9,$D61) -> 6 | H61: =F61/E61 -> 0.31626506 | I61: =G61/F61 -> 0.4 | J61: =G61/E61 -> 0.12650602

Sheet Adj. P&L
D1: =YEAR(D9) -> 2024 | E1: =YEAR(E9) -> 2024 | F1: =YEAR(F9) -> 2024 | G1: =YEAR(G9) -> 2024 | H1: =YEAR(H9) -> 2024 | I1: =YEAR(I9) -> 2024 | J1: =YEAR(J9) -> 2024 | K1: =YEAR(K9) -> 2024 | ... AF1: =YEAR(AF9) -> 2026 | AH1: =YEAR(AH9) -> 2026 | AI1: =YEAR(AI9) -> 2026 | AJ1: =YEAR(AJ9) -> 2026 | AK1: =YEAR(AK9) -> 2026 | AL1: =YEAR(AL9) -> 2026 | AM1: =YEAR(AM9) -> 2026 | AN1: =YEAR(AN9) -> 2026 | AO1: =YEAR(AO9) -> 2027 | ... BQ1: =YEAR(BQ9) -> 2029 | BS1: =YEAR(BS9) -> 2029 | BT1: =YEAR(BT9) -> 2029 | BU1: =YEAR(BU9) -> 2029 | BV1: =YEAR(BV9) -> 2029 | BW1: =YEAR(BW9) -> 2029 | BX1: =YEAR(BX9) -> 2029 | BY1: =YEAR(BY9) -> 2029 | CH1: 1 | CI1: 2 | CJ1: 3 | CN1: DFW
D2: =MONTH(D9) -> 1 | E2: =MONTH(E9) -> 2 | F2: =MONTH(F9) -> 3 | G2: =MONTH(G9) -> 4 | H2: =MONTH(H9) -> 5 | I2: =MONTH(I9) -> 6 | J2: =MONTH(J9) -> 7 | K2: =MONTH(K9) -> 8 | ... AF2: =MONTH(AF9) -> 5 | AH2: =MONTH(AH9) -> 6 | AI2: =MONTH(AI9) -> 7 | AJ2: =MONTH(AJ9) -> 8 | AK2: =MONTH(AK9) -> 9 | AL2: =MONTH(AL9) -> 10 | AM2: =MONTH(AM9) -> 11 | AN2: =MONTH(AN9) -> 12 | AO2: =MONTH(AO9) -> 1 | ... BQ2: =MONTH(BQ9) -> 5 | BS2: =MONTH(BS9) -> 6 | BT2: =MONTH(BT9) -> 7 | BU2: =MONTH(BU9) -> 8 | BV2: =MONTH(BV9) -> 9 | BW2: =MONTH(BW9) -> 10 | BX2: =MONTH(BX9) -> 11 | BY2: =MONTH(BY9) -> 12 | CA2: 2024 | CB2: 2025 | CC2: LTM | CD2: 1 | CE2: 2 | CF2: 3 | CU2: 1 | CV2: 2 | CW2: 3 | CX2: 3
T3: LTM | U3: LTM | V3: LTM | W3: LTM | X3: LTM | Y3: LTM | Z3: LTM | AA3: LTM | AB3: LTM | AC3: LTM | AD3: LTM | AE3: LTM | AH3: 1 | AI3: =AH3 -> 1 | AJ3: =AI3 -> 1 | AK3: =AJ3 -> 1 | AL3: =AK3 -> 1 | AM3: =AL3 -> 1 | AN3: =AM3 -> 1 | AO3: =AN3 -> 1 | AP3: =AO3 -> 1 | ... AS3: =AR3 -> 1 | AT3: =AH3+1 -> 2 | AU3: =AI3+1 -> 2 | AV3: =AJ3+1 -> 2 | AW3: =AK3+1 -> 2 | AX3: =AL3+1 -> 2 | AY3: =AM3+1 -> 2 | AZ3: =AN3+1 -> 2 | BA3: =AO3+1 -> 2 | ... BQ3: =BE3+1 -> 3 | BS3: =BF3+1 -> 4 | BT3: =BG3+1 -> 4 | BU3: =BH3+1 -> 4 | BV3: =BI3+1 -> 4 | BW3: =BJ3+1 -> 4 | BX3: =BK3+1 -> 4 | BY3: =BL3+1 -> 4
C5: =Checks!$C$3 -> Firefly Lane | CN5: {=INDEX('FY25 By Venue Financials'!$1:$1,MATCH(CN1,'FY25 By Venue Financials'!$4:$4,0))} -> J
C6: PF P&L Analysis
D8: Historicals | P8: Historicals | AH8: Forecast | CA8: Historicals | CD8: PF | CH8: PF Drivers | CL8: Current | CN8: WH Comparable Venue | CU8: Annual
D9: 45322 | E9: =EOMONTH(D9,1) -> 45351 | F9: =EOMONTH(E9,1) -> 45382 | G9: =EOMONTH(F9,1) -> 45412 | H9: =EOMONTH(G9,1) -> 45443 | I9: =EOMONTH(H9,1) -> 45473 | J9: =EOMONTH(I9,1) -> 45504 | K9: =EOMONTH(J9,1) -> 45535 | L9: =EOMONTH(K9,1) -> 45565 | ... AF9: =EOMONTH(AE9,1) -> 46173 | AH9: =EOMONTH(AF9,1) -> 46203 | AI9: =EOMONTH(AH9,1) -> 46234 | AJ9: =EOMONTH(AI9,1) -> 46265 | AK9: =EOMONTH(AJ9,1) -> 46295 | AL9: =EOMONTH(AK9,1) -> 46326 | AM9: =EOMONTH(AL9,1) -> 46356 | AN9: =EOMONTH(AM9,1) -> 46387 | AO9: =EOMONTH(AN9,1) -> 46418 | AP9: =EOMONTH(AO9,1) -> 46446 | ... BQ9: =EOMONTH(BP9,1) -> 47269 | BS9: =EOMONTH(BQ9,1) -> 47299 | BT9: =EOMONTH(BS9,1) -> 47330 | BU9: =EOMONTH(BT9,1) -> 47361 | BV9: =EOMONTH(BU9,1) -> 47391 | BW9: =EOMONTH(BV9,1) -> 47422 | BX9: =EOMONTH(BW9,1) -> 47452 | BY9: =EOMONTH(BX9,1) -> 47483 | CA9: 2024 | CB9: 2025 | CC9: ='Events Summary'!$C$12 -> LTM Apr-26 | CD9: Y1 | CE9: Y2 | CF9: Y3 | CH9: Y1 | CI9: Y2 | CJ9: Y3 | CL9: % | CN9: $ | CO9: % | CQ9: % Type | CR9: Historical / PF Comments | CU9: 2026 | CV9: =CU9+1 -> 2027 | CW9: =CV9+1 -> 2028 | CX9: =CW9+1 -> 2029
C11: Leads | AH11: =AH15/AH13 -> 118.89474 | AI11: =AI15/AI13 -> 190.23158 | AJ11: =AJ15/AJ13 -> 166.45263 | AK11: =AK15/AK13 -> 126.82105 | AL11: =AL15/AL13 -> 95.115789 | AM11: =AM15/AM13 -> 126.82105 | AN11: =AN15/AN13 -> 87.189474 | AO11: =AO15/AO13 -> 166.45263 | ... BQ11: =BQ15/BQ13 -> 118.57143 | BS11: =BF11 -> 166 | BT11: =BG11 -> 237.14286 | BU11: =BH11 -> 197.61905 | BV11: =BI11 -> 134.38095 | BW11: =BJ11 -> 94.857143 | BX11: =BK11 -> 118.57143 | BY11: =BL11 -> 47.428571 | CA11: 0 | CB11: 0 | CC11: 0 | CD11: 1506 | CE11: =ROUND(CD11*1.05,0) -> 1581 | CF11: =ROUND(CE11*1.05,0) -> 1660 | CR11: Per Marketing | CU11: =SUMIFS($D11:$BZ11,$D$1:$BZ$1,CU$9) -> 911.52632 | CV11: =SUMIFS($D11:$BZ11,$D$1:$BZ$1,CV$9) -> 1543.0737 | CW11: =SUMIFS($D11:$BZ11,$D$1:$BZ$1,CW$9) -> 1628.4 | CX11: =SUMIFS($D11:$BZ11,$D$1:$BZ$1,CX$9) -> 1660
C13: L->T Conversion | AH13: =SUMIFS($CD13:$CF13,$CD$2:$CF$2,AH$3) -> 0.28220452 | AI13: =SUMIFS($CD13:$CF13,$CD$2:$CF$2,AI$3) -> 0.28220452 | AJ13: =SUMIFS($CD13:$CF13,$CD$2:$CF$2,AJ$3) -> 0.28220452 | AK13: =SUMIFS($CD13:$CF13,$CD$2:$CF$2,AK$3) -> 0.28220452 | AL13: =SUMIFS($CD13:$CF13,$CD$2:$CF$2,AL$3) -> 0.28220452 | AM13: =SUMIFS($CD13:$CF13,$CD$2:$CF$2,AM$3) -> 0.28220452 | AN13: =SUMIFS($CD13:$CF13,$CD$2:$CF$2,AN$3) -> 0.28220452 | AO13: =SUMIFS($CD13:$CF13,$CD$2:$CF$2,AO$3) -> 0.28220452 | ... BQ13: =SUMIFS($CD13:$CF13,$CD$2:$CF$2,BQ$3) -> 0.31626506 | CA13: 0 | CB13: 0 | CC13: 0 | CD13: =CD15/CD11 -> 0.28220452 | CE13: =CE15/CE11 -> 0.30044276 | CF13: =CF15/CF11 -> 0.31626506 | CU13: 0.12 | CV13: 0.12 | CW13: 0.12 | CX13: 0.12
C15: Tours | P15: =SUMIFS('Leads & Tours'!$D:$D,'Leads & Tours'!$A:$A,P$9) -> 29 | Q15: =SUMIFS('Leads & Tours'!$D:$D,'Leads & Tours'!$A:$A,Q$9) -> 16 | R15: =SUMIFS('Leads & Tours'!$D:$D,'Leads & Tours'!$A:$A,R$9) -> 17 | S15: =SUMIFS('Leads & Tours'!$D:$D,'Leads & Tours'!$A:$A,S$9) -> 13 | T15: =SUMIFS('Leads & Tours'!$D:$D,'Leads & Tours'!$A:$A,T$9) -> 19 | U15: =SUMIFS('Leads & Tours'!$D:$D,'Leads & Tours'!$A:$A,U$9) -> 24 | V15: =SUMIFS('Leads & Tours'!$D:$D,'Leads & Tours'!$A:$A,V$9) -> 34 | W15: =SUMIFS('Leads & Tours'!$D:$D,'Leads & Tours'!$A:$A,W$9) -> 30 | ... AF15: =SUMIFS('Leads & Tours'!$D:$D,'Leads & Tours'!$A:$A,AF$9) -> 16 | AH15: =AH22/AH17 -> 33.552632 | AI15: =AI22/AI17 -> 53.684211 | AJ15: =AJ22/AJ17 -> 46.973684 | AK15: =AK22/AK17 -> 35.789474 | AL15: =AL22/AL17 -> 26.842105 | AM15: =AM22/AM17 -> 35.789474 | AN15: =AN22/AN17 -> 24.605263 | AO15: =AO22/AO17 -> 46.973684 | ... BQ15: =BQ22/BQ17 -> 37.5 | BS15: =BF15 -> 52.5 | BT15: =BG15 -> 75 | BU15: =BH15 -> 62.5 | BV15: =BI15 -> 42.5 | BW15: =BJ15 -> 30 | BX15: =BK15 -> 37.5 | BY15: =BL15 -> 15 | CA15: =SUMIFS($D15:$BZ15,$D$1:$BZ$1,CA$2) -> 0 | CB15: =SUMIFS($D15:$BZ15,$D$1:$BZ$1,CB$2) -> 281 | CC15: =SUMIFS($P15:$AF15,$P$3:$AF$3,$CC$2) -> 312 | CD15: 425 | CE15: 475 | CF15: 525 | CU15: =SUMIFS($D15:$BZ15,$D$1:$BZ$1,CU$9) -> 379.23684 | CV15: =SUMIFS($D15:$BZ15,$D$1:$BZ$1,CV$9) -> 452.76316 | CW15: =SUMIFS($D15:$BZ15,$D$1:$BZ$1,CW$9) -> 505 | CX15: =SUMIFS($D15:$BZ15,$D$1:$BZ$1,CX$9) -> 525
C17: T->C Conversion | AH17: =SUMIFS($CD17:$CF17,$CD$2:$CF$2,AH$3) -> 0.44705882 | AI17: =SUMIFS($CD17:$CF17,$CD$2:$CF$2,AI$3) -> 0.44705882 | AJ17: =SUMIFS($CD17:$CF17,$CD$2:$CF$2,AJ$3) -> 0.44705882 | AK17: =SUMIFS($CD17:$CF17,$CD$2:$CF$2,AK$3) -> 0.44705882 | AL17: =SUMIFS($CD17:$CF17,$CD$2:$CF$2,AL$3) -> 0.44705882 | AM17: =SUMIFS($CD17:$CF17,$CD$2:$CF$2,AM$3) -> 0.44705882 | AN17: =SUMIFS($CD17:$CF17,$CD$2:$CF$2,AN$3) -> 0.44705882 | AO17: =SUMIFS($CD17:$CF17,$CD$2:$CF$2,AO$3) -> 0.44705882 | ... BQ17: =SUMIFS($CD17:$CF17,$CD$2:$CF$2,BQ$3) -> 0.4 | CA17: 0 | CB17: =CB22/CB15 -> 0.54092527 | CC17: =CC22/CC15 -> 0.4775641 | CD17: =CD22/CD15 -> 0.44705882 | CE17: =CE22/CE15 -> 0.42105263 | CF17: =CF22/CF15 -> 0.4 | CU17: =AVERAGE(0.39,0.4) -> 0.395 | CV17: =AVERAGE(0.39,0.4) -> 0.395 | CW17: =AVERAGE(0.39,0.4) -> 0.395 | CX17: =AVERAGE(0.39,0.4) -> 0.395
C19: Barn Contracts | D19: =SUMIFS('Events Summary'!$L:$L,'Events Summary'!$C:$C,D$9) -> 0 | E19: =SUMIFS('Events Summary'!$L:$L,'Events Summary'!$C:$C,E$9) -> 0 | F19: =SUMIFS('Events Summary'!$L:$L,'Events Summary'!$C:$C,F$9) -> 5 | G19: =SUMIFS('Events Summary'!$L:$L,'Events Summary'!$C:$C,G$9) -> 20 | H19: =SUMIFS('Events Summary'!$L:$L,'Events Summary'!$C:$C,H$9) -> 17 | I19: =SUMIFS('Events Summary'!$L:$L,'Events Summary'!$C:$C,I$9) -> 16 | J19: =SUMIFS('Events Summary'!$L:$L,'Events Summary'!$C:$C,J$9) -> 7 | K19: =SUMIFS('Events Summary'!$L:$L,'Events Summary'!$C:$C,K$9) -> 16 | ... O19: =SUMIFS('Events Summary'!$L:$L,'Events Summary'!$C:$C,O$9) -> 9 | P19: =SUMIFS('Date Booked Summary'!$D:$D,'Date Booked Summary'!$C:$C,P$9) -> 4 | Q19: =SUMIFS('Date Booked Summary'!$D:$D,'Date Booked Summary'!$C:$C,Q$9) -> 1 | R19: =SUMIFS('Date Booked Summary'!$D:$D,'Date Booked Summary'!$C:$C,R$9) -> 4 | S19: =SUMIFS('Date Booked Summary'!$D:$D,'Date Booked Summary'!$C:$C,S$9) -> 5 | T19: =SUMIFS('Date Booked Summary'!$D:$D,'Date Booked Summary'!$C:$C,T$9) -> 1 | U19: =SUMIFS('Date Booked Summary'!$D:$D,'Date Booked Summary'!$C:$C,U$9) -> 1 | V19: =SUMIFS('Date Booked Summary'!$D:$D,'Date Booked Summary'!$C:$C,V$9) -> 7 | W19: =SUMIFS('Date Booked Summary'!$D:$D,'Date Booked Summary'!$C:$C,W$9) -> 4 | ... AF19: =SUMIFS('Date Booked Summary'!$D:$D,'Date Booked Summary'!$C:$C,AF$9) -> 0 | AH19: 4 | AI19: 6 | AJ19: 5 | AK19: 5 | AL19: 3 | AM19: 4 | AN19: 2 | AO19: 6 | AP19: 3 | AQ19: 5 | AR19: 3 | AS19: 4 | AT19: =ROUND(SUMIFS($CD19:$CF19,$CD$2:$CF$2,AT$3)*AT$23,0) -> 6 | AU19: =ROUND(SUMIFS($CD19:$CF19,$CD$2:$CF$2,AU$3)*AU$23,0) -> 8 | AV19: =ROUND(SUMIFS($CD19:$CF19,$CD$2:$CF$2,AV$3)*AV$23,0) -> 7 | AW19: =ROUND(SUMIFS($CD19:$CF19,$CD$2:$CF$2,AW$3)*AW$23,0) -> 5 | AX19: =ROUND(SUMIFS($CD19:$CF19,$CD$2:$CF$2,AX$3)*AX$23,0) -> 4 | AY19: =ROUND(SUMIFS($CD19:$CF19,$CD$2:$CF$2,AY$3)*AY$23,0) -> 4 | AZ19: =ROUND(SUMIFS($CD19:$CF19,$CD$2:$CF$2,AZ$3)*AZ$23,0) -> 2 | BA19: =ROUND(SUMIFS($CD19:$CF19,$CD$2:$CF$2,BA$3)*BA$23,0) -> 7 | ... BK19: =ROUND(SUMIFS($CD19:$CF19,$CD$2:$CF$2,BK$3)*BK$23,0) -> 5 | BL19: 2 | BM19: =ROUND(SUMIFS($CD19:$CF19,$CD$2:$CF$2,BM$3)*BM$23,0) -> 8 | BN19: =ROUND(SUMIFS($CD19:$CF19,$CD$2:$CF$2,BN$3)*BN$23,0) -> 4 | BO19: =ROUND(SUMIFS($CD19:$CF19,$CD$2:$CF$2,BO$3)*BO$23,0) -> 6 | BP19: =ROUND(SUMIFS($CD19:$CF19,$CD$2:$CF$2,BP$3)*BP$23,0) -> 5 | BQ19: =ROUND(SUMIFS($CD19:$CF19,$CD$2:$CF$2,BQ$3)*BQ$23,0) -> 5 | BS19: =BF19 -> 7 | BT19: =BG19 -> 10 | BU19: =BH19 -> 8 | BV19: =BI19 -> 6 | BW19: =BJ19 -> 4 | BX19: =BK19 -> 5 | BY19: =BL19 -> 2 | CA19: 0 | CB19: =SUMIFS($D19:$BZ19,$D$1:$BZ$1,CB$2) -> 40 | CC19: =SUMIFS($P19:$AF19,$P$3:$AF$3,$CC$2) -> 40 | CD19: =SUMIFS($D19:$BZ19,$D$3:$BZ$3,CD$2) -> 50 | CE19: 60 | CF19: 70 | CU19: =SUMIFS($D19:$BZ19,$D$1:$BZ$1,CU$9) -> 43 | CV19: =SUMIFS($D19:$BZ19,$D$1:$BZ$1,CV$9) -> 57 | CW19: =SUMIFS($D19:$BZ19,$D$1:$BZ$1,CW$9) -> 66 | CX19: =SUMIFS($D19:$BZ19,$D$1:$BZ$1,CX$9) -> 70
C20: Chapel Contracts | P20: =SUMIFS('Date Booked Summary'!$E:$E,'Date Booked Summary'!$C:$C,P$9) -> 6 | Q20: =SUMIFS('Date Booked Summary'!$E:$E,'Date Booked Summary'!$C:$C,Q$9) -> 6 | R20: =SUMIFS('Date Booked Summary'!$E:$E,'Date Booked Summary'!$C:$C,R$9) -> 4 | S20: =SUMIFS('Date Booked Summary'!$E:$E,'Date Booked Summary'!$C:$C,S$9) -> 3 | T20: =SUMIFS('Date Booked Summary'!$E:$E,'Date Booked Summary'!$C:$C,T$9) -> 3 | U20: =SUMIFS('Date Booked Summary'!$E:$E,'Date Booked Summary'!$C:$C,U$9) -> 8 | V20: =SUMIFS('Date Booked Summary'!$E:$E,'Date Booked Summary'!$C:$C,V$9) -> 11 | W20: =SUMIFS('Date Booked Summary'!$E:$E,'Date Booked Summary'!$C:$C,W$9) -> 13 | ... AF20: =SUMIFS('Date Booked Summary'!$E:$E,'Date Booked Summary'!$C:$C,AF$9) -> 0 | AH20: 8 | AI20: 13 | AJ20: 11 | AK20: 8 | AL20: 6 | AM20: 9 | AN20: 6 | AO20: 11 | AP20: 6 | AQ20: 9 | AR20: 7 | AS20: 6 | AT20: =ROUND(SUMIFS($CD20:$CF20,$CD$2:$CF$2,AT$3)*AT$23,0) -> 10 | AU20: =ROUND(SUMIFS($CD20:$CF20,$CD$2:$CF$2,AU$3)*AU$23,0) -> 14 | AV20: =ROUND(SUMIFS($CD20:$CF20,$CD$2:$CF$2,AV$3)*AV$23,0) -> 12 | AW20: =ROUND(SUMIFS($CD20:$CF20,$CD$2:$CF$2,AW$3)*AW$23,0) -> 8 | AX20: =ROUND(SUMIFS($CD20:$CF20,$CD$2:$CF$2,AX$3)*AX$23,0) -> 6 | AY20: =ROUND(SUMIFS($CD20:$CF20,$CD$2:$CF$2,AY$3)*AY$23,0) -> 7 | AZ20: 3 | BA20: =ROUND(SUMIFS($CD20:$CF20,$CD$2:$CF$2,BA$3)*BA$23,0) -> 11 | BB20: =ROUND(SUMIFS($CD20:$CF20,$CD$2:$CF$2,BB$3)*BB$23,0) -> 6 | BC20: =ROUND(SUMIFS($CD20:$CF20,$CD$2:$CF$2,BC$3)*BC$23,0) -> 9 | BD20: =ROUND(SUMIFS($CD20:$CF20,$CD$2:$CF$2,BD$3)*BD$23,0) -> 7 | BE20: =ROUND(SUMIFS($CD20:$CF20,$CD$2:$CF$2,BE$3)*BE$23,0) -> 7 | BF20: =ROUND(SUMIFS($CD20:$CF20,$CD$2:$CF$2,BF$3)*BF$23,0) -> 10 | BG20: =ROUND(SUMIFS($CD20:$CF20,$CD$2:$CF$2,BG$3)*BG$23,0) -> 14 | BH20: =ROUND(SUMIFS($CD20:$CF20,$CD$2:$CF$2,BH$3)*BH$23,0) -> 12 | ... BK20: =ROUND(SUMIFS($CD20:$CF20,$CD$2:$CF$2,BK$3)*BK$23,0) -> 7 | BL20: 3 | BM20: =ROUND(SUMIFS($CD20:$CF20,$CD$2:$CF$2,BM$3)*BM$23,0) -> 11 | BN20: =ROUND(SUMIFS($CD20:$CF20,$CD$2:$CF$2,BN$3)*BN$23,0) -> 6 | BO20: =ROUND(SUMIFS($CD20:$CF20,$CD$2:$CF$2,BO$3)*BO$23,0) -> 9 | BP20: =ROUND(SUMIFS($CD20:$CF20,$CD$2:$CF$2,BP$3)*BP$23,0) -> 7 | BQ20: =ROUND(SUMIFS($CD20:$CF20,$CD$2:$CF$2,BQ$3)*BQ$23,0) -> 7 | BS20: =BF20 -> 10 | BT20: =BG20 -> 14 | BU20: =BH20 -> 12 | BV20: =BI20 -> 8 | BW20: =BJ20 -> 6 | BX20: =BK20 -> 7 | BY20: =BL20 -> 3 | CA20: =SUMIFS($D20:$BZ20,$D$1:$BZ$1,CA$2) -> 0 | CB20: =SUMIFS($D20:$BZ20,$D$1:$BZ$1,CB$2) -> 75 | CC20: =SUMIFS($P20:$AF20,$P$3:$AF$3,$CC$2) -> 81 | CD20: =SUMIFS($D20:$BZ20,$D$3:$BZ$3,CD$2) -> 100 | CE20: 100 | CF20: 100 | CU20: =SUMIFS($D20:$BZ20,$D$1:$BZ$1,CU$9) -> 86 | CV20: =SUMIFS($D20:$BZ20,$D$1:$BZ$1,CV$9) -> 99 | CW20: =SUMIFS($D20:$BZ20,$D$1:$BZ$1,CW$9) -> 100 | CX20: =SUMIFS($D20:$BZ20,$D$1:$BZ$1,CX$9) -> 100
C21: Elopement Contracts | P21: =SUMIFS('Date Booked Summary'!$H:$H,'Date Booked Summary'!$C:$C,P$9) -> 9 | Q21: =SUMIFS('Date Booked Summary'!$H:$H,'Date Booked Summary'!$C:$C,Q$9) -> 5 | R21: =SUMIFS('Date Booked Summary'!$H:$H,'Date Booked Summary'!$C:$C,R$9) -> 2 | S21: =SUMIFS('Date Booked Summary'!$H:$H,'Date Booked Summary'!$C:$C,S$9) -> 2 | T21: =SUMIFS('Date Booked Summary'!$H:$H,'Date Booked Summary'!$C:$C,T$9) -> 0 | U21: =SUMIFS('Date Booked Summary'!$H:$H,'Date Booked Summary'!$C:$C,U$9) -> 4 | V21: =SUMIFS('Date Booked Summary'!$H:$H,'Date Booked Summary'!$C:$C,V$9) -> 4 | W21: =SUMIFS('Date Booked Summary'!$H:$H,'Date Booked Summary'!$C:$C,W$9) -> 1 | ... AF21: =SUMIFS('Date Booked Summary'!$H:$H,'Date Booked Summary'!$C:$C,AF$9) -> 0 | AH21: 3 | AI21: 5 | AJ21: 5 | AK21: 3 | AL21: 3 | AM21: 3 | AN21: 3 | AO21: 4 | AP21: 2 | AQ21: 3 | AR21: 3 | AS21: 3 | AT21: =ROUND(SUMIFS($CD21:$CF21,$CD$2:$CF$2,AT$3)*AT$23,0) -> 4 | AU21: =ROUND(SUMIFS($CD21:$CF21,$CD$2:$CF$2,AU$3)*AU$23,0) -> 6 | AV21: =ROUND(SUMIFS($CD21:$CF21,$CD$2:$CF$2,AV$3)*AV$23,0) -> 5 | AW21: =ROUND(SUMIFS($CD21:$CF21,$CD$2:$CF$2,AW$3)*AW$23,0) -> 3 | AX21: =ROUND(SUMIFS($CD21:$CF21,$CD$2:$CF$2,AX$3)*AX$23,0) -> 2 | AY21: =ROUND(SUMIFS($CD21:$CF21,$CD$2:$CF$2,AY$3)*AY$23,0) -> 3 | AZ21: 1 | BA21: =ROUND(SUMIFS($CD21:$CF21,$CD$2:$CF$2,BA$3)*BA$23,0) -> 4 | BB21: =ROUND(SUMIFS($CD21:$CF21,$CD$2:$CF$2,BB$3)*BB$23,0) -> 2 | BC21: =ROUND(SUMIFS($CD21:$CF21,$CD$2:$CF$2,BC$3)*BC$23,0) -> 4 | BD21: =ROUND(SUMIFS($CD21:$CF21,$CD$2:$CF$2,BD$3)*BD$23,0) -> 3 | BE21: =ROUND(SUMIFS($CD21:$CF21,$CD$2:$CF$2,BE$3)*BE$23,0) -> 3 | BF21: =ROUND(SUMIFS($CD21:$CF21,$CD$2:$CF$2,BF$3)*BF$23,0) -> 4 | BG21: =ROUND(SUMIFS($CD21:$CF21,$CD$2:$CF$2,BG$3)*BG$23,0) -> 6 | BH21: =ROUND(SUMIFS($CD21:$CF21,$CD$2:$CF$2,BH$3)*BH$23,0) -> 5 | ... BK21: =ROUND(SUMIFS($CD21:$CF21,$CD$2:$CF$2,BK$3)*BK$23,0) -> 3 | BL21: 1 | BM21: =ROUND(SUMIFS($CD21:$CF21,$CD$2:$CF$2,BM$3)*BM$23,0) -> 4 | BN21: =ROUND(SUMIFS($CD21:$CF21,$CD$2:$CF$2,BN$3)*BN$23,0) -> 2 | BO21: =ROUND(SUMIFS($CD21:$CF21,$CD$2:$CF$2,BO$3)*BO$23,0) -> 4 | BP21: =ROUND(SUMIFS($CD21:$CF21,$CD$2:$CF$2,BP$3)*BP$23,0) -> 3 | BQ21: =ROUND(SUMIFS($CD21:$CF21,$CD$2:$CF$2,BQ$3)*BQ$23,0) -> 3 | BS21: =BF21 -> 4 | BT21: =BG21 -> 6 | BU21: =BH21 -> 5 | BV21: =BI21 -> 3 | BW21: =BJ21 -> 2 | BX21: =BK21 -> 3 | BY21: =BL21 -> 1 | CA21: =SUMIFS($D21:$BZ21,$D$1:$BZ$1,CA$2) -> 0 | CB21: =SUMIFS($D21:$BZ21,$D$1:$BZ$1,CB$2) -> 37 | CC21: =SUMIFS($P21:$AF21,$P$3:$AF$3,$CC$2) -> 28 | CD21: =SUMIFS($D21:$BZ21,$D$3:$BZ$3,CD$2) -> 40 | CE21: 40 | CF21: 40 | CU21: =SUMIFS($D21:$BZ21,$D$1:$BZ$1,CU$9) -> 34 | CV21: =SUMIFS($D21:$BZ21,$D$1:$BZ$1,CV$9) -> 39 | CW21: =SUMIFS($D21:$BZ21,$D$1:$BZ$1,CW$9) -> 40 | CX21: =SUMIFS($D21:$BZ21,$D$1:$BZ$1,CX$9) -> 40
C22: Contracts | D22: 0 | E22: 0 | F22: 0 | G22: 0 | H22: 0 | I22: 0 | J22: 0 | K22: 0 | L22: 0 | M22: 0 | N22: 0 | O22: 0 | P22: =SUM(P19:P21) -> 19 | Q22: =SUM(Q19:Q21) -> 12 | R22: =SUM(R19:R21) -> 10 | S22: =SUM(S19:S21) -> 10 | T22: =SUM(T19:T21) -> 4 | U22: =SUM(U19:U21) -> 13 | V22: =SUM(V19:V21) -> 22 | W22: =SUM(W19:W21) -> 18 | ... AF22: =SUM(AF19:AF21) -> 0 | AH22: =SUM(AH19:AH21) -> 15 | AI22: =SUM(AI19:AI21) -> 24 | AJ22: =SUM(AJ19:AJ21) -> 21 | AK22: =SUM(AK19:AK21) -> 16 | AL22: =SUM(AL19:AL21) -> 12 | AM22: =SUM(AM19:AM21) -> 16 | AN22: =SUM(AN19:AN21) -> 11 | AO22: =SUM(AO19:AO21) -> 21 | ... BQ22: =SUM(BQ19:BQ21) -> 15 | BS22: =SUM(BS19:BS21) -> 21 | BT22: =SUM(BT19:BT21) -> 30 | BU22: =SUM(BU19:BU21) -> 25 | BV22: =SUM(BV19:BV21) -> 17 | BW22: =SUM(BW19:BW21) -> 12 | BX22: =SUM(BX19:BX21) -> 15 | BY22: =SUM(BY19:BY21) -> 6 | CA22: =SUMIFS($D22:$BZ22,$D$1:$BZ$1,CA$2) -> 0 | CB22: =SUMIFS($D22:$BZ22,$D$1:$BZ$1,CB$2) -> 152 | CC22: =SUMIFS($P22:$AF22,$P$3:$AF$3,$CC$2) -> 149 | CD22: =SUM(CD19:CD21) -> 190 | CE22: =SUM(CE19:CE21) -> 200 | CF22: =SUM(CF19:CF21) -> 210 | CR22: Est.Y3 events are stabilized, so that many contracts each year | CU22: =SUMIFS($D22:$BZ22,$D$1:$BZ$1,CU$9) -> 163 | CV22: =SUMIFS($D22:$BZ22,$D$1:$BZ$1,CV$9) -> 195 | CW22: =SUMIFS($D22:$BZ22,$D$1:$BZ$1,CW$9) -> 206 | CX22: =SUMIFS($D22:$BZ22,$D$1:$BZ$1,CX$9) -> 210
C23: % of Annual Contracts | AH23: {=INDEX('Date Booked Summary'!$T$19:$T$30,MATCH(AH2,'Date Booked Summary'!$S$19:$S$30,0))} -> 0.1 | AI23: {=INDEX('Date Booked Summary'!$T$19:$T$30,MATCH(AI2,'Date Booked Summary'!$S$19:$S$30,0))} -> 0.14 | AJ23: {=INDEX('Date Booked Summary'!$T$19:$T$30,MATCH(AJ2,'Date Booked Summary'!$S$19:$S$30,0))} -> 0.12 | AK23: {=INDEX('Date Booked Summary'!$T$19:$T$30,MATCH(AK2,'Date Booked Summary'!$S$19:$S$30,0))} -> 0.08 | AL23: {=INDEX('Date Booked Summary'!$T$19:$T$30,MATCH(AL2,'Date Booked Summary'!$S$19:$S$30,0))} -> 0.06 | AM23: {=INDEX('Date Booked Summary'!$T$19:$T$30,MATCH(AM2,'Date Booked Summary'!$S$19:$S$30,0))} -> 0.07 | AN23: {=INDEX('Date Booked Summary'!$T$19:$T$30,MATCH(AN2,'Date Booked Summary'!$S$19:$S$30,0))} -> 0.04 | AO23: {=INDEX('Date Booked Summary'!$T$19:$T$30,MATCH(AO2,'Date Booked Summary'!$S$19:$S$30,0))} -> 0.11 | ... BQ23: {=INDEX('Date Booked Summary'!$T$19:$T$30,MATCH(BQ2,'Date Booked Summary'!$S$19:$S$30,0))} -> 0.07 | BS23: {=INDEX('Date Booked Summary'!$T$19:$T$30,MATCH(BS2,'Date Booked Summary'!$S$19:$S$30,0))} -> 0.1 | BT23: {=INDEX('Date Booked Summary'!$T$19:$T$30,MATCH(BT2,'Date Booked Summary'!$S$19:$S$30,0))} -> 0.14 | BU23: {=INDEX('Date Booked Summary'!$T$19:$T$30,MATCH(BU2,'Date Booked Summary'!$S$19:$S$30,0))} -> 0.12 | BV23: {=INDEX('Date Booked Summary'!$T$19:$T$30,MATCH(BV2,'Date Booked Summary'!$S$19:$S$30,0))} -> 0.08 | BW23: {=INDEX('Date Booked Summary'!$T$19:$T$30,MATCH(BW2,'Date Booked Summary'!$S$19:$S$30,0))} -> 0.06 | BX23: {=INDEX('Date Booked Summary'!$T$19:$T$30,MATCH(BX2,'Date Booked Summary'!$S$19:$S$30,0))} -> 0.07 | BY23: {=INDEX('Date Booked Summary'!$T$19:$T$30,MATCH(BY2,'Date Booked Summary'!$S$19:$S$30,0))} -> 0.04 | CD23: =CD22/CD11 -> 0.12616202 | CE23: =CE22/CE11 -> 0.12650221 | CF23: =CF22/CF11 -> 0.12650602
C25: Original - Barn | D25: {=IFERROR(INDEX('Events Summary'!$D:$D,MATCH(D$9,'Events Summary'!$C:$C,0)),0)} -> 0 | E25: {=IFERROR(INDEX('Events Summary'!$D:$D,MATCH(E$9,'Events Summary'!$C:$C,0)),0)} -> 0 | F25: {=IFERROR(INDEX('Events Summary'!$D:$D,MATCH(F$9,'Events Summary'!$C:$C,0)),0)} -> 5 | G25: {=IFERROR(INDEX('Events Summary'!$D:$D,MATCH(G$9,'Events Summary'!$C:$C,0)),0)} -> 8 | H25: {=IFERROR(INDEX('Events Summary'!$D:$D,MATCH(H$9,'Events Summary'!$C:$C,0)),0)} -> 5 | I25: {=IFERROR(INDEX('Events Summary'!$D:$D,MATCH(I$9,'Events Summary'!$C:$C,0)),0)} -> 3 | J25: {=IFERROR(INDEX('Events Summary'!$D:$D,MATCH(J$9,'Events Summary'!$C:$C,0)),0)} -> 0 | K25: {=IFERROR(INDEX('Events Summary'!$D:$D,MATCH(K$9,'Events Summary'!$C:$C,0)),0)} -> 3 | ... AF25: {=IFERROR(INDEX('Events Summary'!$D:$D,MATCH(AF$9,'Events Summary'!$C:$C,0)),0)} -> 7 | AH25: {=IFERROR(INDEX('Events Summary'!$D:$D,MATCH(AH$9,'Events Summary'!$C:$C,0)),0)} -> 2 | AI25: {=IFERROR(INDEX('Events Summary'!$D:$D,MATCH(AI$9,'Events Summary'!$C:$C,0)),0)} -> 1 | AJ25: {=IFERROR(INDEX('Events Summary'!$D:$D,MATCH(AJ$9,'Events Summary'!$C:$C,0)),0)} -> 3 | AK25: {=IFERROR(INDEX('Events Summary'!$D:$D,MATCH(AK$9,'Events Summary'!$C:$C,0)),0)} -> 8 | AL25: {=IFERROR(INDEX('Events Summary'!$D:$D,MATCH(AL$9,'Events Summary'!$C:$C,0)),0)} -> 11 | AM25: {=IFERROR(INDEX('Events Summary'!$D:$D,MATCH(AM$9,'Events Summary'!$C:$C,0)),0)} -> 2 | AN25: {=IFERROR(INDEX('Events Summary'!$D:$D,MATCH(AN$9,'Events Summary'!$C:$C,0)),0)} -> 0 | AO25: {=IFERROR(INDEX('Events Summary'!$D:$D,MATCH(AO$9,'Events Summary'!$C:$C,0)),0)} -> 0 | ... BQ25: {=IFERROR(INDEX('Events Summary'!$D:$D,MATCH(BQ$9,'Events Summary'!$C:$C,0)),0)} -> 0 | BS25: {=IFERROR(INDEX('Events Summary'!$D:$D,MATCH(BS$9,'Events Summary'!$C:$C,0)),0)} -> 0 | BT25: {=IFERROR(INDEX('Events Summary'!$D:$D,MATCH(BT$9,'Events Summary'!$C:$C,0)),0)} -> 0 | BU25: {=IFERROR(INDEX('Events Summary'!$D:$D,MATCH(BU$9,'Events Summary'!$C:$C,0)),0)} -> 0 | BV25: {=IFERROR(INDEX('Events Summary'!$D:$D,MATCH(BV$9,'Events Summary'!$C:$C,0)),0)} -> 0 | BW25: {=IFERROR(INDEX('Events Summary'!$D:$D,MATCH(BW$9,'Events Summary'!$C:$C,0)),0)} -> 0 | BX25: {=IFERROR(INDEX('Events Summary'!$D:$D,MATCH(BX$9,'Events Summary'!$C:$C,0)),0)} -> 0 | BY25: {=IFERROR(INDEX('Events Summary'!$D:$D,MATCH(BY$9,'Events Summary'!$C:$C,0)),0)} -> 0 | CA25: ='Revenue Analysis - Barn'!D11 -> 54 | CB25: ='Revenue Analysis - Barn'!E11 -> 47 | CC25: ='Revenue Analysis - Barn'!F11 -> 40 | CD25: ='Revenue Analysis - Barn'!G11 -> 35 | CE25: ='Revenue Analysis - Barn'!H11 -> 7 | CF25: ='Revenue Analysis - Barn'!I11 -> 0 | CU25: =SUMIFS($D25:$BZ25,$D$1:$BZ$1,CU$9) -> 39 | CV25: =SUMIFS($D25:$BZ25,$D$1:$BZ$1,CV$9) -> 15 | CW25: =SUMIFS($D25:$BZ25,$D$1:$BZ$1,CW$9) -> 0 | CX25: =SUMIFS($D25:$BZ25,$D$1:$BZ$1,CX$9) -> 0
C26: New - Barn | AN26: =AN27-AN25 -> 2 | AO26: =AO27-AO25 -> 0 | AP26: =AP27-AP25 -> 0 | AQ26: =AQ27-AQ25 -> 1 | AR26: =AR27-AR25 -> 6 | AS26: =AS27-AS25 -> 6 | AT26: =AT27-AT25 -> 6 | AU26: =AU27-AU25 -> 4 | ... BQ26: =BQ27-BQ25 -> 11 | BS26: =BS27-BS25 -> 8 | BT26: =BT27-BT25 -> 4 | BU26: =BU27-BU25 -> 7 | BV26: =BV27-BV25 -> 9 | BW26: =BW27-BW25 -> 11 | BX26: =BX27-BX25 -> 6 | BY26: =BY27-BY25 -> 2 | CD26: ='Revenue Analysis - Barn'!G12 -> 15 | CE26: ='Revenue Analysis - Barn'!H12 -> 53 | CF26: ='Revenue Analysis - Barn'!I12 -> 70 | CU26: =SUMIFS($D26:$BZ26,$D$1:$BZ$1,CU$9) -> 2 | CV26: =SUMIFS($D26:$BZ26,$D$1:$BZ$1,CV$9) -> 47 | CW26: =SUMIFS($D26:$BZ26,$D$1:$BZ$1,CW$9) -> 66 | CX26: =SUMIFS($D26:$BZ26,$D$1:$BZ$1,CX$9) -> 70
C27: Events - Barn | D27: =SUM(D25:D26) -> 0 | E27: =SUM(E25:E26) -> 0 | F27: =SUM(F25:F26) -> 5 | G27: =SUM(G25:G26) -> 8 | H27: =SUM(H25:H26) -> 5 | I27: =SUM(I25:I26) -> 3 | J27: =SUM(J25:J26) -> 0 | K27: =SUM(K25:K26) -> 3 | ... AF27: =SUM(AF25:AF26) -> 7 | AH27: =AH25 -> 2 | AI27: =AI25 -> 1 | AJ27: =AJ25 -> 3 | AK27: =AK25 -> 8 | AL27: =AL25 -> 11 | AM27: =AM25 -> 2 | AN27: 2 | AO27: =ROUND(($CD$27-SUM($AH$27:$AM$27))*(AB33/SUM($AA$33:$AF$33)),0) -> 0 | AP27: =ROUND(($CD$27-SUM($AH$27:$AM$27))*(AC33/SUM($AA$33:$AF$33)),0) -> 0 | AQ27: =ROUND(($CD$27-SUM($AH$27:$AM$27))*(AD33/SUM($AA$33:$AF$33)),0) -> 2 | AR27: =ROUND(($CD$27-SUM($AH$27:$AM$27))*(AE33/SUM($AA$33:$AF$33)),0) -> 8 | AS27: =ROUND(($CD$27-SUM($AH$27:$AM$27))*(AF33/SUM($AA$33:$AF$33)),0) -> 11 | AT27: {=ROUND(INDEX('Events Summary'!$AF:$AF,MATCH(AT$2,'Events Summary'!$AE:$AE,0))*SUMIFS($CD27:$CF27,$CD$2:$CF$2,AT$3),0)} -> 7 | AU27: {=ROUND(INDEX('Events Summary'!$AF:$AF,MATCH(AU$2,'Events Summary'!$AE:$AE,0))*SUMIFS($CD27:$CF27,$CD$2:$CF$2,AU$3),0)} -> 4 | AV27: {=ROUND(INDEX('Events Summary'!$AF:$AF,MATCH(AV$2,'Events Summary'!$AE:$AE,0))*SUMIFS($CD27:$CF27,$CD$2:$CF$2,AV$3),0)} -> 6 | AW27: {=ROUND(INDEX('Events Summary'!$AF:$AF,MATCH(AW$2,'Events Summary'!$AE:$AE,0))*SUMIFS($CD27:$CF27,$CD$2:$CF$2,AW$3),0)} -> 8 | AX27: {=ROUND(INDEX('Events Summary'!$AF:$AF,MATCH(AX$2,'Events Summary'!$AE:$AE,0))*SUMIFS($CD27:$CF27,$CD$2:$CF$2,AX$3),0)} -> 9 | AY27: {=ROUND(INDEX('Events Summary'!$AF:$AF,MATCH(AY$2,'Events Summary'!$AE:$AE,0))*SUMIFS($CD27:$CF27,$CD$2:$CF$2,AY$3),0)} -> 5 | AZ27: {=ROUND(INDEX('Events Summary'!$AF:$AF,MATCH(AZ$2,'Events Summary'!$AE:$AE,0))*SUMIFS($CD27:$CF27,$CD$2:$CF$2,AZ$3),0)} -> 2 | BA27: {=ROUND(INDEX('Events Summary'!$AF:$AF,MATCH(BA$2,'Events Summary'!$AE:$AE,0))*SUMIFS($CD27:$CF27,$CD$2:$CF$2,BA$3),0)} -> 0 | ... BK27: {=ROUND(INDEX('Events Summary'!$AF:$AF,MATCH(BK$2,'Events Summary'!$AE:$AE,0))*SUMIFS($CD27:$CF27,$CD$2:$CF$2,BK$3),0)} -> 6 | BL27: 2 | BM27: {=ROUND(INDEX('Events Summary'!$AF:$AF,MATCH(BM$2,'Events Summary'!$AE:$AE,0))*SUMIFS($CD27:$CF27,$CD$2:$CF$2,BM$3),0)} -> 0 | BN27: {=ROUND(INDEX('Events Summary'!$AF:$AF,MATCH(BN$2,'Events Summary'!$AE:$AE,0))*SUMIFS($CD27:$CF27,$CD$2:$CF$2,BN$3),0)} -> 0 | BO27: {=ROUND(INDEX('Events Summary'!$AF:$AF,MATCH(BO$2,'Events Summary'!$AE:$AE,0))*SUMIFS($CD27:$CF27,$CD$2:$CF$2,BO$3),0)} -> 4 | BP27: {=ROUND(INDEX('Events Summary'!$AF:$AF,MATCH(BP$2,'Events Summary'!$AE:$AE,0))*SUMIFS($CD27:$CF27,$CD$2:$CF$2,BP$3),0)} -> 8 | BQ27: {=ROUND(INDEX('Events Summary'!$AF:$AF,MATCH(BQ$2,'Events Summary'!$AE:$AE,0))*SUMIFS($CD27:$CF27,$CD$2:$CF$2,BQ$3),0)} -> 11 | BS27: =BF27 -> 8 | BT27: =BG27 -> 4 | BU27: =BH27 -> 7 | BV27: =BI27 -> 9 | BW27: =BJ27 -> 11 | BX27: =BK27 -> 6 | BY27: =BL27 -> 2 | CA27: =SUM(CA25:CA26) -> 54 | CB27: =SUM(CB25:CB26) -> 47 | CC27: =SUM(CC25:CC26) -> 40 | CD27: =SUM(CD25:CD26) -> 50 | CE27: =SUM(CE25:CE26) -> 60 | CF27: =SUM(CF25:CF26) -> 70 | CR27: See Revenue Analysis - Barn | CU27: =SUM(CU25:CU26) -> 41 | CV27: =SUM(CV25:CV26) -> 62 | CW27: =SUM(CW25:CW26) -> 66 | CX27: =SUM(CX25:CX26) -> 70
C29: Original - Chapel | D29: {=IFERROR(INDEX('Events Summary'!$H:$H,MATCH(D$9,'Events Summary'!$C:$C,0)),0)} -> 0 | E29: {=IFERROR(INDEX('Events Summary'!$H:$H,MATCH(E$9,'Events Summary'!$C:$C,0)),0)} -> 0 | F29: {=IFERROR(INDEX('Events Summary'!$H:$H,MATCH(F$9,'Events Summary'!$C:$C,0)),0)} -> 0 | G29: {=IFERROR(INDEX('Events Summary'!$H:$H,MATCH(G$9,'Events Summary'!$C:$C,0)),0)} -> 12 | H29: {=IFERROR(INDEX('Events Summary'!$H:$H,MATCH(H$9,'Events Summary'!$C:$C,0)),0)} -> 12 | I29: {=IFERROR(INDEX('Events Summary'!$H:$H,MATCH(I$9,'Events Summary'!$C:$C,0)),0)} -> 13 | J29: {=IFERROR(INDEX('Events Summary'!$H:$H,MATCH(J$9,'Events Summary'!$C:$C,0)),0)} -> 7 | K29: {=IFERROR(INDEX('Events Summary'!$H:$H,MATCH(K$9,'Events Summary'!$C:$C,0)),0)} -> 13 | ... AF29: {=IFERROR(INDEX('Events Summary'!$H:$H,MATCH(AF$9,'Events Summary'!$C:$C,0)),0)} -> 15 | AH29: {=IFERROR(INDEX('Events Summary'!$H:$H,MATCH(AH$9,'Events Summary'!$C:$C,0)),0)} -> 10 | AI29: {=IFERROR(INDEX('Events Summary'!$H:$H,MATCH(AI$9,'Events Summary'!$C:$C,0)),0)} -> 9 | AJ29: {=IFERROR(INDEX('Events Summary'!$H:$H,MATCH(AJ$9,'Events Summary'!$C:$C,0)),0)} -> 12 | AK29: {=IFERROR(INDEX('Events Summary'!$H:$H,MATCH(AK$9,'Events Summary'!$C:$C,0)),0)} -> 11 | AL29: {=IFERROR(INDEX('Events Summary'!$H:$H,MATCH(AL$9,'Events Summary'!$C:$C,0)),0)} -> 13 | AM29: {=IFERROR(INDEX('Events Summary'!$H:$H,MATCH(AM$9,'Events Summary'!$C:$C,0)),0)} -> 10 | AN29: {=IFERROR(INDEX('Events Summary'!$H:$H,MATCH(AN$9,'Events Summary'!$C:$C,0)),0)} -> 2 | AO29: {=IFERROR(INDEX('Events Summary'!$H:$H,MATCH(AO$9,'Events Summary'!$C:$C,0)),0)} -> 0 | ... BQ29: {=IFERROR(INDEX('Events Summary'!$H:$H,MATCH(BQ$9,'Events Summary'!$C:$C,0)),0)} -> 0 | BS29: {=IFERROR(INDEX('Events Summary'!$H:$H,MATCH(BS$9,'Events Summary'!$C:$C,0)),0)} -> 0 | BT29: {=IFERROR(INDEX('Events Summary'!$H:$H,MATCH(BT$9,'Events Summary'!$C:$C,0)),0)} -> 0 | BU29: {=IFERROR(INDEX('Events Summary'!$H:$H,MATCH(BU$9,'Events Summary'!$C:$C,0)),0)} -> 0 | BV29: {=IFERROR(INDEX('Events Summary'!$H:$H,MATCH(BV$9,'Events Summary'!$C:$C,0)),0)} -> 0 | BW29: {=IFERROR(INDEX('Events Summary'!$H:$H,MATCH(BW$9,'Events Summary'!$C:$C,0)),0)} -> 0 | BX29: {=IFERROR(INDEX('Events Summary'!$H:$H,MATCH(BX$9,'Events Summary'!$C:$C,0)),0)} -> 0 | BY29: {=IFERROR(INDEX('Events Summary'!$H:$H,MATCH(BY$9,'Events Summary'!$C:$C,0)),0)} -> 0 | CA29: ='Revenue Analysis - Chapel'!D11 -> 99 | CB29: ='Revenue Analysis - Chapel'!E11 -> 86 | CC29: ='Revenue Analysis - Chapel'!F11 -> 91 | CD29: ='Revenue Analysis - Chapel'!G11 -> 87 | CE29: ='Revenue Analysis - Chapel'!H11 -> 23 | CF29: ='Revenue Analysis - Chapel'!I11 -> 0 | CU29: =SUMIFS($D29:$BZ29,$D$1:$BZ$1,CU$9) -> 98 | CV29: =SUMIFS($D29:$BZ29,$D$1:$BZ$1,CV$9) -> 43 | CW29: =SUMIFS($D29:$BZ29,$D$1:$BZ$1,CW$9) -> 0 | CX29: =SUMIFS($D29:$BZ29,$D$1:$BZ$1,CX$9) -> 0
C30: New - Chapel | AN30: =AN31-AN29 -> 1 | AO30: =AO31-AO29 -> 0 | AP30: =AP31-AP29 -> 0 | AQ30: =AQ31-AQ29 -> 4 | AR30: =AR31-AR29 -> 5 | AS30: =AS31-AS29 -> 3 | AT30: =AT31-AT29 -> 1 | AU30: =AU31-AU29 -> 4 | ... BQ30: =BQ31-BQ29 -> 15 | BS30: =BS31-BS29 -> 11 | BT30: =BT31-BT29 -> 6 | BU30: =BU31-BU29 -> 10 | BV30: =BV31-BV29 -> 13 | BW30: =BW31-BW29 -> 15 | BX30: =BX31-BX29 -> 9 | BY30: =BY31-BY29 -> 4 | CD30: ='Revenue Analysis - Chapel'!G12 -> 13 | CE30: ='Revenue Analysis - Chapel'!H12 -> 77 | CF30: ='Revenue Analysis - Chapel'!I12 -> 100 | CU30: =SUMIFS($D30:$BZ30,$D$1:$BZ$1,CU$9) -> 1 | CV30: =SUMIFS($D30:$BZ30,$D$1:$BZ$1,CV$9) -> 57 | CW30: =SUMIFS($D30:$BZ30,$D$1:$BZ$1,CW$9) -> 100 | CX30: =SUMIFS($D30:$BZ30,$D$1:$BZ$1,CX$9) -> 100
C31: Events - Chapel | D31: =SUM(D29:D30) -> 0 | E31: =SUM(E29:E30) -> 0 | F31: =SUM(F29:F30) -> 0 | G31: =SUM(G29:G30) -> 12 | H31: =SUM(H29:H30) -> 12 | I31: =SUM(I29:I30) -> 13 | J31: =SUM(J29:J30) -> 7 | K31: =SUM(K29:K30) -> 13 | ... AF31: =SUM(AF29:AF30) -> 15 | AH31: =AH29 -> 10 | AI31: =AI29 -> 9 | AJ31: =AJ29 -> 12 | AK31: =AK29 -> 11 | AL31: =AL29 -> 13 | AM31: =AM29 -> 10 | AN31: =ROUND(($CD$31-SUM($AH$31:$AM$31))*(AA$33/SUM($AA$33:$AF$33)),0) -> 3 | AO31: =ROUND(($CD$31-SUM($AH$31:$AM$31))*(AB$33/SUM($AA$33:$AF$33)),0) -> 0 | AP31: =ROUND(($CD$31-SUM($AH$31:$AM$31))*(AC$33/SUM($AA$33:$AF$33)),0) -> 0 | AQ31: =ROUND(($CD$31-SUM($AH$31:$AM$31))*(AD$33/SUM($AA$33:$AF$33)),0) -> 4 | AR31: =ROUND(($CD$31-SUM($AH$31:$AM$31))*(AE$33/SUM($AA$33:$AF$33)),0) -> 12 | AS31: =ROUND(($CD$31-SUM($AH$31:$AM$31))*(AF$33/SUM($AA$33:$AF$33)),0) -> 16 | AT31: {=ROUND(INDEX('Events Summary'!$AF:$AF,MATCH(AT$2,'Events Summary'!$AE:$AE,0))*SUMIFS($CD31:$CF31,$CD$2:$CF$2,AT$3),0)} -> 11 | AU31: {=ROUND(INDEX('Events Summary'!$AF:$AF,MATCH(AU$2,'Events Summary'!$AE:$AE,0))*SUMIFS($CD31:$CF31,$CD$2:$CF$2,AU$3),0)} -> 6 | AV31: {=ROUND(INDEX('Events Summary'!$AF:$AF,MATCH(AV$2,'Events Summary'!$AE:$AE,0))*SUMIFS($CD31:$CF31,$CD$2:$CF$2,AV$3),0)} -> 10 | AW31: {=ROUND(INDEX('Events Summary'!$AF:$AF,MATCH(AW$2,'Events Summary'!$AE:$AE,0))*SUMIFS($CD31:$CF31,$CD$2:$CF$2,AW$3),0)} -> 13 | AX31: {=ROUND(INDEX('Events Summary'!$AF:$AF,MATCH(AX$2,'Events Summary'!$AE:$AE,0))*SUMIFS($CD31:$CF31,$CD$2:$CF$2,AX$3),0)} -> 15 | AY31: {=ROUND(INDEX('Events Summary'!$AF:$AF,MATCH(AY$2,'Events Summary'!$AE:$AE,0))*SUMIFS($CD31:$CF31,$CD$2:$CF$2,AY$3),0)} -> 9 | AZ31: {=ROUND(INDEX('Events Summary'!$AF:$AF,MATCH(AZ$2,'Events Summary'!$AE:$AE,0))*SUMIFS($CD31:$CF31,$CD$2:$CF$2,AZ$3),0)} -> 4 | BA31: {=ROUND(INDEX('Events Summary'!$AF:$AF,MATCH(BA$2,'Events Summary'!$AE:$AE,0))*SUMIFS($CD31:$CF31,$CD$2:$CF$2,BA$3),0)} -> 0 | ... BQ31: {=ROUND(INDEX('Events Summary'!$AF:$AF,MATCH(BQ$2,'Events Summary'!$AE:$AE,0))*SUMIFS($CD31:$CF31,$CD$2:$CF$2,BQ$3),0)} -> 15 | BS31: =BF31 -> 11 | BT31: =BG31 -> 6 | BU31: =BH31 -> 10 | BV31: =BI31 -> 13 | BW31: =BJ31 -> 15 | BX31: =BK31 -> 9 | BY31: =BL31 -> 4 | CA31: =SUM(CA29:CA30) -> 99 | CB31: =SUM(CB29:CB30) -> 86 | CC31: =SUM(CC29:CC30) -> 91 | CD31: =SUM(CD29:CD30) -> 100 | CE31: =SUM(CE29:CE30) -> 100 | CF31: =SUM(CF29:CF30) -> 100 | CR31: See Revenue Analysis - Chapel | CU31: =SUM(CU29:CU30) -> 99 | CV31: =SUM(CV29:CV30) -> 100 | CW31: =SUM(CW29:CW30) -> 100 | CX31: =SUM(CX29:CX30) -> 100
C33: Original - B&C | D33: =D25+D29 -> 0 | E33: =E25+E29 -> 0 | F33: =F25+F29 -> 5 | G33: =G25+G29 -> 20 | H33: =H25+H29 -> 17 | I33: =I25+I29 -> 16 | J33: =J25+J29 -> 7 | K33: =K25+K29 -> 16 | ... AF33: =AF25+AF29 -> 22 | AH33: =AH25+AH29 -> 12 | AI33: =AI25+AI29 -> 10 | AJ33: =AJ25+AJ29 -> 15 | AK33: =AK25+AK29 -> 19 | AL33: =AL25+AL29 -> 24 | AM33: =AM25+AM29 -> 12 | AN33: =AN25+AN29 -> 2 | AO33: =AO25+AO29 -> 0 | ... BQ33: =BQ25+BQ29 -> 0 | BS33: =BS25+BS29 -> 0 | BT33: =BT25+BT29 -> 0 | BU33: =BU25+BU29 -> 0 | BV33: =BV25+BV29 -> 0 | BW33: =BW25+BW29 -> 0 | BX33: =BX25+BX29 -> 0 | BY33: =BY25+BY29 -> 0 | CA33: =CA25+CA29 -> 153 | CB33: =CB25+CB29 -> 133 | CC33: =CC25+CC29 -> 131 | CD33: =CD25+CD29 -> 122 | CE33: =CE25+CE29 -> 30 | CF33: =CF25+CF29 -> 0 | CU33: =SUMIFS($D33:$BZ33,$D$1:$BZ$1,CU$9) -> 137 | CV33: =SUMIFS($D33:$BZ33,$D$1:$BZ$1,CV$9) -> 58 | CW33: =SUMIFS($D33:$BZ33,$D$1:$BZ$1,CW$9) -> 0 | CX33: =SUMIFS($D33:$BZ33,$D$1:$BZ$1,CX$9) -> 0
C34: New - B&C | AH34: =AH26+AH30 -> 0 | AI34: =AI26+AI30 -> 0 | AJ34: =AJ26+AJ30 -> 0 | AK34: =AK26+AK30 -> 0 | AL34: =AL26+AL30 -> 0 | AM34: =AM26+AM30 -> 0 | AN34: =AN26+AN30 -> 3 | AO34: =AO26+AO30 -> 0 | ... BQ34: =BQ26+BQ30 -> 26 | BS34: =BS26+BS30 -> 19 | BT34: =BT26+BT30 -> 10 | BU34: =BU26+BU30 -> 17 | BV34: =BV26+BV30 -> 22 | BW34: =BW26+BW30 -> 26 | BX34: =BX26+BX30 -> 15 | BY34: =BY26+BY30 -> 6 | CA34: =CA26+CA30 -> 0 | CB34: =CB26+CB30 -> 0 | CC34: =CC26+CC30 -> 0 | CD34: =CD26+CD30 -> 28 | CE34: =CE26+CE30 -> 130 | CF34: =CF26+CF30 -> 170 | CU34: =SUMIFS($D34:$BZ34,$D$1:$BZ$1,CU$9) -> 3 | CV34: =SUMIFS($D34:$BZ34,$D$1:$BZ$1,CV$9) -> 104 | CW34: =SUMIFS($D34:$BZ34,$D$1:$BZ$1,CW$9) -> 166 | CX34: =SUMIFS($D34:$BZ34,$D$1:$BZ$1,CX$9) -> 170
C35: Events - B&C | D35: =SUM(D33:D34) -> 0 | E35: =SUM(E33:E34) -> 0 | F35: =SUM(F33:F34) -> 5 | G35: =SUM(G33:G34) -> 20 | H35: =SUM(H33:H34) -> 17 | I35: =SUM(I33:I34) -> 16 | J35: =SUM(J33:J34) -> 7 | K35: =SUM(K33:K34) -> 16 | ... AF35: =SUM(AF33:AF34) -> 22 | AH35: =SUM(AH33:AH34) -> 12 | AI35: =SUM(AI33:AI34) -> 10 | AJ35: =SUM(AJ33:AJ34) -> 15 | AK35: =SUM(AK33:AK34) -> 19 | AL35: =SUM(AL33:AL34) -> 24 | AM35: =SUM(AM33:AM34) -> 12 | AN35: =SUM(AN33:AN34) -> 5 | AO35: =SUM(AO33:AO34) -> 0 | ... BQ35: =SUM(BQ33:BQ34) -> 26 | BS35: =SUM(BS33:BS34) -> 19 | BT35: =SUM(BT33:BT34) -> 10 | BU35: =SUM(BU33:BU34) -> 17 | BV35: =SUM(BV33:BV34) -> 22 | BW35: =SUM(BW33:BW34) -> 26 | BX35: =SUM(BX33:BX34) -> 15 | BY35: =SUM(BY33:BY34) -> 6 | CA35: =SUM(CA33:CA34) -> 153 | CB35: =SUM(CB33:CB34) -> 133 | CC35: =SUM(CC33:CC34) -> 131 | CD35: =SUM(CD33:CD34) -> 150 | CE35: =SUM(CE33:CE34) -> 160 | CF35: =SUM(CF33:CF34) -> 170 | CL35: =CC35 -> 131 | CN35: ='Revenue Analysis - Total'!P13 -> 1614 | CU35: =SUM(CU33:CU34) -> 140 | CV35: =SUM(CV33:CV34) -> 162 | CW35: =SUM(CW33:CW34) -> 166 | CX35: =SUM(CX33:CX34) -> 170
C36: % of Annual Events | AH36: =AH35/SUMIFS($CD$35:$CF$35,$CD$2:$CF$2,AH$3) -> 0.08 | AI36: =AI35/SUMIFS($CD$35:$CF$35,$CD$2:$CF$2,AI$3) -> 0.066666667 | AJ36: =AJ35/SUMIFS($CD$35:$CF$35,$CD$2:$CF$2,AJ$3) -> 0.1 | AK36: =AK35/SUMIFS($CD$35:$CF$35,$CD$2:$CF$2,AK$3) -> 0.12666667 | AL36: =AL35/SUMIFS($CD$35:$CF$35,$CD$2:$CF$2,AL$3) -> 0.16 | AM36: =AM35/SUMIFS($CD$35:$CF$35,$CD$2:$CF$2,AM$3) -> 0.08 | AN36: =AN35/SUMIFS($CD$35:$CF$35,$CD$2:$CF$2,AN$3) -> 0.033333333 | AO36: =AO35/SUMIFS($CD$35:$CF$35,$CD$2:$CF$2,AO$3) -> 0 | ... BQ36: =BQ35/SUMIFS($CD$35:$CF$35,$CD$2:$CF$2,BQ$3) -> 0.15294118
C38: Original - Elopements | D38: {=IFERROR(INDEX('Events Summary'!$P:$P,MATCH(D$9,'Events Summary'!$C:$C,0)),0)} -> 0 | E38: {=IFERROR(INDEX('Events Summary'!$P:$P,MATCH(E$9,'Events Summary'!$C:$C,0)),0)} -> 0 | F38: {=IFERROR(INDEX('Events Summary'!$P:$P,MATCH(F$9,'Events Summary'!$C:$C,0)),0)} -> 0 | G38: {=IFERROR(INDEX('Events Summary'!$P:$P,MATCH(G$9,'Events Summary'!$C:$C,0)),0)} -> 1 | H38: {=IFERROR(INDEX('Events Summary'!$P:$P,MATCH(H$9,'Events Summary'!$C:$C,0)),0)} -> 1 | I38: {=IFERROR(INDEX('Events Summary'!$P:$P,MATCH(I$9,'Events Summary'!$C:$C,0)),0)} -> 2 | J38: {=IFERROR(INDEX('Events Summary'!$P:$P,MATCH(J$9,'Events Summary'!$C:$C,0)),0)} -> 1 | K38: {=IFERROR(INDEX('Events Summary'!$P:$P,MATCH(K$9,'Events Summary'!$C:$C,0)),0)} -> 1 | ... AF38: {=IFERROR(INDEX('Events Summary'!$P:$P,MATCH(AF$9,'Events Summary'!$C:$C,0)),0)} -> 5 | AH38: {=IFERROR(INDEX('Events Summary'!$P:$P,MATCH(AH$9,'Events Summary'!$C:$C,0)),0)} -> 4 | AI38: {=IFERROR(INDEX('Events Summary'!$P:$P,MATCH(AI$9,'Events Summary'!$C:$C,0)),0)} -> 0 | AJ38: {=IFERROR(INDEX('Events Summary'!$P:$P,MATCH(AJ$9,'Events Summary'!$C:$C,0)),0)} -> 2 | AK38: {=IFERROR(INDEX('Events Summary'!$P:$P,MATCH(AK$9,'Events Summary'!$C:$C,0)),0)} -> 5 | AL38: {=IFERROR(INDEX('Events Summary'!$P:$P,MATCH(AL$9,'Events Summary'!$C:$C,0)),0)} -> 6 | AM38: {=IFERROR(INDEX('Events Summary'!$P:$P,MATCH(AM$9,'Events Summary'!$C:$C,0)),0)} -> 1 | AN38: {=IFERROR(INDEX('Events Summary'!$P:$P,MATCH(AN$9,'Events Summary'!$C:$C,0)),0)} -> 0 | AO38: {=IFERROR(INDEX('Events Summary'!$P:$P,MATCH(AO$9,'Events Summary'!$C:$C,0)),0)} -> 0 | ... BQ38: {=IFERROR(INDEX('Events Summary'!$P:$P,MATCH(BQ$9,'Events Summary'!$C:$C,0)),0)} -> 0 | BS38: {=IFERROR(INDEX('Events Summary'!$P:$P,MATCH(BS$9,'Events Summary'!$C:$C,0)),0)} -> 0 | BT38: {=IFERROR(INDEX('Events Summary'!$P:$P,MATCH(BT$9,'Events Summary'!$C:$C,0)),0)} -> 0 | BU38: {=IFERROR(INDEX('Events Summary'!$P:$P,MATCH(BU$9,'Events Summary'!$C:$C,0)),0)} -> 0 | BV38: {=IFERROR(INDEX('Events Summary'!$P:$P,MATCH(BV$9,'Events Summary'!$C:$C,0)),0)} -> 0 | BW38: {=IFERROR(INDEX('Events Summary'!$P:$P,MATCH(BW$9,'Events Summary'!$C:$C,0)),0)} -> 0 | BX38: {=IFERROR(INDEX('Events Summary'!$P:$P,MATCH(BX$9,'Events Summary'!$C:$C,0)),0)} -> 0 | BY38: {=IFERROR(INDEX('Events Summary'!$P:$P,MATCH(BY$9,'Events Summary'!$C:$C,0)),0)} -> 0 | CA38: ='Events Summary'!$P$10 -> 22 | CB38: ='Events Summary'!$P$11 -> 39 | CC38: ='Events Summary'!$P$12 -> 40 | CD38: ='Events Summary'!$P$14 -> 18 | CE38: ='Events Summary'!$P$15 -> 0 | CF38: ='Events Summary'!$P$16 -> 0 | CU38: =SUMIFS($D38:$BZ38,$D$1:$BZ$1,CU$9) -> 27 | CV38: =SUMIFS($D38:$BZ38,$D$1:$BZ$1,CV$9) -> 0 | CW38: =SUMIFS($D38:$BZ38,$D$1:$BZ$1,CW$9) -> 0 | CX38: =SUMIFS($D38:$BZ38,$D$1:$BZ$1,CX$9) -> 0
C39: New - Elopements | AN39: =AN40-AN38 -> 0 | AO39: =AO40-AO38 -> 0 | AP39: =AP40-AP38 -> 0 | AQ39: =AQ40-AQ38 -> 2 | AR39: =AR40-AR38 -> 7 | AS39: =AS40-AS38 -> 12 | AT39: =AT40-AT38 -> 4 | AU39: =AU40-AU38 -> 2 | ... BQ39: =BQ40-BQ38 -> 6 | BS39: =BS40-BS38 -> 4 | BT39: =BT40-BT38 -> 2 | BU39: =BU40-BU38 -> 4 | BV39: =BV40-BV38 -> 5 | BW39: =BW40-BW38 -> 6 | BX39: =BX40-BX38 -> 4 | BY39: =BY40-BY38 -> 2 | CD39: 22 | CE39: 40 | CF39: 40 | CU39: =SUMIFS($D39:$BZ39,$D$1:$BZ$1,CU$9) -> 0 | CV39: =SUMIFS($D39:$BZ39,$D$1:$BZ$1,CV$9) -> 48 | CW39: =SUMIFS($D39:$BZ39,$D$1:$BZ$1,CW$9) -> 40 | CX39: =SUMIFS($D39:$BZ39,$D$1:$BZ$1,CX$9) -> 40
C40: Elopements | D40: =SUM(D38:D39) -> 0 | E40: =SUM(E38:E39) -> 0 | F40: =SUM(F38:F39) -> 0 | G40: =SUM(G38:G39) -> 1 | H40: =SUM(H38:H39) -> 1 | I40: =SUM(I38:I39) -> 2 | J40: =SUM(J38:J39) -> 1 | K40: =SUM(K38:K39) -> 1 | ... AF40: =SUM(AF38:AF39) -> 5 | AH40: =AH38 -> 4 | AI40: =AI38 -> 0 | AJ40: =AJ38 -> 2 | AK40: =AK38 -> 5 | AL40: =AL38 -> 6 | AM40: =AM38 -> 1 | AN40: =ROUND(($CD$40-SUM($AH$40:$AM$40))*(AA38/SUM($AA$38:$AF$38)),0) -> 0 | AO40: =ROUND(($CD$40-SUM($AH$40:$AM$40))*(AB38/SUM($AA$38:$AF$38)),0) -> 0 | AP40: =ROUND(($CD$40-SUM($AH$40:$AM$40))*(AC38/SUM($AA$38:$AF$38)),0) -> 0 | AQ40: =ROUND(($CD$40-SUM($AH$40:$AM$40))*(AD38/SUM($AA$38:$AF$38)),0) -> 2 | AR40: =ROUND(($CD$40-SUM($AH$40:$AM$40))*(AE38/SUM($AA$38:$AF$38)),0) -> 7 | AS40: =ROUND(($CD$40-SUM($AH$40:$AM$40))*(AF38/SUM($AA$38:$AF$38)),0) -> 12 | AT40: {=ROUND(INDEX('Events Summary'!$AF:$AF,MATCH(AT$2,'Events Summary'!$AE:$AE,0))*SUMIFS($CD40:$CF40,$CD$2:$CF$2,AT$3),0)} -> 4 | AU40: {=ROUND(INDEX('Events Summary'!$AF:$AF,MATCH(AU$2,'Events Summary'!$AE:$AE,0))*SUMIFS($CD40:$CF40,$CD$2:$CF$2,AU$3),0)} -> 2 | AV40: {=ROUND(INDEX('Events Summary'!$AF:$AF,MATCH(AV$2,'Events Summary'!$AE:$AE,0))*SUMIFS($CD40:$CF40,$CD$2:$CF$2,AV$3),0)} -> 4 | AW40: {=ROUND(INDEX('Events Summary'!$AF:$AF,MATCH(AW$2,'Events Summary'!$AE:$AE,0))*SUMIFS($CD40:$CF40,$CD$2:$CF$2,AW$3),0)} -> 5 | AX40: {=ROUND(INDEX('Events Summary'!$AF:$AF,MATCH(AX$2,'Events Summary'!$AE:$AE,0))*SUMIFS($CD40:$CF40,$CD$2:$CF$2,AX$3),0)} -> 6 | AY40: {=ROUND(INDEX('Events Summary'!$AF:$AF,MATCH(AY$2,'Events Summary'!$AE:$AE,0))*SUMIFS($CD40:$CF40,$CD$2:$CF$2,AY$3),0)} -> 4 | AZ40: {=ROUND(INDEX('Events Summary'!$AF:$AF,MATCH(AZ$2,'Events Summary'!$AE:$AE,0))*SUMIFS($CD40:$CF40,$CD$2:$CF$2,AZ$3),0)} -> 2 | BA40: {=ROUND(INDEX('Events Summary'!$AF:$AF,MATCH(BA$2,'Events Summary'!$AE:$AE,0))*SUMIFS($CD40:$CF40,$CD$2:$CF$2,BA$3),0)} -> 0 | ... BQ40: {=ROUND(INDEX('Events Summary'!$AF:$AF,MATCH(BQ$2,'Events Summary'!$AE:$AE,0))*SUMIFS($CD40:$CF40,$CD$2:$CF$2,BQ$3),0)} -> 6 | BS40: =BF40 -> 4 | BT40: =BG40 -> 2 | BU40: =BH40 -> 4 | BV40: =BI40 -> 5 | BW40: =BJ40 -> 6 | BX40: =BK40 -> 4 | BY40: =BL40 -> 2 | CA40: =SUM(CA38:CA39) -> 22 | CB40: =SUM(CB38:CB39) -> 39 | CC40: =SUM(CC38:CC39) -> 40 | CD40: =SUM(CD38:CD39) -> 40 | CE40: =SUM(CE38:CE39) -> 40 | CF40: =SUM(CF38:CF39) -> 40 | CR40: Assume 40 Annuallyly (conservative once we start pushing marketing here and possibly opening up to other days | CU40: =SUM(CU38:CU39) -> 27 | CV40: =SUM(CV38:CV39) -> 48 | CW40: =SUM(CW38:CW39) -> 40 | CX40: =SUM(CX38:CX39) -> 40
C42: Revenue
C43: Room Rental Revenue | D43: {=INDEX('Events Summary'!$M:$M,MATCH(D$9,'Events Summary'!$C:$C,0))/1000} -> 0 | E43: {=INDEX('Events Summary'!$M:$M,MATCH(E$9,'Events Summary'!$C:$C,0))/1000} -> 0 | F43: {=INDEX('Events Summary'!$M:$M,MATCH(F$9,'Events Summary'!$C:$C,0))/1000} -> 34.75 | G43: {=INDEX('Events Summary'!$M:$M,MATCH(G$9,'Events Summary'!$C:$C,0))/1000} -> 138.25 | H43: {=INDEX('Events Summary'!$M:$M,MATCH(H$9,'Events Summary'!$C:$C,0))/1000} -> 112.75 | I43: {=INDEX('Events Summary'!$M:$M,MATCH(I$9,'Events Summary'!$C:$C,0))/1000} -> 113.5 | J43: {=INDEX('Events Summary'!$M:$M,MATCH(J$9,'Events Summary'!$C:$C,0))/1000} -> 49 | K43: {=INDEX('Events Summary'!$M:$M,MATCH(K$9,'Events Summary'!$C:$C,0))/1000} -> 112.25 | ... AF43: {=INDEX('Events Summary'!$M:$M,MATCH(AF$9,'Events Summary'!$C:$C,0))/1000} -> 169.71 | AH43: =SUMIFS($CD43:$CF43,$CD$2:$CF$2,AH$3)*AH$36 -> 87.544743 | AI43: =SUMIFS($CD43:$CF43,$CD$2:$CF$2,AI$3)*AI$36 -> 72.953953 | AJ43: =SUMIFS($CD43:$CF43,$CD$2:$CF$2,AJ$3)*AJ$36 -> 109.43093 | AK43: =SUMIFS($CD43:$CF43,$CD$2:$CF$2,AK$3)*AK$36 -> 138.61251 | AL43: =SUMIFS($CD43:$CF43,$CD$2:$CF$2,AL$3)*AL$36 -> 175.08949 | AM43: =SUMIFS($CD43:$CF43,$CD$2:$CF$2,AM$3)*AM$36 -> 87.544743 | AN43: =SUMIFS($CD43:$CF43,$CD$2:$CF$2,AN$3)*AN$36 -> 36.476976 | AO43: =SUMIFS($CD43:$CF43,$CD$2:$CF$2,AO$3)*AO$36 -> 0 | ... BQ43: =SUMIFS($CD43:$CF43,$CD$2:$CF$2,BQ$3)*BQ$36 -> 166.607 | BS43: =BF43 -> 121.75127 | BT43: =BG43 -> 64.079616 | BU43: =BH43 -> 108.93535 | BV43: =BI43 -> 140.97516 | BW43: =BJ43 -> 166.607 | BX43: =BK43 -> 96.119424 | BY43: =BL43 -> 38.44777 | CA43: ='Revenue Analysis - Total'!D60+'Revenue Analysis - Total'!D75 -> 1050.35 | CB43: ='Revenue Analysis - Total'!E60+'Revenue Analysis - Total'!E75 -> 910 | CC43: ='Revenue Analysis - Total'!F60+'Revenue Analysis - Total'!F75 -> 899.75 | CD43: ='Revenue Analysis - Total'!G60+'Revenue Analysis - Total'!G75 -> 1094.3093 | CE43: ='Revenue Analysis - Total'!H60+'Revenue Analysis - Total'!H75 -> 1081.7756 | CF43: ='Revenue Analysis - Total'!I60+'Revenue Analysis - Total'!I75 -> 1089.3535 | CN43: =SUMIFS('FY25 By Venue Financials'!$J:$J,'FY25 By Venue Financials'!$A:$A,$C43) -> 8322.8813 | CR43: Annually - split monthly by seasonality | CU43: =SUMIFS($D43:$BZ43,$D$1:$BZ$1,CU$9) -> 1029.8633 | CV43: =SUMIFS($D43:$BZ43,$D$1:$BZ$1,CV$9) -> 1123.6156 | CW43: =SUMIFS($D43:$BZ43,$D$1:$BZ$1,CW$9) -> 1081.7316 | CX43: =SUMIFS($D43:$BZ43,$D$1:$BZ$1,CX$9) -> 1089.3535
C44: Elopement Revenue | D44: {=INDEX('Events Summary'!$Q:$Q,MATCH(D$9,'Events Summary'!$C:$C,0))/1000} -> 0 | E44: {=INDEX('Events Summary'!$Q:$Q,MATCH(E$9,'Events Summary'!$C:$C,0))/1000} -> 0 | F44: {=INDEX('Events Summary'!$Q:$Q,MATCH(F$9,'Events Summary'!$C:$C,0))/1000} -> 0 | G44: {=INDEX('Events Summary'!$Q:$Q,MATCH(G$9,'Events Summary'!$C:$C,0))/1000} -> 1.5 | H44: {=INDEX('Events Summary'!$Q:$Q,MATCH(H$9,'Events Summary'!$C:$C,0))/1000} -> 1.5 | I44: {=INDEX('Events Summary'!$Q:$Q,MATCH(I$9,'Events Summary'!$C:$C,0))/1000} -> 3 | J44: {=INDEX('Events Summary'!$Q:$Q,MATCH(J$9,'Events Summary'!$C:$C,0))/1000} -> 1.5 | K44: {=INDEX('Events Summary'!$Q:$Q,MATCH(K$9,'Events Summary'!$C:$C,0))/1000} -> 1.5 | ... AF44: {=INDEX('Events Summary'!$Q:$Q,MATCH(AF$9,'Events Summary'!$C:$C,0))/1000} -> 8.5 | AH44: =SUMIFS($CH44:$CJ44,$CH$1:$CJ$1,AH$3)*AH$40 -> 7 | AI44: =SUMIFS($CH44:$CJ44,$CH$1:$CJ$1,AI$3)*AI$40 -> 0 | AJ44: =SUMIFS($CH44:$CJ44,$CH$1:$CJ$1,AJ$3)*AJ$40 -> 3.5 | AK44: =SUMIFS($CH44:$CJ44,$CH$1:$CJ$1,AK$3)*AK$40 -> 8.75 | AL44: =SUMIFS($CH44:$CJ44,$CH$1:$CJ$1,AL$3)*AL$40 -> 10.5 | AM44: =SUMIFS($CH44:$CJ44,$CH$1:$CJ$1,AM$3)*AM$40 -> 1.75 | AN44: =SUMIFS($CH44:$CJ44,$CH$1:$CJ$1,AN$3)*AN$40 -> 0 | AO44: =SUMIFS($CH44:$CJ44,$CH$1:$CJ$1,AO$3)*AO$40 -> 0 | ... BQ44: =SUMIFS($CH44:$CJ44,$CH$1:$CJ$1,BQ$3)*BQ$40 -> 10.5 | BS44: =BF44 -> 7 | BT44: =BG44 -> 3.5 | BU44: =BH44 -> 7 | BV44: =BI44 -> 8.75 | BW44: =BJ44 -> 10.5 | BX44: =BK44 -> 7 | BY44: =BL44 -> 3.5 | CA44: =SUMIFS($D44:$BZ44,$D$1:$BZ$1,CA$2) -> 33 | CB44: =SUMIFS($D44:$BZ44,$D$1:$BZ$1,CB$2) -> 58.5 | CC44: =SUMIFS($P44:$AF44,$P$3:$AF$3,$CC$2) -> 67 | CD44: =SUMIFS($D44:$BZ44,$D$3:$BZ$3,CD$2) -> 68.25 | CE44: =SUMIFS($D44:$BZ44,$D$3:$BZ$3,CE$2) -> 70 | CF44: =SUMIFS($D44:$BZ44,$D$3:$BZ$3,CF$2) -> 70 | CH44: 1.75 | CI44: 1.75 | CJ44: 1.75 | CN44: =SUMIFS('FY25 By Venue Financials'!$J:$J,'FY25 By Venue Financials'!$A:$A,$C44) -> 0 | CR44: $ / elopement | CU44: =SUMIFS($D44:$BZ44,$D$1:$BZ$1,CU$9) -> 53 | CV44: =SUMIFS($D44:$BZ44,$D$1:$BZ$1,CV$9) -> 84 | CW44: =SUMIFS($D44:$BZ44,$D$1:$BZ$1,CW$9) -> 70 | CX44: =SUMIFS($D44:$BZ44,$D$1:$BZ$1,CX$9) -> 70
C45: All Inclusive Revenue | D45: =$CA45*D$35/SUM($D$35:$O$35) -> 0 | E45: =$CA45*E$35/SUM($D$35:$O$35) -> 0 | F45: =$CA45*F$35/SUM($D$35:$O$35) -> 7.7056533 | G45: =$CA45*G$35/SUM($D$35:$O$35) -> 30.822613 | H45: =$CA45*H$35/SUM($D$35:$O$35) -> 26.199221 | I45: =$CA45*I$35/SUM($D$35:$O$35) -> 24.65809 | J45: =$CA45*J$35/SUM($D$35:$O$35) -> 10.787915 | K45: =$CA45*K$35/SUM($D$35:$O$35) -> 24.65809 | ... O45: =$CA45*O$35/SUM($D$35:$O$35) -> 13.870176 | P45: =-P61+SUMIFS('All Inclusive Margin'!$C:$C,'All Inclusive Margin'!$E:$E,P$9)/1000 -> 10.13686 | Q45: =-Q61+SUMIFS('All Inclusive Margin'!$C:$C,'All Inclusive Margin'!$E:$E,Q$9)/1000 -> 24.61683 | R45: =-R61+SUMIFS('All Inclusive Margin'!$C:$C,'All Inclusive Margin'!$E:$E,R$9)/1000 -> 7.35358 | S45: =-S61+SUMIFS('All Inclusive Margin'!$C:$C,'All Inclusive Margin'!$E:$E,S$9)/1000 -> 17.79267 | T45: =-T61+SUMIFS('All Inclusive Margin'!$C:$C,'All Inclusive Margin'!$E:$E,T$9)/1000 -> 44.32618 | U45: =-U61+SUMIFS('All Inclusive Margin'!$C:$C,'All Inclusive Margin'!$E:$E,U$9)/1000 -> 63.79715 | V45: =-V61+SUMIFS('All Inclusive Margin'!$C:$C,'All Inclusive Margin'!$E:$E,V$9)/1000 -> 9.52739 | W45: =-W61+SUMIFS('All Inclusive Margin'!$C:$C,'All Inclusive Margin'!$E:$E,W$9)/1000 -> 13.29153 | ... AF45: =-AF61+SUMIFS('All Inclusive Margin'!$C:$C,'All Inclusive Margin'!$E:$E,AF$9)/1000 -> 18.76119 | AH45: =SUMIFS('Future Events'!$AG:$AG,'Future Events'!$D:$D,AH$9)/1000 -> 35.095 | AI45: =SUMIFS('Future Events'!$AG:$AG,'Future Events'!$D:$D,AI$9)/1000 -> 7.925 | AJ45: =SUMIFS('Future Events'!$AG:$AG,'Future Events'!$D:$D,AJ$9)/1000 -> 74.58 | AK45: =SUMIFS('Future Events'!$AG:$AG,'Future Events'!$D:$D,AK$9)/1000 -> 44.485 | AL45: =SUMIFS('Future Events'!$AG:$AG,'Future Events'!$D:$D,AL$9)/1000 -> 31.075 | AM45: =SUMIFS('Future Events'!$AG:$AG,'Future Events'!$D:$D,AM$9)/1000 -> 24.575 | AN45: =SUMIFS('Future Events'!$AG:$AG,'Future Events'!$D:$D,AN$9)/1000 -> 0.95 | AO45: =SUMIFS('Future Events'!$AG:$AG,'Future Events'!$D:$D,AO$9)/1000 -> 0 | ... BQ45: =SUMIFS('Future Events'!$AG:$AG,'Future Events'!$D:$D,BQ$9)/1000 -> 0 | BS45: =SUMIFS('Future Events'!$AG:$AG,'Future Events'!$D:$D,BS$9)/1000 -> 0 | BT45: =SUMIFS('Future Events'!$AG:$AG,'Future Events'!$D:$D,BT$9)/1000 -> 0 | BU45: =SUMIFS('Future Events'!$AG:$AG,'Future Events'!$D:$D,BU$9)/1000 -> 0 | BV45: =SUMIFS('Future Events'!$AG:$AG,'Future Events'!$D:$D,BV$9)/1000 -> 0 | BW45: =SUMIFS('Future Events'!$AG:$AG,'Future Events'!$D:$D,BW$9)/1000 -> 0 | BX45: =SUMIFS('Future Events'!$AG:$AG,'Future Events'!$D:$D,BX$9)/1000 -> 0 | BY45: =SUMIFS('Future Events'!$AG:$AG,'Future Events'!$D:$D,BY$9)/1000 -> 0 | CA45: 235.79299 | CB45: =SUMIFS($D45:$AF45,$D$1:$AF$1,CB$2) -> 359.86643 | CC45: =SUMIFS($P45:$AF45,$P$3:$AF$3,$CC$2) -> 325.50774 | CD45: =SUMIFS($D45:$BZ45,$D$3:$BZ$3,CD$2) -> 288.07 | CE45: =SUMIFS($D45:$BZ45,$D$3:$BZ$3,CE$2) -> 71.645 | CF45: =SUMIFS($D45:$BZ45,$D$3:$BZ$3,CF$2) -> 0 | CN45: =SUMIFS('FY25 By Venue Financials'!$J:$J,'FY25 By Venue Financials'!$A:$A,$C45) -> 0 | CR45: Annually - split monthly by seasonality | CU45: =SUMIFS($D45:$BZ45,$D$1:$BZ$1,CU$9) -> 262.98744 | CV45: =SUMIFS($D45:$BZ45,$D$1:$BZ$1,CV$9) -> 141.03 | CW45: =SUMIFS($D45:$BZ45,$D$1:$BZ$1,CW$9) -> 0 | CX45: =SUMIFS($D45:$BZ45,$D$1:$BZ$1,CX$9) -> 0
C46: Food Revenue | D46: 0 | E46: 0 | F46: 0 | G46: 0 | H46: 0 | I46: 0 | J46: 0 | K46: 0 | L46: 0 | M46: 0 | N46: 0 | O46: 0 | P46: 0 | Q46: 0 | R46: 0 | S46: 0 | T46: 0 | U46: 0 | V46: 0 | W46: 0 | X46: 0 | Y46: 0 | Z46: 0 | AA46: 0 | AB46: 0 | AC46: 0 | AD46: 0 | AE46: 0 | AF46: 0 | AH46: =SUMIFS($CD46:$CF46,$CD$2:$CF$2,AH$3)*AH$36 -> 16.26 | AI46: =SUMIFS($CD46:$CF46,$CD$2:$CF$2,AI$3)*AI$36 -> 13.55 | AJ46: =SUMIFS($CD46:$CF46,$CD$2:$CF$2,AJ$3)*AJ$36 -> 20.325 | AK46: =SUMIFS($CD46:$CF46,$CD$2:$CF$2,AK$3)*AK$36 -> 25.745 | AL46: =SUMIFS($CD46:$CF46,$CD$2:$CF$2,AL$3)*AL$36 -> 32.52 | AM46: =SUMIFS($CD46:$CF46,$CD$2:$CF$2,AM$3)*AM$36 -> 16.26 | AN46: =SUMIFS($CD46:$CF46,$CD$2:$CF$2,AN$3)*AN$36 -> 6.775 | AO46: =SUMIFS($CD46:$CF46,$CD$2:$CF$2,AO$3)*AO$36 -> 0 | ... BQ46: =SUMIFS($CD46:$CF46,$CD$2:$CF$2,BQ$3)*BQ$36 -> 117.43333 | BS46: =BF46 -> 85.816667 | BT46: =BG46 -> 45.166667 | BU46: =BH46 -> 76.783333 | BV46: =BI46 -> 99.366667 | BW46: =BJ46 -> 117.43333 | BX46: =BK46 -> 67.75 | BY46: =BL46 -> 27.1 | CA46: =SUMIFS($D46:$BZ46,$D$1:$BZ$1,CA$2) -> 0 | CB46: =SUMIFS($D46:$BZ46,$D$1:$BZ$1,CB$2) -> 0 | CC46: ='Revenue Analysis - Total'!F61+'Revenue Analysis - Total'!F76 -> 0 | CD46: ='Revenue Analysis - Total'!G61+'Revenue Analysis - Total'!G76 -> 203.25 | CE46: ='Revenue Analysis - Total'!H61+'Revenue Analysis - Total'!H76 -> 476.50833 | CF46: ='Revenue Analysis - Total'!I61+'Revenue Analysis - Total'!I76 -> 767.83333 | CN46: =SUMIFS('FY25 By Venue Financials'!$J:$J,'FY25 By Venue Financials'!$A:$A,$C46) -> 7969.7325 | CR46: Annually - split monthly by seasonality | CU46: =SUMIFS($D46:$BZ46,$D$1:$BZ$1,CU$9) -> 131.435 | CV46: =SUMIFS($D46:$BZ46,$D$1:$BZ$1,CV$9) -> 396.4363 | CW46: =SUMIFS($D46:$BZ46,$D$1:$BZ$1,CW$9) -> 671.3037 | CX46: =SUMIFS($D46:$BZ46,$D$1:$BZ$1,CX$9) -> 767.83333
C47: Beverage Revenue | D47: 0 | E47: 0 | F47: 0 | G47: 0 | H47: 0 | I47: 0 | J47: 0 | K47: 0 | L47: 0 | M47: 0 | N47: 0 | O47: 0 | P47: 0 | Q47: 0 | R47: 0 | S47: 0 | T47: 0 | U47: 0 | V47: 0 | W47: 0 | X47: 0 | Y47: 0 | Z47: 0 | AA47: 0 | AB47: 0 | AC47: 0 | AD47: 0 | AE47: 0 | AF47: 0 | AH47: 0 | AI47: 0 | AJ47: 0 | AK47: 0 | AL47: 0 | AM47: 0 | AN47: 0 | AO47: 0 | AP47: 0 | AQ47: 0 | AR47: 0 | AS47: 0 | AT47: 0 | AU47: 0 | AV47: 0 | AW47: 0 | AX47: 0 | AY47: 0 | AZ47: 0 | BA47: 0 | BB47: 0 | BC47: =SUMIFS($CD47:$CF47,$CD$2:$CF$2,BC$3)*(BC$36/SUM($BC$36:$BE$36)) -> 15.717602 | BD47: =SUMIFS($CD47:$CF47,$CD$2:$CF$2,BD$3)*(BD$36/SUM($BC$36:$BE$36)) -> 37.329304 | BE47: =SUMIFS($CD47:$CF47,$CD$2:$CF$2,BE$3)*(BE$36/SUM($BC$36:$BE$36)) -> 47.152806 | BF47: =SUMIFS($CD47:$CF47,$CD$2:$CF$2,BF$3)*BF$36 -> 58.578293 | BG47: =SUMIFS($CD47:$CF47,$CD$2:$CF$2,BG$3)*BG$36 -> 30.830681 | BH47: =SUMIFS($CD47:$CF47,$CD$2:$CF$2,BH$3)*BH$36 -> 52.412157 | BI47: =SUMIFS($CD47:$CF47,$CD$2:$CF$2,BI$3)*BI$36 -> 67.827497 | BJ47: =SUMIFS($CD47:$CF47,$CD$2:$CF$2,BJ$3)*BJ$36 -> 80.15977 | BK47: =SUMIFS($CD47:$CF47,$CD$2:$CF$2,BK$3)*BK$36 -> 46.246021 | BL47: =SUMIFS($CD47:$CF47,$CD$2:$CF$2,BL$3)*BL$36 -> 18.498408 | BM47: =SUMIFS($CD47:$CF47,$CD$2:$CF$2,BM$3)*BM$36 -> 0 | ... BQ47: =SUMIFS($CD47:$CF47,$CD$2:$CF$2,BQ$3)*BQ$36 -> 80.15977 | BS47: =BF47 -> 58.578293 | BT47: =BG47 -> 30.830681 | BU47: =BH47 -> 52.412157 | BV47: =BI47 -> 67.827497 | BW47: =BJ47 -> 80.15977 | BX47: =BK47 -> 46.246021 | BY47: =BL47 -> 18.498408 | CA47: =SUMIFS($D47:$BZ47,$D$1:$BZ$1,CA$2) -> 0 | CB47: =SUMIFS($D47:$BZ47,$D$1:$BZ$1,CB$2) -> 0 | CC47: ='Revenue Analysis - Total'!F62+'Revenue Analysis - Total'!F77 -> 0 | CD47: ='Revenue Analysis - Total'!G62+'Revenue Analysis - Total'!G77 -> 0 | CE47: ='Revenue Analysis - Total'!H62+'Revenue Analysis - Total'!H77 -> 100.19971 | CF47: ='Revenue Analysis - Total'!I62+'Revenue Analysis - Total'!I77 -> 524.12157 | CN47: =SUMIFS('FY25 By Venue Financials'!$J:$J,'FY25 By Venue Financials'!$A:$A,$C47) -> 4751.2069 | CR47: Assuming we can start using our liquor license 3/4th of the way through Y2 | CU47: =SUMIFS($D47:$BZ47,$D$1:$BZ$1,CU$9) -> 0 | CV47: =SUMIFS($D47:$BZ47,$D$1:$BZ$1,CV$9) -> 0 | CW47: =SUMIFS($D47:$BZ47,$D$1:$BZ$1,CW$9) -> 454.75254 | CX47: =SUMIFS($D47:$BZ47,$D$1:$BZ$1,CX$9) -> 524.12157
C48: Lodging Revenues | D48: 0 | E48: 0 | F48: 0 | G48: 0 | H48: 0 | I48: 0 | J48: 0 | K48: 0 | L48: 0 | M48: 0 | N48: 0 | O48: 0 | P48: 0 | Q48: 0 | R48: 0 | S48: 0 | T48: 0 | U48: 0 | V48: 0 | W48: 0 | X48: 0 | Y48: 0 | Z48: 0 | AA48: 0 | AB48: 0 | AC48: 0 | AD48: 0 | AE48: 0 | AF48: 0 | AH48: =SUMIFS($CD48:$CF48,$CD$2:$CF$2,AH$3)*AH$36 -> 0 | AI48: =SUMIFS($CD48:$CF48,$CD$2:$CF$2,AI$3)*AI$36 -> 0 | AJ48: =SUMIFS($CD48:$CF48,$CD$2:$CF$2,AJ$3)*AJ$36 -> 0 | AK48: =SUMIFS($CD48:$CF48,$CD$2:$CF$2,AK$3)*AK$36 -> 0 | AL48: =SUMIFS($CD48:$CF48,$CD$2:$CF$2,AL$3)*AL$36 -> 0 | AM48: =SUMIFS($CD48:$CF48,$CD$2:$CF$2,AM$3)*AM$36 -> 0 | AN48: =SUMIFS($CD48:$CF48,$CD$2:$CF$2,AN$3)*AN$36 -> 0 | AO48: =SUMIFS($CD48:$CF48,$CD$2:$CF$2,AO$3)*AO$36 -> 0 | ... BQ48: =SUMIFS($CD48:$CF48,$CD$2:$CF$2,BQ$3)*BQ$36 -> 0 | BS48: =BF48 -> 0 | BT48: =BG48 -> 0 | BU48: =BH48 -> 0 | BV48: =BI48 -> 0 | BW48: =BJ48 -> 0 | BX48: =BK48 -> 0 | BY48: =BL48 -> 0 | CA48: =SUMIFS($D48:$BZ48,$D$1:$BZ$1,CA$2) -> 0 | CB48: =SUMIFS($D48:$BZ48,$D$1:$BZ$1,CB$2) -> 0 | CC48: ='Revenue Analysis - Total'!F63+'Revenue Analysis - Total'!F78 -> 0 | CD48: ='Revenue Analysis - Total'!G63+'Revenue Analysis - Total'!G78 -> 0 | CE48: ='Revenue Analysis - Total'!H63+'Revenue Analysis - Total'!H78 -> 0 | CF48: ='Revenue Analysis - Total'!I63+'Revenue Analysis - Total'!I78 -> 0 | CN48: =SUMIFS('FY25 By Venue Financials'!$J:$J,'FY25 By Venue Financials'!$A:$A,$C48) -> 146.209 | CR48: - | CU48: =SUMIFS($D48:$BZ48,$D$1:$BZ$1,CU$9) -> 0 | CV48: =SUMIFS($D48:$BZ48,$D$1:$BZ$1,CV$9) -> 0 | CW48: =SUMIFS($D48:$BZ48,$D$1:$BZ$1,CW$9) -> 0 | CX48: =SUMIFS($D48:$BZ48,$D$1:$BZ$1,CX$9) -> 0
C49: Ancillary Revenue | D49: 0 | E49: 0 | F49: 0 | G49: 0 | H49: 0 | I49: 0 | J49: 0 | K49: 0 | L49: 0 | M49: 0 | N49: 0 | O49: 0 | P49: 0 | Q49: 0 | R49: 0 | S49: 0 | T49: 0 | U49: 0 | V49: 0 | W49: 0 | X49: 0 | Y49: 0 | Z49: 0 | AA49: 0 | AB49: 0 | AC49: 0 | AD49: 0 | AE49: 0 | AF49: 0 | AH49: =SUMIFS($CD49:$CF49,$CD$2:$CF$2,AH$3)*AH$36 -> 21.75879 | AI49: =SUMIFS($CD49:$CF49,$CD$2:$CF$2,AI$3)*AI$36 -> 18.132325 | AJ49: =SUMIFS($CD49:$CF49,$CD$2:$CF$2,AJ$3)*AJ$36 -> 27.198487 | AK49: =SUMIFS($CD49:$CF49,$CD$2:$CF$2,AK$3)*AK$36 -> 34.451417 | AL49: =SUMIFS($CD49:$CF49,$CD$2:$CF$2,AL$3)*AL$36 -> 43.517579 | AM49: =SUMIFS($CD49:$CF49,$CD$2:$CF$2,AM$3)*AM$36 -> 21.75879 | AN49: =SUMIFS($CD49:$CF49,$CD$2:$CF$2,AN$3)*AN$36 -> 9.0661623 | AO49: =SUMIFS($CD49:$CF49,$CD$2:$CF$2,AO$3)*AO$36 -> 0 | ... BQ49: =SUMIFS($CD49:$CF49,$CD$2:$CF$2,BQ$3)*BQ$36 -> 169.51578 | BS49: =BF49 -> 123.87691 | BT49: =BG49 -> 65.198375 | BU49: =BH49 -> 110.83724 | BV49: =BI49 -> 143.43643 | BW49: =BJ49 -> 169.51578 | BX49: =BK49 -> 97.797563 | BY49: =BL49 -> 39.119025 | CA49: =SUMIFS($D49:$BZ49,$D$1:$BZ$1,CA$2) -> 0 | CB49: =SUMIFS($D49:$BZ49,$D$1:$BZ$1,CB$2) -> 0 | CC49: =SUM('Revenue Analysis - Total'!F64:F69)+SUM('Revenue Analysis - Total'!F79:F84) -> 0 | CD49: =SUM('Revenue Analysis - Total'!G64:G69)+SUM('Revenue Analysis - Total'!G79:G84) -> 271.98487 | CE49: =SUM('Revenue Analysis - Total'!H64:H69)+SUM('Revenue Analysis - Total'!H79:H84) -> 687.57419 | CF49: =SUM('Revenue Analysis - Total'!I64:I69)+SUM('Revenue Analysis - Total'!I79:I84) -> 1108.3724 | CN49: =SUMIFS('FY25 By Venue Financials'!$J:$J,'FY25 By Venue Financials'!$A:$A,$C49) -> 9747.4759 | CR49: Annually - split monthly by seasonality | CU49: =SUMIFS($D49:$BZ49,$D$1:$BZ$1,CU$9) -> 175.88355 | CV49: =SUMIFS($D49:$BZ49,$D$1:$BZ$1,CV$9) -> 564.51124 | CW49: =SUMIFS($D49:$BZ49,$D$1:$BZ$1,CW$9) -> 968.94559 | CX49: =SUMIFS($D49:$BZ49,$D$1:$BZ$1,CX$9) -> 1108.3724
C50: Service Charge | D50: 0 | E50: 0 | F50: 0 | G50: 0 | H50: 0 | I50: 0 | J50: 0 | K50: 0 | L50: 0 | M50: 0 | N50: 0 | O50: 0 | P50: 0 | Q50: 0 | R50: 0 | S50: 0 | T50: 0 | U50: 0 | V50: 0 | W50: 0 | X50: 0 | Y50: 0 | Z50: 0 | AA50: 0 | AB50: 0 | AC50: 0 | AD50: 0 | AE50: 0 | AF50: 0 | AH50: =SUMIFS($CD50:$CF50,$CD$2:$CF$2,AH$3)*AH$36 -> 3.0040435 | AI50: =SUMIFS($CD50:$CF50,$CD$2:$CF$2,AI$3)*AI$36 -> 2.5033696 | AJ50: =SUMIFS($CD50:$CF50,$CD$2:$CF$2,AJ$3)*AJ$36 -> 3.7550543 | AK50: =SUMIFS($CD50:$CF50,$CD$2:$CF$2,AK$3)*AK$36 -> 4.7564022 | AL50: =SUMIFS($CD50:$CF50,$CD$2:$CF$2,AL$3)*AL$36 -> 6.0080869 | AM50: =SUMIFS($CD50:$CF50,$CD$2:$CF$2,AM$3)*AM$36 -> 3.0040435 | AN50: =SUMIFS($CD50:$CF50,$CD$2:$CF$2,AN$3)*AN$36 -> 1.2516848 | AO50: =SUMIFS($CD50:$CF50,$CD$2:$CF$2,AO$3)*AO$36 -> 0 | ... BQ50: =SUMIFS($CD50:$CF50,$CD$2:$CF$2,BQ$3)*BQ$36 -> 36.65354 | BS50: =BF50 -> 26.785279 | BT50: =BG50 -> 14.097516 | BU50: =BH50 -> 23.965776 | BV50: =BI50 -> 31.014534 | BW50: =BJ50 -> 36.65354 | BX50: =BK50 -> 21.146273 | BY50: =BL50 -> 8.4585093 | CA50: =SUMIFS($D50:$BZ50,$D$1:$BZ$1,CA$2) -> 0 | CB50: =SUMIFS($D50:$BZ50,$D$1:$BZ$1,CB$2) -> 0 | CC50: ='Revenue Analysis - Total'!F85 -> 0 | CD50: ='Revenue Analysis - Total'!G85 -> 37.550543 | CE50: ='Revenue Analysis - Total'!H85 -> 183.37014 | CF50: ='Revenue Analysis - Total'!I85 -> 239.65776 | CN50: =SUMIFS('FY25 By Venue Financials'!$J:$J,'FY25 By Venue Financials'!$A:$A,$C50) -> 6093.3021 | CR50: Annually - split monthly by seasonality | CU50: =SUMIFS($D50:$BZ50,$D$1:$BZ$1,CU$9) -> 24.282685 | CV50: =SUMIFS($D50:$BZ50,$D$1:$BZ$1,CV$9) -> 138.18877 | CW50: =SUMIFS($D50:$BZ50,$D$1:$BZ$1,CW$9) -> 220.57066 | CX50: =SUMIFS($D50:$BZ50,$D$1:$BZ$1,CX$9) -> 239.65776
C51: Cancelled Events | D51: =$CA51*D$35/SUM($D$35:$O$35) -> 0 | E51: =$CA51*E$35/SUM($D$35:$O$35) -> 0 | F51: =$CA51*F$35/SUM($D$35:$O$35) -> 1.2712745 | G51: =$CA51*G$35/SUM($D$35:$O$35) -> 5.085098 | H51: =$CA51*H$35/SUM($D$35:$O$35) -> 4.3223333 | I51: =$CA51*I$35/SUM($D$35:$O$35) -> 4.0680784 | J51: =$CA51*J$35/SUM($D$35:$O$35) -> 1.7797843 | K51: =$CA51*K$35/SUM($D$35:$O$35) -> 4.0680784 | ... O51: =$CA51*O$35/SUM($D$35:$O$35) -> 2.2882941 | P51: =$CB51*P$35/SUM($P$35:$AA$35) -> 0 | Q51: =$CB51*Q$35/SUM($P$35:$AA$35) -> 0 | R51: =$CB51*R$35/SUM($P$35:$AA$35) -> 2.0704962 | S51: =$CB51*S$35/SUM($P$35:$AA$35) -> 3.8821805 | T51: =$CB51*T$35/SUM($P$35:$AA$35) -> 6.2114887 | U51: =$CB51*U$35/SUM($P$35:$AA$35) -> 4.1409925 | V51: =$CB51*V$35/SUM($P$35:$AA$35) -> 2.3293083 | W51: =$CB51*W$35/SUM($P$35:$AA$35) -> 3.1057444 | ... AA51: =$CB51*AA$35/SUM($P$35:$AA$35) -> 1.0352481 | AB51: =P51 -> 0 | AC51: =Q51 -> 0 | AD51: =R51 -> 2.0704962 | AE51: =S51 -> 3.8821805 | AF51: =T51 -> 6.2114887 | AH51: =SUMIFS($CD51:$CF51,$CD$2:$CF$2,AH$3)*AH$36 -> 0 | AI51: =SUMIFS($CD51:$CF51,$CD$2:$CF$2,AI$3)*AI$36 -> 0 | AJ51: =SUMIFS($CD51:$CF51,$CD$2:$CF$2,AJ$3)*AJ$36 -> 0 | AK51: =SUMIFS($CD51:$CF51,$CD$2:$CF$2,AK$3)*AK$36 -> 0 | AL51: =SUMIFS($CD51:$CF51,$CD$2:$CF$2,AL$3)*AL$36 -> 0 | AM51: =SUMIFS($CD51:$CF51,$CD$2:$CF$2,AM$3)*AM$36 -> 0 | AN51: =SUMIFS($CD51:$CF51,$CD$2:$CF$2,AN$3)*AN$36 -> 0 | AO51: =SUMIFS($CD51:$CF51,$CD$2:$CF$2,AO$3)*AO$36 -> 0 | ... BQ51: =SUMIFS($CD51:$CF51,$CD$2:$CF$2,BQ$3)*BQ$36 -> 0 | BS51: =BF51 -> 0 | BT51: =BG51 -> 0 | BU51: =BH51 -> 0 | BV51: =BI51 -> 0 | BW51: =BJ51 -> 0 | BX51: =BK51 -> 0 | BY51: =BL51 -> 0 | CA51: 38.901 | CB51: 34.422 | CC51: =CB51 -> 34.422 | CD51: =SUM(CD$43:CD$50)*CH51 -> 0 | CE51: =SUM(CE$43:CE$50)*CI51 -> 0 | CF51: =SUM(CF$43:CF$50)*CJ51 -> 0 | CH51: 0 | CI51: 0 | CJ51: 0 | CL51: =IFERROR(CC51/CC4,0) -> 0 | CN51: =SUMIFS('FY25 By Venue Financials'!$J:$J,'FY25 By Venue Financials'!$A:$A,$C51) -> 717.19878 | CO51: =CN51/SUM($CN$43:$CN$50) -> 0.019367624 | CR51: N/A 'LTM Est. Flat from 2025, not estimating additional revenue from this going forward | CU51: =SUMIFS($D51:$BZ51,$D$1:$BZ$1,CU$9) -> 12.164165 | CV51: =SUMIFS($D51:$BZ51,$D$1:$BZ$1,CV$9) -> 0 | CW51: =SUMIFS($D51:$BZ51,$D$1:$BZ$1,CW$9) -> 0 | CX51: =SUMIFS($D51:$BZ51,$D$1:$BZ$1,CX$9) -> 0
C52: Discounts | D52: 0 | E52: 0 | F52: 0 | G52: 0 | H52: 0 | I52: 0 | J52: 0 | K52: 0 | L52: 0 | M52: 0 | N52: 0 | O52: 0 | P52: 0 | Q52: 0 | R52: 0 | S52: 0 | T52: 0 | U52: 0 | V52: 0 | W52: 0 | X52: 0 | Y52: 0 | Z52: 0 | AA52: 0 | AB52: 0 | AC52: 0 | AD52: 0 | AE52: 0 | AF52: 0 | AH52: =SUMIFS($CD52:$CF52,$CD$2:$CF$2,AH$3)*AH$36 -> 0 | AI52: =SUMIFS($CD52:$CF52,$CD$2:$CF$2,AI$3)*AI$36 -> 0 | AJ52: =SUMIFS($CD52:$CF52,$CD$2:$CF$2,AJ$3)*AJ$36 -> 0 | AK52: =SUMIFS($CD52:$CF52,$CD$2:$CF$2,AK$3)*AK$36 -> 0 | AL52: =SUMIFS($CD52:$CF52,$CD$2:$CF$2,AL$3)*AL$36 -> 0 | AM52: =SUMIFS($CD52:$CF52,$CD$2:$CF$2,AM$3)*AM$36 -> 0 | AN52: =SUMIFS($CD52:$CF52,$CD$2:$CF$2,AN$3)*AN$36 -> 0 | AO52: =SUMIFS($CD52:$CF52,$CD$2:$CF$2,AO$3)*AO$36 -> 0 | ... BQ52: =SUMIFS($CD52:$CF52,$CD$2:$CF$2,BQ$3)*BQ$36 -> 0 | BS52: =BF52 -> 0 | BT52: =BG52 -> 0 | BU52: =BH52 -> 0 | BV52: =BI52 -> 0 | BW52: =BJ52 -> 0 | BX52: =BK52 -> 0 | BY52: =BL52 -> 0 | CA52: =SUMIFS($D52:$BZ52,$D$1:$BZ$1,CA$2) -> 0 | CB52: =SUMIFS($D52:$BZ52,$D$1:$BZ$1,CB$2) -> 0 | CC52: 0 | CD52: =SUM(CD$43:CD$50)*CH52 -> 0 | CE52: =SUM(CE$43:CE$50)*CI52 -> 0 | CF52: =SUM(CF$43:CF$50)*CJ52 -> 0 | CH52: 0 | CI52: 0 | CJ52: 0 | CL52: =IFERROR(CC52/CC6,0) -> 0 | CN52: =SUMIFS('FY25 By Venue Financials'!$J:$J,'FY25 By Venue Financials'!$A:$A,$C52) -> -1498.1672 | CO52: =CN52/SUM($CN$43:$CN$50) -> -0.040457319 | CR52: - | CU52: =SUMIFS($D52:$BZ52,$D$1:$BZ$1,CU$9) -> 0 | CV52: =SUMIFS($D52:$BZ52,$D$1:$BZ$1,CV$9) -> 0 | CW52: =SUMIFS($D52:$BZ52,$D$1:$BZ$1,CW$9) -> 0 | CX52: =SUMIFS($D52:$BZ52,$D$1:$BZ$1,CX$9) -> 0
C53: Other Revenue | D53: 0 | E53: 0 | F53: 0 | G53: 0 | H53: 0 | I53: 0 | J53: 0 | K53: 0 | L53: 0 | M53: 0 | N53: 0 | O53: 0 | P53: 0 | Q53: 0 | R53: 0 | S53: 0 | T53: 0 | U53: 0 | V53: 0 | W53: 0 | X53: 0 | Y53: 0 | Z53: 0 | AA53: 0 | AB53: 0 | AC53: 0 | AD53: 0 | AE53: 0 | AF53: 0 | AH53: =SUMIFS($CD53:$CF53,$CD$2:$CF$2,AH$3)*AH$36 -> 0 | AI53: =SUMIFS($CD53:$CF53,$CD$2:$CF$2,AI$3)*AI$36 -> 0 | AJ53: =SUMIFS($CD53:$CF53,$CD$2:$CF$2,AJ$3)*AJ$36 -> 0 | AK53: =SUMIFS($CD53:$CF53,$CD$2:$CF$2,AK$3)*AK$36 -> 0 | AL53: =SUMIFS($CD53:$CF53,$CD$2:$CF$2,AL$3)*AL$36 -> 0 | AM53: =SUMIFS($CD53:$CF53,$CD$2:$CF$2,AM$3)*AM$36 -> 0 | AN53: =SUMIFS($CD53:$CF53,$CD$2:$CF$2,AN$3)*AN$36 -> 0 | AO53: =SUMIFS($CD53:$CF53,$CD$2:$CF$2,AO$3)*AO$36 -> 0 | ... BQ53: =SUMIFS($CD53:$CF53,$CD$2:$CF$2,BQ$3)*BQ$36 -> 0 | BS53: =BF53 -> 0 | BT53: =BG53 -> 0 | BU53: =BH53 -> 0 | BV53: =BI53 -> 0 | BW53: =BJ53 -> 0 | BX53: =BK53 -> 0 | BY53: =BL53 -> 0 | CA53: =SUMIFS($D53:$BZ53,$D$1:$BZ$1,CA$2) -> 0 | CB53: =SUMIFS($D53:$BZ53,$D$1:$BZ$1,CB$2) -> 0 | CC53: 0 | CD53: =SUM(CD$43:CD$50)*CH53 -> 0 | CE53: =SUM(CE$43:CE$50)*CI53 -> 0 | CF53: =SUM(CF$43:CF$50)*CJ53 -> 0 | CH53: 0 | CI53: 0 | CJ53: 0 | CL53: =IFERROR(CC53/CC7,0) -> 0 | CN53: =SUMIFS('FY25 By Venue Financials'!$J:$J,'FY25 By Venue Financials'!$A:$A,$C53) -> 1.45657 | CO53: =CN53/SUM($CN$43:$CN$50) -> 3.9334006e-05 | CR53: - | CU53: =SUMIFS($D53:$BZ53,$D$1:$BZ$1,CU$9) -> 0 | CV53: =SUMIFS($D53:$BZ53,$D$1:$BZ$1,CV$9) -> 0 | CW53: =SUMIFS($D53:$BZ53,$D$1:$BZ$1,CW$9) -> 0 | CX53: =SUMIFS($D53:$BZ53,$D$1:$BZ$1,CX$9) -> 0
C55: Total Revenue | D55: =SUM(D43:D54) -> 0 | E55: =SUM(E43:E54) -> 0 | F55: =SUM(F43:F54) -> 43.726928 | G55: =SUM(G43:G54) -> 175.65771 | H55: =SUM(H43:H54) -> 144.77155 | I55: =SUM(I43:I54) -> 145.22617 | J55: =SUM(J43:J54) -> 63.067699 | K55: =SUM(K43:K54) -> 142.47617 | ... AF55: =SUM(AF43:AF54) -> 203.18268 | AH55: =SUM(AH43:AH54) -> 170.66258 | AI55: =SUM(AI43:AI54) -> 115.06465 | AJ55: =SUM(AJ43:AJ54) -> 238.78947 | AK55: =SUM(AK43:AK54) -> 256.80033 | AL55: =SUM(AL43:AL54) -> 298.71015 | AM55: =SUM(AM43:AM54) -> 154.89258 | AN55: =SUM(AN43:AN54) -> 54.519823 | AO55: =SUM(AO43:AO54) -> 0 | ... BQ55: =SUM(BQ43:BQ54) -> 580.86942 | BS55: =SUM(BS43:BS54) -> 423.80842 | BT55: =SUM(BT43:BT54) -> 222.87285 | BU55: =SUM(BU43:BU54) -> 379.93385 | BV55: =SUM(BV43:BV54) -> 491.37028 | BW55: =SUM(BW43:BW54) -> 580.86942 | BX55: =SUM(BX43:BX54) -> 336.05928 | BY55: =SUM(BY43:BY54) -> 135.12371 | CA55: =SUM(CA43:CA54) -> 1358.044 | CB55: =SUM(CB43:CB54) -> 1362.7884 | CC55: =SUM(CC43:CC54) -> 1326.6797 | CD55: =SUM(CD43:CD54) -> 1963.4147 | CE55: =SUM(CE43:CE54) -> 2671.073 | CF55: =SUM(CF43:CF54) -> 3799.3385 | CN55: =SUM(CN43:CN54) -> 36251.296 | CU55: =SUM(CU43:CU54) -> 1689.6162 | CV55: =SUM(CV43:CV54) -> 2447.7819 | CW55: =SUM(CW43:CW54) -> 3467.3041 | CX55: =SUM(CX43:CX54) -> 3799.3385
C57: COGS
C58: Food COGS | P58: =-SUMIFS('Monthly P&L'!H:H,'Monthly P&L'!$A:$A,$C58)/1000 -> 0 | Q58: =-SUMIFS('Monthly P&L'!I:I,'Monthly P&L'!$A:$A,$C58)/1000 -> 0 | R58: =-SUMIFS('Monthly P&L'!J:J,'Monthly P&L'!$A:$A,$C58)/1000 -> 0 | S58: =-SUMIFS('Monthly P&L'!K:K,'Monthly P&L'!$A:$A,$C58)/1000 -> 0 | T58: =-SUMIFS('Monthly P&L'!L:L,'Monthly P&L'!$A:$A,$C58)/1000 -> 0 | U58: =-SUMIFS('Monthly P&L'!M:M,'Monthly P&L'!$A:$A,$C58)/1000 -> 0 | V58: =-SUMIFS('Monthly P&L'!N:N,'Monthly P&L'!$A:$A,$C58)/1000 -> 0 | W58: =-SUMIFS('Monthly P&L'!O:O,'Monthly P&L'!$A:$A,$C58)/1000 -> 0 | X58: =-SUMIFS('Monthly P&L'!P:P,'Monthly P&L'!$A:$A,$C58)/1000 -> 0 | Y58: =-SUMIFS('Monthly P&L'!Q:Q,'Monthly P&L'!$A:$A,$C58)/1000 -> 0 | Z58: =-SUMIFS('Monthly P&L'!R:R,'Monthly P&L'!$A:$A,$C58)/1000 -> 0 | AA58: =-SUMIFS('Monthly P&L'!S:S,'Monthly P&L'!$A:$A,$C58)/1000 -> 0 | AB58: =-SUMIFS('Monthly P&L'!T:T,'Monthly P&L'!$A:$A,$C58)/1000 -> 0 | AC58: =-SUMIFS('Monthly P&L'!U:U,'Monthly P&L'!$A:$A,$C58)/1000 -> 0 | AD58: =-SUMIFS('Monthly P&L'!V:V,'Monthly P&L'!$A:$A,$C58)/1000 -> 0 | AE58: =-SUMIFS('Monthly P&L'!W:W,'Monthly P&L'!$A:$A,$C58)/1000 -> 0 | AF58: =-SUMIFS('Monthly P&L'!X:X,'Monthly P&L'!$A:$A,$C58)/1000 -> 0 | AH58: =SUMIFS($CH58:$CJ58,$CH$1:$CJ$1,AH$3)*AH$46 -> -12.92066 | AI58: =SUMIFS($CH58:$CJ58,$CH$1:$CJ$1,AI$3)*AI$46 -> -10.767217 | AJ58: =SUMIFS($CH58:$CJ58,$CH$1:$CJ$1,AJ$3)*AJ$46 -> -16.150825 | AK58: =SUMIFS($CH58:$CJ58,$CH$1:$CJ$1,AK$3)*AK$46 -> -20.457712 | AL58: =SUMIFS($CH58:$CJ58,$CH$1:$CJ$1,AL$3)*AL$46 -> -25.84132 | AM58: =SUMIFS($CH58:$CJ58,$CH$1:$CJ$1,AM$3)*AM$46 -> -12.92066 | AN58: =SUMIFS($CH58:$CJ58,$CH$1:$CJ$1,AN$3)*AN$46 -> -5.3836084 | AO58: =SUMIFS($CH58:$CJ58,$CH$1:$CJ$1,AO$3)*AO$46 -> 0 | ... BQ58: =SUMIFS($CH58:$CJ58,$CH$1:$CJ$1,BQ$3)*BQ$46 -> -93.315878 | BS58: =BF58 -> -68.192372 | BT58: =BG58 -> -35.890722 | BU58: =BH58 -> -61.014228 | BV58: =BI58 -> -78.959589 | BW58: =BJ58 -> -93.315878 | BX58: =BK58 -> -53.836084 | BY58: =BL58 -> -21.534433 | CA58: =-SUMIFS('Monthly P&L'!$E:$E,'Monthly P&L'!$A:$A,$C58)/1000 -> 0 | CB58: =SUMIFS($D58:$BZ58,$D$1:$BZ$1,CB$2) -> 0 | CC58: =SUMIFS($P58:$AF58,$P$3:$AF$3,$CC$2) -> 0 | CD58: =SUMIFS($D58:$BZ58,$D$3:$BZ$3,CD$2) -> -161.50825 | CE58: =SUMIFS($D58:$BZ58,$D$3:$BZ$3,CE$2) -> -378.64712 | CF58: =SUMIFS($D58:$BZ58,$D$3:$BZ$3,CF$2) -> -610.14228 | CH58: =$CC$61/$CC$45 -> -0.79462854 | CI58: =CH58 -> -0.79462854 | CJ58: =CI58 -> -0.79462854 | CL58: =IFERROR(CC58/CC46,0) -> 0 | CN58: =-SUMIFS('FY25 By Venue Financials'!$J:$J,'FY25 By Venue Financials'!$A:$A,$C58) -> -1149.3134 | CO58: =IFERROR(CN58/CN46,0) -> -0.14420978 | CQ58: % Food Rev | CR58: Monthly - existing all inclusive margin//assuming we maintain their packages and partnerships but have our own photography / dj | CU58: =SUMIFS($D58:$BZ58,$D$1:$BZ$1,CU$9) -> -104.442 | CV58: =SUMIFS($D58:$BZ58,$D$1:$BZ$1,CV$9) -> -315.0196 | CW58: =SUMIFS($D58:$BZ58,$D$1:$BZ$1,CW$9) -> -533.43708 | CX58: =SUMIFS($D58:$BZ58,$D$1:$BZ$1,CX$9) -> -610.14228
C59: Ancillary COGS | P59: =-SUMIFS('Monthly P&L'!H:H,'Monthly P&L'!$A:$A,$C59)/1000 -> 0 | Q59: =-SUMIFS('Monthly P&L'!I:I,'Monthly P&L'!$A:$A,$C59)/1000 -> 0 | R59: =-SUMIFS('Monthly P&L'!J:J,'Monthly P&L'!$A:$A,$C59)/1000 -> 0 | S59: =-SUMIFS('Monthly P&L'!K:K,'Monthly P&L'!$A:$A,$C59)/1000 -> 0 | T59: =-SUMIFS('Monthly P&L'!L:L,'Monthly P&L'!$A:$A,$C59)/1000 -> 0 | U59: =-SUMIFS('Monthly P&L'!M:M,'Monthly P&L'!$A:$A,$C59)/1000 -> 0 | V59: =-SUMIFS('Monthly P&L'!N:N,'Monthly P&L'!$A:$A,$C59)/1000 -> 0 | W59: =-SUMIFS('Monthly P&L'!O:O,'Monthly P&L'!$A:$A,$C59)/1000 -> 0 | X59: =-SUMIFS('Monthly P&L'!P:P,'Monthly P&L'!$A:$A,$C59)/1000 -> 0 | Y59: =-SUMIFS('Monthly P&L'!Q:Q,'Monthly P&L'!$A:$A,$C59)/1000 -> 0 | Z59: =-SUMIFS('Monthly P&L'!R:R,'Monthly P&L'!$A:$A,$C59)/1000 -> 0 | AA59: =-SUMIFS('Monthly P&L'!S:S,'Monthly P&L'!$A:$A,$C59)/1000 -> 0 | AB59: =-SUMIFS('Monthly P&L'!T:T,'Monthly P&L'!$A:$A,$C59)/1000 -> 0 | AC59: =-SUMIFS('Monthly P&L'!U:U,'Monthly P&L'!$A:$A,$C59)/1000 -> 0 | AD59: =-SUMIFS('Monthly P&L'!V:V,'Monthly P&L'!$A:$A,$C59)/1000 -> 0 | AE59: =-SUMIFS('Monthly P&L'!W:W,'Monthly P&L'!$A:$A,$C59)/1000 -> 0 | AF59: =-SUMIFS('Monthly P&L'!X:X,'Monthly P&L'!$A:$A,$C59)/1000 -> 0 | AH59: =SUMIFS($CH59:$CJ59,$CH$1:$CJ$1,AH$3)*AH$49 -> -17.290155 | AI59: =SUMIFS($CH59:$CJ59,$CH$1:$CJ$1,AI$3)*AI$49 -> -14.408463 | AJ59: =SUMIFS($CH59:$CJ59,$CH$1:$CJ$1,AJ$3)*AJ$49 -> -21.612694 | AK59: =SUMIFS($CH59:$CJ59,$CH$1:$CJ$1,AK$3)*AK$49 -> -27.376079 | AL59: =SUMIFS($CH59:$CJ59,$CH$1:$CJ$1,AL$3)*AL$49 -> -34.58031 | AM59: =SUMIFS($CH59:$CJ59,$CH$1:$CJ$1,AM$3)*AM$49 -> -17.290155 | AN59: =SUMIFS($CH59:$CJ59,$CH$1:$CJ$1,AN$3)*AN$49 -> -7.2042313 | AO59: =SUMIFS($CH59:$CJ59,$CH$1:$CJ$1,AO$3)*AO$49 -> 0 | ... BQ59: =SUMIFS($CH59:$CJ59,$CH$1:$CJ$1,BQ$3)*BQ$49 -> -134.70207 | BS59: =BF59 -> -98.43613 | BT59: =BG59 -> -51.80849 | BU59: =BH59 -> -88.074432 | BV59: =BI59 -> -113.97868 | BW59: =BJ59 -> -134.70207 | BX59: =BK59 -> -77.712734 | BY59: =BL59 -> -31.085094 | CA59: =-SUMIFS('Monthly P&L'!$E:$E,'Monthly P&L'!$A:$A,$C59)/1000 -> 0 | CB59: =SUMIFS($D59:$BZ59,$D$1:$BZ$1,CB$2) -> 0 | CC59: =SUMIFS($P59:$AF59,$P$3:$AF$3,$CC$2) -> 0 | CD59: =SUMIFS($D59:$BZ59,$D$3:$BZ$3,CD$2) -> -216.12694 | CE59: =SUMIFS($D59:$BZ59,$D$3:$BZ$3,CE$2) -> -546.36607 | CF59: =SUMIFS($D59:$BZ59,$D$3:$BZ$3,CF$2) -> -880.74432 | CH59: =$CC$61/$CC$45 -> -0.79462854 | CI59: =CH59 -> -0.79462854 | CJ59: =CI59 -> -0.79462854 | CL59: =IFERROR(CC59/CC49,0) -> 0 | CN59: =-SUMIFS('FY25 By Venue Financials'!$J:$J,'FY25 By Venue Financials'!$A:$A,$C59) -> -1852.7598 | CO59: =IFERROR(CN59/CN$49,0) -> -0.19007585 | CQ59: % Ancillary Rev | CR59: Monthly - existing all inclusive margin//assuming we maintain their packages and partnerships but have our own photography / dj | CU59: =SUMIFS($D59:$BZ59,$D$1:$BZ$1,CU$9) -> -139.76209 | CV59: =SUMIFS($D59:$BZ59,$D$1:$BZ$1,CV$9) -> -448.57674 | CW59: =SUMIFS($D59:$BZ59,$D$1:$BZ$1,CW$9) -> -769.95182 | CX59: =SUMIFS($D59:$BZ59,$D$1:$BZ$1,CX$9) -> -880.74432
C60: Alcohol COGS | P60: =-SUMIFS('Monthly P&L'!H:H,'Monthly P&L'!$A:$A,$C60)/1000 -> 0 | Q60: =-SUMIFS('Monthly P&L'!I:I,'Monthly P&L'!$A:$A,$C60)/1000 -> 0 | R60: =-SUMIFS('Monthly P&L'!J:J,'Monthly P&L'!$A:$A,$C60)/1000 -> 0 | S60: =-SUMIFS('Monthly P&L'!K:K,'Monthly P&L'!$A:$A,$C60)/1000 -> 0 | T60: =-SUMIFS('Monthly P&L'!L:L,'Monthly P&L'!$A:$A,$C60)/1000 -> 0 | U60: =-SUMIFS('Monthly P&L'!M:M,'Monthly P&L'!$A:$A,$C60)/1000 -> 0 | V60: =-SUMIFS('Monthly P&L'!N:N,'Monthly P&L'!$A:$A,$C60)/1000 -> 0 | W60: =-SUMIFS('Monthly P&L'!O:O,'Monthly P&L'!$A:$A,$C60)/1000 -> 0 | X60: =-SUMIFS('Monthly P&L'!P:P,'Monthly P&L'!$A:$A,$C60)/1000 -> 0 | Y60: =-SUMIFS('Monthly P&L'!Q:Q,'Monthly P&L'!$A:$A,$C60)/1000 -> 0 | Z60: =-SUMIFS('Monthly P&L'!R:R,'Monthly P&L'!$A:$A,$C60)/1000 -> 0 | AA60: =-SUMIFS('Monthly P&L'!S:S,'Monthly P&L'!$A:$A,$C60)/1000 -> 0 | AB60: =-SUMIFS('Monthly P&L'!T:T,'Monthly P&L'!$A:$A,$C60)/1000 -> 0 | AC60: =-SUMIFS('Monthly P&L'!U:U,'Monthly P&L'!$A:$A,$C60)/1000 -> 0 | AD60: =-SUMIFS('Monthly P&L'!V:V,'Monthly P&L'!$A:$A,$C60)/1000 -> 0 | AE60: =-SUMIFS('Monthly P&L'!W:W,'Monthly P&L'!$A:$A,$C60)/1000 -> 0 | AF60: =-SUMIFS('Monthly P&L'!X:X,'Monthly P&L'!$A:$A,$C60)/1000 -> 0 | AH60: =SUMIFS($CH60:$CJ60,$CH$1:$CJ$1,AH$3)*AH$47 -> 0 | AI60: =SUMIFS($CH60:$CJ60,$CH$1:$CJ$1,AI$3)*AI$47 -> 0 | AJ60: =SUMIFS($CH60:$CJ60,$CH$1:$CJ$1,AJ$3)*AJ$47 -> 0 | AK60: =SUMIFS($CH60:$CJ60,$CH$1:$CJ$1,AK$3)*AK$47 -> 0 | AL60: =SUMIFS($CH60:$CJ60,$CH$1:$CJ$1,AL$3)*AL$47 -> 0 | AM60: =SUMIFS($CH60:$CJ60,$CH$1:$CJ$1,AM$3)*AM$47 -> 0 | AN60: =SUMIFS($CH60:$CJ60,$CH$1:$CJ$1,AN$3)*AN$47 -> 0 | AO60: =SUMIFS($CH60:$CJ60,$CH$1:$CJ$1,AO$3)*AO$47 -> 0 | ... BQ60: =SUMIFS($CH60:$CJ60,$CH$1:$CJ$1,BQ$3)*BQ$47 -> -8.7498282 | BS60: =BF60 -> -6.3941052 | BT60: =BG60 -> -3.3653185 | BU60: =BH60 -> -5.7210415 | BV60: =BI60 -> -7.4037008 | BW60: =BJ60 -> -8.7498282 | BX60: =BK60 -> -5.0479778 | BY60: =BL60 -> -2.0191911 | CA60: =-SUMIFS('Monthly P&L'!$E:$E,'Monthly P&L'!$A:$A,$C60)/1000 -> 0 | CB60: =SUMIFS($D60:$BZ60,$D$1:$BZ$1,CB$2) -> 0 | CC60: =SUMIFS($P60:$AF60,$P$3:$AF$3,$CC$2) -> 0 | CD60: =SUMIFS($D60:$BZ60,$D$3:$BZ$3,CD$2) -> 0 | CE60: =SUMIFS($D60:$BZ60,$D$3:$BZ$3,CE$2) -> -10.937285 | CF60: =SUMIFS($D60:$BZ60,$D$3:$BZ$3,CF$2) -> -57.210415 | CH60: =$CO60 -> -0.10915486 | CI60: =$CO60 -> -0.10915486 | CJ60: =$CO60 -> -0.10915486 | CL60: =IFERROR(CC60/CC47,0) -> 0 | CN60: =-SUMIFS('FY25 By Venue Financials'!$J:$J,'FY25 By Venue Financials'!$A:$A,$C60) -> -518.61731 | CO60: =IFERROR(CN60/CN47,0) -> -0.10915486 | CQ60: % Alcohol Rev | CR60: N/A Assuming no alcohol until we can confirm we'll receive our liquor license | CU60: =SUMIFS($D60:$BZ60,$D$1:$BZ$1,CU$9) -> 0 | CV60: =SUMIFS($D60:$BZ60,$D$1:$BZ$1,CV$9) -> 0 | CW60: =SUMIFS($D60:$BZ60,$D$1:$BZ$1,CW$9) -> -49.638448 | CX60: =SUMIFS($D60:$BZ60,$D$1:$BZ$1,CX$9) -> -57.210415
C61: All Inclusive COGS | P61: =-SUMIFS('Monthly P&L'!H:H,'Monthly P&L'!$A:$A,$C61)/1000 -> -10.13686 | Q61: =-SUMIFS('Monthly P&L'!I:I,'Monthly P&L'!$A:$A,$C61)/1000 -> -24.61683 | R61: =-SUMIFS('Monthly P&L'!J:J,'Monthly P&L'!$A:$A,$C61)/1000 -> -3.75358 | S61: =-SUMIFS('Monthly P&L'!K:K,'Monthly P&L'!$A:$A,$C61)/1000 -> -4.24267 | T61: =-SUMIFS('Monthly P&L'!L:L,'Monthly P&L'!$A:$A,$C61)/1000 -> -33.51418 | U61: =-SUMIFS('Monthly P&L'!M:M,'Monthly P&L'!$A:$A,$C61)/1000 -> -44.74815 | V61: =-SUMIFS('Monthly P&L'!N:N,'Monthly P&L'!$A:$A,$C61)/1000 -> -8.97739 | W61: =-SUMIFS('Monthly P&L'!O:O,'Monthly P&L'!$A:$A,$C61)/1000 -> -11.28953 | X61: =-SUMIFS('Monthly P&L'!P:P,'Monthly P&L'!$A:$A,$C61)/1000 -> -37.84624 | Y61: =-SUMIFS('Monthly P&L'!Q:Q,'Monthly P&L'!$A:$A,$C61)/1000 -> -51.03666 | Z61: =-SUMIFS('Monthly P&L'!R:R,'Monthly P&L'!$A:$A,$C61)/1000 -> -43.1094 | AA61: =-SUMIFS('Monthly P&L'!S:S,'Monthly P&L'!$A:$A,$C61)/1000 -> -2.59494 | AB61: =-SUMIFS('Monthly P&L'!T:T,'Monthly P&L'!$A:$A,$C61)/1000 -> -0.88855 | AC61: =-SUMIFS('Monthly P&L'!U:U,'Monthly P&L'!$A:$A,$C61)/1000 -> -1.247 | AD61: =-SUMIFS('Monthly P&L'!V:V,'Monthly P&L'!$A:$A,$C61)/1000 -> -5.95736 | AE61: =-SUMIFS('Monthly P&L'!W:W,'Monthly P&L'!$A:$A,$C61)/1000 -> -17.44834 | AF61: =-SUMIFS('Monthly P&L'!X:X,'Monthly P&L'!$A:$A,$C61)/1000 -> -14.06119 | AH61: =-SUMIFS('Future Events'!$AH:$AH,'Future Events'!$D:$D,AH$9)/1000 -> -30.495 | AI61: =-SUMIFS('Future Events'!$AH:$AH,'Future Events'!$D:$D,AI$9)/1000 -> -7.525 | AJ61: =-SUMIFS('Future Events'!$AH:$AH,'Future Events'!$D:$D,AJ$9)/1000 -> -63.48 | AK61: =-SUMIFS('Future Events'!$AH:$AH,'Future Events'!$D:$D,AK$9)/1000 -> -37.485 | AL61: =-SUMIFS('Future Events'!$AH:$AH,'Future Events'!$D:$D,AL$9)/1000 -> -27.575 | AM61: =-SUMIFS('Future Events'!$AH:$AH,'Future Events'!$D:$D,AM$9)/1000 -> -20.575 | AN61: =-SUMIFS('Future Events'!$AH:$AH,'Future Events'!$D:$D,AN$9)/1000 -> -0.55 | AO61: =-SUMIFS('Future Events'!$AH:$AH,'Future Events'!$D:$D,AO$9)/1000 -> 0 | ... BQ61: =-SUMIFS('Future Events'!$AH:$AH,'Future Events'!$D:$D,BQ$9)/1000 -> 0 | BS61: =-SUMIFS('Future Events'!$AH:$AH,'Future Events'!$D:$D,BS$9)/1000 -> 0 | BT61: =-SUMIFS('Future Events'!$AH:$AH,'Future Events'!$D:$D,BT$9)/1000 -> 0 | BU61: =-SUMIFS('Future Events'!$AH:$AH,'Future Events'!$D:$D,BU$9)/1000 -> 0 | BV61: =-SUMIFS('Future Events'!$AH:$AH,'Future Events'!$D:$D,BV$9)/1000 -> 0 | BW61: =-SUMIFS('Future Events'!$AH:$AH,'Future Events'!$D:$D,BW$9)/1000 -> 0 | BX61: =-SUMIFS('Future Events'!$AH:$AH,'Future Events'!$D:$D,BX$9)/1000 -> 0 | BY61: =-SUMIFS('Future Events'!$AH:$AH,'Future Events'!$D:$D,BY$9)/1000 -> 0 | CA61: =-SUMIFS('Monthly P&L'!$E:$E,'Monthly P&L'!$A:$A,$C61)/1000 -> -167.41099 | CB61: =SUMIFS($D61:$BZ61,$D$1:$BZ$1,CB$2) -> -275.86643 | CC61: =SUMIFS($P61:$AF61,$P$3:$AF$3,$CC$2) -> -258.65774 | CD61: =SUMIFS($D61:$BZ61,$D$3:$BZ$3,CD$2) -> -246.07 | CE61: =SUMIFS($D61:$BZ61,$D$3:$BZ$3,CE$2) -> -62.445 | CF61: =SUMIFS($D61:$BZ61,$D$3:$BZ$3,CF$2) -> 0 | CN61: =-SUMIFS('FY25 By Venue Financials'!$J:$J,'FY25 By Venue Financials'!$A:$A,$C61) -> 0 | CO61: =IFERROR(CN61/CN$55,0) -> 0 | CQ61: % Total Rev | CR61: Monthly - COGS for all inclusive events prior to close | CU61: =SUMIFS($D61:$BZ61,$D$1:$BZ$1,CU$9) -> -227.28744 | CV61: =SUMIFS($D61:$BZ61,$D$1:$BZ$1,CV$9) -> -120.83 | CW61: =SUMIFS($D61:$BZ61,$D$1:$BZ$1,CW$9) -> 0 | CX61: =SUMIFS($D61:$BZ61,$D$1:$BZ$1,CX$9) -> 0
C62: Other COGS | P62: =-SUMIFS('Monthly P&L'!H:H,'Monthly P&L'!$A:$A,$C62)/1000 -> -0.25649 | Q62: =-SUMIFS('Monthly P&L'!I:I,'Monthly P&L'!$A:$A,$C62)/1000 -> 0 | R62: =-SUMIFS('Monthly P&L'!J:J,'Monthly P&L'!$A:$A,$C62)/1000 -> -0.23652 | S62: =-SUMIFS('Monthly P&L'!K:K,'Monthly P&L'!$A:$A,$C62)/1000 -> -0.19974 | T62: =-SUMIFS('Monthly P&L'!L:L,'Monthly P&L'!$A:$A,$C62)/1000 -> -0.016 | U62: =-SUMIFS('Monthly P&L'!M:M,'Monthly P&L'!$A:$A,$C62)/1000 -> -0.30123 | V62: =-SUMIFS('Monthly P&L'!N:N,'Monthly P&L'!$A:$A,$C62)/1000 -> 0 | W62: =-SUMIFS('Monthly P&L'!O:O,'Monthly P&L'!$A:$A,$C62)/1000 -> 0 | X62: =-SUMIFS('Monthly P&L'!P:P,'Monthly P&L'!$A:$A,$C62)/1000 -> 0 | Y62: =-SUMIFS('Monthly P&L'!Q:Q,'Monthly P&L'!$A:$A,$C62)/1000 -> -0.38845 | Z62: =-SUMIFS('Monthly P&L'!R:R,'Monthly P&L'!$A:$A,$C62)/1000 -> -0.12452 | AA62: =-SUMIFS('Monthly P&L'!S:S,'Monthly P&L'!$A:$A,$C62)/1000 -> 0 | AB62: =-SUMIFS('Monthly P&L'!T:T,'Monthly P&L'!$A:$A,$C62)/1000 -> 0 | AC62: =-SUMIFS('Monthly P&L'!U:U,'Monthly P&L'!$A:$A,$C62)/1000 -> -0.22271 | AD62: =-SUMIFS('Monthly P&L'!V:V,'Monthly P&L'!$A:$A,$C62)/1000 -> -0.1382 | AE62: =-SUMIFS('Monthly P&L'!W:W,'Monthly P&L'!$A:$A,$C62)/1000 -> 0 | AF62: =-SUMIFS('Monthly P&L'!X:X,'Monthly P&L'!$A:$A,$C62)/1000 -> 0 | AH62: =SUMIFS($CH62:$CJ62,$CH$1:$CJ$1,AH$3)*AH$55 -> -1.994284 | AI62: =SUMIFS($CH62:$CJ62,$CH$1:$CJ$1,AI$3)*AI$55 -> -1.3445923 | AJ62: =SUMIFS($CH62:$CJ62,$CH$1:$CJ$1,AJ$3)*AJ$55 -> -2.7903834 | AK62: =SUMIFS($CH62:$CJ62,$CH$1:$CJ$1,AK$3)*AK$55 -> -3.00085 | AL62: =SUMIFS($CH62:$CJ62,$CH$1:$CJ$1,AL$3)*AL$55 -> -3.4905888 | AM62: =SUMIFS($CH62:$CJ62,$CH$1:$CJ$1,AM$3)*AM$55 -> -1.8100031 | AN62: =SUMIFS($CH62:$CJ62,$CH$1:$CJ$1,AN$3)*AN$55 -> -0.63709346 | AO62: =SUMIFS($CH62:$CJ62,$CH$1:$CJ$1,AO$3)*AO$55 -> 0 | ... BQ62: =SUMIFS($CH62:$CJ62,$CH$1:$CJ$1,BQ$3)*BQ$55 -> -6.7877716 | BS62: =BF62 -> -4.9524293 | BT62: =BG62 -> -2.6043892 | BU62: =BH62 -> -4.4397314 | BV62: =BI62 -> -5.741926 | BW62: =BJ62 -> -6.7877716 | BX62: =BK62 -> -3.9270334 | BY62: =BL62 -> -1.5789932 | CA62: =-SUMIFS('Monthly P&L'!$E:$E,'Monthly P&L'!$A:$A,$C62)/1000 -> -4.84112 | CB62: =SUMIFS($D62:$BZ62,$D$1:$BZ$1,CB$2) -> -1.52295 | CC62: =SUMIFS($P62:$AF62,$P$3:$AF$3,$CC$2) -> -1.19111 | CD62: =SUMIFS($D62:$BZ62,$D$3:$BZ$3,CD$2) -> -22.943557 | CE62: =SUMIFS($D62:$BZ62,$D$3:$BZ$3,CE$2) -> -31.212925 | CF62: =SUMIFS($D62:$BZ62,$D$3:$BZ$3,CF$2) -> -44.397314 | CH62: =$CL62 -> -0.011685538 | CI62: =$CL62 -> -0.011685538 | CJ62: =$CL62 -> -0.011685538 | CL62: =$CO62 -> -0.011685538 | CN62: =-SUMIFS('FY25 By Venue Financials'!$J:$J,'FY25 By Venue Financials'!$A:$A,$C62) -> -423.61589 | CO62: =IFERROR(CN62/CN$55,0) -> -0.011685538 | CQ62: % Total Rev | CR62: Monthly | CU62: =SUMIFS($D62:$BZ62,$D$1:$BZ$1,CU$9) -> -15.428705 | CV62: =SUMIFS($D62:$BZ62,$D$1:$BZ$1,CV$9) -> -28.603648 | CW62: =SUMIFS($D62:$BZ62,$D$1:$BZ$1,CW$9) -> -40.517313 | CX62: =SUMIFS($D62:$BZ62,$D$1:$BZ$1,CX$9) -> -44.397314
C63: Room COGS | P63: =-SUMIFS('Monthly P&L'!H:H,'Monthly P&L'!$A:$A,$C63)/1000 -> 0 | Q63: =-SUMIFS('Monthly P&L'!I:I,'Monthly P&L'!$A:$A,$C63)/1000 -> 0 | R63: =-SUMIFS('Monthly P&L'!J:J,'Monthly P&L'!$A:$A,$C63)/1000 -> 0 | S63: =-SUMIFS('Monthly P&L'!K:K,'Monthly P&L'!$A:$A,$C63)/1000 -> 0 | T63: =-SUMIFS('Monthly P&L'!L:L,'Monthly P&L'!$A:$A,$C63)/1000 -> 0 | U63: =-SUMIFS('Monthly P&L'!M:M,'Monthly P&L'!$A:$A,$C63)/1000 -> 0 | V63: =-SUMIFS('Monthly P&L'!N:N,'Monthly P&L'!$A:$A,$C63)/1000 -> 0 | W63: =-SUMIFS('Monthly P&L'!O:O,'Monthly P&L'!$A:$A,$C63)/1000 -> 0 | X63: =-SUMIFS('Monthly P&L'!P:P,'Monthly P&L'!$A:$A,$C63)/1000 -> 0 | Y63: =-SUMIFS('Monthly P&L'!Q:Q,'Monthly P&L'!$A:$A,$C63)/1000 -> 0 | Z63: =-SUMIFS('Monthly P&L'!R:R,'Monthly P&L'!$A:$A,$C63)/1000 -> 0 | AA63: =-SUMIFS('Monthly P&L'!S:S,'Monthly P&L'!$A:$A,$C63)/1000 -> 0 | AB63: =-SUMIFS('Monthly P&L'!T:T,'Monthly P&L'!$A:$A,$C63)/1000 -> 0 | AC63: =-SUMIFS('Monthly P&L'!U:U,'Monthly P&L'!$A:$A,$C63)/1000 -> 0 | AD63: =-SUMIFS('Monthly P&L'!V:V,'Monthly P&L'!$A:$A,$C63)/1000 -> 0 | AE63: =-SUMIFS('Monthly P&L'!W:W,'Monthly P&L'!$A:$A,$C63)/1000 -> 0 | AF63: =-SUMIFS('Monthly P&L'!X:X,'Monthly P&L'!$A:$A,$C63)/1000 -> 0 | AH63: 0 | AI63: 0 | AJ63: 0 | AK63: 0 | AL63: 0 | AM63: 0 | AN63: 0 | AO63: 0 | AP63: 0 | AQ63: 0 | AR63: 0 | AS63: 0 | AT63: 0 | AU63: 0 | AV63: 0 | AW63: 0 | AX63: 0 | AY63: 0 | AZ63: 0 | BA63: 0 | BB63: 0 | BC63: 0 | BD63: 0 | BE63: 0 | BF63: 0 | BG63: 0 | BH63: 0 | BI63: 0 | BJ63: 0 | BK63: 0 | BL63: 0 | BM63: 0 | BN63: 0 | BO63: 0 | BP63: 0 | BQ63: 0 | BS63: 0 | BT63: 0 | BU63: 0 | BV63: 0 | BW63: 0 | BX63: 0 | BY63: 0 | CA63: 0 | CB63: 0 | CC63: 0 | CD63: 0 | CE63: 0 | CF63: 0 | CH63: =$CO63 -> -0.0019558304 | CI63: =$CO63 -> -0.0019558304 | CJ63: =$CO63 -> -0.0019558304 | CL63: =IFERROR(CC63/CC43,0) -> 0 | CN63: =-SUMIFS('FY25 By Venue Financials'!$J:$J,'FY25 By Venue Financials'!$A:$A,$C63) -> -0.28596 | CO63: =IFERROR(CN63/CN48,0) -> -0.0019558304 | CQ63: % Lodging Rev | CR63: - | CU63: =SUMIFS($D63:$BZ63,$D$1:$BZ$1,CU$9) -> 0 | CV63: =SUMIFS($D63:$BZ63,$D$1:$BZ$1,CV$9) -> 0 | CW63: =SUMIFS($D63:$BZ63,$D$1:$BZ$1,CW$9) -> 0 | CX63: =SUMIFS($D63:$BZ63,$D$1:$BZ$1,CX$9) -> 0
C65: Total COGS | D65: =SUM(D58:D64) -> 0 | E65: =SUM(E58:E64) -> 0 | F65: =SUM(F58:F64) -> 0 | G65: =SUM(G58:G64) -> 0 | H65: =SUM(H58:H64) -> 0 | I65: =SUM(I58:I64) -> 0 | J65: =SUM(J58:J64) -> 0 | K65: =SUM(K58:K64) -> 0 | ... AF65: =SUM(AF58:AF64) -> -14.06119 | AH65: =SUM(AH58:AH64) -> -62.700099 | AI65: =SUM(AI58:AI64) -> -34.045272 | AJ65: =SUM(AJ58:AJ64) -> -104.0339 | AK65: =SUM(AK58:AK64) -> -88.319641 | AL65: =SUM(AL58:AL64) -> -91.487219 | AM65: =SUM(AM58:AM64) -> -52.595818 | AN65: =SUM(AN58:AN64) -> -13.774933 | AO65: =SUM(AO58:AO64) -> 0 | ... BQ65: =SUM(BQ58:BQ64) -> -243.55555 | BS65: =SUM(BS58:BS64) -> -177.97504 | BT65: =SUM(BT58:BT64) -> -93.66892 | BU65: =SUM(BU58:BU64) -> -159.24943 | BV65: =SUM(BV58:BV64) -> -206.08389 | BW65: =SUM(BW58:BW64) -> -243.55555 | BX65: =SUM(BX58:BX64) -> -140.52383 | BY65: =SUM(BY58:BY64) -> -56.217712 | CA65: =SUM(CA58:CA64) -> -172.25211 | CB65: =SUM(CB58:CB64) -> -277.38938 | CC65: =SUM(CC58:CC64) -> -259.84885 | CD65: =SUM(CD58:CD64) -> -646.64875 | CE65: =SUM(CE58:CE64) -> -1029.6084 | CF65: =SUM(CF58:CF64) -> -1592.4943 | CH65: =IFERROR(CD65/CD$55,0) -> -0.32934904 | CI65: =IFERROR(CE65/CE$55,0) -> -0.38546621 | CJ65: =IFERROR(CF65/CF$55,0) -> -0.41915042 | CL65: =IFERROR(CC65/CC$55,0) -> -0.19586404 | CN65: =SUM(CN58:CN64) -> -3944.5923 | CO65: =IFERROR(CN65/CN$55,0) -> -0.10881245 | CQ65: % Total Rev | CU65: =SUM(CU58:CU64) -> -486.92023 | CV65: =SUM(CV58:CV64) -> -913.02999 | CW65: =SUM(CW58:CW64) -> -1393.5447 | CX65: =SUM(CX58:CX64) -> -1592.4943
C67: Gross Margin | D67: =D55+D65 -> 0 | E67: =E55+E65 -> 0 | F67: =F55+F65 -> 43.726928 | G67: =G55+G65 -> 175.65771 | H67: =H55+H65 -> 144.77155 | I67: =I55+I65 -> 145.22617 | J67: =J55+J65 -> 63.067699 | K67: =K55+K65 -> 142.47617 | ... AF67: =AF55+AF65 -> 189.12149 | AH67: =AH55+AH65 -> 107.96248 | AI67: =AI55+AI65 -> 81.019375 | AJ67: =AJ55+AJ65 -> 134.75557 | AK67: =AK55+AK65 -> 168.48069 | AL67: =AL55+AL65 -> 207.22293 | AM67: =AM55+AM65 -> 102.29676 | AN67: =AN55+AN65 -> 40.74489 | AO67: =AO55+AO65 -> 0 | ... BQ67: =BQ55+BQ65 -> 337.31387 | BS67: =BS55+BS65 -> 245.83339 | BT67: =BT55+BT65 -> 129.20393 | BU67: =BU55+BU65 -> 220.68442 | BV67: =BV55+BV65 -> 285.28639 | BW67: =BW55+BW65 -> 337.31387 | BX67: =BX55+BX65 -> 195.53545 | BY67: =BY55+BY65 -> 78.906001 | CA67: =CA55+CA65 -> 1185.7919 | CB67: =CB55+CB65 -> 1085.399 | CC67: =CC55+CC65 -> 1066.8309 | CD67: =CD55+CD65 -> 1316.766 | CE67: =CE55+CE65 -> 1641.4646 | CF67: =CF55+CF65 -> 2206.8442 | CH67: =IFERROR(CD67/CD$55,0) -> 0.67065096 | CI67: =IFERROR(CE67/CE$55,0) -> 0.61453379 | CJ67: =IFERROR(CF67/CF$55,0) -> 0.58084958 | CL67: =IFERROR(CC67/CC$55,0) -> 0.80413596 | CN67: =CN55+CN65 -> 32306.704 | CO67: =IFERROR(CN67/CN$55,0) -> 0.89118755 | CQ67: % Total Rev | CU67: =CU55+CU65 -> 1202.6959 | CV67: =CV55+CV65 -> 1534.7519 | CW67: =CW55+CW65 -> 2073.7594 | CX67: =CX55+CX65 -> 2206.8442
C69: Payroll
C70: Sales Team Payroll | P70: =-SUMIFS('Monthly P&L'!H:H,'Monthly P&L'!$A:$A,$C70)/1000 -> 0 | Q70: =-SUMIFS('Monthly P&L'!I:I,'Monthly P&L'!$A:$A,$C70)/1000 -> 0 | R70: =-SUMIFS('Monthly P&L'!J:J,'Monthly P&L'!$A:$A,$C70)/1000 -> 0 | S70: =-SUMIFS('Monthly P&L'!K:K,'Monthly P&L'!$A:$A,$C70)/1000 -> 0 | T70: =-SUMIFS('Monthly P&L'!L:L,'Monthly P&L'!$A:$A,$C70)/1000 -> 0 | U70: =-SUMIFS('Monthly P&L'!M:M,'Monthly P&L'!$A:$A,$C70)/1000 -> 0 | V70: =-SUMIFS('Monthly P&L'!N:N,'Monthly P&L'!$A:$A,$C70)/1000 -> 0 | W70: =-SUMIFS('Monthly P&L'!O:O,'Monthly P&L'!$A:$A,$C70)/1000 -> 0 | X70: =-SUMIFS('Monthly P&L'!P:P,'Monthly P&L'!$A:$A,$C70)/1000 -> 0 | Y70: =-SUMIFS('Monthly P&L'!Q:Q,'Monthly P&L'!$A:$A,$C70)/1000 -> 0 | Z70: =-SUMIFS('Monthly P&L'!R:R,'Monthly P&L'!$A:$A,$C70)/1000 -> 0 | AA70: =-SUMIFS('Monthly P&L'!S:S,'Monthly P&L'!$A:$A,$C70)/1000 -> 0 | AB70: =-SUMIFS('Monthly P&L'!T:T,'Monthly P&L'!$A:$A,$C70)/1000 -> 0 | AC70: =-SUMIFS('Monthly P&L'!U:U,'Monthly P&L'!$A:$A,$C70)/1000 -> 0 | AD70: =-SUMIFS('Monthly P&L'!V:V,'Monthly P&L'!$A:$A,$C70)/1000 -> 0 | AE70: =-SUMIFS('Monthly P&L'!W:W,'Monthly P&L'!$A:$A,$C70)/1000 -> 0 | AF70: =-SUMIFS('Monthly P&L'!X:X,'Monthly P&L'!$A:$A,$C70)/1000*2 -> 0 | AH70: =SUMIFS($CD70:$CF70,$CD$2:$CF$2,AH$3)/12 -> -12.913667 | AI70: =SUMIFS($CD70:$CF70,$CD$2:$CF$2,AI$3)/12 -> -12.913667 | AJ70: =SUMIFS($CD70:$CF70,$CD$2:$CF$2,AJ$3)/12 -> -12.913667 | AK70: =SUMIFS($CD70:$CF70,$CD$2:$CF$2,AK$3)/12 -> -12.913667 | AL70: =SUMIFS($CD70:$CF70,$CD$2:$CF$2,AL$3)/12 -> -12.913667 | AM70: =SUMIFS($CD70:$CF70,$CD$2:$CF$2,AM$3)/12 -> -12.913667 | AN70: =SUMIFS($CD70:$CF70,$CD$2:$CF$2,AN$3)/12 -> -12.913667 | AO70: =SUMIFS($CD70:$CF70,$CD$2:$CF$2,AO$3)/12 -> -12.913667 | ... BQ70: =SUMIFS($CD70:$CF70,$CD$2:$CF$2,BQ$3)/12 -> -15.625537 | BS70: =BF70 -> -15.625537 | BT70: =BG70 -> -15.625537 | BU70: =BH70 -> -15.625537 | BV70: =BI70 -> -15.625537 | BW70: =BJ70 -> -15.625537 | BX70: =BK70 -> -15.625537 | BY70: =BL70 -> -15.625537 | CA70: =-SUMIFS('Monthly P&L'!$E:$E,'Monthly P&L'!$A:$A,$C70)/1000 -> 0 | CB70: =SUMIFS($D70:$AF70,$D$1:$AF$1,CB$2) -> 0 | CC70: =SUMIFS($P70:$AF70,$P$3:$AF$3,$CC$2) -> 0 | CD70: =-SUMIFS('Go-Forward Payroll'!$G$3:$G$10,'Go-Forward Payroll'!$I$3:$I$10,$C70)/1000 -> -154.964 | CE70: =CD70*(1+CI70) -> -170.4604 | CF70: =CE70*(1+CJ70) -> -187.50644 | CI70: 0.1 | CJ70: 0.1 | CL70: =IFERROR(CC70/CC$55,0) -> 0 | CN70: =-SUMIFS('FY25 By Venue Financials'!$J:$J,'FY25 By Venue Financials'!$A:$A,$C70) -> -1532.0437 | CQ70: YoY Growth | CR70: Annually - Split / 12 - YoY Growth from AJ/DZ estimates | CU70: =SUMIFS($D70:$BZ70,$D$1:$BZ$1,CU$9) -> -90.395667 | CV70: =SUMIFS($D70:$BZ70,$D$1:$BZ$1,CV$9) -> -164.00357 | CW70: =SUMIFS($D70:$BZ70,$D$1:$BZ$1,CW$9) -> -180.40392 | CX70: =SUMIFS($D70:$BZ70,$D$1:$BZ$1,CX$9) -> -187.50644
C71: Planning Team Payroll | P71: =-SUMIFS('Monthly P&L'!H:H,'Monthly P&L'!$A:$A,$C71)/1000 -> 0 | Q71: =-SUMIFS('Monthly P&L'!I:I,'Monthly P&L'!$A:$A,$C71)/1000 -> 0 | R71: =-SUMIFS('Monthly P&L'!J:J,'Monthly P&L'!$A:$A,$C71)/1000 -> 0 | S71: =-SUMIFS('Monthly P&L'!K:K,'Monthly P&L'!$A:$A,$C71)/1000 -> 0 | T71: =-SUMIFS('Monthly P&L'!L:L,'Monthly P&L'!$A:$A,$C71)/1000 -> 0 | U71: =-SUMIFS('Monthly P&L'!M:M,'Monthly P&L'!$A:$A,$C71)/1000 -> 0 | V71: =-SUMIFS('Monthly P&L'!N:N,'Monthly P&L'!$A:$A,$C71)/1000 -> 0 | W71: =-SUMIFS('Monthly P&L'!O:O,'Monthly P&L'!$A:$A,$C71)/1000 -> 0 | X71: =-SUMIFS('Monthly P&L'!P:P,'Monthly P&L'!$A:$A,$C71)/1000 -> 0 | Y71: =-SUMIFS('Monthly P&L'!Q:Q,'Monthly P&L'!$A:$A,$C71)/1000 -> 0 | Z71: =-SUMIFS('Monthly P&L'!R:R,'Monthly P&L'!$A:$A,$C71)/1000 -> 0 | AA71: =-SUMIFS('Monthly P&L'!S:S,'Monthly P&L'!$A:$A,$C71)/1000 -> 0 | AB71: =-SUMIFS('Monthly P&L'!T:T,'Monthly P&L'!$A:$A,$C71)/1000 -> 0 | AC71: =-SUMIFS('Monthly P&L'!U:U,'Monthly P&L'!$A:$A,$C71)/1000 -> 0 | AD71: =-SUMIFS('Monthly P&L'!V:V,'Monthly P&L'!$A:$A,$C71)/1000 -> 0 | AE71: =-SUMIFS('Monthly P&L'!W:W,'Monthly P&L'!$A:$A,$C71)/1000 -> 0 | AF71: =-SUMIFS('Monthly P&L'!X:X,'Monthly P&L'!$A:$A,$C71)/1000*2 -> 0 | AH71: =SUMIFS($CD71:$CF71,$CD$2:$CF$2,AH$3)/12 -> -6.981 | AI71: =SUMIFS($CD71:$CF71,$CD$2:$CF$2,AI$3)/12 -> -6.981 | AJ71: =SUMIFS($CD71:$CF71,$CD$2:$CF$2,AJ$3)/12 -> -6.981 | AK71: =SUMIFS($CD71:$CF71,$CD$2:$CF$2,AK$3)/12 -> -6.981 | AL71: =SUMIFS($CD71:$CF71,$CD$2:$CF$2,AL$3)/12 -> -6.981 | AM71: =SUMIFS($CD71:$CF71,$CD$2:$CF$2,AM$3)/12 -> -6.981 | AN71: =SUMIFS($CD71:$CF71,$CD$2:$CF$2,AN$3)/12 -> -6.981 | AO71: =SUMIFS($CD71:$CF71,$CD$2:$CF$2,AO$3)/12 -> -6.981 | ... BQ71: =SUMIFS($CD71:$CF71,$CD$2:$CF$2,BQ$3)/12 -> -8.44701 | BS71: =BF71 -> -8.44701 | BT71: =BG71 -> -8.44701 | BU71: =BH71 -> -8.44701 | BV71: =BI71 -> -8.44701 | BW71: =BJ71 -> -8.44701 | BX71: =BK71 -> -8.44701 | BY71: =BL71 -> -8.44701 | CA71: =-SUMIFS('Monthly P&L'!$E:$E,'Monthly P&L'!$A:$A,$C71)/1000 -> 0 | CB71: =SUMIFS($D71:$AF71,$D$1:$AF$1,CB$2) -> 0 | CC71: =SUMIFS($P71:$AF71,$P$3:$AF$3,$CC$2) -> 0 | CD71: =-SUMIFS('Go-Forward Payroll'!$G$3:$G$10,'Go-Forward Payroll'!$I$3:$I$10,$C71)/1000 -> -83.772 | CE71: =CD71*(1+CI71) -> -92.1492 | CF71: =CE71*(1+CJ71) -> -101.36412 | CI71: 0.1 | CJ71: 0.1 | CL71: =IFERROR(CC71/CC$55,0) -> 0 | CN71: =-SUMIFS('FY25 By Venue Financials'!$J:$J,'FY25 By Venue Financials'!$A:$A,$C71) -> -1777.4212 | CQ71: YoY Growth | CR71: Annually - Split / 12 - YoY Growth from AJ/DZ estimates | CU71: =SUMIFS($D71:$BZ71,$D$1:$BZ$1,CU$9) -> -48.867 | CV71: =SUMIFS($D71:$BZ71,$D$1:$BZ$1,CV$9) -> -88.6587 | CW71: =SUMIFS($D71:$BZ71,$D$1:$BZ$1,CW$9) -> -97.52457 | CX71: =SUMIFS($D71:$BZ71,$D$1:$BZ$1,CX$9) -> -101.36412
C72: Operations Team Payroll | P72: =-SUMIFS('Monthly P&L'!H:H,'Monthly P&L'!$A:$A,$C72)/1000 -> -5.08896 | Q72: =-SUMIFS('Monthly P&L'!I:I,'Monthly P&L'!$A:$A,$C72)/1000 -> -2.202 | R72: =-SUMIFS('Monthly P&L'!J:J,'Monthly P&L'!$A:$A,$C72)/1000 -> -1.3826 | S72: =-SUMIFS('Monthly P&L'!K:K,'Monthly P&L'!$A:$A,$C72)/1000 -> -7.0238 | T72: =-SUMIFS('Monthly P&L'!L:L,'Monthly P&L'!$A:$A,$C72)/1000 -> -12.11184 | U72: =-SUMIFS('Monthly P&L'!M:M,'Monthly P&L'!$A:$A,$C72)/1000 -> -12.97526 | V72: =-SUMIFS('Monthly P&L'!N:N,'Monthly P&L'!$A:$A,$C72)/1000 -> -10.42691 | W72: =-SUMIFS('Monthly P&L'!O:O,'Monthly P&L'!$A:$A,$C72)/1000 -> -5.35932 | X72: =-SUMIFS('Monthly P&L'!P:P,'Monthly P&L'!$A:$A,$C72)/1000 -> -8.46748 | Y72: =-SUMIFS('Monthly P&L'!Q:Q,'Monthly P&L'!$A:$A,$C72)/1000 -> -12.55895 | Z72: =-SUMIFS('Monthly P&L'!R:R,'Monthly P&L'!$A:$A,$C72)/1000 -> -13.5855 | AA72: =-SUMIFS('Monthly P&L'!S:S,'Monthly P&L'!$A:$A,$C72)/1000 -> -6.9984 | AB72: =-SUMIFS('Monthly P&L'!T:T,'Monthly P&L'!$A:$A,$C72)/1000 -> -2.33824 | AC72: =-SUMIFS('Monthly P&L'!U:U,'Monthly P&L'!$A:$A,$C72)/1000 -> 0 | AD72: =-SUMIFS('Monthly P&L'!V:V,'Monthly P&L'!$A:$A,$C72)/1000 -> -0.965 | AE72: =-SUMIFS('Monthly P&L'!W:W,'Monthly P&L'!$A:$A,$C72)/1000 -> -9.32044 | AF72: =-SUMIFS('Monthly P&L'!X:X,'Monthly P&L'!$A:$A,$C72)/1000*2 -> -19.04632 | AH72: =SUMIFS($CD72:$CF72,$CD$2:$CF$2,AH$3)*AH$36 -> -10.7264 | AI72: =SUMIFS($CD72:$CF72,$CD$2:$CF$2,AI$3)*AI$36 -> -8.9386667 | AJ72: =SUMIFS($CD72:$CF72,$CD$2:$CF$2,AJ$3)*AJ$36 -> -13.408 | AK72: =SUMIFS($CD72:$CF72,$CD$2:$CF$2,AK$3)*AK$36 -> -16.983467 | AL72: =SUMIFS($CD72:$CF72,$CD$2:$CF$2,AL$3)*AL$36 -> -21.4528 | AM72: =SUMIFS($CD72:$CF72,$CD$2:$CF$2,AM$3)*AM$36 -> -10.7264 | AN72: =SUMIFS($CD72:$CF72,$CD$2:$CF$2,AN$3)*AN$36 -> -4.4693333 | AO72: =SUMIFS($CD72:$CF72,$CD$2:$CF$2,AO$3)*AO$36 -> 0 | ... BQ72: =SUMIFS($CD72:$CF72,$CD$2:$CF$2,BQ$3)*BQ$36 -> -23.240533 | BS72: =BF72 -> -16.983467 | BT72: =BG72 -> -8.9386667 | BU72: =BH72 -> -15.195733 | BV72: =BI72 -> -19.665067 | BW72: =BJ72 -> -23.240533 | BX72: =BK72 -> -13.408 | BY72: =BL72 -> -5.3632 | CA72: =-SUMIFS('Monthly P&L'!$E:$E,'Monthly P&L'!$A:$A,$C72)/1000 -> -125.88753 | CB72: =SUMIFS($D72:$AF72,$D$1:$AF$1,CB$2) -> -98.18102 | CC72: =SUMIFS($P72:$AF72,$P$3:$AF$3,$CC$2) -> -95.10734 | CD72: =-SUMIFS('Go-Forward Payroll'!$G$3:$G$10,'Go-Forward Payroll'!$I$3:$I$10,$C72)/1000 -> -134.08 | CE72: =CE35*CI72 -> -143.01867 | CF72: =CF35*CJ72 -> -151.95733 | CH72: =CD72/$CD$35 -> -0.89386667 | CI72: =CH72 -> -0.89386667 | CJ72: =CI72 -> -0.89386667 | CL72: =IFERROR(CC72/CC$55,0) -> -0.071688243 | CN72: =-SUMIFS('FY25 By Venue Financials'!$J:$J,'FY25 By Venue Financials'!$A:$A,$C72) -> -1231.9639 | CO72: =IFERROR(CN72/CN$55,0) -> -0.033983996 | CQ72: $ / event | CR72: Annual - split monthly by seasonality - AJ/DZ estimates | CU72: =SUMIFS($D72:$BZ72,$D$1:$BZ$1,CU$9) -> -118.37507 | CV72: =SUMIFS($D72:$BZ72,$D$1:$BZ$1,CV$9) -> -144.8064 | CW72: =SUMIFS($D72:$BZ72,$D$1:$BZ$1,CW$9) -> -148.38187 | CX72: =SUMIFS($D72:$BZ72,$D$1:$BZ$1,CX$9) -> -151.95733
C73: Ancillary Payroll | P73: =-SUMIFS('Monthly P&L'!H:H,'Monthly P&L'!$A:$A,$C73)/1000 -> 0 | Q73: =-SUMIFS('Monthly P&L'!I:I,'Monthly P&L'!$A:$A,$C73)/1000 -> 0 | R73: =-SUMIFS('Monthly P&L'!J:J,'Monthly P&L'!$A:$A,$C73)/1000 -> 0 | S73: =-SUMIFS('Monthly P&L'!K:K,'Monthly P&L'!$A:$A,$C73)/1000 -> 0 | T73: =-SUMIFS('Monthly P&L'!L:L,'Monthly P&L'!$A:$A,$C73)/1000 -> 0 | U73: =-SUMIFS('Monthly P&L'!M:M,'Monthly P&L'!$A:$A,$C73)/1000 -> 0 | V73: =-SUMIFS('Monthly P&L'!N:N,'Monthly P&L'!$A:$A,$C73)/1000 -> 0 | W73: =-SUMIFS('Monthly P&L'!O:O,'Monthly P&L'!$A:$A,$C73)/1000 -> 0 | X73: =-SUMIFS('Monthly P&L'!P:P,'Monthly P&L'!$A:$A,$C73)/1000 -> 0 | Y73: =-SUMIFS('Monthly P&L'!Q:Q,'Monthly P&L'!$A:$A,$C73)/1000 -> 0 | Z73: =-SUMIFS('Monthly P&L'!R:R,'Monthly P&L'!$A:$A,$C73)/1000 -> 0 | AA73: =-SUMIFS('Monthly P&L'!S:S,'Monthly P&L'!$A:$A,$C73)/1000 -> 0 | AB73: =-SUMIFS('Monthly P&L'!T:T,'Monthly P&L'!$A:$A,$C73)/1000 -> 0 | AC73: =-SUMIFS('Monthly P&L'!U:U,'Monthly P&L'!$A:$A,$C73)/1000 -> 0 | AD73: =-SUMIFS('Monthly P&L'!V:V,'Monthly P&L'!$A:$A,$C73)/1000 -> 0 | AE73: =-SUMIFS('Monthly P&L'!W:W,'Monthly P&L'!$A:$A,$C73)/1000 -> 0 | AF73: =-SUMIFS('Monthly P&L'!X:X,'Monthly P&L'!$A:$A,$C73)/1000*2 -> 0 | AH73: =SUMIFS($CD73:$CF73,$CD$2:$CF$2,AH$3)*AH$36 -> 0 | AI73: =SUMIFS($CD73:$CF73,$CD$2:$CF$2,AI$3)*AI$36 -> 0 | AJ73: =SUMIFS($CD73:$CF73,$CD$2:$CF$2,AJ$3)*AJ$36 -> 0 | AK73: =SUMIFS($CD73:$CF73,$CD$2:$CF$2,AK$3)*AK$36 -> 0 | AL73: =SUMIFS($CD73:$CF73,$CD$2:$CF$2,AL$3)*AL$36 -> 0 | AM73: =SUMIFS($CD73:$CF73,$CD$2:$CF$2,AM$3)*AM$36 -> 0 | AN73: =SUMIFS($CD73:$CF73,$CD$2:$CF$2,AN$3)*AN$36 -> 0 | AO73: =SUMIFS($CD73:$CF73,$CD$2:$CF$2,AO$3)*AO$36 -> 0 | ... BQ73: =SUMIFS($CD73:$CF73,$CD$2:$CF$2,BQ$3)*BQ$36 -> 0 | BS73: =BF73 -> 0 | BT73: =BG73 -> 0 | BU73: =BH73 -> 0 | BV73: =BI73 -> 0 | BW73: =BJ73 -> 0 | BX73: =BK73 -> 0 | BY73: =BL73 -> 0 | CA73: =-SUMIFS('Monthly P&L'!$E:$E,'Monthly P&L'!$A:$A,$C73)/1000 -> 0 | CB73: =SUMIFS($D73:$AF73,$D$1:$AF$1,CB$2) -> 0 | CC73: =SUMIFS($P73:$AF73,$P$3:$AF$3,$CC$2) -> 0 | CD73: =CD$49*CH73 -> 0 | CE73: =CE$49*CI73 -> 0 | CF73: =CF$49*CJ73 -> 0 | CL73: =IFERROR(CC73/CC62,0) -> 0 | CN73: =-SUMIFS('FY25 By Venue Financials'!$J:$J,'FY25 By Venue Financials'!$A:$A,$C73) -> -2853.354 | CO73: =IFERROR(CN73/CN$49,0) -> -0.29272747 | CQ73: % Ancillary Rev | CR73: N/A - Using 3rd party vendors, payout captured above in COGS | CU73: =SUMIFS($D73:$BZ73,$D$1:$BZ$1,CU$9) -> 0 | CV73: =SUMIFS($D73:$BZ73,$D$1:$BZ$1,CV$9) -> 0 | CW73: =SUMIFS($D73:$BZ73,$D$1:$BZ$1,CW$9) -> 0 | CX73: =SUMIFS($D73:$BZ73,$D$1:$BZ$1,CX$9) -> 0
C74: Corporate Team Payroll | P74: =-SUMIFS('Monthly P&L'!H:H,'Monthly P&L'!$A:$A,$C74)/1000 -> 0 | Q74: =-SUMIFS('Monthly P&L'!I:I,'Monthly P&L'!$A:$A,$C74)/1000 -> 0 | R74: =-SUMIFS('Monthly P&L'!J:J,'Monthly P&L'!$A:$A,$C74)/1000 -> 0 | S74: =-SUMIFS('Monthly P&L'!K:K,'Monthly P&L'!$A:$A,$C74)/1000 -> 0 | T74: =-SUMIFS('Monthly P&L'!L:L,'Monthly P&L'!$A:$A,$C74)/1000 -> 0 | U74: =-SUMIFS('Monthly P&L'!M:M,'Monthly P&L'!$A:$A,$C74)/1000 -> 0 | V74: =-SUMIFS('Monthly P&L'!N:N,'Monthly P&L'!$A:$A,$C74)/1000 -> 0 | W74: =-SUMIFS('Monthly P&L'!O:O,'Monthly P&L'!$A:$A,$C74)/1000 -> 0 | X74: =-SUMIFS('Monthly P&L'!P:P,'Monthly P&L'!$A:$A,$C74)/1000 -> 0 | Y74: =-SUMIFS('Monthly P&L'!Q:Q,'Monthly P&L'!$A:$A,$C74)/1000 -> 0 | Z74: =-SUMIFS('Monthly P&L'!R:R,'Monthly P&L'!$A:$A,$C74)/1000 -> 0 | AA74: =-SUMIFS('Monthly P&L'!S:S,'Monthly P&L'!$A:$A,$C74)/1000 -> 0 | AB74: =-SUMIFS('Monthly P&L'!T:T,'Monthly P&L'!$A:$A,$C74)/1000 -> 0 | AC74: =-SUMIFS('Monthly P&L'!U:U,'Monthly P&L'!$A:$A,$C74)/1000 -> 0 | AD74: =-SUMIFS('Monthly P&L'!V:V,'Monthly P&L'!$A:$A,$C74)/1000 -> 0 | AE74: =-SUMIFS('Monthly P&L'!W:W,'Monthly P&L'!$A:$A,$C74)/1000 -> 0 | AF74: =-SUMIFS('Monthly P&L'!X:X,'Monthly P&L'!$A:$A,$C74)/1000*2 -> 0 | AH74: =SUMIFS($CD74:$CF74,$CD$2:$CF$2,AH$3)*AH$36 -> -0.0098720753 | AI74: =SUMIFS($CD74:$CF74,$CD$2:$CF$2,AI$3)*AI$36 -> -0.0082267294 | AJ74: =SUMIFS($CD74:$CF74,$CD$2:$CF$2,AJ$3)*AJ$36 -> -0.012340094 | AK74: =SUMIFS($CD74:$CF74,$CD$2:$CF$2,AK$3)*AK$36 -> -0.015630786 | AL74: =SUMIFS($CD74:$CF74,$CD$2:$CF$2,AL$3)*AL$36 -> -0.019744151 | AM74: =SUMIFS($CD74:$CF74,$CD$2:$CF$2,AM$3)*AM$36 -> -0.0098720753 | AN74: =SUMIFS($CD74:$CF74,$CD$2:$CF$2,AN$3)*AN$36 -> -0.0041133647 | AO74: =SUMIFS($CD74:$CF74,$CD$2:$CF$2,AO$3)*AO$36 -> 0 | ... BQ74: =SUMIFS($CD74:$CF74,$CD$2:$CF$2,BQ$3)*BQ$36 -> -0.03652068 | BS74: =BF74 -> -0.026688189 | BT74: =BG74 -> -0.014046415 | BU74: =BH74 -> -0.023878906 | BV74: =BI74 -> -0.030902114 | BW74: =BJ74 -> -0.03652068 | BX74: =BK74 -> -0.021069623 | BY74: =BL74 -> -0.0084278492 | CA74: =-SUMIFS('Monthly P&L'!$E:$E,'Monthly P&L'!$A:$A,$C74)/1000 -> 0 | CB74: =SUMIFS($D74:$AF74,$D$1:$AF$1,CB$2) -> 0 | CC74: =SUMIFS($P74:$AF74,$P$3:$AF$3,$CC$2) -> 0 | CD74: =CD$55*CH74 -> -0.12340094 | CE74: =CE$55*CI74 -> -0.16787738 | CF74: =CF$55*CJ74 -> -0.23878906 | CH74: =$CO74 -> -6.2850167e-05 | CI74: =$CO74 -> -6.2850167e-05 | CJ74: =$CO74 -> -6.2850167e-05 | CL74: =IFERROR(CC74/CC$55,0) -> 0 | CN74: =-SUMIFS('FY25 By Venue Financials'!$J:$J,'FY25 By Venue Financials'!$A:$A,$C74) -> -2.2784 | CO74: =IFERROR(CN74/CN$55,0) -> -6.2850167e-05 | CQ74: % Total Rev | CR74: Annually - Split / 12 | CU74: =SUMIFS($D74:$BZ74,$D$1:$BZ$1,CU$9) -> -0.079799275 | CV74: =SUMIFS($D74:$BZ74,$D$1:$BZ$1,CV$9) -> -0.15796813 | CW74: =SUMIFS($D74:$BZ74,$D$1:$BZ$1,CW$9) -> -0.21504469 | CX74: =SUMIFS($D74:$BZ74,$D$1:$BZ$1,CX$9) -> -0.23878906
C75: F&B Team Payroll | P75: =-SUMIFS('Monthly P&L'!H:H,'Monthly P&L'!$A:$A,$C75)/1000 -> 0 | Q75: =-SUMIFS('Monthly P&L'!I:I,'Monthly P&L'!$A:$A,$C75)/1000 -> 0 | R75: =-SUMIFS('Monthly P&L'!J:J,'Monthly P&L'!$A:$A,$C75)/1000 -> 0 | S75: =-SUMIFS('Monthly P&L'!K:K,'Monthly P&L'!$A:$A,$C75)/1000 -> 0 | T75: =-SUMIFS('Monthly P&L'!L:L,'Monthly P&L'!$A:$A,$C75)/1000 -> 0 | U75: =-SUMIFS('Monthly P&L'!M:M,'Monthly P&L'!$A:$A,$C75)/1000 -> 0 | V75: =-SUMIFS('Monthly P&L'!N:N,'Monthly P&L'!$A:$A,$C75)/1000 -> 0 | W75: =-SUMIFS('Monthly P&L'!O:O,'Monthly P&L'!$A:$A,$C75)/1000 -> 0 | X75: =-SUMIFS('Monthly P&L'!P:P,'Monthly P&L'!$A:$A,$C75)/1000 -> 0 | Y75: =-SUMIFS('Monthly P&L'!Q:Q,'Monthly P&L'!$A:$A,$C75)/1000 -> 0 | Z75: =-SUMIFS('Monthly P&L'!R:R,'Monthly P&L'!$A:$A,$C75)/1000 -> 0 | AA75: =-SUMIFS('Monthly P&L'!S:S,'Monthly P&L'!$A:$A,$C75)/1000 -> 0 | AB75: =-SUMIFS('Monthly P&L'!T:T,'Monthly P&L'!$A:$A,$C75)/1000 -> 0 | AC75: =-SUMIFS('Monthly P&L'!U:U,'Monthly P&L'!$A:$A,$C75)/1000 -> 0 | AD75: =-SUMIFS('Monthly P&L'!V:V,'Monthly P&L'!$A:$A,$C75)/1000 -> 0 | AE75: =-SUMIFS('Monthly P&L'!W:W,'Monthly P&L'!$A:$A,$C75)/1000 -> 0 | AF75: =-SUMIFS('Monthly P&L'!X:X,'Monthly P&L'!$A:$A,$C75)/1000*2 -> 0 | AH75: =SUMIFS($CD75:$CF75,$CD$2:$CF$2,AH$3)*AH$36 -> 0 | AI75: =SUMIFS($CD75:$CF75,$CD$2:$CF$2,AI$3)*AI$36 -> 0 | AJ75: =SUMIFS($CD75:$CF75,$CD$2:$CF$2,AJ$3)*AJ$36 -> 0 | AK75: =SUMIFS($CD75:$CF75,$CD$2:$CF$2,AK$3)*AK$36 -> 0 | AL75: =SUMIFS($CD75:$CF75,$CD$2:$CF$2,AL$3)*AL$36 -> 0 | AM75: =SUMIFS($CD75:$CF75,$CD$2:$CF$2,AM$3)*AM$36 -> 0 | AN75: =SUMIFS($CD75:$CF75,$CD$2:$CF$2,AN$3)*AN$36 -> 0 | AO75: =SUMIFS($CD75:$CF75,$CD$2:$CF$2,AO$3)*AO$36 -> 0 | ... BQ75: =SUMIFS($CD75:$CF75,$CD$2:$CF$2,BQ$3)*BQ$36 -> 0 | BS75: =BF75 -> 0 | BT75: =BG75 -> 0 | BU75: =BH75 -> 0 | BV75: =BI75 -> 0 | BW75: =BJ75 -> 0 | BX75: =BK75 -> 0 | BY75: =BL75 -> 0 | CA75: =-SUMIFS('Monthly P&L'!$E:$E,'Monthly P&L'!$A:$A,$C75)/1000 -> 0 | CB75: =SUMIFS($D75:$AF75,$D$1:$AF$1,CB$2) -> 0 | CC75: =SUMIFS($P75:$AF75,$P$3:$AF$3,$CC$2) -> 0 | CD75: =SUM(CD46:CD47)*CH75 -> 0 | CE75: =SUM(CE46:CE47)*CI75 -> 0 | CF75: =SUM(CF46:CF47)*CJ75 -> 0 | CL75: =IFERROR(CC75/CC$55,0) -> 0 | CN75: =-SUMIFS('FY25 By Venue Financials'!$J:$J,'FY25 By Venue Financials'!$A:$A,$C75) -> -2106.4351 | CO75: =CN75/SUM(CN46:CN47) -> -0.16558801 | CQ75: % F&B Rev | CR75: N/A - Using 3rd party vendors, payout captured above in COGS | CU75: =SUMIFS($D75:$BZ75,$D$1:$BZ$1,CU$9) -> 0 | CV75: =SUMIFS($D75:$BZ75,$D$1:$BZ$1,CV$9) -> 0 | CW75: =SUMIFS($D75:$BZ75,$D$1:$BZ$1,CW$9) -> 0 | CX75: =SUMIFS($D75:$BZ75,$D$1:$BZ$1,CX$9) -> 0
C76: Owner Salaries | P76: =-SUMIFS('Monthly P&L'!H:H,'Monthly P&L'!$A:$A,$C76)/1000 -> 0 | Q76: =-SUMIFS('Monthly P&L'!I:I,'Monthly P&L'!$A:$A,$C76)/1000 -> 0 | R76: =-SUMIFS('Monthly P&L'!J:J,'Monthly P&L'!$A:$A,$C76)/1000 -> 0 | S76: =-SUMIFS('Monthly P&L'!K:K,'Monthly P&L'!$A:$A,$C76)/1000 -> 0 | T76: =-SUMIFS('Monthly P&L'!L:L,'Monthly P&L'!$A:$A,$C76)/1000 -> 0 | U76: =-SUMIFS('Monthly P&L'!M:M,'Monthly P&L'!$A:$A,$C76)/1000 -> 0 | V76: =-SUMIFS('Monthly P&L'!N:N,'Monthly P&L'!$A:$A,$C76)/1000 -> 0 | W76: =-SUMIFS('Monthly P&L'!O:O,'Monthly P&L'!$A:$A,$C76)/1000 -> 0 | X76: =-SUMIFS('Monthly P&L'!P:P,'Monthly P&L'!$A:$A,$C76)/1000 -> 0 | Y76: =-SUMIFS('Monthly P&L'!Q:Q,'Monthly P&L'!$A:$A,$C76)/1000 -> 0 | Z76: =-SUMIFS('Monthly P&L'!R:R,'Monthly P&L'!$A:$A,$C76)/1000 -> 0 | AA76: =-SUMIFS('Monthly P&L'!S:S,'Monthly P&L'!$A:$A,$C76)/1000 -> 0 | AB76: =-SUMIFS('Monthly P&L'!T:T,'Monthly P&L'!$A:$A,$C76)/1000 -> 0 | AC76: =-SUMIFS('Monthly P&L'!U:U,'Monthly P&L'!$A:$A,$C76)/1000 -> 0 | AD76: =-SUMIFS('Monthly P&L'!V:V,'Monthly P&L'!$A:$A,$C76)/1000 -> 0 | AE76: =-SUMIFS('Monthly P&L'!W:W,'Monthly P&L'!$A:$A,$C76)/1000 -> 0 | AF76: =-SUMIFS('Monthly P&L'!X:X,'Monthly P&L'!$A:$A,$C76)/1000*2 -> 0 | AH76: =SUMIFS($CD76:$CF76,$CD$2:$CF$2,AH$3)*AH$36 -> 0 | AI76: =SUMIFS($CD76:$CF76,$CD$2:$CF$2,AI$3)*AI$36 -> 0 | AJ76: =SUMIFS($CD76:$CF76,$CD$2:$CF$2,AJ$3)*AJ$36 -> 0 | AK76: =SUMIFS($CD76:$CF76,$CD$2:$CF$2,AK$3)*AK$36 -> 0 | AL76: =SUMIFS($CD76:$CF76,$CD$2:$CF$2,AL$3)*AL$36 -> 0 | AM76: =SUMIFS($CD76:$CF76,$CD$2:$CF$2,AM$3)*AM$36 -> 0 | AN76: =SUMIFS($CD76:$CF76,$CD$2:$CF$2,AN$3)*AN$36 -> 0 | AO76: =SUMIFS($CD76:$CF76,$CD$2:$CF$2,AO$3)*AO$36 -> 0 | ... BQ76: =SUMIFS($CD76:$CF76,$CD$2:$CF$2,BQ$3)*BQ$36 -> 0 | BS76: =BF76 -> 0 | BT76: =BG76 -> 0 | BU76: =BH76 -> 0 | BV76: =BI76 -> 0 | BW76: =BJ76 -> 0 | BX76: =BK76 -> 0 | BY76: =BL76 -> 0 | CA76: =-SUMIFS('Monthly P&L'!$E:$E,'Monthly P&L'!$A:$A,$C76)/1000 -> 0 | CB76: =SUMIFS($D76:$AF76,$D$1:$AF$1,CB$2) -> 0 | CC76: =SUMIFS($P76:$AF76,$P$3:$AF$3,$CC$2) -> 0 | CD76: =CD$55*CH76 -> 0 | CE76: =CE$55*CI76 -> 0 | CF76: =CF$55*CJ76 -> 0 | CH76: =$CO76 -> 0 | CI76: =$CO76 -> 0 | CJ76: =$CO76 -> 0 | CL76: =IFERROR(CC76/CC$55,0) -> 0 | CN76: =-SUMIFS('FY25 By Venue Financials'!$J:$J,'FY25 By Venue Financials'!$A:$A,$C76) -> 0 | CO76: =IFERROR(CN76/CN$55,0) -> 0 | CQ76: % Total Rev | CR76: - | CU76: =SUMIFS($D76:$BZ76,$D$1:$BZ$1,CU$9) -> 0 | CV76: =SUMIFS($D76:$BZ76,$D$1:$BZ$1,CV$9) -> 0 | CW76: =SUMIFS($D76:$BZ76,$D$1:$BZ$1,CW$9) -> 0 | CX76: =SUMIFS($D76:$BZ76,$D$1:$BZ$1,CX$9) -> 0
C77: Payroll Admin & Benefit Expenses | P77: =-SUMIFS('Monthly P&L'!H:H,'Monthly P&L'!$A:$A,$C77)/1000 -> -1.195 | Q77: =-SUMIFS('Monthly P&L'!I:I,'Monthly P&L'!$A:$A,$C77)/1000 -> -2.19385 | R77: =-SUMIFS('Monthly P&L'!J:J,'Monthly P&L'!$A:$A,$C77)/1000 -> -2.36887 | S77: =-SUMIFS('Monthly P&L'!K:K,'Monthly P&L'!$A:$A,$C77)/1000 -> -1.33425 | T77: =-SUMIFS('Monthly P&L'!L:L,'Monthly P&L'!$A:$A,$C77)/1000 -> 0 | U77: =-SUMIFS('Monthly P&L'!M:M,'Monthly P&L'!$A:$A,$C77)/1000 -> 0 | V77: =-SUMIFS('Monthly P&L'!N:N,'Monthly P&L'!$A:$A,$C77)/1000 -> 0 | W77: =-SUMIFS('Monthly P&L'!O:O,'Monthly P&L'!$A:$A,$C77)/1000 -> 0 | X77: =-SUMIFS('Monthly P&L'!P:P,'Monthly P&L'!$A:$A,$C77)/1000 -> 0 | Y77: =-SUMIFS('Monthly P&L'!Q:Q,'Monthly P&L'!$A:$A,$C77)/1000 -> 0 | Z77: =-SUMIFS('Monthly P&L'!R:R,'Monthly P&L'!$A:$A,$C77)/1000 -> 0 | AA77: =-SUMIFS('Monthly P&L'!S:S,'Monthly P&L'!$A:$A,$C77)/1000 -> 0 | AB77: =-SUMIFS('Monthly P&L'!T:T,'Monthly P&L'!$A:$A,$C77)/1000 -> 0 | AC77: =-SUMIFS('Monthly P&L'!U:U,'Monthly P&L'!$A:$A,$C77)/1000 -> 0 | AD77: =-SUMIFS('Monthly P&L'!V:V,'Monthly P&L'!$A:$A,$C77)/1000 -> 0 | AE77: =-SUMIFS('Monthly P&L'!W:W,'Monthly P&L'!$A:$A,$C77)/1000 -> 0 | AF77: =-SUMIFS('Monthly P&L'!X:X,'Monthly P&L'!$A:$A,$C77)/1000*2 -> 0 | AH77: =SUM(AH70:AH76,AH78)*SUMIFS($CH$77:$CJ$77,$CD$2:$CF$2,AH$3) -> -3.5896132 | AI77: =SUM(AI70:AI76,AI78)*SUMIFS($CH$77:$CJ$77,$CD$2:$CF$2,AI$3) -> -3.3774705 | AJ77: =SUM(AJ70:AJ76,AJ78)*SUMIFS($CH$77:$CJ$77,$CD$2:$CF$2,AJ$3) -> -3.9078272 | AK77: =SUM(AK70:AK76,AK78)*SUMIFS($CH$77:$CJ$77,$CD$2:$CF$2,AK$3) -> -4.3321127 | AL77: =SUM(AL70:AL76,AL78)*SUMIFS($CH$77:$CJ$77,$CD$2:$CF$2,AL$3) -> -4.8624694 | AM77: =SUM(AM70:AM76,AM78)*SUMIFS($CH$77:$CJ$77,$CD$2:$CF$2,AM$3) -> -3.5896132 | AN77: =SUM(AN70:AN76,AN78)*SUMIFS($CH$77:$CJ$77,$CD$2:$CF$2,AN$3) -> -2.8471137 | AO77: =SUM(AO70:AO76,AO78)*SUMIFS($CH$77:$CJ$77,$CD$2:$CF$2,AO$3) -> -2.3167569 | ... BQ77: =SUM(BQ70:BQ76,BQ78)*SUMIFS($CH$77:$CJ$77,$CD$2:$CF$2,BQ$3) -> -5.5975404 | BS77: =BF77 -> -4.8452384 | BT77: =BG77 -> -3.877993 | BU77: =BH77 -> -4.630295 | BV77: =BI77 -> -5.1676535 | BW77: =BJ77 -> -5.5975404 | BX77: =BK77 -> -4.4153515 | BY77: =BL77 -> -3.4481061 | CA77: =-SUMIFS('Monthly P&L'!$E:$E,'Monthly P&L'!$A:$A,$C77)/1000 -> -25.3007 | CB77: =SUMIFS($D77:$AF77,$D$1:$AF$1,CB$2) -> -7.09197 | CC77: =SUMIFS($P77:$AF77,$P$3:$AF$3,$CC$2) -> 0 | CD77: =SUMIFS($D77:$BZ77,$D$3:$BZ$3,CD$2) -> -43.711786 | CE77: =SUMIFS($D77:$BZ77,$D$3:$BZ$3,CE$2) -> -47.639834 | CF77: =SUMIFS($D77:$BZ77,$D$3:$BZ$3,CF$2) -> -51.909501 | CH77: =$CO77 -> 0.11645116 | CI77: =$CO77 -> 0.11645116 | CJ77: =$CO77 -> 0.11645116 | CL77: =IFERROR(CC77/SUM(CC70:CC73,CC74:CC76,CC78),0) -> 0 | CN77: =-SUMIFS('FY25 By Venue Financials'!$J:$J,'FY25 By Venue Financials'!$A:$A,$C77) -> -1111.9102 | CO77: =CN77/SUM(CN70:CN73,CN74:CN76,CN78) -> 0.11645116 | CQ77: % Total Other Payroll | CR77: Monthly | CU77: =SUMIFS($D77:$BZ77,$D$1:$BZ$1,CU$9) -> -26.50622 | CV77: =SUMIFS($D77:$BZ77,$D$1:$BZ$1,CV$9) -> -46.665795 | CW77: =SUMIFS($D77:$BZ77,$D$1:$BZ$1,CW$9) -> -50.161783 | CX77: =SUMIFS($D77:$BZ77,$D$1:$BZ$1,CX$9) -> -51.909501
C78: Other Payroll | P78: =-SUMIFS('Monthly P&L'!H:H,'Monthly P&L'!$A:$A,$C78)/1000 -> -24.18769 | Q78: =-SUMIFS('Monthly P&L'!I:I,'Monthly P&L'!$A:$A,$C78)/1000 -> -11.93135 | R78: =-SUMIFS('Monthly P&L'!J:J,'Monthly P&L'!$A:$A,$C78)/1000 -> -13.75441 | S78: =-SUMIFS('Monthly P&L'!K:K,'Monthly P&L'!$A:$A,$C78)/1000 -> -20.90426 | T78: =-SUMIFS('Monthly P&L'!L:L,'Monthly P&L'!$A:$A,$C78)/1000 -> -22.70429 | U78: =-SUMIFS('Monthly P&L'!M:M,'Monthly P&L'!$A:$A,$C78)/1000 -> -29.67085 | V78: =-SUMIFS('Monthly P&L'!N:N,'Monthly P&L'!$A:$A,$C78)/1000 -> -33.71978 | W78: =-SUMIFS('Monthly P&L'!O:O,'Monthly P&L'!$A:$A,$C78)/1000 -> -28.89445 | X78: =-SUMIFS('Monthly P&L'!P:P,'Monthly P&L'!$A:$A,$C78)/1000 -> -27.68061 | Y78: =-SUMIFS('Monthly P&L'!Q:Q,'Monthly P&L'!$A:$A,$C78)/1000 -> -45.93833 | Z78: =-SUMIFS('Monthly P&L'!R:R,'Monthly P&L'!$A:$A,$C78)/1000 -> -18.86054 | AA78: =-SUMIFS('Monthly P&L'!S:S,'Monthly P&L'!$A:$A,$C78)/1000 -> -16.22836 | AB78: =-SUMIFS('Monthly P&L'!T:T,'Monthly P&L'!$A:$A,$C78)/1000 -> -19.68122 | AC78: =-SUMIFS('Monthly P&L'!U:U,'Monthly P&L'!$A:$A,$C78)/1000 -> -22.22098 | AD78: =-SUMIFS('Monthly P&L'!V:V,'Monthly P&L'!$A:$A,$C78)/1000 -> -25.70476 | AE78: =-SUMIFS('Monthly P&L'!W:W,'Monthly P&L'!$A:$A,$C78)/1000 -> -29.38468 | AF78: =-SUMIFS('Monthly P&L'!X:X,'Monthly P&L'!$A:$A,$C78)/1000*2 -> -27.29524 | AH78: =SUMIFS($CD78:$CF78,$CD$2:$CF$2,AH$3)*AH$36 -> -0.19411549 | AI78: =SUMIFS($CD78:$CF78,$CD$2:$CF$2,AI$3)*AI$36 -> -0.16176291 | AJ78: =SUMIFS($CD78:$CF78,$CD$2:$CF$2,AJ$3)*AJ$36 -> -0.24264436 | AK78: =SUMIFS($CD78:$CF78,$CD$2:$CF$2,AK$3)*AK$36 -> -0.30734952 | AL78: =SUMIFS($CD78:$CF78,$CD$2:$CF$2,AL$3)*AL$36 -> -0.38823097 | AM78: =SUMIFS($CD78:$CF78,$CD$2:$CF$2,AM$3)*AM$36 -> -0.19411549 | AN78: =SUMIFS($CD78:$CF78,$CD$2:$CF$2,AN$3)*AN$36 -> -0.080881453 | AO78: =SUMIFS($CD78:$CF78,$CD$2:$CF$2,AO$3)*AO$36 -> 0 | ... BQ78: =SUMIFS($CD78:$CF78,$CD$2:$CF$2,BQ$3)*BQ$36 -> -0.71810934 | BS78: =BF78 -> -0.52477221 | BT78: =BG78 -> -0.2761959 | BU78: =BH78 -> -0.46953303 | BV78: =BI78 -> -0.60763098 | BW78: =BJ78 -> -0.71810934 | BX78: =BK78 -> -0.41429385 | BY78: =BL78 -> -0.16571754 | CA78: =-SUMIFS('Monthly P&L'!$E:$E,'Monthly P&L'!$A:$A,$C78)/1000 -> -301.01383 | CB78: =SUMIFS($D78:$AF78,$D$1:$AF$1,CB$2) -> -294.47492 | CC78: =SUMIFS($P78:$AF78,$P$3:$AF$3,$CC$2) -> -320.68885 | CD78: =CD$55*CH78 -> -2.4264436 | CE78: =CE$55*CI78 -> -3.3009878 | CF78: =CF$55*CJ78 -> -4.6953303 | CH78: =$CO78 -> -0.0012358284 | CI78: =$CO78 -> -0.0012358284 | CJ78: =$CO78 -> -0.0012358284 | CL78: =IFERROR(CC78/CC$55,0) -> -0.24172288 | CN78: =-SUMIFS('FY25 By Venue Financials'!$J:$J,'FY25 By Venue Financials'!$A:$A,$C78) -> -44.80038 | CO78: =IFERROR(CN78/CN$55,0) -> -0.0012358284 | CQ78: % Total Rev | CR78: Annually - split monthly by seasonality | CU78: =SUMIFS($D78:$BZ78,$D$1:$BZ$1,CU$9) -> -125.85598 | CV78: =SUMIFS($D78:$BZ78,$D$1:$BZ$1,CV$9) -> -3.1061413 | CW78: =SUMIFS($D78:$BZ78,$D$1:$BZ$1,CW$9) -> -4.2284427 | CX78: =SUMIFS($D78:$BZ78,$D$1:$BZ$1,CX$9) -> -4.6953303
C80: Total Payroll | D80: =SUM(D70:D79) -> 0 | E80: =SUM(E70:E79) -> 0 | F80: =SUM(F70:F79) -> 0 | G80: =SUM(G70:G79) -> 0 | H80: =SUM(H70:H79) -> 0 | I80: =SUM(I70:I79) -> 0 | J80: =SUM(J70:J79) -> 0 | K80: =SUM(K70:K79) -> 0 | ... AF80: =SUM(AF70:AF79) -> -46.34156 | AH80: =SUM(AH70:AH79) -> -34.414667 | AI80: =SUM(AI70:AI79) -> -32.380793 | AJ80: =SUM(AJ70:AJ79) -> -37.465478 | AK80: =SUM(AK70:AK79) -> -41.533226 | AL80: =SUM(AL70:AL79) -> -46.617911 | AM80: =SUM(AM70:AM79) -> -34.414667 | AN80: =SUM(AN70:AN79) -> -27.296109 | AO80: =SUM(AO70:AO79) -> -22.211424 | ... BQ80: =SUM(BQ70:BQ79) -> -53.66525 | BS80: =SUM(BS70:BS79) -> -46.452712 | BT80: =SUM(BT70:BT79) -> -37.179449 | BU80: =SUM(BU70:BU79) -> -44.391987 | BV80: =SUM(BV70:BV79) -> -49.5438 | BW80: =SUM(BW70:BW79) -> -53.66525 | BX80: =SUM(BX70:BX79) -> -42.331262 | BY80: =SUM(BY70:BY79) -> -33.057998 | CA80: =SUM(CA70:CA79) -> -452.20206 | CB80: =SUM(CB70:CB79) -> -399.74791 | CC80: =SUM(CC70:CC79) -> -415.79619 | CD80: =SUM(CD70:CD79) -> -419.07763 | CE80: =SUM(CE70:CE79) -> -456.73697 | CF80: =SUM(CF70:CF79) -> -497.67151 | CH80: =IFERROR(CD80/CD$55,0) -> -0.21344326 | CI80: =IFERROR(CE80/CE$55,0) -> -0.17099381 | CJ80: =IFERROR(CF80/CF$55,0) -> -0.13098899 | CL80: =IFERROR(CC80/CC$55,0) -> -0.31341113 | CN80: =SUM(CN70:CN79) -> -10660.207 | CO80: =IFERROR(CN80/CN$55,0) -> -0.29406416 | CQ80: % Total Rev | CU80: =SUM(CU70:CU79) -> -410.07973 | CV80: =SUM(CV70:CV79) -> -447.39857 | CW80: =SUM(CW70:CW79) -> -480.91563 | CX80: =SUM(CX70:CX79) -> -497.67151
C82: Operating Expenses
C83: Marketing Expense | P83: =-SUMIFS('Monthly P&L'!H:H,'Monthly P&L'!$A:$A,$C83)/1000 -> -2.82415 | Q83: =-SUMIFS('Monthly P&L'!I:I,'Monthly P&L'!$A:$A,$C83)/1000 -> -3.81293 | R83: =-SUMIFS('Monthly P&L'!J:J,'Monthly P&L'!$A:$A,$C83)/1000 -> -3.437 | S83: =-SUMIFS('Monthly P&L'!K:K,'Monthly P&L'!$A:$A,$C83)/1000 -> -2.93655 | T83: =-SUMIFS('Monthly P&L'!L:L,'Monthly P&L'!$A:$A,$C83)/1000 -> -10.25724 | U83: =-SUMIFS('Monthly P&L'!M:M,'Monthly P&L'!$A:$A,$C83)/1000 -> -9.7341 | V83: =-SUMIFS('Monthly P&L'!N:N,'Monthly P&L'!$A:$A,$C83)/1000 -> -3 | W83: =-SUMIFS('Monthly P&L'!O:O,'Monthly P&L'!$A:$A,$C83)/1000 -> -4.89974 | X83: =-SUMIFS('Monthly P&L'!P:P,'Monthly P&L'!$A:$A,$C83)/1000 -> -7.8745 | Y83: =-SUMIFS('Monthly P&L'!Q:Q,'Monthly P&L'!$A:$A,$C83)/1000 -> -1.35028 | Z83: =-SUMIFS('Monthly P&L'!R:R,'Monthly P&L'!$A:$A,$C83)/1000 -> -7.91972 | AA83: =-SUMIFS('Monthly P&L'!S:S,'Monthly P&L'!$A:$A,$C83)/1000 -> -3.79925 | AB83: =-SUMIFS('Monthly P&L'!T:T,'Monthly P&L'!$A:$A,$C83)/1000 -> -1.96299 | AC83: =-SUMIFS('Monthly P&L'!U:U,'Monthly P&L'!$A:$A,$C83)/1000 -> -0.1 | AD83: =-SUMIFS('Monthly P&L'!V:V,'Monthly P&L'!$A:$A,$C83)/1000 -> -2.65662 | AE83: =-SUMIFS('Monthly P&L'!W:W,'Monthly P&L'!$A:$A,$C83)/1000 -> 0 | AF83: =-SUMIFS('Monthly P&L'!X:X,'Monthly P&L'!$A:$A,$C83)/1000*2 -> 0 | AH83: =SUMIFS($CD83:$CF83,$CD$2:$CF$2,AH$3)/12 -> -7.5861434 | AI83: =SUMIFS($CD83:$CF83,$CD$2:$CF$2,AI$3)/12 -> -7.5861434 | AJ83: =SUMIFS($CD83:$CF83,$CD$2:$CF$2,AJ$3)/12 -> -7.5861434 | AK83: =SUMIFS($CD83:$CF83,$CD$2:$CF$2,AK$3)/12 -> -7.5861434 | AL83: =SUMIFS($CD83:$CF83,$CD$2:$CF$2,AL$3)/12 -> -7.5861434 | AM83: =SUMIFS($CD83:$CF83,$CD$2:$CF$2,AM$3)/12 -> -7.5861434 | AN83: =SUMIFS($CD83:$CF83,$CD$2:$CF$2,AN$3)/12 -> -7.5861434 | AO83: =SUMIFS($CD83:$CF83,$CD$2:$CF$2,AO$3)/12 -> -7.5861434 | ... BQ83: =SUMIFS($CD83:$CF83,$CD$2:$CF$2,BQ$3)/12 -> -14.679694 | BS83: =BF83 -> -14.679694 | BT83: =BG83 -> -14.679694 | BU83: =BH83 -> -14.679694 | BV83: =BI83 -> -14.679694 | BW83: =BJ83 -> -14.679694 | BX83: =BK83 -> -14.679694 | BY83: =BL83 -> -14.679694 | CA83: =-SUMIFS('Monthly P&L'!$E:$E,'Monthly P&L'!$A:$A,$C83)/1000 -> -47.54656 | CB83: =SUMIFS($D83:$AF83,$D$1:$AF$1,CB$2) -> -61.84546 | CC83: =SUMIFS($P83:$AF83,$P$3:$AF$3,$CC$2) -> -53.55444 | CD83: =CD$55*CH83 -> -91.033721 | CE83: =CE$55*CI83 -> -123.8443 | CF83: =CF$55*CJ83 -> -176.15633 | CH83: =$CO83 -> -0.046364999 | CI83: =$CO83 -> -0.046364999 | CJ83: =$CO83 -> -0.046364999 | CL83: =IFERROR(CC83/CC$55,0) -> -0.040367271 | CN83: =-SUMIFS('FY25 By Venue Financials'!$J:$J,'FY25 By Venue Financials'!$A:$A,$C83) -> -1680.7913 | CO83: =IFERROR(CN83/CN$55,0) -> -0.046364999 | CQ83: % Total Rev | CR83: Annually - Split / 12 | CU83: =SUMIFS($D83:$BZ83,$D$1:$BZ$1,CU$9) -> -57.822614 | CV83: =SUMIFS($D83:$BZ83,$D$1:$BZ$1,CV$9) -> -110.17322 | CW83: =SUMIFS($D83:$BZ83,$D$1:$BZ$1,CW$9) -> -154.35965 | CX83: =SUMIFS($D83:$BZ83,$D$1:$BZ$1,CX$9) -> -176.15633
C84: Maintenance Expense | P84: =-SUMIFS('Monthly P&L'!H:H,'Monthly P&L'!$A:$A,$C84)/1000 -> -10.18896 | Q84: =-SUMIFS('Monthly P&L'!I:I,'Monthly P&L'!$A:$A,$C84)/1000 -> -5.61409 | R84: =-SUMIFS('Monthly P&L'!J:J,'Monthly P&L'!$A:$A,$C84)/1000 -> -9.505 | S84: =-SUMIFS('Monthly P&L'!K:K,'Monthly P&L'!$A:$A,$C84)/1000 -> -8.1 | T84: =-SUMIFS('Monthly P&L'!L:L,'Monthly P&L'!$A:$A,$C84)/1000 -> -6.49282 | U84: =-SUMIFS('Monthly P&L'!M:M,'Monthly P&L'!$A:$A,$C84)/1000 -> -3.83402 | V84: =-SUMIFS('Monthly P&L'!N:N,'Monthly P&L'!$A:$A,$C84)/1000 -> -1.35168 | W84: =-SUMIFS('Monthly P&L'!O:O,'Monthly P&L'!$A:$A,$C84)/1000 -> -6.90371 | X84: =-SUMIFS('Monthly P&L'!P:P,'Monthly P&L'!$A:$A,$C84)/1000 -> -2.20402 | Y84: =-SUMIFS('Monthly P&L'!Q:Q,'Monthly P&L'!$A:$A,$C84)/1000 -> -4.70167 | Z84: =-SUMIFS('Monthly P&L'!R:R,'Monthly P&L'!$A:$A,$C84)/1000 -> -15.07755 | AA84: =-SUMIFS('Monthly P&L'!S:S,'Monthly P&L'!$A:$A,$C84)/1000 -> -7.65686 | AB84: =-SUMIFS('Monthly P&L'!T:T,'Monthly P&L'!$A:$A,$C84)/1000 -> -3.67805 | AC84: =-SUMIFS('Monthly P&L'!U:U,'Monthly P&L'!$A:$A,$C84)/1000 -> -16.77975 | AD84: =-SUMIFS('Monthly P&L'!V:V,'Monthly P&L'!$A:$A,$C84)/1000 -> -13.81361 | AE84: =-SUMIFS('Monthly P&L'!W:W,'Monthly P&L'!$A:$A,$C84)/1000 -> -1.389 | AF84: =-SUMIFS('Monthly P&L'!X:X,'Monthly P&L'!$A:$A,$C84)/1000*2 -> -11.45784 | AH84: =SUMIFS($CD84:$CF84,$CD$2:$CF$2,AH$3)/12 -> -4.0020391 | AI84: =SUMIFS($CD84:$CF84,$CD$2:$CF$2,AI$3)/12 -> -4.0020391 | AJ84: =SUMIFS($CD84:$CF84,$CD$2:$CF$2,AJ$3)/12 -> -4.0020391 | AK84: =SUMIFS($CD84:$CF84,$CD$2:$CF$2,AK$3)/12 -> -4.0020391 | AL84: =SUMIFS($CD84:$CF84,$CD$2:$CF$2,AL$3)/12 -> -4.0020391 | AM84: =SUMIFS($CD84:$CF84,$CD$2:$CF$2,AM$3)/12 -> -4.0020391 | AN84: =SUMIFS($CD84:$CF84,$CD$2:$CF$2,AN$3)/12 -> -4.0020391 | AO84: =SUMIFS($CD84:$CF84,$CD$2:$CF$2,AO$3)/12 -> -4.0020391 | ... BQ84: =SUMIFS($CD84:$CF84,$CD$2:$CF$2,BQ$3)/12 -> -4.5356443 | BS84: =BF84 -> -4.5356443 | BT84: =BG84 -> -4.5356443 | BU84: =BH84 -> -4.5356443 | BV84: =BI84 -> -4.5356443 | BW84: =BJ84 -> -4.5356443 | BX84: =BK84 -> -4.5356443 | BY84: =BL84 -> -4.5356443 | CA84: =-SUMIFS('Monthly P&L'!$E:$E,'Monthly P&L'!$A:$A,$C84)/1000 -> -65.59616 | CB84: =SUMIFS($D84:$AF84,$D$1:$AF$1,CB$2) -> -81.63038 | CC84: =SUMIFS($P84:$AF84,$P$3:$AF$3,$CC$2) -> -83.88274 | CD84: =CH84*CD$35 -> -48.024469 | CE84: =CI84*CE$35 -> -51.226101 | CF84: =CJ84*CF$35 -> -54.427732 | CH84: =$CL84/2 -> -0.32016313 | CI84: =$CL84/2 -> -0.32016313 | CJ84: =$CL84/2 -> -0.32016313 | CL84: =IFERROR(CC84/CL$35,0) -> -0.64032626 | CN84: =-SUMIFS('FY25 By Venue Financials'!$J:$J,'FY25 By Venue Financials'!$A:$A,$C84) -> -1322.0857 | CO84: =CN84/CN$35 -> -0.81913615 | CQ84: $ / Event | CR84: Annually - Split / 12 - ~half of their historical repairs/maintenance costs are personal | CU84: =SUMIFS($D84:$BZ84,$D$1:$BZ$1,CU$9) -> -75.132524 | CV84: =SUMIFS($D84:$BZ84,$D$1:$BZ$1,CV$9) -> -49.892088 | CW84: =SUMIFS($D84:$BZ84,$D$1:$BZ$1,CW$9) -> -53.093719 | CX84: =SUMIFS($D84:$BZ84,$D$1:$BZ$1,CX$9) -> -54.427732
C85: Utilities Expense | P85: =-SUMIFS('Monthly P&L'!H:H,'Monthly P&L'!$A:$A,$C85)/1000 -> -2.42118 | Q85: =-SUMIFS('Monthly P&L'!I:I,'Monthly P&L'!$A:$A,$C85)/1000 -> -0.54398 | R85: =-SUMIFS('Monthly P&L'!J:J,'Monthly P&L'!$A:$A,$C85)/1000 -> -4.90404 | S85: =-SUMIFS('Monthly P&L'!K:K,'Monthly P&L'!$A:$A,$C85)/1000 -> -2.81664 | T85: =-SUMIFS('Monthly P&L'!L:L,'Monthly P&L'!$A:$A,$C85)/1000 -> -2.57965 | U85: =-SUMIFS('Monthly P&L'!M:M,'Monthly P&L'!$A:$A,$C85)/1000 -> -1.90313 | V85: =-SUMIFS('Monthly P&L'!N:N,'Monthly P&L'!$A:$A,$C85)/1000 -> -1.56963 | W85: =-SUMIFS('Monthly P&L'!O:O,'Monthly P&L'!$A:$A,$C85)/1000 -> -2.60721 | X85: =-SUMIFS('Monthly P&L'!P:P,'Monthly P&L'!$A:$A,$C85)/1000 -> -2.03918 | Y85: =-SUMIFS('Monthly P&L'!Q:Q,'Monthly P&L'!$A:$A,$C85)/1000 -> -2.04039 | Z85: =-SUMIFS('Monthly P&L'!R:R,'Monthly P&L'!$A:$A,$C85)/1000 -> -2.12759 | AA85: =-SUMIFS('Monthly P&L'!S:S,'Monthly P&L'!$A:$A,$C85)/1000 -> -2.19988 | AB85: =-SUMIFS('Monthly P&L'!T:T,'Monthly P&L'!$A:$A,$C85)/1000 -> -2.2999 | AC85: =-SUMIFS('Monthly P&L'!U:U,'Monthly P&L'!$A:$A,$C85)/1000 -> -3.58938 | AD85: =-SUMIFS('Monthly P&L'!V:V,'Monthly P&L'!$A:$A,$C85)/1000 -> -3.48664 | AE85: =-SUMIFS('Monthly P&L'!W:W,'Monthly P&L'!$A:$A,$C85)/1000 -> -1.78442 | AF85: =-SUMIFS('Monthly P&L'!X:X,'Monthly P&L'!$A:$A,$C85)/1000*2 -> -2.7191 | AH85: =SUMIFS($CD85:$CF85,$CD$2:$CF$2,AH$3)*AH$36 -> -2.5856794 | AI85: =SUMIFS($CD85:$CF85,$CD$2:$CF$2,AI$3)*AI$36 -> -2.1547328 | AJ85: =SUMIFS($CD85:$CF85,$CD$2:$CF$2,AJ$3)*AJ$36 -> -3.2320992 | AK85: =SUMIFS($CD85:$CF85,$CD$2:$CF$2,AK$3)*AK$36 -> -4.0939924 | AL85: =SUMIFS($CD85:$CF85,$CD$2:$CF$2,AL$3)*AL$36 -> -5.1713588 | AM85: =SUMIFS($CD85:$CF85,$CD$2:$CF$2,AM$3)*AM$36 -> -2.5856794 | AN85: =SUMIFS($CD85:$CF85,$CD$2:$CF$2,AN$3)*AN$36 -> -1.0773664 | AO85: =SUMIFS($CD85:$CF85,$CD$2:$CF$2,AO$3)*AO$36 -> 0 | ... BQ85: =SUMIFS($CD85:$CF85,$CD$2:$CF$2,BQ$3)*BQ$36 -> -5.6023053 | BS85: =BF85 -> -4.0939924 | BT85: =BG85 -> -2.1547328 | BU85: =BH85 -> -3.6630458 | BV85: =BI85 -> -4.7404122 | BW85: =BJ85 -> -5.6023053 | BX85: =BK85 -> -3.2320992 | BY85: =BL85 -> -1.2928397 | CA85: =-SUMIFS('Monthly P&L'!$E:$E,'Monthly P&L'!$A:$A,$C85)/1000 -> -32.04557 | CB85: =SUMIFS($D85:$AF85,$D$1:$AF$1,CB$2) -> -27.7525 | CC85: =SUMIFS($P85:$AF85,$P$3:$AF$3,$CC$2) -> -28.227 | CD85: =CH85*CD$35 -> -32.320992 | CE85: =CI85*CE$35 -> -34.475725 | CF85: =CJ85*CF$35 -> -36.630458 | CH85: =$CL$85 -> -0.21547328 | CI85: =$CL$85 -> -0.21547328 | CJ85: =$CL$85 -> -0.21547328 | CL85: =IFERROR(CC85/CL$35,0) -> -0.21547328 | CN85: =-SUMIFS('FY25 By Venue Financials'!$J:$J,'FY25 By Venue Financials'!$A:$A,$C85) -> -1170.8024 | CO85: =CN85/CN$35 -> -0.72540421 | CQ85: $ / Event | CR85: Annually - Split / 12 | CU85: =SUMIFS($D85:$BZ85,$D$1:$BZ$1,CU$9) -> -34.780348 | CV85: =SUMIFS($D85:$BZ85,$D$1:$BZ$1,CV$9) -> -34.906672 | CW85: =SUMIFS($D85:$BZ85,$D$1:$BZ$1,CW$9) -> -35.768565 | CX85: =SUMIFS($D85:$BZ85,$D$1:$BZ$1,CX$9) -> -36.630458
C86: Office Expense | P86: =-SUMIFS('Monthly P&L'!H:H,'Monthly P&L'!$A:$A,$C86)/1000 -> -1.03604 | Q86: =-SUMIFS('Monthly P&L'!I:I,'Monthly P&L'!$A:$A,$C86)/1000 -> -0.57494 | R86: =-SUMIFS('Monthly P&L'!J:J,'Monthly P&L'!$A:$A,$C86)/1000 -> -2.21355 | S86: =-SUMIFS('Monthly P&L'!K:K,'Monthly P&L'!$A:$A,$C86)/1000 -> -0.33368 | T86: =-SUMIFS('Monthly P&L'!L:L,'Monthly P&L'!$A:$A,$C86)/1000 -> -1.32153 | U86: =-SUMIFS('Monthly P&L'!M:M,'Monthly P&L'!$A:$A,$C86)/1000 -> -1.35696 | V86: =-SUMIFS('Monthly P&L'!N:N,'Monthly P&L'!$A:$A,$C86)/1000 -> -0.71568 | W86: =-SUMIFS('Monthly P&L'!O:O,'Monthly P&L'!$A:$A,$C86)/1000 -> -0.53268 | X86: =-SUMIFS('Monthly P&L'!P:P,'Monthly P&L'!$A:$A,$C86)/1000 -> -0.54174 | Y86: =-SUMIFS('Monthly P&L'!Q:Q,'Monthly P&L'!$A:$A,$C86)/1000 -> -1.78259 | Z86: =-SUMIFS('Monthly P&L'!R:R,'Monthly P&L'!$A:$A,$C86)/1000 -> -0.23001 | AA86: =-SUMIFS('Monthly P&L'!S:S,'Monthly P&L'!$A:$A,$C86)/1000 -> -0.32501 | AB86: =-SUMIFS('Monthly P&L'!T:T,'Monthly P&L'!$A:$A,$C86)/1000 -> -0.15645 | AC86: =-SUMIFS('Monthly P&L'!U:U,'Monthly P&L'!$A:$A,$C86)/1000 -> -0.37672 | AD86: =-SUMIFS('Monthly P&L'!V:V,'Monthly P&L'!$A:$A,$C86)/1000 -> -0.4728 | AE86: =-SUMIFS('Monthly P&L'!W:W,'Monthly P&L'!$A:$A,$C86)/1000 -> -0.21817 | AF86: =-SUMIFS('Monthly P&L'!X:X,'Monthly P&L'!$A:$A,$C86)/1000*2 -> -0.38218 | AH86: =SUMIFS($CD86:$CF86,$CD$2:$CF$2,AH$3)/12 -> -1.1333785 | AI86: =SUMIFS($CD86:$CF86,$CD$2:$CF$2,AI$3)/12 -> -1.1333785 | AJ86: =SUMIFS($CD86:$CF86,$CD$2:$CF$2,AJ$3)/12 -> -1.1333785 | AK86: =SUMIFS($CD86:$CF86,$CD$2:$CF$2,AK$3)/12 -> -1.1333785 | AL86: =SUMIFS($CD86:$CF86,$CD$2:$CF$2,AL$3)/12 -> -1.1333785 | AM86: =SUMIFS($CD86:$CF86,$CD$2:$CF$2,AM$3)/12 -> -1.1333785 | AN86: =SUMIFS($CD86:$CF86,$CD$2:$CF$2,AN$3)/12 -> -1.1333785 | AO86: =SUMIFS($CD86:$CF86,$CD$2:$CF$2,AO$3)/12 -> -1.1333785 | ... BQ86: =SUMIFS($CD86:$CF86,$CD$2:$CF$2,BQ$3)/12 -> -2.1931631 | BS86: =BF86 -> -2.1931631 | BT86: =BG86 -> -2.1931631 | BU86: =BH86 -> -2.1931631 | BV86: =BI86 -> -2.1931631 | BW86: =BJ86 -> -2.1931631 | BX86: =BK86 -> -2.1931631 | BY86: =BL86 -> -2.1931631 | CA86: =-SUMIFS('Monthly P&L'!$E:$E,'Monthly P&L'!$A:$A,$C86)/1000 -> -8.33775 | CB86: =SUMIFS($D86:$AF86,$D$1:$AF$1,CB$2) -> -10.96441 | CC86: =SUMIFS($P86:$AF86,$P$3:$AF$3,$CC$2) -> -8.03034 | CD86: =CD$55*CH86 -> -13.600542 | CE86: =CE$55*CI86 -> -18.50248 | CF86: =CF$55*CJ86 -> -26.317957 | CH86: =$CO86 -> -0.0069269841 | CI86: =$CO86 -> -0.0069269841 | CJ86: =$CO86 -> -0.0069269841 | CL86: =IFERROR(CC86/CC$55,0) -> -0.0060529605 | CN86: =-SUMIFS('FY25 By Venue Financials'!$J:$J,'FY25 By Venue Financials'!$A:$A,$C86) -> -251.11215 | CO86: =IFERROR(CN86/CN$55,0) -> -0.0069269841 | CQ86: % Total Rev | CR86: Annually - Split / 12 | CU86: =SUMIFS($D86:$BZ86,$D$1:$BZ$1,CU$9) -> -9.5399697 | CV86: =SUMIFS($D86:$BZ86,$D$1:$BZ$1,CV$9) -> -16.460006 | CW86: =SUMIFS($D86:$BZ86,$D$1:$BZ$1,CW$9) -> -23.061509 | CX86: =SUMIFS($D86:$BZ86,$D$1:$BZ$1,CX$9) -> -26.317957
C87: Computer Expense | P87: =-SUMIFS('Monthly P&L'!H:H,'Monthly P&L'!$A:$A,$C87)/1000 -> -1.06814 | Q87: =-SUMIFS('Monthly P&L'!I:I,'Monthly P&L'!$A:$A,$C87)/1000 -> -0.77201 | R87: =-SUMIFS('Monthly P&L'!J:J,'Monthly P&L'!$A:$A,$C87)/1000 -> -1.6352 | S87: =-SUMIFS('Monthly P&L'!K:K,'Monthly P&L'!$A:$A,$C87)/1000 -> -0.72453 | T87: =-SUMIFS('Monthly P&L'!L:L,'Monthly P&L'!$A:$A,$C87)/1000 -> -0.98009 | U87: =-SUMIFS('Monthly P&L'!M:M,'Monthly P&L'!$A:$A,$C87)/1000 -> -1.42544 | V87: =-SUMIFS('Monthly P&L'!N:N,'Monthly P&L'!$A:$A,$C87)/1000 -> -1.02497 | W87: =-SUMIFS('Monthly P&L'!O:O,'Monthly P&L'!$A:$A,$C87)/1000 -> -0.72986 | X87: =-SUMIFS('Monthly P&L'!P:P,'Monthly P&L'!$A:$A,$C87)/1000 -> -0.555 | Y87: =-SUMIFS('Monthly P&L'!Q:Q,'Monthly P&L'!$A:$A,$C87)/1000 -> -1.52559 | Z87: =-SUMIFS('Monthly P&L'!R:R,'Monthly P&L'!$A:$A,$C87)/1000 -> 0 | AA87: =-SUMIFS('Monthly P&L'!S:S,'Monthly P&L'!$A:$A,$C87)/1000 -> -2.28507 | AB87: =-SUMIFS('Monthly P&L'!T:T,'Monthly P&L'!$A:$A,$C87)/1000 -> 0 | AC87: =-SUMIFS('Monthly P&L'!U:U,'Monthly P&L'!$A:$A,$C87)/1000 -> 0 | AD87: =-SUMIFS('Monthly P&L'!V:V,'Monthly P&L'!$A:$A,$C87)/1000 -> 0 | AE87: =-SUMIFS('Monthly P&L'!W:W,'Monthly P&L'!$A:$A,$C87)/1000 -> 0 | AF87: =-SUMIFS('Monthly P&L'!X:X,'Monthly P&L'!$A:$A,$C87)/1000*2 -> 0 | AH87: =SUMIFS($CD87:$CF87,$CD$2:$CF$2,AH$3)/12 -> -0.094786346 | AI87: =SUMIFS($CD87:$CF87,$CD$2:$CF$2,AI$3)/12 -> -0.094786346 | AJ87: =SUMIFS($CD87:$CF87,$CD$2:$CF$2,AJ$3)/12 -> -0.094786346 | AK87: =SUMIFS($CD87:$CF87,$CD$2:$CF$2,AK$3)/12 -> -0.094786346 | AL87: =SUMIFS($CD87:$CF87,$CD$2:$CF$2,AL$3)/12 -> -0.094786346 | AM87: =SUMIFS($CD87:$CF87,$CD$2:$CF$2,AM$3)/12 -> -0.094786346 | AN87: =SUMIFS($CD87:$CF87,$CD$2:$CF$2,AN$3)/12 -> -0.094786346 | AO87: =SUMIFS($CD87:$CF87,$CD$2:$CF$2,AO$3)/12 -> -0.094786346 | ... BQ87: =SUMIFS($CD87:$CF87,$CD$2:$CF$2,BQ$3)/12 -> -0.18341791 | BS87: =BF87 -> -0.18341791 | BT87: =BG87 -> -0.18341791 | BU87: =BH87 -> -0.18341791 | BV87: =BI87 -> -0.18341791 | BW87: =BJ87 -> -0.18341791 | BX87: =BK87 -> -0.18341791 | BY87: =BL87 -> -0.18341791 | CA87: =-SUMIFS('Monthly P&L'!$E:$E,'Monthly P&L'!$A:$A,$C87)/1000 -> -3.56722 | CB87: =SUMIFS($D87:$AF87,$D$1:$AF$1,CB$2) -> -12.7259 | CC87: =SUMIFS($P87:$AF87,$P$3:$AF$3,$CC$2) -> -8.52602 | CD87: =CD$55*CH87 -> -1.1374362 | CE87: =CE$55*CI87 -> -1.5473934 | CF87: =CF$55*CJ87 -> -2.2010149 | CH87: =$CO87 -> -0.00057931529 | CI87: =$CO87 -> -0.00057931529 | CJ87: =$CO87 -> -0.00057931529 | CL87: =IFERROR(CC87/CC$55,0) -> -0.0064265849 | CN87: =-SUMIFS('FY25 By Venue Financials'!$J:$J,'FY25 By Venue Financials'!$A:$A,$C87) -> -21.00093 | CO87: =IFERROR(CN87/CN$55,0) -> -0.00057931529 | CQ87: % Total Rev | CR87: Annually - Split / 12 | CU87: =SUMIFS($D87:$BZ87,$D$1:$BZ$1,CU$9) -> -0.66350442 | CV87: =SUMIFS($D87:$BZ87,$D$1:$BZ$1,CV$9) -> -1.3765779 | CW87: =SUMIFS($D87:$BZ87,$D$1:$BZ$1,CW$9) -> -1.9286726 | CX87: =SUMIFS($D87:$BZ87,$D$1:$BZ$1,CX$9) -> -2.2010149
C88: Automobile Expenses | P88: =-SUMIFS('Monthly P&L'!H:H,'Monthly P&L'!$A:$A,$C88)/1000 -> -0.56669 | Q88: =-SUMIFS('Monthly P&L'!I:I,'Monthly P&L'!$A:$A,$C88)/1000 -> -0.60518 | R88: =-SUMIFS('Monthly P&L'!J:J,'Monthly P&L'!$A:$A,$C88)/1000 -> -1.35364 | S88: =-SUMIFS('Monthly P&L'!K:K,'Monthly P&L'!$A:$A,$C88)/1000 -> -0.56669 | T88: =-SUMIFS('Monthly P&L'!L:L,'Monthly P&L'!$A:$A,$C88)/1000 -> -24.58669 | U88: =-SUMIFS('Monthly P&L'!M:M,'Monthly P&L'!$A:$A,$C88)/1000 -> -0.56669 | V88: =-SUMIFS('Monthly P&L'!N:N,'Monthly P&L'!$A:$A,$C88)/1000 -> -0.6822 | W88: =-SUMIFS('Monthly P&L'!O:O,'Monthly P&L'!$A:$A,$C88)/1000 -> -1.15159 | X88: =-SUMIFS('Monthly P&L'!P:P,'Monthly P&L'!$A:$A,$C88)/1000 -> -0.73291 | Y88: =-SUMIFS('Monthly P&L'!Q:Q,'Monthly P&L'!$A:$A,$C88)/1000 -> -0.74419 | Z88: =-SUMIFS('Monthly P&L'!R:R,'Monthly P&L'!$A:$A,$C88)/1000 -> -1.00586 | AA88: =-SUMIFS('Monthly P&L'!S:S,'Monthly P&L'!$A:$A,$C88)/1000 -> -1.24953 | AB88: =-SUMIFS('Monthly P&L'!T:T,'Monthly P&L'!$A:$A,$C88)/1000 -> -0.56669 | AC88: =-SUMIFS('Monthly P&L'!U:U,'Monthly P&L'!$A:$A,$C88)/1000 -> -0.83927 | AD88: =-SUMIFS('Monthly P&L'!V:V,'Monthly P&L'!$A:$A,$C88)/1000 -> -0.83927 | AE88: =-SUMIFS('Monthly P&L'!W:W,'Monthly P&L'!$A:$A,$C88)/1000 -> -0.56669 | AF88: =-SUMIFS('Monthly P&L'!X:X,'Monthly P&L'!$A:$A,$C88)/1000*2 -> 0 | AH88: =SUMIFS($CD88:$CF88,$CD$2:$CF$2,AH$3)/12 -> -0.57485879 | AI88: =SUMIFS($CD88:$CF88,$CD$2:$CF$2,AI$3)/12 -> -0.57485879 | AJ88: =SUMIFS($CD88:$CF88,$CD$2:$CF$2,AJ$3)/12 -> -0.57485879 | AK88: =SUMIFS($CD88:$CF88,$CD$2:$CF$2,AK$3)/12 -> -0.57485879 | AL88: =SUMIFS($CD88:$CF88,$CD$2:$CF$2,AL$3)/12 -> -0.57485879 | AM88: =SUMIFS($CD88:$CF88,$CD$2:$CF$2,AM$3)/12 -> -0.57485879 | AN88: =SUMIFS($CD88:$CF88,$CD$2:$CF$2,AN$3)/12 -> -0.57485879 | AO88: =SUMIFS($CD88:$CF88,$CD$2:$CF$2,AO$3)/12 -> -0.57485879 | ... BQ88: =SUMIFS($CD88:$CF88,$CD$2:$CF$2,BQ$3)/12 -> -1.1123901 | BS88: =BF88 -> -1.1123901 | BT88: =BG88 -> -1.1123901 | BU88: =BH88 -> -1.1123901 | BV88: =BI88 -> -1.1123901 | BW88: =BJ88 -> -1.1123901 | BX88: =BK88 -> -1.1123901 | BY88: =BL88 -> -1.1123901 | CA88: =-SUMIFS('Monthly P&L'!$E:$E,'Monthly P&L'!$A:$A,$C88)/1000 -> -12.59141 | CB88: =SUMIFS($D88:$AF88,$D$1:$AF$1,CB$2) -> -33.81186 | CC88: =SUMIFS($P88:$AF88,$P$3:$AF$3,$CC$2) -> -33.53158 | CD88: =CD$55*CH88 -> -6.8983054 | CE88: =CE$55*CI88 -> -9.3846081 | CF88: =CF$55*CJ88 -> -13.348682 | CH88: =$CO88 -> -0.0035134225 | CI88: =$CO88 -> -0.0035134225 | CJ88: =$CO88 -> -0.0035134225 | CL88: =IFERROR(CC88/CC$55,0) -> -0.025274811 | CN88: =-SUMIFS('FY25 By Venue Financials'!$J:$J,'FY25 By Venue Financials'!$A:$A,$C88) -> -127.36612 | CO88: =IFERROR(CN88/CN$55,0) -> -0.0035134225 | CQ88: % Total Rev | CR88: Annually - Split / 12 | CU88: =SUMIFS($D88:$BZ88,$D$1:$BZ$1,CU$9) -> -6.8359315 | CV88: =SUMIFS($D88:$BZ88,$D$1:$BZ$1,CV$9) -> -8.3486487 | CW88: =SUMIFS($D88:$BZ88,$D$1:$BZ$1,CW$9) -> -11.696984 | CX88: =SUMIFS($D88:$BZ88,$D$1:$BZ$1,CX$9) -> -13.348682
C89: Training & Development Expense | P89: =-SUMIFS('Monthly P&L'!H:H,'Monthly P&L'!$A:$A,$C89)/1000 -> 0 | Q89: =-SUMIFS('Monthly P&L'!I:I,'Monthly P&L'!$A:$A,$C89)/1000 -> 0 | R89: =-SUMIFS('Monthly P&L'!J:J,'Monthly P&L'!$A:$A,$C89)/1000 -> 0 | S89: =-SUMIFS('Monthly P&L'!K:K,'Monthly P&L'!$A:$A,$C89)/1000 -> 0 | T89: =-SUMIFS('Monthly P&L'!L:L,'Monthly P&L'!$A:$A,$C89)/1000 -> 0 | U89: =-SUMIFS('Monthly P&L'!M:M,'Monthly P&L'!$A:$A,$C89)/1000 -> 0 | V89: =-SUMIFS('Monthly P&L'!N:N,'Monthly P&L'!$A:$A,$C89)/1000 -> 0 | W89: =-SUMIFS('Monthly P&L'!O:O,'Monthly P&L'!$A:$A,$C89)/1000 -> 0 | X89: =-SUMIFS('Monthly P&L'!P:P,'Monthly P&L'!$A:$A,$C89)/1000 -> 0 | Y89: =-SUMIFS('Monthly P&L'!Q:Q,'Monthly P&L'!$A:$A,$C89)/1000 -> 0 | Z89: =-SUMIFS('Monthly P&L'!R:R,'Monthly P&L'!$A:$A,$C89)/1000 -> 0 | AA89: =-SUMIFS('Monthly P&L'!S:S,'Monthly P&L'!$A:$A,$C89)/1000 -> 0 | AB89: =-SUMIFS('Monthly P&L'!T:T,'Monthly P&L'!$A:$A,$C89)/1000 -> 0 | AC89: =-SUMIFS('Monthly P&L'!U:U,'Monthly P&L'!$A:$A,$C89)/1000 -> 0 | AD89: =-SUMIFS('Monthly P&L'!V:V,'Monthly P&L'!$A:$A,$C89)/1000 -> 0 | AE89: =-SUMIFS('Monthly P&L'!W:W,'Monthly P&L'!$A:$A,$C89)/1000 -> 0 | AF89: =-SUMIFS('Monthly P&L'!X:X,'Monthly P&L'!$A:$A,$C89)/1000*2 -> 0 | AH89: =SUMIFS($CD89:$CF89,$CD$2:$CF$2,AH$3)/12 -> -0.0028418848 | AI89: =SUMIFS($CD89:$CF89,$CD$2:$CF$2,AI$3)/12 -> -0.0028418848 | AJ89: =SUMIFS($CD89:$CF89,$CD$2:$CF$2,AJ$3)/12 -> -0.0028418848 | AK89: =SUMIFS($CD89:$CF89,$CD$2:$CF$2,AK$3)/12 -> -0.0028418848 | AL89: =SUMIFS($CD89:$CF89,$CD$2:$CF$2,AL$3)/12 -> -0.0028418848 | AM89: =SUMIFS($CD89:$CF89,$CD$2:$CF$2,AM$3)/12 -> -0.0028418848 | AN89: =SUMIFS($CD89:$CF89,$CD$2:$CF$2,AN$3)/12 -> -0.0028418848 | AO89: =SUMIFS($CD89:$CF89,$CD$2:$CF$2,AO$3)/12 -> -0.0028418848 | ... BQ89: =SUMIFS($CD89:$CF89,$CD$2:$CF$2,BQ$3)/12 -> -0.0054992367 | BS89: =BF89 -> -0.0054992367 | BT89: =BG89 -> -0.0054992367 | BU89: =BH89 -> -0.0054992367 | BV89: =BI89 -> -0.0054992367 | BW89: =BJ89 -> -0.0054992367 | BX89: =BK89 -> -0.0054992367 | BY89: =BL89 -> -0.0054992367 | CA89: =-SUMIFS('Monthly P&L'!$E:$E,'Monthly P&L'!$A:$A,$C89)/1000 -> 0 | CB89: =SUMIFS($D89:$AF89,$D$1:$AF$1,CB$2) -> 0 | CC89: =SUMIFS($P89:$AF89,$P$3:$AF$3,$CC$2) -> 0 | CD89: =CD$55*CH89 -> -0.034102617 | CE89: =CE$55*CI89 -> -0.046393959 | CF89: =CF$55*CJ89 -> -0.065990841 | CH89: =$CO89 -> -1.7369034e-05 | CI89: =$CO89 -> -1.7369034e-05 | CJ89: =$CO89 -> -1.7369034e-05 | CL89: =IFERROR(CC89/CC$55,0) -> 0 | CN89: =-SUMIFS('FY25 By Venue Financials'!$J:$J,'FY25 By Venue Financials'!$A:$A,$C89) -> -0.62965 | CO89: =IFERROR(CN89/CN$55,0) -> -1.7369034e-05 | CQ89: % Total Rev | CR89: Annually - Split / 12 | CU89: =SUMIFS($D89:$BZ89,$D$1:$BZ$1,CU$9) -> -0.019893193 | CV89: =SUMIFS($D89:$BZ89,$D$1:$BZ$1,CV$9) -> -0.041272566 | CW89: =SUMIFS($D89:$BZ89,$D$1:$BZ$1,CW$9) -> -0.057825473 | CX89: =SUMIFS($D89:$BZ89,$D$1:$BZ$1,CX$9) -> -0.065990841
C90: Tax Expense | P90: =-SUMIFS('Monthly P&L'!H:H,'Monthly P&L'!$A:$A,$C90)/1000 -> 0 | Q90: =-SUMIFS('Monthly P&L'!I:I,'Monthly P&L'!$A:$A,$C90)/1000 -> 0 | R90: =-SUMIFS('Monthly P&L'!J:J,'Monthly P&L'!$A:$A,$C90)/1000 -> 0 | S90: =-SUMIFS('Monthly P&L'!K:K,'Monthly P&L'!$A:$A,$C90)/1000 -> -0.1 | T90: =-SUMIFS('Monthly P&L'!L:L,'Monthly P&L'!$A:$A,$C90)/1000 -> -6.745 | U90: =-SUMIFS('Monthly P&L'!M:M,'Monthly P&L'!$A:$A,$C90)/1000 -> 0 | V90: =-SUMIFS('Monthly P&L'!N:N,'Monthly P&L'!$A:$A,$C90)/1000 -> 0 | W90: =-SUMIFS('Monthly P&L'!O:O,'Monthly P&L'!$A:$A,$C90)/1000 -> 0 | X90: =-SUMIFS('Monthly P&L'!P:P,'Monthly P&L'!$A:$A,$C90)/1000 -> -3.272 | Y90: =-SUMIFS('Monthly P&L'!Q:Q,'Monthly P&L'!$A:$A,$C90)/1000 -> 0 | Z90: =-SUMIFS('Monthly P&L'!R:R,'Monthly P&L'!$A:$A,$C90)/1000 -> -1.62 | AA90: =-SUMIFS('Monthly P&L'!S:S,'Monthly P&L'!$A:$A,$C90)/1000 -> -0.53071 | AB90: =-SUMIFS('Monthly P&L'!T:T,'Monthly P&L'!$A:$A,$C90)/1000 -> 0 | AC90: =-SUMIFS('Monthly P&L'!U:U,'Monthly P&L'!$A:$A,$C90)/1000 -> 0 | AD90: =-SUMIFS('Monthly P&L'!V:V,'Monthly P&L'!$A:$A,$C90)/1000 -> -6.618 | AE90: =-SUMIFS('Monthly P&L'!W:W,'Monthly P&L'!$A:$A,$C90)/1000 -> -4.91249 | AF90: =-SUMIFS('Monthly P&L'!X:X,'Monthly P&L'!$A:$A,$C90)/1000*2 -> 0 | AH90: =SUMIFS($CD90:$CF90,$CD$2:$CF$2,AH$3)/12 -> -3.22485 | AI90: =SUMIFS($CD90:$CF90,$CD$2:$CF$2,AI$3)/12 -> -3.22485 | AJ90: =SUMIFS($CD90:$CF90,$CD$2:$CF$2,AJ$3)/12 -> -3.22485 | AK90: =SUMIFS($CD90:$CF90,$CD$2:$CF$2,AK$3)/12 -> -3.22485 | AL90: =SUMIFS($CD90:$CF90,$CD$2:$CF$2,AL$3)/12 -> -3.22485 | AM90: =SUMIFS($CD90:$CF90,$CD$2:$CF$2,AM$3)/12 -> -3.22485 | AN90: =SUMIFS($CD90:$CF90,$CD$2:$CF$2,AN$3)/12 -> -3.22485 | AO90: =SUMIFS($CD90:$CF90,$CD$2:$CF$2,AO$3)/12 -> -3.22485 | ... BQ90: =SUMIFS($CD90:$CF90,$CD$2:$CF$2,BQ$3)/12 -> -3.22485 | BS90: =BF90 -> -3.22485 | BT90: =BG90 -> -3.22485 | BU90: =BH90 -> -3.22485 | BV90: =BI90 -> -3.22485 | BW90: =BJ90 -> -3.22485 | BX90: =BK90 -> -3.22485 | BY90: =BL90 -> -3.22485 | CA90: =-SUMIFS('Monthly P&L'!$E:$E,'Monthly P&L'!$A:$A,$C90)/1000 -> -5.131 | CB90: =SUMIFS($D90:$AF90,$D$1:$AF$1,CB$2) -> -12.26771 | CC90: =SUMIFS($P90:$AF90,$P$3:$AF$3,$CC$2) -> -23.6982 | CD90: =$CL90 -> -38.6982 | CE90: =$CL90 -> -38.6982 | CF90: =$CL90 -> -38.6982 | CL90: =CC90-15 -> -38.6982 | CN90: =-SUMIFS('FY25 By Venue Financials'!$J:$J,'FY25 By Venue Financials'!$A:$A,$C90) -> -1349.9496 | CO90: =IFERROR(CN90/CN$55,0) -> -0.037238657 | CQ90: Fixed | CR90: Annually - Split / 12 - no more greenbelt taxes | CU90: =SUMIFS($D90:$BZ90,$D$1:$BZ$1,CU$9) -> -34.10444 | CV90: =SUMIFS($D90:$BZ90,$D$1:$BZ$1,CV$9) -> -38.6982 | CW90: =SUMIFS($D90:$BZ90,$D$1:$BZ$1,CW$9) -> -38.6982 | CX90: =SUMIFS($D90:$BZ90,$D$1:$BZ$1,CX$9) -> -38.6982
C91: Travel Expense | P91: =-SUMIFS('Monthly P&L'!H:H,'Monthly P&L'!$A:$A,$C91)/1000 -> 0 | Q91: =-SUMIFS('Monthly P&L'!I:I,'Monthly P&L'!$A:$A,$C91)/1000 -> -0.04341 | R91: =-SUMIFS('Monthly P&L'!J:J,'Monthly P&L'!$A:$A,$C91)/1000 -> 0 | S91: =-SUMIFS('Monthly P&L'!K:K,'Monthly P&L'!$A:$A,$C91)/1000 -> 0 | T91: =-SUMIFS('Monthly P&L'!L:L,'Monthly P&L'!$A:$A,$C91)/1000 -> -1.10985 | U91: =-SUMIFS('Monthly P&L'!M:M,'Monthly P&L'!$A:$A,$C91)/1000 -> 0 | V91: =-SUMIFS('Monthly P&L'!N:N,'Monthly P&L'!$A:$A,$C91)/1000 -> 0 | W91: =-SUMIFS('Monthly P&L'!O:O,'Monthly P&L'!$A:$A,$C91)/1000 -> 0 | X91: =-SUMIFS('Monthly P&L'!P:P,'Monthly P&L'!$A:$A,$C91)/1000 -> 0 | Y91: =-SUMIFS('Monthly P&L'!Q:Q,'Monthly P&L'!$A:$A,$C91)/1000 -> 0 | Z91: =-SUMIFS('Monthly P&L'!R:R,'Monthly P&L'!$A:$A,$C91)/1000 -> -0.05479 | AA91: =-SUMIFS('Monthly P&L'!S:S,'Monthly P&L'!$A:$A,$C91)/1000 -> -0.585 | AB91: =-SUMIFS('Monthly P&L'!T:T,'Monthly P&L'!$A:$A,$C91)/1000 -> 0 | AC91: =-SUMIFS('Monthly P&L'!U:U,'Monthly P&L'!$A:$A,$C91)/1000 -> 0 | AD91: =-SUMIFS('Monthly P&L'!V:V,'Monthly P&L'!$A:$A,$C91)/1000 -> 0 | AE91: =-SUMIFS('Monthly P&L'!W:W,'Monthly P&L'!$A:$A,$C91)/1000 -> 0 | AF91: =-SUMIFS('Monthly P&L'!X:X,'Monthly P&L'!$A:$A,$C91)/1000*2 -> 0 | AH91: =SUMIFS($CD91:$CF91,$CD$2:$CF$2,AH$3)/12 -> -0.013493638 | AI91: =SUMIFS($CD91:$CF91,$CD$2:$CF$2,AI$3)/12 -> -0.013493638 | AJ91: =SUMIFS($CD91:$CF91,$CD$2:$CF$2,AJ$3)/12 -> -0.013493638 | AK91: =SUMIFS($CD91:$CF91,$CD$2:$CF$2,AK$3)/12 -> -0.013493638 | AL91: =SUMIFS($CD91:$CF91,$CD$2:$CF$2,AL$3)/12 -> -0.013493638 | AM91: =SUMIFS($CD91:$CF91,$CD$2:$CF$2,AM$3)/12 -> -0.013493638 | AN91: =SUMIFS($CD91:$CF91,$CD$2:$CF$2,AN$3)/12 -> -0.013493638 | AO91: =SUMIFS($CD91:$CF91,$CD$2:$CF$2,AO$3)/12 -> -0.013493638 | ... BQ91: =SUMIFS($CD91:$CF91,$CD$2:$CF$2,BQ$3)/12 -> -0.02611109 | BS91: =BF91 -> -0.02611109 | BT91: =BG91 -> -0.02611109 | BU91: =BH91 -> -0.02611109 | BV91: =BI91 -> -0.02611109 | BW91: =BJ91 -> -0.02611109 | BX91: =BK91 -> -0.02611109 | BY91: =BL91 -> -0.02611109 | CA91: =-SUMIFS('Monthly P&L'!$E:$E,'Monthly P&L'!$A:$A,$C91)/1000 -> -1.72421 | CB91: =SUMIFS($D91:$AF91,$D$1:$AF$1,CB$2) -> -1.79305 | CC91: =SUMIFS($P91:$AF91,$P$3:$AF$3,$CC$2) -> -1.74964 | CD91: =CD$55*CH91 -> -0.16192366 | CE91: =CE$55*CI91 -> -0.22028454 | CF91: =CF$55*CJ91 -> -0.31333308 | CH91: =$CO91 -> -8.2470431e-05 | CI91: =$CO91 -> -8.2470431e-05 | CJ91: =$CO91 -> -8.2470431e-05 | CL91: =IFERROR(CC91/CC$55,0) -> -0.0013188111 | CN91: =-SUMIFS('FY25 By Venue Financials'!$J:$J,'FY25 By Venue Financials'!$A:$A,$C91) -> -2.98966 | CO91: =IFERROR(CN91/CN$55,0) -> -8.2470431e-05 | CQ91: % Total Rev | CR91: Annually - Split / 12 | CU91: =SUMIFS($D91:$BZ91,$D$1:$BZ$1,CU$9) -> -0.094455466 | CV91: =SUMIFS($D91:$BZ91,$D$1:$BZ$1,CV$9) -> -0.19596751 | CW91: =SUMIFS($D91:$BZ91,$D$1:$BZ$1,CW$9) -> -0.27456286 | CX91: =SUMIFS($D91:$BZ91,$D$1:$BZ$1,CX$9) -> -0.31333308
C92: Professional Expenses | P92: =-SUMIFS('Monthly P&L'!H:H,'Monthly P&L'!$A:$A,$C92)/1000 -> 0 | Q92: =-SUMIFS('Monthly P&L'!I:I,'Monthly P&L'!$A:$A,$C92)/1000 -> -0.9 | R92: =-SUMIFS('Monthly P&L'!J:J,'Monthly P&L'!$A:$A,$C92)/1000 -> -1 | S92: =-SUMIFS('Monthly P&L'!K:K,'Monthly P&L'!$A:$A,$C92)/1000 -> 0 | T92: =-SUMIFS('Monthly P&L'!L:L,'Monthly P&L'!$A:$A,$C92)/1000 -> 0 | U92: =-SUMIFS('Monthly P&L'!M:M,'Monthly P&L'!$A:$A,$C92)/1000 -> -2.11625 | V92: =-SUMIFS('Monthly P&L'!N:N,'Monthly P&L'!$A:$A,$C92)/1000 -> 0 | W92: =-SUMIFS('Monthly P&L'!O:O,'Monthly P&L'!$A:$A,$C92)/1000 -> 0 | X92: =-SUMIFS('Monthly P&L'!P:P,'Monthly P&L'!$A:$A,$C92)/1000 -> -5.31758 | Y92: =-SUMIFS('Monthly P&L'!Q:Q,'Monthly P&L'!$A:$A,$C92)/1000 -> 0 | Z92: =-SUMIFS('Monthly P&L'!R:R,'Monthly P&L'!$A:$A,$C92)/1000 -> -4 | AA92: =-SUMIFS('Monthly P&L'!S:S,'Monthly P&L'!$A:$A,$C92)/1000 -> -0.0525 | AB92: =-SUMIFS('Monthly P&L'!T:T,'Monthly P&L'!$A:$A,$C92)/1000 -> -0.29163 | AC92: =-SUMIFS('Monthly P&L'!U:U,'Monthly P&L'!$A:$A,$C92)/1000 -> 0 | AD92: =-SUMIFS('Monthly P&L'!V:V,'Monthly P&L'!$A:$A,$C92)/1000 -> -0.9575 | AE92: =-SUMIFS('Monthly P&L'!W:W,'Monthly P&L'!$A:$A,$C92)/1000 -> -0.22825 | AF92: =-SUMIFS('Monthly P&L'!X:X,'Monthly P&L'!$A:$A,$C92)/1000*2 -> -0.9 | AH92: =SUMIFS($CD92:$CF92,$CD$2:$CF$2,AH$3)/12 -> -0.035088983 | AI92: =SUMIFS($CD92:$CF92,$CD$2:$CF$2,AI$3)/12 -> -0.035088983 | AJ92: =SUMIFS($CD92:$CF92,$CD$2:$CF$2,AJ$3)/12 -> -0.035088983 | AK92: =SUMIFS($CD92:$CF92,$CD$2:$CF$2,AK$3)/12 -> -0.035088983 | AL92: =SUMIFS($CD92:$CF92,$CD$2:$CF$2,AL$3)/12 -> -0.035088983 | AM92: =SUMIFS($CD92:$CF92,$CD$2:$CF$2,AM$3)/12 -> -0.035088983 | AN92: =SUMIFS($CD92:$CF92,$CD$2:$CF$2,AN$3)/12 -> -0.035088983 | AO92: =SUMIFS($CD92:$CF92,$CD$2:$CF$2,AO$3)/12 -> -0.035088983 | ... BQ92: =SUMIFS($CD92:$CF92,$CD$2:$CF$2,BQ$3)/12 -> -0.067899525 | BS92: =BF92 -> -0.067899525 | BT92: =BG92 -> -0.067899525 | BU92: =BH92 -> -0.067899525 | BV92: =BI92 -> -0.067899525 | BW92: =BJ92 -> -0.067899525 | BX92: =BK92 -> -0.067899525 | BY92: =BL92 -> -0.067899525 | CA92: =-SUMIFS('Monthly P&L'!$E:$E,'Monthly P&L'!$A:$A,$C92)/1000 -> -3.49065 | CB92: =SUMIFS($D92:$AF92,$D$1:$AF$1,CB$2) -> -13.38633 | CC92: =SUMIFS($P92:$AF92,$P$3:$AF$3,$CC$2) -> -12.96371 | CD92: =CD$55*CH92 -> -0.4210678 | CE92: =CE$55*CI92 -> -0.57283 | CF92: =CF$55*CJ92 -> -0.8147943 | CH92: =$CO92 -> -0.00021445688 | CI92: =$CO92 -> -0.00021445688 | CJ92: =$CO92 -> -0.00021445688 | CL92: =IFERROR(CC92/CC$55,0) -> -0.0097715444 | CN92: =-SUMIFS('FY25 By Venue Financials'!$J:$J,'FY25 By Venue Financials'!$A:$A,$C92) -> -7.77434 | CO92: =IFERROR(CN92/CN$55,0) -> -0.00021445688 | CQ92: % Total Rev | CR92: Annually - Split / 12 | CU92: =SUMIFS($D92:$BZ92,$D$1:$BZ$1,CU$9) -> -2.6230029 | CV92: =SUMIFS($D92:$BZ92,$D$1:$BZ$1,CV$9) -> -0.50959575 | CW92: =SUMIFS($D92:$BZ92,$D$1:$BZ$1,CW$9) -> -0.71397584 | CX92: =SUMIFS($D92:$BZ92,$D$1:$BZ$1,CX$9) -> -0.8147943
C93: Rent Expense | P93: =-SUMIFS('Monthly P&L'!H:H,'Monthly P&L'!$A:$A,$C93)/1000 -> -15.5 | Q93: =-SUMIFS('Monthly P&L'!I:I,'Monthly P&L'!$A:$A,$C93)/1000 -> -31 | R93: =-SUMIFS('Monthly P&L'!J:J,'Monthly P&L'!$A:$A,$C93)/1000 -> -15.5 | S93: =-SUMIFS('Monthly P&L'!K:K,'Monthly P&L'!$A:$A,$C93)/1000 -> 0 | T93: =-SUMIFS('Monthly P&L'!L:L,'Monthly P&L'!$A:$A,$C93)/1000 -> -38 | U93: =-SUMIFS('Monthly P&L'!M:M,'Monthly P&L'!$A:$A,$C93)/1000 -> -15.5 | V93: =-SUMIFS('Monthly P&L'!N:N,'Monthly P&L'!$A:$A,$C93)/1000 -> -15.5 | W93: =-SUMIFS('Monthly P&L'!O:O,'Monthly P&L'!$A:$A,$C93)/1000 -> -15.5 | X93: =-SUMIFS('Monthly P&L'!P:P,'Monthly P&L'!$A:$A,$C93)/1000 -> -15.5 | Y93: =-SUMIFS('Monthly P&L'!Q:Q,'Monthly P&L'!$A:$A,$C93)/1000 -> -15.5 | Z93: =-SUMIFS('Monthly P&L'!R:R,'Monthly P&L'!$A:$A,$C93)/1000 -> -15.5 | AA93: =-SUMIFS('Monthly P&L'!S:S,'Monthly P&L'!$A:$A,$C93)/1000 -> -15.5 | AB93: =-SUMIFS('Monthly P&L'!T:T,'Monthly P&L'!$A:$A,$C93)/1000 -> -15.5 | AC93: =-SUMIFS('Monthly P&L'!U:U,'Monthly P&L'!$A:$A,$C93)/1000 -> -15.5 | AD93: =-SUMIFS('Monthly P&L'!V:V,'Monthly P&L'!$A:$A,$C93)/1000 -> -13.77 | AE93: =-SUMIFS('Monthly P&L'!W:W,'Monthly P&L'!$A:$A,$C93)/1000 -> -15.5 | AF93: =-SUMIFS('Monthly P&L'!X:X,'Monthly P&L'!$A:$A,$C93)/1000*2 -> -62 | AH93: =SUMIFS($CD93:$CF93,$CD$2:$CF$2,AH$3)/12 -> 0 | AI93: =SUMIFS($CD93:$CF93,$CD$2:$CF$2,AI$3)/12 -> 0 | AJ93: =SUMIFS($CD93:$CF93,$CD$2:$CF$2,AJ$3)/12 -> 0 | AK93: =SUMIFS($CD93:$CF93,$CD$2:$CF$2,AK$3)/12 -> 0 | AL93: =SUMIFS($CD93:$CF93,$CD$2:$CF$2,AL$3)/12 -> 0 | AM93: =SUMIFS($CD93:$CF93,$CD$2:$CF$2,AM$3)/12 -> 0 | AN93: =SUMIFS($CD93:$CF93,$CD$2:$CF$2,AN$3)/12 -> 0 | AO93: =SUMIFS($CD93:$CF93,$CD$2:$CF$2,AO$3)/12 -> 0 | ... BQ93: =SUMIFS($CD93:$CF93,$CD$2:$CF$2,BQ$3)/12 -> 0 | BS93: =BF93 -> 0 | BT93: =BG93 -> 0 | BU93: =BH93 -> 0 | BV93: =BI93 -> 0 | BW93: =BJ93 -> 0 | BX93: =BK93 -> 0 | BY93: =BL93 -> 0 | CA93: =-SUMIFS('Monthly P&L'!$E:$E,'Monthly P&L'!$A:$A,$C93)/1000 -> -170.5 | CB93: =SUMIFS($D93:$AF93,$D$1:$AF$1,CB$2) -> -208.5 | CC93: =SUMIFS($P93:$AF93,$P$3:$AF$3,$CC$2) -> -206.77 | CD93: =CD$55*CH93 -> 0 | CE93: =CE$55*CI93 -> 0 | CF93: =CF$55*CJ93 -> 0 | CH93: 0 | CI93: 0 | CJ93: 0 | CL93: =IFERROR(CC93/CC$55,0) -> -0.15585525 | CN93: =-SUMIFS('FY25 By Venue Financials'!$J:$J,'FY25 By Venue Financials'!$A:$A,$C93) -> -3254.2021 | CO93: =IFERROR(CN93/CN$55,0) -> -0.089767883 | CQ93: % Total Rev | CR93: - | CU93: =SUMIFS($D93:$BZ93,$D$1:$BZ$1,CU$9) -> -122.27 | CV93: =SUMIFS($D93:$BZ93,$D$1:$BZ$1,CV$9) -> 0 | CW93: =SUMIFS($D93:$BZ93,$D$1:$BZ$1,CW$9) -> 0 | CX93: =SUMIFS($D93:$BZ93,$D$1:$BZ$1,CX$9) -> 0
C94: Insurance | P94: =-SUMIFS('Monthly P&L'!H:H,'Monthly P&L'!$A:$A,$C94)/1000 -> 0 | Q94: =-SUMIFS('Monthly P&L'!I:I,'Monthly P&L'!$A:$A,$C94)/1000 -> -3.378 | R94: =-SUMIFS('Monthly P&L'!J:J,'Monthly P&L'!$A:$A,$C94)/1000 -> 0 | S94: =-SUMIFS('Monthly P&L'!K:K,'Monthly P&L'!$A:$A,$C94)/1000 -> -0.025 | T94: =-SUMIFS('Monthly P&L'!L:L,'Monthly P&L'!$A:$A,$C94)/1000 -> -4.251 | U94: =-SUMIFS('Monthly P&L'!M:M,'Monthly P&L'!$A:$A,$C94)/1000 -> -0.025 | V94: =-SUMIFS('Monthly P&L'!N:N,'Monthly P&L'!$A:$A,$C94)/1000 -> 0 | W94: =-SUMIFS('Monthly P&L'!O:O,'Monthly P&L'!$A:$A,$C94)/1000 -> -5.638 | X94: =-SUMIFS('Monthly P&L'!P:P,'Monthly P&L'!$A:$A,$C94)/1000 -> -0.03 | Y94: =-SUMIFS('Monthly P&L'!Q:Q,'Monthly P&L'!$A:$A,$C94)/1000 -> -5.63 | Z94: =-SUMIFS('Monthly P&L'!R:R,'Monthly P&L'!$A:$A,$C94)/1000 -> 0 | AA94: =-SUMIFS('Monthly P&L'!S:S,'Monthly P&L'!$A:$A,$C94)/1000 -> -5.63 | AB94: =-SUMIFS('Monthly P&L'!T:T,'Monthly P&L'!$A:$A,$C94)/1000 -> 0 | AC94: =-SUMIFS('Monthly P&L'!U:U,'Monthly P&L'!$A:$A,$C94)/1000 -> 0 | AD94: =-SUMIFS('Monthly P&L'!V:V,'Monthly P&L'!$A:$A,$C94)/1000 -> 0 | AE94: =-SUMIFS('Monthly P&L'!W:W,'Monthly P&L'!$A:$A,$C94)/1000 -> 0 | AF94: =-SUMIFS('Monthly P&L'!X:X,'Monthly P&L'!$A:$A,$C94)/1000*2 -> 0 | AH94: =SUMIFS($CD94:$CF94,$CD$2:$CF$2,AH$3)/12 -> -3.0935941 | AI94: =SUMIFS($CD94:$CF94,$CD$2:$CF$2,AI$3)/12 -> -3.0935941 | AJ94: =SUMIFS($CD94:$CF94,$CD$2:$CF$2,AJ$3)/12 -> -3.0935941 | AK94: =SUMIFS($CD94:$CF94,$CD$2:$CF$2,AK$3)/12 -> -3.0935941 | AL94: =SUMIFS($CD94:$CF94,$CD$2:$CF$2,AL$3)/12 -> -3.0935941 | AM94: =SUMIFS($CD94:$CF94,$CD$2:$CF$2,AM$3)/12 -> -3.0935941 | AN94: =SUMIFS($CD94:$CF94,$CD$2:$CF$2,AN$3)/12 -> -3.0935941 | AO94: =SUMIFS($CD94:$CF94,$CD$2:$CF$2,AO$3)/12 -> -3.0935941 | ... BQ94: =SUMIFS($CD94:$CF94,$CD$2:$CF$2,BQ$3)/12 -> -5.9863112 | BS94: =BF94 -> -5.9863112 | BT94: =BG94 -> -5.9863112 | BU94: =BH94 -> -5.9863112 | BV94: =BI94 -> -5.9863112 | BW94: =BJ94 -> -5.9863112 | BX94: =BK94 -> -5.9863112 | BY94: =BL94 -> -5.9863112 | CA94: =-SUMIFS('Monthly P&L'!$E:$E,'Monthly P&L'!$A:$A,$C94)/1000 -> -10.164 | CB94: =SUMIFS($D94:$AF94,$D$1:$AF$1,CB$2) -> -24.607 | CC94: =SUMIFS($P94:$AF94,$P$3:$AF$3,$CC$2) -> -21.204 | CD94: =CD$55*CH94 -> -37.12313 | CE94: =CE$55*CI94 -> -50.503131 | CF94: =CF$55*CJ94 -> -71.835734 | CH94: =$CO94 -> -0.018907432 | CI94: =$CO94 -> -0.018907432 | CJ94: =$CO94 -> -0.018907432 | CL94: =IFERROR(CC94/CC$55,0) -> -0.015982757 | CN94: =-SUMIFS('FY25 By Venue Financials'!$J:$J,'FY25 By Venue Financials'!$A:$A,$C94) -> -685.41891 | CO94: =IFERROR(CN94/CN$55,0) -> -0.018907432 | CQ94: % Total Rev | CR94: Annually - Split / 12 | CU94: =SUMIFS($D94:$BZ94,$D$1:$BZ$1,CU$9) -> -21.655159 | CV94: =SUMIFS($D94:$BZ94,$D$1:$BZ$1,CV$9) -> -44.928131 | CW94: =SUMIFS($D94:$BZ94,$D$1:$BZ$1,CW$9) -> -62.94715 | CX94: =SUMIFS($D94:$BZ94,$D$1:$BZ$1,CX$9) -> -71.835734
C95: Finance Expenses | P95: =-SUMIFS('Monthly P&L'!H:H,'Monthly P&L'!$A:$A,$C95)/1000 -> 0 | Q95: =-SUMIFS('Monthly P&L'!I:I,'Monthly P&L'!$A:$A,$C95)/1000 -> -0.016 | R95: =-SUMIFS('Monthly P&L'!J:J,'Monthly P&L'!$A:$A,$C95)/1000 -> 0 | S95: =-SUMIFS('Monthly P&L'!K:K,'Monthly P&L'!$A:$A,$C95)/1000 -> 0 | T95: =-SUMIFS('Monthly P&L'!L:L,'Monthly P&L'!$A:$A,$C95)/1000 -> 0 | U95: =-SUMIFS('Monthly P&L'!M:M,'Monthly P&L'!$A:$A,$C95)/1000 -> 0 | V95: =-SUMIFS('Monthly P&L'!N:N,'Monthly P&L'!$A:$A,$C95)/1000 -> -0.099 | W95: =-SUMIFS('Monthly P&L'!O:O,'Monthly P&L'!$A:$A,$C95)/1000 -> 0 | X95: =-SUMIFS('Monthly P&L'!P:P,'Monthly P&L'!$A:$A,$C95)/1000 -> 0 | Y95: =-SUMIFS('Monthly P&L'!Q:Q,'Monthly P&L'!$A:$A,$C95)/1000 -> 0 | Z95: =-SUMIFS('Monthly P&L'!R:R,'Monthly P&L'!$A:$A,$C95)/1000 -> 0 | AA95: =-SUMIFS('Monthly P&L'!S:S,'Monthly P&L'!$A:$A,$C95)/1000 -> 0 | AB95: =-SUMIFS('Monthly P&L'!T:T,'Monthly P&L'!$A:$A,$C95)/1000 -> 0 | AC95: =-SUMIFS('Monthly P&L'!U:U,'Monthly P&L'!$A:$A,$C95)/1000 -> 0 | AD95: =-SUMIFS('Monthly P&L'!V:V,'Monthly P&L'!$A:$A,$C95)/1000 -> 0 | AE95: =-SUMIFS('Monthly P&L'!W:W,'Monthly P&L'!$A:$A,$C95)/1000 -> 0 | AF95: =-SUMIFS('Monthly P&L'!X:X,'Monthly P&L'!$A:$A,$C95)/1000*2 -> 0 | AH95: =SUMIFS($CD95:$CF95,$CD$2:$CF$2,AH$3)/12 -> -1.5489048 | AI95: =SUMIFS($CD95:$CF95,$CD$2:$CF$2,AI$3)/12 -> -1.5489048 | AJ95: =SUMIFS($CD95:$CF95,$CD$2:$CF$2,AJ$3)/12 -> -1.5489048 | AK95: =SUMIFS($CD95:$CF95,$CD$2:$CF$2,AK$3)/12 -> -1.5489048 | AL95: =SUMIFS($CD95:$CF95,$CD$2:$CF$2,AL$3)/12 -> -1.5489048 | AM95: =SUMIFS($CD95:$CF95,$CD$2:$CF$2,AM$3)/12 -> -1.5489048 | AN95: =SUMIFS($CD95:$CF95,$CD$2:$CF$2,AN$3)/12 -> -1.5489048 | AO95: =SUMIFS($CD95:$CF95,$CD$2:$CF$2,AO$3)/12 -> -1.5489048 | ... BQ95: =SUMIFS($CD95:$CF95,$CD$2:$CF$2,BQ$3)/12 -> -2.9972341 | BS95: =BF95 -> -2.9972341 | BT95: =BG95 -> -2.9972341 | BU95: =BH95 -> -2.9972341 | BV95: =BI95 -> -2.9972341 | BW95: =BJ95 -> -2.9972341 | BX95: =BK95 -> -2.9972341 | BY95: =BL95 -> -2.9972341 | CA95: =-SUMIFS('Monthly P&L'!$E:$E,'Monthly P&L'!$A:$A,$C95)/1000 -> 0 | CB95: =SUMIFS($D95:$AF95,$D$1:$AF$1,CB$2) -> -0.115 | CC95: =SUMIFS($P95:$AF95,$P$3:$AF$3,$CC$2) -> -0.099 | CD95: =CD$55*CH95 -> -18.586857 | CE95: =CE$55*CI95 -> -25.285974 | CF95: =CF$55*CJ95 -> -35.96681 | CH95: =$CO95 -> -0.0094665978 | CI95: =$CO95 -> -0.0094665978 | CJ95: =$CO95 -> -0.0094665978 | CL95: =IFERROR(CC95/CC$55,0) -> -7.462238e-05 | CN95: =-SUMIFS('FY25 By Venue Financials'!$J:$J,'FY25 By Venue Financials'!$A:$A,$C95) -> -343.17644 | CO95: =IFERROR(CN95/CN$55,0) -> -0.0094665978 | CQ95: % Total Rev | CR95: Annually - Split / 12 | CU95: =SUMIFS($D95:$BZ95,$D$1:$BZ$1,CU$9) -> -10.842333 | CV95: =SUMIFS($D95:$BZ95,$D$1:$BZ$1,CV$9) -> -22.494675 | CW95: =SUMIFS($D95:$BZ95,$D$1:$BZ$1,CW$9) -> -31.516462 | CX95: =SUMIFS($D95:$BZ95,$D$1:$BZ$1,CX$9) -> -35.96681
C96: Personal Expenses | P96: =-SUMIFS('Monthly P&L'!H:H,'Monthly P&L'!$A:$A,$C96)/1000 -> 0 | Q96: =-SUMIFS('Monthly P&L'!I:I,'Monthly P&L'!$A:$A,$C96)/1000 -> 0 | R96: =-SUMIFS('Monthly P&L'!J:J,'Monthly P&L'!$A:$A,$C96)/1000 -> 0 | S96: =-SUMIFS('Monthly P&L'!K:K,'Monthly P&L'!$A:$A,$C96)/1000 -> 0 | T96: =-SUMIFS('Monthly P&L'!L:L,'Monthly P&L'!$A:$A,$C96)/1000 -> 0 | U96: =-SUMIFS('Monthly P&L'!M:M,'Monthly P&L'!$A:$A,$C96)/1000 -> 0 | V96: =-SUMIFS('Monthly P&L'!N:N,'Monthly P&L'!$A:$A,$C96)/1000 -> 0 | W96: =-SUMIFS('Monthly P&L'!O:O,'Monthly P&L'!$A:$A,$C96)/1000 -> 0 | X96: =-SUMIFS('Monthly P&L'!P:P,'Monthly P&L'!$A:$A,$C96)/1000 -> 0 | Y96: =-SUMIFS('Monthly P&L'!Q:Q,'Monthly P&L'!$A:$A,$C96)/1000 -> 0 | Z96: =-SUMIFS('Monthly P&L'!R:R,'Monthly P&L'!$A:$A,$C96)/1000 -> 0 | AA96: =-SUMIFS('Monthly P&L'!S:S,'Monthly P&L'!$A:$A,$C96)/1000 -> 0 | AB96: =-SUMIFS('Monthly P&L'!T:T,'Monthly P&L'!$A:$A,$C96)/1000 -> 0 | AC96: =-SUMIFS('Monthly P&L'!U:U,'Monthly P&L'!$A:$A,$C96)/1000 -> 0 | AD96: =-SUMIFS('Monthly P&L'!V:V,'Monthly P&L'!$A:$A,$C96)/1000 -> 0 | AE96: =-SUMIFS('Monthly P&L'!W:W,'Monthly P&L'!$A:$A,$C96)/1000 -> 0 | AF96: =-SUMIFS('Monthly P&L'!X:X,'Monthly P&L'!$A:$A,$C96)/1000*2 -> 0 | AH96: =SUMIFS($CD96:$CF96,$CD$2:$CF$2,AH$3)/12 -> 0 | AI96: =SUMIFS($CD96:$CF96,$CD$2:$CF$2,AI$3)/12 -> 0 | AJ96: =SUMIFS($CD96:$CF96,$CD$2:$CF$2,AJ$3)/12 -> 0 | AK96: =SUMIFS($CD96:$CF96,$CD$2:$CF$2,AK$3)/12 -> 0 | AL96: =SUMIFS($CD96:$CF96,$CD$2:$CF$2,AL$3)/12 -> 0 | AM96: =SUMIFS($CD96:$CF96,$CD$2:$CF$2,AM$3)/12 -> 0 | AN96: =SUMIFS($CD96:$CF96,$CD$2:$CF$2,AN$3)/12 -> 0 | AO96: =SUMIFS($CD96:$CF96,$CD$2:$CF$2,AO$3)/12 -> 0 | ... BQ96: =SUMIFS($CD96:$CF96,$CD$2:$CF$2,BQ$3)/12 -> 0 | BS96: =BF96 -> 0 | BT96: =BG96 -> 0 | BU96: =BH96 -> 0 | BV96: =BI96 -> 0 | BW96: =BJ96 -> 0 | BX96: =BK96 -> 0 | BY96: =BL96 -> 0 | CA96: =-SUMIFS('Monthly P&L'!$E:$E,'Monthly P&L'!$A:$A,$C96)/1000 -> 0 | CB96: =SUMIFS($D96:$AF96,$D$1:$AF$1,CB$2) -> 0 | CC96: =SUMIFS($P96:$AF96,$P$3:$AF$3,$CC$2) -> 0 | CD96: =CD$55*CH96 -> 0 | CE96: =CE$55*CI96 -> 0 | CF96: =CF$55*CJ96 -> 0 | CH96: 0 | CI96: 0 | CJ96: 0 | CL96: =IFERROR(CC96/CC$55,0) -> 0 | CN96: =-SUMIFS('FY25 By Venue Financials'!$J:$J,'FY25 By Venue Financials'!$A:$A,$C96) -> 0 | CO96: =IFERROR(CN96/CN$55,0) -> 0 | CQ96: % Total Rev | CR96: - | CU96: =SUMIFS($D96:$BZ96,$D$1:$BZ$1,CU$9) -> 0 | CV96: =SUMIFS($D96:$BZ96,$D$1:$BZ$1,CV$9) -> 0 | CW96: =SUMIFS($D96:$BZ96,$D$1:$BZ$1,CW$9) -> 0 | CX96: =SUMIFS($D96:$BZ96,$D$1:$BZ$1,CX$9) -> 0
C97: Other Operating Expenses | P97: =-SUMIFS('Monthly P&L'!H:H,'Monthly P&L'!$A:$A,$C97)/1000 -> -1.45 | Q97: =-SUMIFS('Monthly P&L'!I:I,'Monthly P&L'!$A:$A,$C97)/1000 -> -7.65699 | R97: =-SUMIFS('Monthly P&L'!J:J,'Monthly P&L'!$A:$A,$C97)/1000 -> -18.12248 | S97: =-SUMIFS('Monthly P&L'!K:K,'Monthly P&L'!$A:$A,$C97)/1000 -> -1.57139 | T97: =-SUMIFS('Monthly P&L'!L:L,'Monthly P&L'!$A:$A,$C97)/1000 -> -1.72088 | U97: =-SUMIFS('Monthly P&L'!M:M,'Monthly P&L'!$A:$A,$C97)/1000 -> -2.81874 | V97: =-SUMIFS('Monthly P&L'!N:N,'Monthly P&L'!$A:$A,$C97)/1000 -> -11.28 | W97: =-SUMIFS('Monthly P&L'!O:O,'Monthly P&L'!$A:$A,$C97)/1000 -> -6.21813 | X97: =-SUMIFS('Monthly P&L'!P:P,'Monthly P&L'!$A:$A,$C97)/1000 -> -1.14161 | Y97: =-SUMIFS('Monthly P&L'!Q:Q,'Monthly P&L'!$A:$A,$C97)/1000 -> -3.90232 | Z97: =-SUMIFS('Monthly P&L'!R:R,'Monthly P&L'!$A:$A,$C97)/1000 -> -0.53121 | AA97: =-SUMIFS('Monthly P&L'!S:S,'Monthly P&L'!$A:$A,$C97)/1000 -> -0.26873 | AB97: =-SUMIFS('Monthly P&L'!T:T,'Monthly P&L'!$A:$A,$C97)/1000 -> 0 | AC97: =-SUMIFS('Monthly P&L'!U:U,'Monthly P&L'!$A:$A,$C97)/1000 -> -5.9669 | AD97: =-SUMIFS('Monthly P&L'!V:V,'Monthly P&L'!$A:$A,$C97)/1000 -> -22.48 | AE97: =-SUMIFS('Monthly P&L'!W:W,'Monthly P&L'!$A:$A,$C97)/1000 -> -1.90944 | AF97: =-SUMIFS('Monthly P&L'!X:X,'Monthly P&L'!$A:$A,$C97)/1000*2 -> -5.09144 | AH97: =SUMIFS($CD97:$CF97,$CD$2:$CF$2,AH$3)/12 -> -1.3833612 | AI97: =SUMIFS($CD97:$CF97,$CD$2:$CF$2,AI$3)/12 -> -1.3833612 | AJ97: =SUMIFS($CD97:$CF97,$CD$2:$CF$2,AJ$3)/12 -> -1.3833612 | AK97: =SUMIFS($CD97:$CF97,$CD$2:$CF$2,AK$3)/12 -> -1.3833612 | AL97: =SUMIFS($CD97:$CF97,$CD$2:$CF$2,AL$3)/12 -> -1.3833612 | AM97: =SUMIFS($CD97:$CF97,$CD$2:$CF$2,AM$3)/12 -> -1.3833612 | AN97: =SUMIFS($CD97:$CF97,$CD$2:$CF$2,AN$3)/12 -> -1.3833612 | AO97: =SUMIFS($CD97:$CF97,$CD$2:$CF$2,AO$3)/12 -> -1.3833612 | ... BQ97: =SUMIFS($CD97:$CF97,$CD$2:$CF$2,BQ$3)/12 -> -2.6768963 | BS97: =BF97 -> -2.6768963 | BT97: =BG97 -> -2.6768963 | BU97: =BH97 -> -2.6768963 | BV97: =BI97 -> -2.6768963 | BW97: =BJ97 -> -2.6768963 | BX97: =BK97 -> -2.6768963 | BY97: =BL97 -> -2.6768963 | CA97: =-SUMIFS('Monthly P&L'!$E:$E,'Monthly P&L'!$A:$A,$C97)/1000 -> -28.68462 | CB97: =SUMIFS($D97:$AF97,$D$1:$AF$1,CB$2) -> -56.68248 | CC97: =SUMIFS($P97:$AF97,$P$3:$AF$3,$CC$2) -> -58.23796 | CD97: =CD$55*CH97 -> -16.600335 | CE97: =CE$55*CI97 -> -22.583464 | CF97: =CF$55*CJ97 -> -32.122756 | CH97: =$CO97 -> -0.0084548285 | CI97: =$CO97 -> -0.0084548285 | CJ97: =$CO97 -> -0.0084548285 | CL97: =IFERROR(CC97/CC$55,0) -> -0.043897527 | CN97: =-SUMIFS('FY25 By Venue Financials'!$J:$J,'FY25 By Venue Financials'!$A:$A,$C97) -> -306.49849 | CO97: =IFERROR(CN97/CN$55,0) -> -0.0084548285 | CQ97: % Total Rev | CR97: Annually - Split / 12 | CU97: =SUMIFS($D97:$BZ97,$D$1:$BZ$1,CU$9) -> -45.131308 | CV97: =SUMIFS($D97:$BZ97,$D$1:$BZ$1,CV$9) -> -20.090494 | CW97: =SUMIFS($D97:$BZ97,$D$1:$BZ$1,CW$9) -> -28.148051 | CX97: =SUMIFS($D97:$BZ97,$D$1:$BZ$1,CX$9) -> -32.122756
C99: Total Operating Expenses | D99: =SUM(D83:D98) -> 0 | E99: =SUM(E83:E98) -> 0 | F99: =SUM(F83:F98) -> 0 | G99: =SUM(G83:G98) -> 0 | H99: =SUM(H83:H98) -> 0 | I99: =SUM(I83:I98) -> 0 | J99: =SUM(J83:J98) -> 0 | K99: =SUM(K83:K98) -> 0 | ... AF99: =SUM(AF83:AF98) -> -82.55056 | AH99: =SUM(AH83:AH98) -> -25.27902 | AI99: =SUM(AI83:AI98) -> -24.848074 | AJ99: =SUM(AJ83:AJ98) -> -25.92544 | AK99: =SUM(AK83:AK98) -> -26.787333 | AL99: =SUM(AL83:AL98) -> -27.8647 | AM99: =SUM(AM83:AM98) -> -25.27902 | AN99: =SUM(AN83:AN98) -> -23.770707 | AO99: =SUM(AO83:AO98) -> -22.693341 | ... BQ99: =SUM(BQ83:BQ98) -> -43.291416 | BS99: =SUM(BS83:BS98) -> -41.783103 | BT99: =SUM(BT83:BT98) -> -39.843844 | BU99: =SUM(BU83:BU98) -> -41.352157 | BV99: =SUM(BV83:BV98) -> -42.429523 | BW99: =SUM(BW83:BW98) -> -43.291416 | BX99: =SUM(BX83:BX98) -> -40.92121 | BY99: =SUM(BY83:BY98) -> -38.981951 | CA99: =SUM(CA83:CA98) -> -389.37915 | CB99: =SUM(CB83:CB98) -> -546.08208 | CC99: =SUM(CC83:CC98) -> -540.47463 | CD99: =SUM(CD83:CD98) -> -304.64108 | CE99: =SUM(CE83:CE98) -> -376.89088 | CF99: =SUM(CF83:CF98) -> -488.89979 | CH99: =IFERROR(CD99/CD$55,0) -> -0.15515881 | CI99: =IFERROR(CE99/CE$55,0) -> -0.14110093 | CJ99: =IFERROR(CF99/CF$55,0) -> -0.12868024 | CL99: =SUM(CL83:CL98) -> -39.859022 | CN99: =SUM(CN83:CN98) -> -10523.798 | CO99: =IFERROR(CN99/CN$55,0) -> -0.29030129 | CU99: =SUM(CU83:CU98) -> -421.51548 | CV99: =SUM(CV83:CV98) -> -348.11555 | CW99: =SUM(CW83:CW98) -> -442.26532 | CX99: =SUM(CX83:CX98) -> -488.89979
C101: EBITDAR | D101: =D67+D80+D99 -> 0 | E101: =E67+E80+E99 -> 0 | F101: =F67+F80+F99 -> 43.726928 | G101: =G67+G80+G99 -> 175.65771 | H101: =H67+H80+H99 -> 144.77155 | I101: =I67+I80+I99 -> 145.22617 | J101: =J67+J80+J99 -> 63.067699 | K101: =K67+K80+K99 -> 142.47617 | ... AF101: =AF67+AF80+AF99 -> 60.229369 | AH101: =AH67+AH80+AH99 -> 48.268789 | AI101: =AI67+AI80+AI99 -> 23.790508 | AJ101: =AJ67+AJ80+AJ99 -> 71.364649 | AK101: =AK67+AK80+AK99 -> 100.16013 | AL101: =AL67+AL80+AL99 -> 132.74032 | AM101: =AM67+AM80+AM99 -> 42.60307 | AN101: =AN67+AN80+AN99 -> -10.321925 | AO101: =AO67+AO80+AO99 -> -44.904764 | ... BQ101: =BQ67+BQ80+BQ99 -> 240.3572 | BS101: =BS67+BS80+BS99 -> 157.59757 | BT101: =BT67+BT80+BT99 -> 52.180642 | BU101: =BU67+BU80+BU99 -> 134.94027 | BV101: =BV67+BV80+BV99 -> 193.31306 | BW101: =BW67+BW80+BW99 -> 240.3572 | BX101: =BX67+BX80+BX99 -> 112.28298 | BY101: =BY67+BY80+BY99 -> 6.8660521 | CA101: =CA67+CA80+CA99 -> 344.21067 | CB101: =CB67+CB80+CB99 -> 139.56906 | CC101: =CC67+CC80+CC99 -> 110.56007 | CD101: =CD67+CD80+CD99 -> 593.04724 | CE101: =CE67+CE80+CE99 -> 807.83677 | CF101: =CF67+CF80+CF99 -> 1220.2729 | CH101: =IFERROR(CD101/CD$55,0) -> 0.3020489 | CI101: =IFERROR(CE101/CE$55,0) -> 0.30243904 | CJ101: =IFERROR(CF101/CF$55,0) -> 0.32118035 | CL101: =IFERROR(CC101/CC$55,0) -> 0.083335915 | CN101: =CN67+CN80+CN99 -> 11122.699 | CO101: =IFERROR(CN101/CN$55,0) -> 0.30682211 | CQ101: % Total Rev | CU101: =CU67+CU80+CU99 -> 371.10073 | CV101: =CV67+CV80+CV99 -> 739.2378 | CW101: =CW67+CW80+CW99 -> 1150.5784 | CX101: =CX67+CX80+CX99 -> 1220.2729
C103: Other Adjustments
C104: Addback: Rent | D104: [ ] | E104: [ ] | F104: [ ] | G104: [ ] | H104: [ ] | I104: [ ] | J104: [ ] | K104: [ ] | L104: [ ] | M104: [ ] | N104: [ ] | O104: [ ] | P104: =-P93 -> 15.5 | Q104: =-Q93 -> 31 | R104: =-R93 -> 15.5 | S104: =-S93 -> 0 | T104: =-T93 -> 38 | U104: =-U93 -> 15.5 | V104: =-V93 -> 15.5 | W104: =-W93 -> 15.5 | ... AF104: =-AF93 -> 62 | CA104: =-CA93 -> 170.5 | CB104: =SUMIFS($D104:$AF104,$D$1:$AF$1,CB$2) -> 208.5 | CC104: =SUMIFS($P104:$AF104,$P$3:$AF$3,$CC$2) -> 206.77 | CR104: Owners paid themselves rent | CU104: =SUMIFS($D104:$BZ104,$D$1:$BZ$1,CU$9) -> 122.27 | CV104: =SUMIFS($D104:$BZ104,$D$1:$BZ$1,CV$9) -> 0 | CW104: =SUMIFS($D104:$BZ104,$D$1:$BZ$1,CW$9) -> 0 | CX104: =SUMIFS($D104:$BZ104,$D$1:$BZ$1,CX$9) -> 0
C105: Addback: Personal Expenses | D105: [ ] | E105: [ ] | F105: [ ] | G105: [ ] | H105: [ ] | I105: [ ] | J105: [ ] | K105: [ ] | L105: [ ] | M105: [ ] | N105: [ ] | O105: [ ] | P105: =SUMIFS('2025 Addbacks'!$G$90:$G$101,'2025 Addbacks'!$A$90:$A$101,P$9)/1000 -> 9.6435 | Q105: =SUMIFS('2025 Addbacks'!$G$90:$G$101,'2025 Addbacks'!$A$90:$A$101,Q$9)/1000 -> 6.20474 | R105: =SUMIFS('2025 Addbacks'!$G$90:$G$101,'2025 Addbacks'!$A$90:$A$101,R$9)/1000 -> 18.23876 | S105: =SUMIFS('2025 Addbacks'!$G$90:$G$101,'2025 Addbacks'!$A$90:$A$101,S$9)/1000 -> 7.5096 | T105: =SUMIFS('2025 Addbacks'!$G$90:$G$101,'2025 Addbacks'!$A$90:$A$101,T$9)/1000 -> 58.93294 | U105: =SUMIFS('2025 Addbacks'!$G$90:$G$101,'2025 Addbacks'!$A$90:$A$101,U$9)/1000 -> 2.53458 | V105: =SUMIFS('2025 Addbacks'!$G$90:$G$101,'2025 Addbacks'!$A$90:$A$101,V$9)/1000 -> 0.7812 | W105: =SUMIFS('2025 Addbacks'!$G$90:$G$101,'2025 Addbacks'!$A$90:$A$101,W$9)/1000 -> 1.05157 | ... AA105: =SUMIFS('2025 Addbacks'!$G$90:$G$101,'2025 Addbacks'!$A$90:$A$101,AA$9)/1000 -> 12.04897 | AB105: =SUMIFS('2026 Addbacks'!$C:$C,'2026 Addbacks'!$B:$B,AB$9)/1000 -> 2.644585 | AC105: =SUMIFS('2026 Addbacks'!$C:$C,'2026 Addbacks'!$B:$B,AC$9)/1000 -> 13.13615 | AD105: =SUMIFS('2026 Addbacks'!$C:$C,'2026 Addbacks'!$B:$B,AD$9)/1000 -> 32.13164 | AE105: =SUMIFS('2026 Addbacks'!$C:$C,'2026 Addbacks'!$B:$B,AE$9)/1000 -> 2.644585 | AF105: =SUMIFS('2026 Addbacks'!$C:$C,'2026 Addbacks'!$B:$B,AF$9)/1000 -> 0 | CA105: =SUM('2024 Addbacks'!B4:B21)/1000 -> 99.01537 | CB105: =SUMIFS($D105:$AF105,$D$1:$AF$1,CB$2) -> 133.45005 | CC105: =SUMIFS($P105:$AF105,$P$3:$AF$3,$CC$2) -> 142.41041 | CU105: =SUMIFS($D105:$BZ105,$D$1:$BZ$1,CU$9) -> 50.55696 | CV105: =SUMIFS($D105:$BZ105,$D$1:$BZ$1,CV$9) -> 0 | CW105: =SUMIFS($D105:$BZ105,$D$1:$BZ$1,CW$9) -> 0 | CX105: =SUMIFS($D105:$BZ105,$D$1:$BZ$1,CX$9) -> 0
C106: Addback: Owner Payroll | P106: =115/12 -> 9.5833333 | Q106: =115/12 -> 9.5833333 | R106: =115/12 -> 9.5833333 | S106: =115/12 -> 9.5833333 | T106: =115/12 -> 9.5833333 | U106: =115/12 -> 9.5833333 | V106: =115/12 -> 9.5833333 | W106: =115/12 -> 9.5833333 | ... AA106: =115/12 -> 9.5833333 | AB106: =36/4 -> 9 | AC106: =36/4 -> 9 | AD106: =36/4 -> 9 | AE106: =36/4 -> 9 | AF106: 0 | CA106: 0 | CB106: =SUMIFS($D106:$AF106,$D$1:$AF$1,CB$2) -> 115 | CC106: =SUMIFS($P106:$AF106,$P$3:$AF$3,$CC$2) -> 112.66667 | CR106: Owners paid themselves / kids (not related to work done at venue) ~$115k in 2025, assuming that continued into 2026, waiting on confirmation; had previously | CU106: =SUMIFS($D106:$BZ106,$D$1:$BZ$1,CU$9) -> 36 | CV106: =SUMIFS($D106:$BZ106,$D$1:$BZ$1,CV$9) -> 0 | CW106: =SUMIFS($D106:$BZ106,$D$1:$BZ$1,CW$9) -> 0 | CX106: =SUMIFS($D106:$BZ106,$D$1:$BZ$1,CX$9) -> 0
C107: Less: Annuallzing Comp | P107: =-(10/3+(16*8*3*50)/1000/12) -> -4.9333333 | Q107: =-(10/3+(16*8*3*50)/1000/12) -> -4.9333333 | R107: =-(10/3+(16*8*3*50)/1000/12) -> -4.9333333 | S107: =-(16*8*3*50)/1000/12 -> -1.6 | T107: =-(16*8*3*50)/1000/12 -> -1.6 | U107: =-(16*8*3*50)/1000/12 -> -1.6 | V107: =-(16*8*3*50)/1000/12 -> -1.6 | W107: =-(16*8*3*50)/1000/12 -> -1.6 | X107: =-(16*8*3*50)/1000/12 -> -1.6 | Y107: =-(16*8*3*50)/1000/12 -> -1.6 | Z107: =-(16*8*3*50)/1000/12 -> -1.6 | AA107: =-(16*8*3*50)/1000/12 -> -1.6 | AB107: 0 | AC107: 0 | AD107: 0 | AE107: 0 | AF107: 0 | CA107: 0 | CB107: =SUMIFS($D107:$AF107,$D$1:$AF$1,CB$2) -> -29.2 | CC107: =SUMIFS($P107:$AF107,$P$3:$AF$3,$CC$2) -> -12.8 | CR107: Anna started in late March-25, adding $10k for what she would have made in Jan-Mar, Maddie started in 2026, so adding her est. comp for 2025 | CU107: =SUMIFS($D107:$BZ107,$D$1:$BZ$1,CU$9) -> 0 | CV107: =SUMIFS($D107:$BZ107,$D$1:$BZ$1,CV$9) -> 0 | CW107: =SUMIFS($D107:$BZ107,$D$1:$BZ$1,CW$9) -> 0 | CX107: =SUMIFS($D107:$BZ107,$D$1:$BZ$1,CX$9) -> 0
C109: Total Other Adj. | D109: =SUM(D104:D108) -> 0 | E109: =SUM(E104:E108) -> 0 | F109: =SUM(F104:F108) -> 0 | G109: =SUM(G104:G108) -> 0 | H109: =SUM(H104:H108) -> 0 | I109: =SUM(I104:I108) -> 0 | J109: =SUM(J104:J108) -> 0 | K109: =SUM(K104:K108) -> 0 | ... AF109: =SUM(AF104:AF108) -> 62 | CA109: =SUM(CA104:CA108) -> 269.51537 | CB109: =SUM(CB104:CB108) -> 427.75005 | CC109: =SUM(CC104:CC108) -> 449.04708 | CD109: =SUM(CD104:CD108) -> 0 | CE109: =SUM(CE104:CE108) -> 0 | CF109: =SUM(CF104:CF108) -> 0 | CH109: =SUM(CH104:CH108) -> 0 | CI109: =SUM(CI104:CI108) -> 0 | CJ109: =SUM(CJ104:CJ108) -> 0 | CL109: =SUM(CL104:CL108) -> 0 | CN109: =SUM(CN104:CN108) -> 0 | CO109: =SUM(CO104:CO108) -> 0 | CU109: =SUM(CU104:CU108) -> 208.82696 | CV109: =SUM(CV104:CV108) -> 0 | CW109: =SUM(CW104:CW108) -> 0 | CX109: =SUM(CX104:CX108) -> 0
C111: Adjusted EBITDAR | D111: =D101+D109 -> 0 | E111: =E101+E109 -> 0 | F111: =F101+F109 -> 43.726928 | G111: =G101+G109 -> 175.65771 | H111: =H101+H109 -> 144.77155 | I111: =I101+I109 -> 145.22617 | J111: =J101+J109 -> 63.067699 | K111: =K101+K109 -> 142.47617 | ... AF111: =AF101+AF109 -> 122.22937 | AH111: =AH101+AH109 -> 48.268789 | AI111: =AI101+AI109 -> 23.790508 | AJ111: =AJ101+AJ109 -> 71.364649 | AK111: =AK101+AK109 -> 100.16013 | AL111: =AL101+AL109 -> 132.74032 | AM111: =AM101+AM109 -> 42.60307 | AN111: =AN101+AN109 -> -10.321925 | AO111: =AO101+AO109 -> -44.904764 | ... BQ111: =BQ101+BQ109 -> 240.3572 | BS111: =BS101+BS109 -> 157.59757 | BT111: =BT101+BT109 -> 52.180642 | BU111: =BU101+BU109 -> 134.94027 | BV111: =BV101+BV109 -> 193.31306 | BW111: =BW101+BW109 -> 240.3572 | BX111: =BX101+BX109 -> 112.28298 | BY111: =BY101+BY109 -> 6.8660521 | CA111: =CA101+CA109 -> 613.72604 | CB111: =CB101+CB109 -> 567.31911 | CC111: =CC101+CC109 -> 559.60715 | CD111: =CD101+CD109 -> 593.04724 | CE111: =CE101+CE109 -> 807.83677 | CF111: =CF101+CF109 -> 1220.2729 | CH111: =IFERROR(CD111/CD$55,0) -> 0.3020489 | CI111: =IFERROR(CE111/CE$55,0) -> 0.30243904 | CJ111: =IFERROR(CF111/CF$55,0) -> 0.32118035 | CL111: =CL101+CL109 -> 0.083335915 | CN111: =CN101+CN109 -> 11122.699 | CO111: =CO101+CO109 -> 0.30682211 | CU111: =CU101+CU109 -> 579.92769 | CV111: =CV101+CV109 -> 739.2378 | CW111: =CW101+CW109 -> 1150.5784 | CX111: =CX101+CX109 -> 1220.2729
CU112: =SUM(AB111:AN111) -> 579.92769 | CV112: =SUM(AO111:AZ111) -> 739.2378 | CW112: =SUM(BA111:BL111) -> 1150.5784 | CX112: =SUM(BM111:BY111) -> 1220.2729
C115: All Inclusive Revenue
C116: Total | AH116: =AH45 -> 35.095 | AI116: =AI45 -> 7.925 | AJ116: =AJ45 -> 74.58 | AK116: =AK45 -> 44.485 | AL116: =AL45 -> 31.075 | AM116: =AM45 -> 24.575 | AN116: =AN45 -> 0.95 | AO116: =AO45 -> 0 | ... BQ116: =BQ45 -> 0 | BS116: =BS45 -> 0 | BT116: =BT45 -> 0 | BU116: =BU45 -> 0 | BV116: =BV45 -> 0 | BW116: =BW45 -> 0 | BX116: =BX45 -> 0 | BY116: =BY45 -> 0 | CA116: =SUMIFS($D116:$BZ116,$D$1:$BZ$1,CA$2) -> 0 | CB116: =SUMIFS($D116:$BZ116,$D$1:$BZ$1,CB$2) -> 0 | CC116: =SUMIFS($P116:$AF116,$P$3:$AF$3,$CC$2) -> 0 | CD116: =SUMIFS($D116:$BZ116,$D$3:$BZ$3,CD$2) -> 288.07 | CE116: =SUMIFS($D116:$BZ116,$D$3:$BZ$3,CE$2) -> 71.645 | CF116: =SUMIFS($D116:$BZ116,$D$3:$BZ$3,CF$2) -> 0
C117: Food | AH117: =SUMIFS('Future Events'!$K:$K,'Future Events'!$D:$D,AH$9)/1000 -> 3.6 | AI117: =SUMIFS('Future Events'!$K:$K,'Future Events'!$D:$D,AI$9)/1000 -> 0 | AJ117: =SUMIFS('Future Events'!$K:$K,'Future Events'!$D:$D,AJ$9)/1000 -> 10 | AK117: =SUMIFS('Future Events'!$K:$K,'Future Events'!$D:$D,AK$9)/1000 -> 12 | AL117: =SUMIFS('Future Events'!$K:$K,'Future Events'!$D:$D,AL$9)/1000 -> 0 | AM117: =SUMIFS('Future Events'!$K:$K,'Future Events'!$D:$D,AM$9)/1000 -> 2 | AN117: =SUMIFS('Future Events'!$K:$K,'Future Events'!$D:$D,AN$9)/1000 -> 0 | AO117: =SUMIFS('Future Events'!$K:$K,'Future Events'!$D:$D,AO$9)/1000 -> 0 | ... BQ117: =SUMIFS('Future Events'!$K:$K,'Future Events'!$D:$D,BQ$9)/1000 -> 0 | BS117: =SUMIFS('Future Events'!$K:$K,'Future Events'!$D:$D,BS$9)/1000 -> 0 | BT117: =SUMIFS('Future Events'!$K:$K,'Future Events'!$D:$D,BT$9)/1000 -> 0 | BU117: =SUMIFS('Future Events'!$K:$K,'Future Events'!$D:$D,BU$9)/1000 -> 0 | BV117: =SUMIFS('Future Events'!$K:$K,'Future Events'!$D:$D,BV$9)/1000 -> 0 | BW117: =SUMIFS('Future Events'!$K:$K,'Future Events'!$D:$D,BW$9)/1000 -> 0 | BX117: =SUMIFS('Future Events'!$K:$K,'Future Events'!$D:$D,BX$9)/1000 -> 0 | BY117: =SUMIFS('Future Events'!$K:$K,'Future Events'!$D:$D,BY$9)/1000 -> 0 | CA117: =SUMIFS($D117:$BZ117,$D$1:$BZ$1,CA$2) -> 0 | CB117: =SUMIFS($D117:$BZ117,$D$1:$BZ$1,CB$2) -> 0 | CC117: =SUMIFS($P117:$AF117,$P$3:$AF$3,$CC$2) -> 0 | CD117: =SUMIFS($D117:$BZ117,$D$3:$BZ$3,CD$2) -> 38.6 | CE117: =SUMIFS($D117:$BZ117,$D$3:$BZ$3,CE$2) -> 14.6 | CF117: =SUMIFS($D117:$BZ117,$D$3:$BZ$3,CF$2) -> 0
C118: Ancillary | AH118: =AH116-AH117 -> 31.495 | AI118: =AI116-AI117 -> 7.925 | AJ118: =AJ116-AJ117 -> 64.58 | AK118: =AK116-AK117 -> 32.485 | AL118: =AL116-AL117 -> 31.075 | AM118: =AM116-AM117 -> 22.575 | AN118: =AN116-AN117 -> 0.95 | AO118: =AO116-AO117 -> 0 | ... BQ118: =BQ116-BQ117 -> 0 | BS118: =SUMIFS('Future Events'!$K:$K,'Future Events'!$D:$D,BS$9)/1000 -> 0 | BT118: =SUMIFS('Future Events'!$K:$K,'Future Events'!$D:$D,BT$9)/1000 -> 0 | BU118: =SUMIFS('Future Events'!$K:$K,'Future Events'!$D:$D,BU$9)/1000 -> 0 | BV118: =SUMIFS('Future Events'!$K:$K,'Future Events'!$D:$D,BV$9)/1000 -> 0 | BW118: =SUMIFS('Future Events'!$K:$K,'Future Events'!$D:$D,BW$9)/1000 -> 0 | BX118: =SUMIFS('Future Events'!$K:$K,'Future Events'!$D:$D,BX$9)/1000 -> 0 | BY118: =SUMIFS('Future Events'!$K:$K,'Future Events'!$D:$D,BY$9)/1000 -> 0 | CA118: =SUMIFS($D118:$BZ118,$D$1:$BZ$1,CA$2) -> 0 | CB118: =SUMIFS($D118:$BZ118,$D$1:$BZ$1,CB$2) -> 0 | CC118: =SUMIFS($P118:$AF118,$P$3:$AF$3,$CC$2) -> 0 | CD118: =SUMIFS($D118:$BZ118,$D$3:$BZ$3,CD$2) -> 249.47 | CE118: =SUMIFS($D118:$BZ118,$D$3:$BZ$3,CE$2) -> 57.045 | CF118: =SUMIFS($D118:$BZ118,$D$3:$BZ$3,CF$2) -> 0

Sheet Revenue Analysis - Total
C3: =Checks!$C$3 -> Firefly Lane
C4: Revenue Analysis
C6: $ in thousands | D6: =$C$3 -> Firefly Lane | K6: Drivers | O6: To Compare
D7: Historical | G7: PF | P7: WH Venue | Q7: WH Region
D8: =Checks!$D$11 -> 2024 | E8: =Checks!$D$12 -> 2025 | F8: =Checks!$D$13 -> LTM Apr-26 | G8: Y1 | H8: Y2 | I8: Y3 | K8: Y1 | L8: Y2 | M8: Y3 | O8: =C3 -> Firefly Lane | P8: ='Adj. P&L'!CN1 -> DFW | Q8: DFW | R8: WH Average
C10: Events
C11: OC | D11: ='Revenue Analysis - Barn'!D11+'Revenue Analysis - Chapel'!D11 -> 153 | E11: ='Revenue Analysis - Barn'!E11+'Revenue Analysis - Chapel'!E11 -> 133 | F11: ='Revenue Analysis - Barn'!F11+'Revenue Analysis - Chapel'!F11 -> 131 | G11: ='Revenue Analysis - Barn'!G11+'Revenue Analysis - Chapel'!G11 -> 122 | H11: ='Revenue Analysis - Barn'!H11+'Revenue Analysis - Chapel'!H11 -> 30 | I11: ='Revenue Analysis - Barn'!I11+'Revenue Analysis - Chapel'!I11 -> 0
