Workbook
Name _____I2: {"PVGraph2",#N/A,FALSE,"PV Data"}
Name _____I3: {"PVGraph2",#N/A,FALSE,"PV Data"}
Name _____w1: {"PVGraph2",#N/A,FALSE,"PV Data"}
Name _____w2: {"PVGraph2",#N/A,FALSE,"PV Data"}
Name _____w3: {"PVGraph2",#N/A,FALSE,"PV Data"}
Name _____y2: {"PVGraph2",#N/A,FALSE,"PV Data"}
Name ___I2: {"PVGraph2",#N/A,FALSE,"PV Data"}
Name ___I3: {"PVGraph2",#N/A,FALSE,"PV Data"}
Name ___w1: {"PVGraph2",#N/A,FALSE,"PV Data"}
Name ___w2: {"PVGraph2",#N/A,FALSE,"PV Data"}
Name ___w3: {"PVGraph2",#N/A,FALSE,"PV Data"}
Name ___y2: {"PVGraph2",#N/A,FALSE,"PV Data"}
Name __PL4: {#N/A,#N/A,FALSE,"Report Data";#N/A,#N/A,FALSE,"COMP POOL";#N/A,#N/A,FALSE,"COMP POOL NB95";#N/A,#N/A,FALSE,"COMP POOL NB94"}
Name _A11: {#N/A,#N/A,FALSE,"Umsatz 99";#N/A,#N/A,FALSE,"ER 99 "}
Name _c: {"Fiesta Facer Page",#N/A,FALSE,"Q_C_S";"Fiesta Main Page",#N/A,FALSE,"V_L";"Fiesta 95BP Struct",#N/A,FALSE,"StructBP";"Fiesta Post 95BP Struct",#N/A,FALSE,"AdjStructBP"}
Name _c83: {0,0,0,0;0,0,0,0;0,0,0,0}
Name _cd1: {#N/A,#N/A,FALSE,"Job Sched"}
Name _cd2: {#N/A,#N/A,FALSE,"Job Sched"}
Name _CD3: {#N/A,#N/A,FALSE,"Job Sched"}
Name _cd4: {#N/A,#N/A,FALSE,"Job Sched"}
Name _Cd5: {#N/A,#N/A,FALSE,"A"}
Name _cd8: {#N/A,#N/A,FALSE,"Job Sched"}
Name _fdf1: {"incomemth",#N/A,TRUE,"forecast00";"incomepercentmth",#N/A,TRUE,"forecast00";"balancemth",#N/A,TRUE,"forecast00";"cashmth",#N/A,TRUE,"forecast00";"covenantmth",#N/A,TRUE,"forecast00"}
Name _fdg1: {"incomemth",#N/A,TRUE,"forecast00";"incomepercentmth",#N/A,TRUE,"forecast00";"balancemth",#N/A,TRUE,"forecast00";"cashmth",#N/A,TRUE,"forecast00";"covenantmth",#N/A,TRUE,"forecast00"}
Name _gf1: {"incomemth",#N/A,TRUE,"forecast00";"incomepercentmth",#N/A,TRUE,"forecast00";"balancemth",#N/A,TRUE,"forecast00";"cashmth",#N/A,TRUE,"forecast00";"covenantmth",#N/A,TRUE,"forecast00"}
Name _I2: {"PVGraph2",#N/A,FALSE,"PV Data"}
Name _I3: {"PVGraph2",#N/A,FALSE,"PV Data"}
Name _mfg2: {"PAGE 1",#N/A,FALSE,"WEST_OT"}
Name _mfg3: {"PAGE 1",#N/A,FALSE,"WEST_OT"}
Name _mfg4: {"PAGE 1",#N/A,FALSE,"WEST_OT"}
Name _mfg5: {"PAGE 1",#N/A,FALSE,"WEST_OT"}
Name _nm12: {#N/A,#N/A,FALSE,"Land";#N/A,#N/A,FALSE,"Cost Analysis";"Summary",#N/A,FALSE,"Equipment"}
Name _rod1: {#N/A,#N/A,FALSE,"Projections";#N/A,#N/A,FALSE,"Multiples Valuation";#N/A,#N/A,FALSE,"LBO";#N/A,#N/A,FALSE,"Multiples_Sensitivity";#N/A,#N/A,FALSE,"Summary"}
Name _t1: {"bs",#N/A,FALSE,"SCF"}
Name _w1: {"PVGraph2",#N/A,FALSE,"PV Data"}
Name _w2: {"PVGraph2",#N/A,FALSE,"PV Data"}
Name _w3: {"PVGraph2",#N/A,FALSE,"PV Data"}
Name _wrn2: {#N/A,#N/A,FALSE,"ASSUMPTIONS";#N/A,#N/A,FALSE,"Valuation Summary";"page1",#N/A,FALSE,"PRESENTATION";"page2",#N/A,FALSE,"PRESENTATION";#N/A,#N/A,FALSE,"ORIGINAL_ROLLBACK"}
Name _wrn3: {#N/A,#N/A,FALSE,"ASSUMPTIONS";#N/A,#N/A,FALSE,"Valuation Summary";"page1",#N/A,FALSE,"PRESENTATION";"page2",#N/A,FALSE,"PRESENTATION";#N/A,#N/A,FALSE,"ORIGINAL_ROLLBACK"}
Name _wrn4: {"general",#N/A,FALSE,"Assumptions"}
Name _x1: {#N/A,#N/A,FALSE,"FY97";#N/A,#N/A,FALSE,"FY98";#N/A,#N/A,FALSE,"FY99";#N/A,#N/A,FALSE,"FY00";#N/A,#N/A,FALSE,"FY01"}
Name _y2: {"PVGraph2",#N/A,FALSE,"PV Data"}
Name a: {"histincome",#N/A,FALSE,"hyfins";"closing balance",#N/A,FALSE,"hyfins"}
Name a.: {#N/A,#N/A,TRUE,"KEY DATA";#N/A,#N/A,TRUE,"KEY DATA Base Case";#N/A,#N/A,TRUE,"JULY";#N/A,#N/A,TRUE,"AUG";#N/A,#N/A,TRUE,"SEPT";#N/A,#N/A,TRUE,"3Q"}
Name A..: {#N/A,#N/A,TRUE,"KEY DATA";#N/A,#N/A,TRUE,"KEY DATA Base Case";#N/A,#N/A,TRUE,"JULY";#N/A,#N/A,TRUE,"AUG";#N/A,#N/A,TRUE,"SEPT";#N/A,#N/A,TRUE,"3Q"}
Name aa: {#N/A,#N/A,TRUE,"KEY DATA";#N/A,#N/A,TRUE,"KEY DATA Base Case";#N/A,#N/A,TRUE,"JULY";#N/A,#N/A,TRUE,"AUG";#N/A,#N/A,TRUE,"SEPT";#N/A,#N/A,TRUE,"3Q"}
Name aaa: {#N/A,#N/A,TRUE,"Falcons_Standalone";#N/A,#N/A,TRUE,"Target_Input";#N/A,#N/A,TRUE,"Target_Calendarized"}
Name aaa.: {#N/A,#N/A,TRUE,"KEY DATA";#N/A,#N/A,TRUE,"KEY DATA Base Case";#N/A,#N/A,TRUE,"JULY";#N/A,#N/A,TRUE,"AUG";#N/A,#N/A,TRUE,"SEPT";#N/A,#N/A,TRUE,"3Q"}
Name aaaaaaa: {"Outflow 1",#N/A,FALSE,"Outflows-Inflows";"Outflow 2",#N/A,FALSE,"Outflows-Inflows";"Inflow 1",#N/A,FALSE,"Outflows-Inflows";"Inflow 2",#N/A,FALSE,"Outflows-Inflows"}
Name aaaasdf: {#N/A,#N/A,TRUE,"GEM Total";#N/A,#N/A,TRUE,"Final Assembly";#N/A,#N/A,TRUE,"Cleaning";#N/A,#N/A,TRUE,"Schooping,Clearing";#N/A,#N/A,TRUE,"Winding"}
Name aabb: {#N/A,#N/A,FALSE,"Projections";#N/A,#N/A,FALSE,"Multiples Valuation";#N/A,#N/A,FALSE,"LBO";#N/A,#N/A,FALSE,"Multiples_Sensitivity";#N/A,#N/A,FALSE,"Summary"}
Name aasda: {"PrintView",#N/A,FALSE,"Cash & Equiv";"PrintView",#N/A,FALSE,"Investments";"Other Assets Print View",#N/A,FALSE,"Other Assets"}
Name aasdfa: {"rtn",#N/A,FALSE,"RTN";"tables",#N/A,FALSE,"RTN";"cf",#N/A,FALSE,"CF";"stats",#N/A,FALSE,"Stats";"prop",#N/A,FALSE,"Prop"}
Name abcd: {"histincome",#N/A,FALSE,"hyfins";"closing balance",#N/A,FALSE,"hyfins"}
Name adfadf: {"histincome",#N/A,FALSE,"hyfins";"closing balance",#N/A,FALSE,"hyfins"}
Name adfda: {"histincome",#N/A,FALSE,"hyfins";"closing balance",#N/A,FALSE,"hyfins"}
Name adfdasfasd: {"histincome",#N/A,FALSE,"hyfins";"closing balance",#N/A,FALSE,"hyfins"}
Name adfj: {"bs",#N/A,FALSE,"SCF"}
Name adg: {"'Sheet1'!$A$1:$O$40"}
Name ads: {#N/A,#N/A,FALSE,"AD_Purch";#N/A,#N/A,FALSE,"Projections";#N/A,#N/A,FALSE,"DCF";#N/A,#N/A,FALSE,"Mkt Val"}

Sheet Detailed P&L
D1: =YEAR(D9) -> 2024 | E1: =YEAR(E9) -> 2024 | F1: =YEAR(F9) -> 2024 | G1: =YEAR(G9) -> 2024 | H1: =YEAR(H9) -> 2024 | I1: =YEAR(I9) -> 2024 | J1: =YEAR(J9) -> 2024 | K1: =YEAR(K9) -> 2024 | ... AI1: =YEAR(AI9) -> 2026 | AK1: =YEAR(AK9) -> 2026 | AL1: =YEAR(AL9) -> 2026 | AM1: =YEAR(AM9) -> 2026 | AN1: =YEAR(AN9) -> 2026 | AO1: =YEAR(AO9) -> 2027 | AP1: =YEAR(AP9) -> 2027 | AQ1: =YEAR(AQ9) -> 2027 | AR1: =YEAR(AR9) -> 2027 | ... BX1: =YEAR(BX9) -> 2029 | CC1: 1 | CD1: 2 | CE1: 3 | CM1: ATL
D2: =MONTH(D9) -> 1 | E2: =MONTH(E9) -> 2 | F2: =MONTH(F9) -> 3 | G2: =MONTH(G9) -> 4 | H2: =MONTH(H9) -> 5 | I2: =MONTH(I9) -> 6 | J2: =MONTH(J9) -> 7 | K2: =MONTH(K9) -> 8 | ... AI2: =MONTH(AI9) -> 8 | AK2: =MONTH(AK9) -> 9 | AL2: =MONTH(AL9) -> 10 | AM2: =MONTH(AM9) -> 11 | AN2: =MONTH(AN9) -> 12 | AO2: =MONTH(AO9) -> 1 | AP2: =MONTH(AP9) -> 2 | AQ2: =MONTH(AQ9) -> 3 | AR2: =MONTH(AR9) -> 4 | ... BX2: =MONTH(BX9) -> 12
W3: LTM | X3: LTM | Y3: LTM | Z3: LTM | AA3: LTM | AB3: LTM | AC3: LTM | AD3: LTM | AE3: LTM | AF3: LTM | AG3: LTM | AH3: LTM | AK3: 1 | AL3: =AK3 -> 1 | AM3: =AL3 -> 1 | AN3: =AM3 -> 1 | AO3: =AN3 -> 1 | AP3: =AO3 -> 1 | AQ3: =AP3 -> 1 | AR3: =AQ3 -> 1 | AS3: =AR3 -> 1 | ... AV3: =AU3 -> 1 | AW3: =AK3+1 -> 2 | AX3: =AL3+1 -> 2 | AY3: =AM3+1 -> 2 | AZ3: =AN3+1 -> 2 | BA3: =AO3+1 -> 2 | BB3: =AP3+1 -> 2 | BC3: =AQ3+1 -> 2 | BD3: =AR3+1 -> 2 | ... BX3: =BL3+1 -> 4
C5: =Summary!$C$3 -> Hadden Estate | CM5: =INDEX('FY25 By Venue Financials'!$1:$1,MATCH(CM1,'FY25 By Venue Financials'!$4:$4,0)) -> N
C6: PF P&L Analysis
D8: Historicals | P8: Historicals | AK8: Forecast | BZ8: Historicals | CC8: PF | CG8: PF Drivers | CK8: Current | CM8: WH Comparable Venue
D9: 45322 | E9: =EOMONTH(D9,1) -> 45351 | F9: =EOMONTH(E9,1) -> 45382 | G9: =EOMONTH(F9,1) -> 45412 | H9: =EOMONTH(G9,1) -> 45443 | I9: =EOMONTH(H9,1) -> 45473 | J9: =EOMONTH(I9,1) -> 45504 | K9: =EOMONTH(J9,1) -> 45535 | L9: =EOMONTH(K9,1) -> 45565 | ... AI9: =EOMONTH(AH9,1) -> 46265 | AK9: =EOMONTH(AI9,1) -> 46295 | AL9: =EOMONTH(AK9,1) -> 46326 | AM9: =EOMONTH(AL9,1) -> 46356 | AN9: =EOMONTH(AM9,1) -> 46387 | AO9: =EOMONTH(AN9,1) -> 46418 | AP9: =EOMONTH(AO9,1) -> 46446 | AQ9: =EOMONTH(AP9,1) -> 46477 | AR9: =EOMONTH(AQ9,1) -> 46507 | AS9: =EOMONTH(AR9,1) -> 46538 | ... BX9: =EOMONTH(BW9,1) -> 47483 | BZ9: 2024 | CA9: 2025 | CB9: ='Events Summary'!$C$12 -> LTM Jul-26 | CC9: Y1 | CD9: Y2 | CE9: Y3 | CG9: Y1 | CH9: Y2 | CI9: Y3 | CK9: % | CM9: $ | CN9: % | CP9: % Type | CQ9: Monthly Split | CR9: Historical / PF Comments
C11: Leads | AB11: =SUMIFS(Leads!$I$4:$I$10,Leads!$H$4:$H$10,AB$9) -> 67 | AC11: =SUMIFS(Leads!$I$4:$I$10,Leads!$H$4:$H$10,AC$9) -> 30 | AD11: =SUMIFS(Leads!$I$4:$I$10,Leads!$H$4:$H$10,AD$9) -> 29 | AE11: =SUMIFS(Leads!$I$4:$I$10,Leads!$H$4:$H$10,AE$9) -> 53 | AF11: =SUMIFS(Leads!$I$4:$I$10,Leads!$H$4:$H$10,AF$9) -> 45 | AG11: =SUMIFS(Leads!$I$4:$I$10,Leads!$H$4:$H$10,AG$9) -> 43 | AH11: =SUMIFS(Leads!$I$4:$I$10,Leads!$H$4:$H$10,AH$9) -> 38 | AI11: 85 | AK11: 90 | AL11: 115 | AM11: 110 | AN11: 110 | AO11: 175 | AP11: =($CC$11-SUM($AK$11:$AO$11))*(AP91/SUM($AP$91:$AV$91)) -> 142.10526 | AQ11: =($CC$11-SUM($AK$11:$AO$11))*(AQ91/SUM($AP$91:$AV$91)) -> 126.31579 | AR11: =($CC$11-SUM($AK$11:$AO$11))*(AR91/SUM($AP$91:$AV$91)) -> 126.31579 | AS11: =($CC$11-SUM($AK$11:$AO$11))*(AS91/SUM($AP$91:$AV$91)) -> 126.31579 | AT11: =($CC$11-SUM($AK$11:$AO$11))*(AT91/SUM($AP$91:$AV$91)) -> 126.31579 | AU11: =($CC$11-SUM($AK$11:$AO$11))*(AU91/SUM($AP$91:$AV$91)) -> 126.31579 | AV11: =($CC$11-SUM($AK$11:$AO$11))*(AV91/SUM($AP$91:$AV$91)) -> 126.31579 | AW11: =ROUND(SUMIFS($CC11:$CE11,$CC$1:$CE$1,AW$3)*AW$91,0) -> 140 | AX11: =ROUND(SUMIFS($CC11:$CE11,$CC$1:$CE$1,AX$3)*AX$91,0) -> 140 | AY11: =ROUND(SUMIFS($CC11:$CE11,$CC$1:$CE$1,AY$3)*AY$91,0) -> 123 | AZ11: =ROUND(SUMIFS($CC11:$CE11,$CC$1:$CE$1,AZ$3)*AZ$91,0) -> 123 | BA11: 226 | BB11: =ROUND(SUMIFS($CC11:$CE11,$CC$1:$CE$1,BB$3)*BB$91,0) -> 158 | BC11: =ROUND(SUMIFS($CC11:$CE11,$CC$1:$CE$1,BC$3)*BC$91,0) -> 140 | BD11: =ROUND(SUMIFS($CC11:$CE11,$CC$1:$CE$1,BD$3)*BD$91,0) -> 140 | BE11: =ROUND(SUMIFS($CC11:$CE11,$CC$1:$CE$1,BE$3)*BE$91,0) -> 140 | BF11: =ROUND(SUMIFS($CC11:$CE11,$CC$1:$CE$1,BF$3)*BF$91,0) -> 140 | BG11: =ROUND(SUMIFS($CC11:$CE11,$CC$1:$CE$1,BG$3)*BG$91,0) -> 140 | BH11: =ROUND(SUMIFS($CC11:$CE11,$CC$1:$CE$1,BH$3)*BH$91,0) -> 140 | BI11: =ROUND(SUMIFS($CC11:$CE11,$CC$1:$CE$1,BI$3)*BI$91,0) -> 160 | ... BT11: =ROUND(SUMIFS($CC11:$CE11,$CC$1:$CE$1,BT$3)*BT$91,0) -> 160 | BU11: =BI11 -> 160 | BV11: =BJ11 -> 160 | BW11: =BK11 -> 140 | BX11: =BL11 -> 140 | CC11: 1500 | CD11: 1750 | CE11: 2000
C13: L->T Conversion | AB13: =AB15/AB11 -> 0.029850746 | AC13: =AC15/AC11 -> 0.1 | AD13: =AD15/AD11 -> 0.20689655 | AE13: =AE15/AE11 -> 0.056603774 | AF13: =AF15/AF11 -> 0.22222222 | AG13: =AG15/AG11 -> 0.11627907 | AH13: =AH15/AH11 -> 0.31578947 | AK13: =AK15/AK11 -> 0.16666667 | AL13: =AL15/AL11 -> 0.13043478 | AM13: =AM15/AM11 -> 0.17272727 | AN13: =AN15/AN11 -> 0.24545455 | AO13: =AO15/AO11 -> 0.31428571 | AP13: =AP15/AP11 -> 0.21814815 | AQ13: =AQ15/AQ11 -> 0.21375 | AR13: =AR15/AR11 -> 0.18208333 | ... BX13: =BX15/BX11 -> 0.28571429 | CC13: =CC15/CC11 -> 0.2 | CD13: =CD15/CD11 -> 0.2 | CE13: =CE15/CE11 -> 0.2
C15: Tours | AB15: =SUMIFS(Tours!$G$3:$G$9,Tours!$F$3:$F$9,AB$9) -> 2 | AC15: =SUMIFS(Tours!$G$3:$G$9,Tours!$F$3:$F$9,AC$9) -> 3 | AD15: =SUMIFS(Tours!$G$3:$G$9,Tours!$F$3:$F$9,AD$9) -> 6 | AE15: =SUMIFS(Tours!$G$3:$G$9,Tours!$F$3:$F$9,AE$9) -> 3 | AF15: =SUMIFS(Tours!$G$3:$G$9,Tours!$F$3:$F$9,AF$9) -> 10 | AG15: =SUMIFS(Tours!$G$3:$G$9,Tours!$F$3:$F$9,AG$9) -> 5 | AH15: =SUMIFS(Tours!$G$3:$G$9,Tours!$F$3:$F$9,AH$9) -> 12 | AI15: 9 | AK15: 15 | AL15: 15 | AM15: 19 | AN15: 27 | AO15: 55 | AP15: 31 | AQ15: 27 | AR15: 23 | AS15: 19 | AT15: 23 | AU15: 23 | AV15: 23 | AW15: =ROUND(SUMIFS($CC15:$CE15,$CC$1:$CE$1,AW$3)*AW$92,0) -> 30 | AX15: =ROUND(SUMIFS($CC15:$CE15,$CC$1:$CE$1,AX$3)*AX$92,0) -> 30 | AY15: =ROUND(SUMIFS($CC15:$CE15,$CC$1:$CE$1,AY$3)*AY$92,0) -> 33 | AZ15: =ROUND(SUMIFS($CC15:$CE15,$CC$1:$CE$1,AZ$3)*AZ$92,0) -> 35 | BA15: =ROUND(SUMIFS($CC15:$CE15,$CC$1:$CE$1,BA$3)*BA$92,0) -> 41 | BB15: =ROUND(SUMIFS($CC15:$CE15,$CC$1:$CE$1,BB$3)*BB$92,0) -> 29 | BC15: =ROUND(SUMIFS($CC15:$CE15,$CC$1:$CE$1,BC$3)*BC$92,0) -> 27 | BD15: 23 | BE15: 21 | BF15: =ROUND(SUMIFS($CC15:$CE15,$CC$1:$CE$1,BF$3)*BF$92,0) -> 25 | BG15: =ROUND(SUMIFS($CC15:$CE15,$CC$1:$CE$1,BG$3)*BG$92,0) -> 30 | BH15: =ROUND(SUMIFS($CC15:$CE15,$CC$1:$CE$1,BH$3)*BH$92,0) -> 26 | BI15: =ROUND(SUMIFS($CC15:$CE15,$CC$1:$CE$1,BI$3)*BI$92,0) -> 34 | BJ15: =ROUND(SUMIFS($CC15:$CE15,$CC$1:$CE$1,BJ$3)*BJ$92,0) -> 34 | BK15: =ROUND(SUMIFS($CC15:$CE15,$CC$1:$CE$1,BK$3)*BK$92,0) -> 38 | BL15: =ROUND(SUMIFS($CC15:$CE15,$CC$1:$CE$1,BL$3)*BL$92,0) -> 40 | BM15: =ROUND(SUMIFS($CC15:$CE15,$CC$1:$CE$1,BM$3)*BM$92,0) -> 47 | ... BP15: =ROUND(SUMIFS($CC15:$CE15,$CC$1:$CE$1,BP$3)*BP$92,0) -> 27 | BQ15: 24 | BR15: =ROUND(SUMIFS($CC15:$CE15,$CC$1:$CE$1,BR$3)*BR$92,0) -> 28 | BS15: =ROUND(SUMIFS($CC15:$CE15,$CC$1:$CE$1,BS$3)*BS$92,0) -> 34 | BT15: =ROUND(SUMIFS($CC15:$CE15,$CC$1:$CE$1,BT$3)*BT$92,0) -> 30 | BU15: =BI15 -> 34 | BV15: =BJ15 -> 34 | BW15: =BK15 -> 38 | BX15: =BL15 -> 40 | CC15: 300 | CD15: 350 | CE15: 400
C17: T->C Conversion | AK17: =AK19/AK15 -> 0.33333333 | AL17: =AL19/AL15 -> 0.33333333 | AM17: =AM19/AM15 -> 0.26315789 | AN17: =AN19/AN15 -> 0.25925926 | AO17: =AO19/AO15 -> 0.25454545 | AP17: =AP19/AP15 -> 0.25806452 | AQ17: =AQ19/AQ15 -> 0.25925926 | AR17: =AR19/AR15 -> 0.26086957 | ... BX17: =BX19/BX15 -> 0.25 | CC17: =CC19/CC15 -> 0.26666667 | CD17: =CD19/CD15 -> 0.25714286 | CE17: =CE19/CE15 -> 0.25
C19: Contracts | D19: 0 | E19: 0 | F19: 0 | G19: 0 | H19: 0 | I19: 0 | J19: 0 | K19: 0 | L19: 0 | M19: 0 | N19: 0 | O19: 0 | P19: 0 | Q19: 0 | R19: 0 | S19: 0 | T19: 0 | U19: 0 | V19: 0 | W19: 0 | X19: 0 | Y19: 0 | Z19: 0 | AA19: 0 | AB19: 0 | AC19: 0 | AD19: 0 | AE19: 0 | AF19: 0 | AG19: 0 | AH19: 0 | AI19: 5 | AK19: 5 | AL19: 5 | AM19: 5 | AN19: 7 | AO19: 14 | AP19: 8 | AQ19: 7 | AR19: 6 | AS19: 5 | AT19: 6 | AU19: 6 | AV19: 6 | AW19: 5 | AX19: =ROUND(SUMIFS($CC19:$CE19,$CC$1:$CE$1,AX$3)*AX$93,0) -> 8 | AY19: =ROUND(SUMIFS($CC19:$CE19,$CC$1:$CE$1,AY$3)*AY$93,0) -> 6 | AZ19: =ROUND(SUMIFS($CC19:$CE19,$CC$1:$CE$1,AZ$3)*AZ$93,0) -> 9 | BA19: =ROUND(SUMIFS($CC19:$CE19,$CC$1:$CE$1,BA$3)*BA$93,0) -> 11 | BB19: =ROUND(SUMIFS($CC19:$CE19,$CC$1:$CE$1,BB$3)*BB$93,0) -> 9 | BC19: =ROUND(SUMIFS($CC19:$CE19,$CC$1:$CE$1,BC$3)*BC$93,0) -> 8 | BD19: =ROUND(SUMIFS($CC19:$CE19,$CC$1:$CE$1,BD$3)*BD$93,0) -> 7 | BE19: =ROUND(SUMIFS($CC19:$CE19,$CC$1:$CE$1,BE$3)*BE$93,0) -> 6 | ... BP19: =ROUND(SUMIFS($CC19:$CE19,$CC$1:$CE$1,BP$3)*BP$93,0) -> 8 | BQ19: 7 | BR19: =ROUND(SUMIFS($CC19:$CE19,$CC$1:$CE$1,BR$3)*BR$93,0) -> 7 | BS19: =ROUND(SUMIFS($CC19:$CE19,$CC$1:$CE$1,BS$3)*BS$93,0) -> 7 | BT19: =ROUND(SUMIFS($CC19:$CE19,$CC$1:$CE$1,BT$3)*BT$93,0) -> 8 | BU19: =BI19 -> 7 | BV19: =BJ19 -> 9 | BW19: =BK19 -> 7 | BX19: =BL19 -> 10 | CC19: 80 | CD19: 90 | CE19: 100
C21: Original | D21: =SUMIFS('Events Summary'!$P:$P,'Events Summary'!$C:$C,D$9) -> 0 | E21: =SUMIFS('Events Summary'!$P:$P,'Events Summary'!$C:$C,E$9) -> 3 | F21: =SUMIFS('Events Summary'!$P:$P,'Events Summary'!$C:$C,F$9) -> 5 | G21: =SUMIFS('Events Summary'!$P:$P,'Events Summary'!$C:$C,G$9) -> 4 | H21: =SUMIFS('Events Summary'!$P:$P,'Events Summary'!$C:$C,H$9) -> 8 | I21: =SUMIFS('Events Summary'!$P:$P,'Events Summary'!$C:$C,I$9) -> 6 | J21: =SUMIFS('Events Summary'!$P:$P,'Events Summary'!$C:$C,J$9) -> 1 | K21: =SUMIFS('Events Summary'!$P:$P,'Events Summary'!$C:$C,K$9) -> 0 | ... AI21: =SUMIFS('Events Summary'!$P:$P,'Events Summary'!$C:$C,AI$9) -> 7 | AK21: =SUMIFS('Events Summary'!$P:$P,'Events Summary'!$C:$C,AK$9) -> 6 | AL21: =SUMIFS('Events Summary'!$P:$P,'Events Summary'!$C:$C,AL$9) -> 6 | AM21: =SUMIFS('Events Summary'!$P:$P,'Events Summary'!$C:$C,AM$9) -> 2 | AN21: =SUMIFS('Events Summary'!$P:$P,'Events Summary'!$C:$C,AN$9) -> 0 | AO21: =SUMIFS('Events Summary'!$P:$P,'Events Summary'!$C:$C,AO$9) -> 0 | AP21: =SUMIFS('Events Summary'!$P:$P,'Events Summary'!$C:$C,AP$9) -> 0 | AQ21: =SUMIFS('Events Summary'!$P:$P,'Events Summary'!$C:$C,AQ$9) -> 1 | AR21: =SUMIFS('Events Summary'!$P:$P,'Events Summary'!$C:$C,AR$9) -> 2 | ... BX21: =SUMIFS('Events Summary'!$P:$P,'Events Summary'!$C:$C,BX$9) -> 0 | BZ21: ='Revenue Analysis'!D11 -> 42 | CA21: ='Revenue Analysis'!E11 -> 43 | CB21: ='Revenue Analysis'!F11 -> 39 | CC21: ='Revenue Analysis'!G11 -> 24 | CD21: ='Revenue Analysis'!H11 -> 1 | CE21: ='Revenue Analysis'!I11 -> 0
C22: New | AK22: 0 | AL22: 0 | AM22: 0 | AN22: 2 | AO22: 0 | AP22: 0 | AQ22: 0 | AR22: 2 | AS22: 4 | AT22: 2 | AU22: 2 | AV22: 4 | AW22: =AW23-AW21 -> 6 | AX22: =AX23-AX21 -> 6 | AY22: =AY23-AY21 -> 6 | AZ22: =AZ23-AZ21 -> 5 | BA22: =BA23-BA21 -> 3 | BB22: =BB23-BB21 -> 4 | BC22: =BC23-BC21 -> 5 | BD22: =BD23-BD21 -> 5 | ... BX22: =BX23-BX21 -> 6 | BZ22: ='Revenue Analysis'!D12 -> 0 | CA22: ='Revenue Analysis'!E12 -> 0 | CB22: ='Revenue Analysis'!F12 -> 0 | CC22: ='Revenue Analysis'!G12 -> 16 | CD22: ='Revenue Analysis'!H12 -> 64 | CE22: ='Revenue Analysis'!I12 -> 80
C23: Events | D23: =SUM(D21:D22) -> 0 | E23: =SUM(E21:E22) -> 3 | F23: =SUM(F21:F22) -> 5 | G23: =SUM(G21:G22) -> 4 | H23: =SUM(H21:H22) -> 8 | I23: =SUM(I21:I22) -> 6 | J23: =SUM(J21:J22) -> 1 | K23: =SUM(K21:K22) -> 0 | ... AI23: =SUM(AI21:AI22) -> 7 | AK23: =AK21+AK22 -> 6 | AL23: =AL21+AL22 -> 6 | AM23: =AM21+AM22 -> 2 | AN23: =AN21+AN22 -> 2 | AO23: =AO21+AO22 -> 0 | AP23: =AP21+AP22 -> 0 | AQ23: =SUM(AQ21:AQ22) -> 1 | AR23: =SUM(AR21:AR22) -> 4 | AS23: =SUM(AS21:AS22) -> 8 | AT23: =SUM(AT21:AT22) -> 5 | AU23: =SUM(AU21:AU22) -> 2 | AV23: =SUM(AV21:AV22) -> 4 | AW23: =ROUND(AW$94*SUMIFS($CC23:$CE23,$CC$1:$CE$1,AW$3),0) -> 6 | AX23: =ROUND(AX$94*SUMIFS($CC23:$CE23,$CC$1:$CE$1,AX$3),0) -> 7 | AY23: =ROUND(AY$94*SUMIFS($CC23:$CE23,$CC$1:$CE$1,AY$3),0) -> 6 | AZ23: =ROUND(AZ$94*SUMIFS($CC23:$CE23,$CC$1:$CE$1,AZ$3),0) -> 5 | BA23: =ROUND(BA$94*SUMIFS($CC23:$CE23,$CC$1:$CE$1,BA$3),0) -> 3 | BB23: =ROUND(BB$94*SUMIFS($CC23:$CE23,$CC$1:$CE$1,BB$3),0) -> 4 | BC23: =ROUND(BC$94*SUMIFS($CC23:$CE23,$CC$1:$CE$1,BC$3),0) -> 5 | BD23: =ROUND(BD$94*SUMIFS($CC23:$CE23,$CC$1:$CE$1,BD$3),0) -> 5 | BE23: 8 | BF23: =ROUND(BF$94*SUMIFS($CC23:$CE23,$CC$1:$CE$1,BF$3),0) -> 6 | BG23: =ROUND(BG$94*SUMIFS($CC23:$CE23,$CC$1:$CE$1,BG$3),0) -> 5 | BH23: =ROUND(BH$94*SUMIFS($CC23:$CE23,$CC$1:$CE$1,BH$3),0) -> 5 | BI23: =ROUND(BI$94*SUMIFS($CC23:$CE23,$CC$1:$CE$1,BI$3),0) -> 8 | BJ23: =ROUND(BJ$94*SUMIFS($CC23:$CE23,$CC$1:$CE$1,BJ$3),0) -> 9 | BK23: =ROUND(BK$94*SUMIFS($CC23:$CE23,$CC$1:$CE$1,BK$3),0) -> 8 | BL23: =ROUND(BL$94*SUMIFS($CC23:$CE23,$CC$1:$CE$1,BL$3),0) -> 6 | BM23: =ROUND(BM$94*SUMIFS($CC23:$CE23,$CC$1:$CE$1,BM$3),0) -> 4 | ... BP23: =ROUND(BP$94*SUMIFS($CC23:$CE23,$CC$1:$CE$1,BP$3),0) -> 6 | BQ23: 8 | BR23: =ROUND(BR$94*SUMIFS($CC23:$CE23,$CC$1:$CE$1,BR$3),0) -> 8 | BS23: =ROUND(BS$94*SUMIFS($CC23:$CE23,$CC$1:$CE$1,BS$3),0) -> 6 | BT23: =ROUND(BT$94*SUMIFS($CC23:$CE23,$CC$1:$CE$1,BT$3),0) -> 6 | BU23: =BI23 -> 8 | BV23: =BJ23 -> 9 | BW23: =BK23 -> 8 | BX23: =BL23 -> 6 | BZ23: =SUM(BZ21:BZ22) -> 42 | CA23: =SUM(CA21:CA22) -> 43 | CB23: =SUM(CB21:CB22) -> 39 | CC23: =SUM(CC21:CC22) -> 40 | CD23: =SUM(CD21:CD22) -> 65 | CE23: =SUM(CE21:CE22) -> 80 | CK23: =CB23 -> 39 | CM23: ='Revenue Analysis'!$Q$13 -> 245
C24: % of Annual Events | AK24: =AK23/SUMIFS($CC$23:$CE$23,$CC$1:$CE$1,AK$3) -> 0.15 | AL24: =AL23/SUMIFS($CC$23:$CE$23,$CC$1:$CE$1,AL$3) -> 0.15 | AM24: =AM23/SUMIFS($CC$23:$CE$23,$CC$1:$CE$1,AM$3) -> 0.05 | AN24: =AN23/SUMIFS($CC$23:$CE$23,$CC$1:$CE$1,AN$3) -> 0.05 | AO24: =AO23/SUMIFS($CC$23:$CE$23,$CC$1:$CE$1,AO$3) -> 0 | AP24: =AP23/SUMIFS($CC$23:$CE$23,$CC$1:$CE$1,AP$3) -> 0 | AQ24: =AQ23/SUMIFS($CC$23:$CE$23,$CC$1:$CE$1,AQ$3) -> 0.025 | AR24: =AR23/SUMIFS($CC$23:$CE$23,$CC$1:$CE$1,AR$3) -> 0.1 | ... BT24: =BT23/SUMIFS($CC$23:$CE$23,$CC$1:$CE$1,BT$3) -> 0.075 | CC24: =SUM(AK23:AV23)-CC23 -> 0
AK25: =AK94 -> 0.097389487 | AL25: =AL94 -> 0.11295986 | AM25: =AM94 -> 0.099464075 | AN25: =AN94 -> 0.079707106 | AO25: =AO94 -> 0.044982847 | AP25: =AP94 -> 0.058016636 | AQ25: =AQ94 -> 0.078703584 | AR25: =AR94 -> 0.078777127 | ... BX25: =BX94 -> 0.079707106
C26: Revenue
C27: Room Rental Revenue | D27: =INDEX('Events Summary'!$E:$E,MATCH(D$9,'Events Summary'!$C:$C,0))/1000 -> 0 | E27: =INDEX('Events Summary'!$E:$E,MATCH(E$9,'Events Summary'!$C:$C,0))/1000 -> 12.12665 | F27: =INDEX('Events Summary'!$E:$E,MATCH(F$9,'Events Summary'!$C:$C,0))/1000 -> 50.2 | G27: =INDEX('Events Summary'!$E:$E,MATCH(G$9,'Events Summary'!$C:$C,0))/1000 -> 58.6 | H27: =INDEX('Events Summary'!$E:$E,MATCH(H$9,'Events Summary'!$C:$C,0))/1000 -> 52.982 | I27: =INDEX('Events Summary'!$E:$E,MATCH(I$9,'Events Summary'!$C:$C,0))/1000 -> 82 | J27: =INDEX('Events Summary'!$E:$E,MATCH(J$9,'Events Summary'!$C:$C,0))/1000 -> 14 | K27: =INDEX('Events Summary'!$E:$E,MATCH(K$9,'Events Summary'!$C:$C,0))/1000 -> 0 | ... AH27: =INDEX('Events Summary'!$E:$E,MATCH(AH$9,'Events Summary'!$C:$C,0))/1000 -> 18 | AK27: =SUMIFS($CC27:$CE27,$CC$1:$CE$1,AK$3)*AK$24 -> 109.19594 | AL27: =SUMIFS($CC27:$CE27,$CC$1:$CE$1,AL$3)*AL$24 -> 109.19594 | AM27: =SUMIFS($CC27:$CE27,$CC$1:$CE$1,AM$3)*AM$24 -> 36.398648 | AN27: =SUMIFS($CC27:$CE27,$CC$1:$CE$1,AN$3)*AN$24 -> 36.398648 | AO27: =SUMIFS($CC27:$CE27,$CC$1:$CE$1,AO$3)*AO$24 -> 0 | AP27: =SUMIFS($CC27:$CE27,$CC$1:$CE$1,AP$3)*AP$24 -> 0 | AQ27: =SUMIFS($CC27:$CE27,$CC$1:$CE$1,AQ$3)*AQ$24 -> 18.199324 | AR27: =SUMIFS($CC27:$CE27,$CC$1:$CE$1,AR$3)*AR$24 -> 72.797295 | ... BT27: =SUMIFS($CC27:$CE27,$CC$1:$CE$1,BT$3)*BT$24 -> 90.983607 | BU27: =BI27 -> 121.31148 | BV27: =BJ27 -> 136.47541 | BW27: =BK27 -> 121.31148 | BX27: =BL27 -> 90.983607 | BZ27: =SUMIFS($D27:$AJ27,$D$1:$AJ$1,BZ$9) -> 352.75965 | CA27: =SUMIFS($D27:$AJ27,$D$1:$AJ$1,CA$9) -> 319.97463 | CB27: =SUMIFS($D27:$AJ27,$D$3:$AJ$3,"LTM") -> 452.64363 | CC27: ='Revenue Analysis'!G60+'Revenue Analysis'!G75 -> 727.97295 | CD27: ='Revenue Analysis'!H60+'Revenue Analysis'!H75 -> 989.9918 | CE27: ='Revenue Analysis'!I60+'Revenue Analysis'!I75 -> 1213.1148 | CM27: =SUMIFS('FY25 By Venue Financials'!$N:$N,'FY25 By Venue Financials'!$A:$A,$C27) -> 1646.586
C28: Food Revenue | D28: 0 | E28: 0 | F28: 0 | G28: 0 | H28: 0 | I28: 0 | J28: 0 | K28: 0 | L28: 0 | M28: 0 | N28: 0 | O28: 0 | P28: 0 | Q28: 0 | R28: 0 | S28: 0 | T28: 0 | U28: 0 | V28: 0 | W28: 0 | X28: 0 | Y28: 0 | Z28: 0 | AA28: 0 | AB28: 0 | AC28: 0 | AD28: 0 | AE28: 0 | AF28: 0 | AG28: 0 | AH28: 0 | AK28: =SUMIFS($CC28:$CE28,$CC$1:$CE$1,AK$3)*AK$24 -> 0 | AL28: =SUMIFS($CC28:$CE28,$CC$1:$CE$1,AL$3)*AL$24 -> 0 | AM28: =SUMIFS($CC28:$CE28,$CC$1:$CE$1,AM$3)*AM$24 -> 0 | AN28: =SUMIFS($CC28:$CE28,$CC$1:$CE$1,AN$3)*AN$24 -> 0 | AO28: =SUMIFS($CC28:$CE28,$CC$1:$CE$1,AO$3)*AO$24 -> 0 | AP28: =SUMIFS($CC28:$CE28,$CC$1:$CE$1,AP$3)*AP$24 -> 0 | AQ28: =SUMIFS($CC28:$CE28,$CC$1:$CE$1,AQ$3)*AQ$24 -> 0 | AR28: =SUMIFS($CC28:$CE28,$CC$1:$CE$1,AR$3)*AR$24 -> 0 | ... BT28: =SUMIFS($CC28:$CE28,$CC$1:$CE$1,BT$3)*BT$24 -> 30.313996 | BU28: =BI28 -> 40.418662 | BV28: =BJ28 -> 45.470995 | BW28: =BK28 -> 40.418662 | BX28: =BL28 -> 30.313996 | BZ28: =SUMIFS($D28:$AJ28,$D$1:$AJ$1,BZ$9) -> 0 | CA28: =SUMIFS($D28:$AJ28,$D$1:$AJ$1,CA$9) -> 0 | CB28: =SUMIFS($D28:$AJ28,$D$3:$AJ$3,"LTM") -> 0 | CC28: ='Revenue Analysis'!G61+'Revenue Analysis'!G76 -> 0 | CD28: ='Revenue Analysis'!H61+'Revenue Analysis'!H76 -> 161.67465 | CE28: ='Revenue Analysis'!I61+'Revenue Analysis'!I76 -> 404.18662 | CM28: =SUMIFS('FY25 By Venue Financials'!$N:$N,'FY25 By Venue Financials'!$A:$A,$C28) -> 1731.7743
C29: Beverage Revenue | D29: 0 | E29: 0 | F29: 0 | G29: 0 | H29: 0 | I29: 0 | J29: 0 | K29: 0 | L29: 0 | M29: 0 | N29: 0 | O29: 0 | P29: 0 | Q29: 0 | R29: 0 | S29: 0 | T29: 0 | U29: 0 | V29: 0 | W29: 0 | X29: 0 | Y29: 0 | Z29: 0 | AA29: 0 | AB29: 0 | AC29: 0 | AD29: 0 | AE29: 0 | AF29: 0 | AG29: 0 | AH29: 0 | AK29: =SUMIFS($CC29:$CE29,$CC$1:$CE$1,AK$3)*AK$24 -> 0.9 | AL29: =SUMIFS($CC29:$CE29,$CC$1:$CE$1,AL$3)*AL$24 -> 0.9 | AM29: =SUMIFS($CC29:$CE29,$CC$1:$CE$1,AM$3)*AM$24 -> 0.3 | AN29: =SUMIFS($CC29:$CE29,$CC$1:$CE$1,AN$3)*AN$24 -> 0.3 | AO29: =SUMIFS($CC29:$CE29,$CC$1:$CE$1,AO$3)*AO$24 -> 0 | AP29: =SUMIFS($CC29:$CE29,$CC$1:$CE$1,AP$3)*AP$24 -> 0 | AQ29: =SUMIFS($CC29:$CE29,$CC$1:$CE$1,AQ$3)*AQ$24 -> 0.15 | AR29: =SUMIFS($CC29:$CE29,$CC$1:$CE$1,AR$3)*AR$24 -> 0.6 | ... BT29: =SUMIFS($CC29:$CE29,$CC$1:$CE$1,BT$3)*BT$24 -> 4.5 | BU29: =BI29 -> 6 | BV29: =BJ29 -> 6.75 | BW29: =BK29 -> 6 | BX29: =BL29 -> 4.5 | BZ29: =SUMIFS($D29:$AJ29,$D$1:$AJ$1,BZ$9) -> 0 | CA29: =SUMIFS($D29:$AJ29,$D$1:$AJ$1,CA$9) -> 0 | CB29: =SUMIFS($D29:$AJ29,$D$3:$AJ$3,"LTM") -> 0 | CC29: ='Revenue Analysis'!G62+'Revenue Analysis'!G77 -> 6 | CD29: ='Revenue Analysis'!H62+'Revenue Analysis'!H77 -> 36 | CE29: ='Revenue Analysis'!I62+'Revenue Analysis'!I77 -> 60 | CM29: =SUMIFS('FY25 By Venue Financials'!$N:$N,'FY25 By Venue Financials'!$A:$A,$C29) -> 980.4895
C30: Lodging Revenues | D30: =INDEX('Events Summary'!$I:$I,MATCH(D$9,'Events Summary'!$C:$C,0))/1000 -> 0 | E30: =INDEX('Events Summary'!$I:$I,MATCH(E$9,'Events Summary'!$C:$C,0))/1000 -> 4.8 | F30: =INDEX('Events Summary'!$I:$I,MATCH(F$9,'Events Summary'!$C:$C,0))/1000 -> 0 | G30: =INDEX('Events Summary'!$I:$I,MATCH(G$9,'Events Summary'!$C:$C,0))/1000 -> 10.3 | H30: =INDEX('Events Summary'!$I:$I,MATCH(H$9,'Events Summary'!$C:$C,0))/1000 -> 4.7 | I30: =INDEX('Events Summary'!$I:$I,MATCH(I$9,'Events Summary'!$C:$C,0))/1000 -> 3.8 | J30: =INDEX('Events Summary'!$I:$I,MATCH(J$9,'Events Summary'!$C:$C,0))/1000 -> 5.1 | K30: =INDEX('Events Summary'!$I:$I,MATCH(K$9,'Events Summary'!$C:$C,0))/1000 -> 0 | ... AH30: =INDEX('Events Summary'!$I:$I,MATCH(AH$9,'Events Summary'!$C:$C,0))/1000 -> 5.2 | AK30: =SUMIFS($CC30:$CE30,$CC$1:$CE$1,AK$3)*AK$24 -> 11.835 | AL30: =SUMIFS($CC30:$CE30,$CC$1:$CE$1,AL$3)*AL$24 -> 11.835 | AM30: =SUMIFS($CC30:$CE30,$CC$1:$CE$1,AM$3)*AM$24 -> 3.945 | AN30: =SUMIFS($CC30:$CE30,$CC$1:$CE$1,AN$3)*AN$24 -> 3.945 | AO30: =SUMIFS($CC30:$CE30,$CC$1:$CE$1,AO$3)*AO$24 -> 0 | AP30: =SUMIFS($CC30:$CE30,$CC$1:$CE$1,AP$3)*AP$24 -> 0 | AQ30: =SUMIFS($CC30:$CE30,$CC$1:$CE$1,AQ$3)*AQ$24 -> 1.9725 | AR30: =SUMIFS($CC30:$CE30,$CC$1:$CE$1,AR$3)*AR$24 -> 7.89 | ... BT30: =SUMIFS($CC30:$CE30,$CC$1:$CE$1,BT$3)*BT$24 -> 9 | BU30: =BI30 -> 12 | BV30: =BJ30 -> 13.5 | BW30: =BK30 -> 12 | BX30: =BL30 -> 9 | BZ30: =SUMIFS($D30:$AJ30,$D$1:$AJ$1,BZ$9) -> 41.26 | CA30: =SUMIFS($D30:$AJ30,$D$1:$AJ$1,CA$9) -> 67.8 | CB30: =SUMIFS($D30:$AJ30,$D$3:$AJ$3,"LTM") -> 69.8 | CC30: ='Revenue Analysis'!G63+'Revenue Analysis'!G78 -> 78.9 | CD30: ='Revenue Analysis'!H63+'Revenue Analysis'!H78 -> 96 | CE30: ='Revenue Analysis'!I63+'Revenue Analysis'!I78 -> 120 | CM30: =SUMIFS('FY25 By Venue Financials'!$N:$N,'FY25 By Venue Financials'!$A:$A,$C30) -> 0
C31: Ancillary Revenue | D31: =INDEX('Events Summary'!$M:$M,MATCH(D$9,'Events Summary'!$C:$C,0))/1000 -> 0 | E31: =INDEX('Events Summary'!$M:$M,MATCH(E$9,'Events Summary'!$C:$C,0))/1000 -> 1 | F31: =INDEX('Events Summary'!$M:$M,MATCH(F$9,'Events Summary'!$C:$C,0))/1000 -> 0 | G31: =INDEX('Events Summary'!$M:$M,MATCH(G$9,'Events Summary'!$C:$C,0))/1000 -> 3.929 | H31: =INDEX('Events Summary'!$M:$M,MATCH(H$9,'Events Summary'!$C:$C,0))/1000 -> 0.52 | I31: =INDEX('Events Summary'!$M:$M,MATCH(I$9,'Events Summary'!$C:$C,0))/1000 -> 1.248 | J31: =INDEX('Events Summary'!$M:$M,MATCH(J$9,'Events Summary'!$C:$C,0))/1000 -> 1.07967 | K31: =INDEX('Events Summary'!$M:$M,MATCH(K$9,'Events Summary'!$C:$C,0))/1000 -> 0 | ... AH31: =INDEX('Events Summary'!$M:$M,MATCH(AH$9,'Events Summary'!$C:$C,0))/1000 -> 0 | AK31: =SUMIFS($CC31:$CE31,$CC$1:$CE$1,AK$3)*AK$24 -> 2.9424495 | AL31: =SUMIFS($CC31:$CE31,$CC$1:$CE$1,AL$3)*AL$24 -> 2.9424495 | AM31: =SUMIFS($CC31:$CE31,$CC$1:$CE$1,AM$3)*AM$24 -> 0.98081651 | AN31: =SUMIFS($CC31:$CE31,$CC$1:$CE$1,AN$3)*AN$24 -> 0.98081651 | AO31: =SUMIFS($CC31:$CE31,$CC$1:$CE$1,AO$3)*AO$24 -> 0 | AP31: =SUMIFS($CC31:$CE31,$CC$1:$CE$1,AP$3)*AP$24 -> 0 | AQ31: =SUMIFS($CC31:$CE31,$CC$1:$CE$1,AQ$3)*AQ$24 -> 0.49040826 | AR31: =SUMIFS($CC31:$CE31,$CC$1:$CE$1,AR$3)*AR$24 -> 1.961633 | ... BT31: =SUMIFS($CC31:$CE31,$CC$1:$CE$1,BT$3)*BT$24 -> 24.971406 | BU31: =BI31 -> 33.295208 | BV31: =BJ31 -> 37.457109 | BW31: =BK31 -> 33.295208 | BX31: =BL31 -> 24.971406 | BZ31: =SUMIFS($D31:$AJ31,$D$1:$AJ$1,BZ$9) -> 11.25867 | CA31: =SUMIFS($D31:$AJ31,$D$1:$AJ$1,CA$9) -> 15.29051 | CB31: =SUMIFS($D31:$AJ31,$D$3:$AJ$3,"LTM") -> 23.3665 | CC31: =SUM('Revenue Analysis'!G64:G69)+SUM('Revenue Analysis'!G79:G84) -> 19.61633 | CD31: =SUM('Revenue Analysis'!H64:H69)+SUM('Revenue Analysis'!H79:H84) -> 148.18495 | CE31: =SUM('Revenue Analysis'!I64:I69)+SUM('Revenue Analysis'!I79:I84) -> 332.95208 | CM31: =SUMIFS('FY25 By Venue Financials'!$N:$N,'FY25 By Venue Financials'!$A:$A,$C31) -> 1517.7478
C32: Service Charge | D32: 0 | E32: 0 | F32: 0 | G32: 0 | H32: 0 | I32: 0 | J32: 0 | K32: 0 | L32: 0 | M32: 0 | N32: 0 | O32: 0 | P32: 0 | Q32: 0 | R32: 0 | S32: 0 | T32: 0 | U32: 0 | V32: 0 | W32: 0 | X32: 0 | Y32: 0 | Z32: 0 | AA32: 0 | AB32: 0 | AC32: 0 | AD32: 0 | AE32: 0 | AF32: 0 | AG32: 0 | AH32: 0 | AK32: =SUMIFS($CC32:$CE32,$CC$1:$CE$1,AK$3)*AK$24 -> 9.4409463 | AL32: =SUMIFS($CC32:$CE32,$CC$1:$CE$1,AL$3)*AL$24 -> 9.4409463 | AM32: =SUMIFS($CC32:$CE32,$CC$1:$CE$1,AM$3)*AM$24 -> 3.1469821 | AN32: =SUMIFS($CC32:$CE32,$CC$1:$CE$1,AN$3)*AN$24 -> 3.1469821 | AO32: =SUMIFS($CC32:$CE32,$CC$1:$CE$1,AO$3)*AO$24 -> 0 | AP32: =SUMIFS($CC32:$CE32,$CC$1:$CE$1,AP$3)*AP$24 -> 0 | AQ32: =SUMIFS($CC32:$CE32,$CC$1:$CE$1,AQ$3)*AQ$24 -> 1.573491 | AR32: =SUMIFS($CC32:$CE32,$CC$1:$CE$1,AR$3)*AR$24 -> 6.2939642 | ... BT32: =SUMIFS($CC32:$CE32,$CC$1:$CE$1,BT$3)*BT$24 -> 35.149182 | BU32: =BI32 -> 46.865576 | BV32: =BJ32 -> 52.723773 | BW32: =BK32 -> 46.865576 | BX32: =BL32 -> 35.149182 | BZ32: =SUMIFS($D32:$AJ32,$D$1:$AJ$1,BZ$9) -> 0 | CA32: =SUMIFS($D32:$AJ32,$D$1:$AJ$1,CA$9) -> 0 | CB32: =SUMIFS($D32:$AJ32,$D$3:$AJ$3,"LTM") -> 0 | CC32: ='Revenue Analysis'!G85 -> 62.939642 | CD32: ='Revenue Analysis'!H85 -> 310.71731 | CE32: ='Revenue Analysis'!I85 -> 468.65576 | CM32: =SUMIFS('FY25 By Venue Financials'!$N:$N,'FY25 By Venue Financials'!$A:$A,$C32) -> 1209.2074
C33: Cancelled Events | D33: 0 | E33: 0 | F33: 0 | G33: 0 | H33: 0 | I33: 0 | J33: 0 | K33: 0 | L33: 0 | M33: 0 | N33: 0 | O33: 0 | P33: 0 | Q33: 0 | R33: 0 | S33: 0 | T33: 0 | U33: 0 | V33: 0 | W33: 0 | X33: 0 | Y33: 0 | Z33: 0 | AA33: 0 | AB33: 0 | AC33: 0 | AD33: 0 | AE33: 0 | AF33: 0 | AG33: 0 | AH33: 0 | AK33: =SUMIFS($CC33:$CE33,$CC$1:$CE$1,AK$3)*AK$24 -> 2.3152501 | AL33: =SUMIFS($CC33:$CE33,$CC$1:$CE$1,AL$3)*AL$24 -> 2.3152501 | AM33: =SUMIFS($CC33:$CE33,$CC$1:$CE$1,AM$3)*AM$24 -> 0.77175004 | AN33: =SUMIFS($CC33:$CE33,$CC$1:$CE$1,AN$3)*AN$24 -> 0.77175004 | AO33: =SUMIFS($CC33:$CE33,$CC$1:$CE$1,AO$3)*AO$24 -> 0 | AP33: =SUMIFS($CC33:$CE33,$CC$1:$CE$1,AP$3)*AP$24 -> 0 | AQ33: =SUMIFS($CC33:$CE33,$CC$1:$CE$1,AQ$3)*AQ$24 -> 0.38587502 | AR33: =SUMIFS($CC33:$CE33,$CC$1:$CE$1,AR$3)*AR$24 -> 1.5435001 | ... BT33: =SUMIFS($CC33:$CE33,$CC$1:$CE$1,BT$3)*BT$24 -> 3.3599121 | BU33: =BI33 -> 4.4798828 | BV33: =BJ33 -> 5.0398681 | BW33: =BK33 -> 4.4798828 | BX33: =BL33 -> 3.3599121 | BZ33: =SUMIFS($D33:$AJ33,$D$1:$AJ$1,BZ$9) -> 0 | CA33: =SUMIFS($D33:$AJ33,$D$1:$AJ$1,CA$9) -> 0 | CB33: =SUMIFS($D33:$AJ33,$D$3:$AJ$3,"LTM") -> 0 | CC33: =SUM(CC$27:CC$32)*CG33 -> 15.435001 | CD33: =SUM(CD$27:CD$32)*CH33 -> 30.037615 | CE33: =SUM(CE$27:CE$32)*CI33 -> 44.798828 | CG33: =$CN33 -> 0.01723755 | CH33: =$CN33 -> 0.01723755 | CI33: =$CN33 -> 0.01723755 | CK33: =IFERROR(CB33/CB4,0) -> 0 | CM33: =SUMIFS('FY25 By Venue Financials'!$N:$N,'FY25 By Venue Financials'!$A:$A,$C33) -> 122.14192 | CN33: =CM33/SUM($CM$27:$CM$32) -> 0.01723755 | CP33: % Total Rev | CQ33: % of Total Events | CR33: Avg ATL
C34: Outside Events | D34: 0 | E34: 0 | F34: 0 | G34: 0 | H34: 0 | I34: 0 | J34: 0 | K34: 0 | L34: 0 | M34: 0 | N34: 0 | O34: 0 | P34: 0 | Q34: 0 | R34: 0 | S34: 0 | T34: 0 | U34: 0 | V34: 0 | W34: 0 | X34: 0 | Y34: 0 | Z34: 0 | AA34: 0 | AB34: 0 | AC34: 0 | AD34: 0 | AE34: 0 | AF34: 0 | AG34: 0 | AH34: 0 | AK34: =SUMIFS($CC34:$CE34,$CC$1:$CE$1,AK$3)*AK$24 -> 0 | AL34: =SUMIFS($CC34:$CE34,$CC$1:$CE$1,AL$3)*AL$24 -> 0 | AM34: =SUMIFS($CC34:$CE34,$CC$1:$CE$1,AM$3)*AM$24 -> 0 | AN34: =SUMIFS($CC34:$CE34,$CC$1:$CE$1,AN$3)*AN$24 -> 0 | AO34: =SUMIFS($CC34:$CE34,$CC$1:$CE$1,AO$3)*AO$24 -> 0 | AP34: =SUMIFS($CC34:$CE34,$CC$1:$CE$1,AP$3)*AP$24 -> 0 | AQ34: =SUMIFS($CC34:$CE34,$CC$1:$CE$1,AQ$3)*AQ$24 -> 0 | AR34: =SUMIFS($CC34:$CE34,$CC$1:$CE$1,AR$3)*AR$24 -> 0 | ... BT34: =SUMIFS($CC34:$CE34,$CC$1:$CE$1,BT$3)*BT$24 -> 0 | BU34: =BI34 -> 0 | BV34: =BJ34 -> 0 | BW34: =BK34 -> 0 | BX34: =BL34 -> 0 | BZ34: =SUMIFS($D34:$AJ34,$D$1:$AJ$1,BZ$9) -> 0 | CA34: =SUMIFS($D34:$AJ34,$D$1:$AJ$1,CA$9) -> 0 | CB34: =SUMIFS($D34:$AJ34,$D$3:$AJ$3,"LTM") -> 0 | CC34: =SUM(CC$27:CC$32)*CG34 -> 0 | CD34: =SUM(CD$27:CD$32)*CH34 -> 0 | CE34: =SUM(CE$27:CE$32)*CI34 -> 0 | CG34: =$CN34 -> 0 | CH34: =$CN34 -> 0 | CI34: =$CN34 -> 0 | CK34: =IFERROR(CB34/CB5,0) -> 0 | CM34: =SUMIFS('FY25 By Venue Financials'!$N:$N,'FY25 By Venue Financials'!$A:$A,$C34) -> 0 | CN34: =CM34/SUM($CM$27:$CM$32) -> 0 | CP34: % Total Rev | CQ34: % of Total Events
C35: Discounts | D35: 0 | E35: 0 | F35: 0 | G35: 0 | H35: 0 | I35: 0 | J35: 0 | K35: 0 | L35: 0 | M35: 0 | N35: 0 | O35: 0 | P35: 0 | Q35: 0 | R35: 0 | S35: 0 | T35: 0 | U35: 0 | V35: 0 | W35: 0 | X35: 0 | Y35: 0 | Z35: 0 | AA35: 0 | AB35: 0 | AC35: 0 | AD35: 0 | AE35: 0 | AF35: 0 | AG35: 0 | AH35: 0 | AK35: =SUMIFS($CC35:$CE35,$CC$1:$CE$1,AK$3)*AK$24 -> -2.9288386 | AL35: =SUMIFS($CC35:$CE35,$CC$1:$CE$1,AL$3)*AL$24 -> -2.9288386 | AM35: =SUMIFS($CC35:$CE35,$CC$1:$CE$1,AM$3)*AM$24 -> -0.97627955 | AN35: =SUMIFS($CC35:$CE35,$CC$1:$CE$1,AN$3)*AN$24 -> -0.97627955 | AO35: =SUMIFS($CC35:$CE35,$CC$1:$CE$1,AO$3)*AO$24 -> 0 | AP35: =SUMIFS($CC35:$CE35,$CC$1:$CE$1,AP$3)*AP$24 -> 0 | AQ35: =SUMIFS($CC35:$CE35,$CC$1:$CE$1,AQ$3)*AQ$24 -> -0.48813977 | AR35: =SUMIFS($CC35:$CE35,$CC$1:$CE$1,AR$3)*AR$24 -> -1.9525591 | ... BT35: =SUMIFS($CC35:$CE35,$CC$1:$CE$1,BT$3)*BT$24 -> -4.2503573 | BU35: =BI35 -> -5.6671431 | BV35: =BJ35 -> -6.375536 | BW35: =BK35 -> -5.6671431 | BX35: =BL35 -> -4.2503573 | BZ35: =SUMIFS($D35:$AJ35,$D$1:$AJ$1,BZ$9) -> 0 | CA35: =SUMIFS($D35:$AJ35,$D$1:$AJ$1,CA$9) -> 0 | CB35: =SUMIFS($D35:$AJ35,$D$3:$AJ$3,"LTM") -> 0 | CC35: =SUM(CC$27:CC$32)*CG35 -> -19.525591 | CD35: =SUM(CD$27:CD$32)*CH35 -> -37.998196 | CE35: =SUM(CE$27:CE$32)*CI35 -> -56.671431 | CG35: =$CN35 -> -0.021805852 | CH35: =$CN35 -> -0.021805852 | CI35: =$CN35 -> -0.021805852 | CK35: =IFERROR(CB35/CB6,0) -> 0 | CM35: =SUMIFS('FY25 By Venue Financials'!$N:$N,'FY25 By Venue Financials'!$A:$A,$C35) -> -154.51202 | CN35: =CM35/SUM($CM$27:$CM$32) -> -0.021805852 | CP35: % Total Rev | CQ35: % of Total Events | CR35: Avg ATL
C36: Other Revenue | D36: =SUMIFS('P&L'!C:C,'P&L'!$A:$A,$C36)/1000 -> 0.38245 | E36: =SUMIFS('P&L'!D:D,'P&L'!$A:$A,$C36)/1000 -> 0 | F36: =SUMIFS('P&L'!E:E,'P&L'!$A:$A,$C36)/1000 -> 0 | G36: =SUMIFS('P&L'!F:F,'P&L'!$A:$A,$C36)/1000 -> 3.7616 | H36: =SUMIFS('P&L'!G:G,'P&L'!$A:$A,$C36)/1000 -> 14.6798 | I36: =SUMIFS('P&L'!H:H,'P&L'!$A:$A,$C36)/1000 -> 23.39819 | J36: =SUMIFS('P&L'!I:I,'P&L'!$A:$A,$C36)/1000 -> 3.091 | K36: =SUMIFS('P&L'!J:J,'P&L'!$A:$A,$C36)/1000 -> 0.836 | L36: =SUMIFS('P&L'!K:K,'P&L'!$A:$A,$C36)/1000 -> 3.907 | M36: =SUMIFS('P&L'!L:L,'P&L'!$A:$A,$C36)/1000 -> 1.738 | N36: =SUMIFS('P&L'!M:M,'P&L'!$A:$A,$C36)/1000 -> 7.5 | O36: =SUMIFS('P&L'!N:N,'P&L'!$A:$A,$C36)/1000 -> 1.892 | P36: =SUMIFS('P&L'!O:O,'P&L'!$A:$A,$C36)/1000 -> 2.625 | Q36: =SUMIFS('P&L'!P:P,'P&L'!$A:$A,$C36)/1000 -> 2.633 | R36: =SUMIFS('P&L'!Q:Q,'P&L'!$A:$A,$C36)/1000 -> 2.521 | S36: =SUMIFS('P&L'!R:R,'P&L'!$A:$A,$C36)/1000 -> 3.129 | T36: =SUMIFS('P&L'!S:S,'P&L'!$A:$A,$C36)/1000 -> 6.24116 | U36: =SUMIFS('P&L'!T:T,'P&L'!$A:$A,$C36)/1000 -> 15.96192 | V36: =SUMIFS('P&L'!U:U,'P&L'!$A:$A,$C36)/1000 -> 0.175 | W36: =SUMIFS('P&L'!V:V,'P&L'!$A:$A,$C36)/1000 -> 0 | X36: =SUMIFS('P&L'!W:W,'P&L'!$A:$A,$C36)/1000 -> 0 | Y36: =SUMIFS('P&L'!X:X,'P&L'!$A:$A,$C36)/1000 -> 0 | Z36: =SUMIFS('P&L'!Y:Y,'P&L'!$A:$A,$C36)/1000 -> 1.334 | AA36: =SUMIFS('P&L'!Z:Z,'P&L'!$A:$A,$C36)/1000 -> 0 | AB36: =SUMIFS('P&L'!AA:AA,'P&L'!$A:$A,$C36)/1000 -> 0 | AC36: =SUMIFS('P&L'!AB:AB,'P&L'!$A:$A,$C36)/1000 -> 0 | AD36: =SUMIFS('P&L'!AC:AC,'P&L'!$A:$A,$C36)/1000 -> 0 | AE36: =SUMIFS('P&L'!AD:AD,'P&L'!$A:$A,$C36)/1000 -> 0.15 | AF36: =SUMIFS('P&L'!AE:AE,'P&L'!$A:$A,$C36)/1000 -> 0 | AG36: =SUMIFS('P&L'!AF:AF,'P&L'!$A:$A,$C36)/1000 -> 11.17399 | AH36: =SUMIFS('P&L'!AG:AG,'P&L'!$A:$A,$C36)/1000 -> 2.38166 | AK36: =SUMIFS($CC36:$CE36,$CC$1:$CE$1,AK$3)*AK$24 -> 2.2559475 | AL36: =SUMIFS($CC36:$CE36,$CC$1:$CE$1,AL$3)*AL$24 -> 2.2559475 | AM36: =SUMIFS($CC36:$CE36,$CC$1:$CE$1,AM$3)*AM$24 -> 0.7519825 | AN36: =SUMIFS($CC36:$CE36,$CC$1:$CE$1,AN$3)*AN$24 -> 0.7519825 | AO36: =SUMIFS($CC36:$CE36,$CC$1:$CE$1,AO$3)*AO$24 -> 0 | AP36: =SUMIFS($CC36:$CE36,$CC$1:$CE$1,AP$3)*AP$24 -> 0 | AQ36: =SUMIFS($CC36:$CE36,$CC$1:$CE$1,AQ$3)*AQ$24 -> 0.37599125 | AR36: =SUMIFS($CC36:$CE36,$CC$1:$CE$1,AR$3)*AR$24 -> 1.503965 | ... BT36: =SUMIFS($CC36:$CE36,$CC$1:$CE$1,BT$3)*BT$24 -> 1.1279737 | BU36: =BI36 -> 1.503965 | BV36: =BJ36 -> 1.6919606 | BW36: =BK36 -> 1.503965 | BX36: =BL36 -> 1.1279737 | BZ36: =SUMIFS($D36:$AJ36,$D$1:$AJ$1,BZ$9) -> 61.18604 | CA36: =SUMIFS($D36:$AJ36,$D$1:$AJ$1,CA$9) -> 34.62008 | CB36: =SUMIFS($D36:$AJ36,$D$3:$AJ$3,"LTM") -> 15.03965 | CC36: =CB36 -> 15.03965 | CD36: =CC36 -> 15.03965 | CE36: =CD36 -> 15.03965 | CG36: =$CN36 -> 0 | CH36: =$CN36 -> 0 | CI36: =$CN36 -> 0 | CK36: =IFERROR(CB36/CB7,0) -> 0 | CM36: =SUMIFS('FY25 By Venue Financials'!$N:$N,'FY25 By Venue Financials'!$A:$A,$C36) -> 0 | CN36: =CM36/SUM($CM$27:$CM$32) -> 0 | CP36: % Total Rev | CQ36: % of Total Events | CR36: Blueberries, Pop Up events, merch
C38: Total Revenue | D38: =SUM(D27:D37) -> 0.38245 | E38: =SUM(E27:E37) -> 17.92665 | F38: =SUM(F27:F37) -> 50.2 | G38: =SUM(G27:G37) -> 76.5906 | H38: =SUM(H27:H37) -> 72.8818 | I38: =SUM(I27:I37) -> 110.44619 | J38: =SUM(J27:J37) -> 23.27067 | K38: =SUM(K27:K37) -> 0.836 | ... AH38: =SUM(AH27:AH37) -> 25.58166 | AK38: =SUM(AK27:AK37) -> 135.9567 | AL38: =SUM(AL27:AL37) -> 135.9567 | AM38: =SUM(AM27:AM37) -> 45.318899 | AN38: =SUM(AN27:AN37) -> 45.318899 | AO38: =SUM(AO27:AO37) -> 0 | AP38: =SUM(AP27:AP37) -> 0 | AQ38: =SUM(AQ27:AQ37) -> 22.65945 | AR38: =SUM(AR27:AR37) -> 90.637798 | ... BX38: =SUM(BX27:BX37) -> 195.15572 | BZ38: =SUM(BZ27:BZ37) -> 466.46436 | CA38: =SUM(CA27:CA37) -> 437.68522 | CB38: =SUM(CB27:CB37) -> 560.84978 | CC38: =SUM(CC27:CC37) -> 906.37798 | CD38: =SUM(CD27:CD37) -> 1749.6478 | CE38: =SUM(CE27:CE37) -> 2602.0763 | CM38: =SUM(CM27:CM37) -> 7053.435
C40: COGS
C41: Food COGS | D41: =-SUMIFS('P&L'!C:C,'P&L'!$A:$A,$C41)/1000 -> 0 | E41: =-SUMIFS('P&L'!D:D,'P&L'!$A:$A,$C41)/1000 -> 0 | F41: =-SUMIFS('P&L'!E:E,'P&L'!$A:$A,$C41)/1000 -> 0 | G41: =-SUMIFS('P&L'!F:F,'P&L'!$A:$A,$C41)/1000 -> 0 | H41: =-SUMIFS('P&L'!G:G,'P&L'!$A:$A,$C41)/1000 -> 0 | I41: =-SUMIFS('P&L'!H:H,'P&L'!$A:$A,$C41)/1000 -> 0 | J41: =-SUMIFS('P&L'!I:I,'P&L'!$A:$A,$C41)/1000 -> 0 | K41: =-SUMIFS('P&L'!J:J,'P&L'!$A:$A,$C41)/1000 -> 0 | L41: =-SUMIFS('P&L'!K:K,'P&L'!$A:$A,$C41)/1000 -> 0 | M41: =-SUMIFS('P&L'!L:L,'P&L'!$A:$A,$C41)/1000 -> 0 | N41: =-SUMIFS('P&L'!M:M,'P&L'!$A:$A,$C41)/1000 -> 0 | O41: =-SUMIFS('P&L'!N:N,'P&L'!$A:$A,$C41)/1000 -> 0 | P41: =-SUMIFS('P&L'!O:O,'P&L'!$A:$A,$C41)/1000 -> 0 | Q41: =-SUMIFS('P&L'!P:P,'P&L'!$A:$A,$C41)/1000 -> 0 | R41: =-SUMIFS('P&L'!Q:Q,'P&L'!$A:$A,$C41)/1000 -> 0 | S41: =-SUMIFS('P&L'!R:R,'P&L'!$A:$A,$C41)/1000 -> 0 | T41: =-SUMIFS('P&L'!S:S,'P&L'!$A:$A,$C41)/1000 -> 0 | U41: =-SUMIFS('P&L'!T:T,'P&L'!$A:$A,$C41)/1000 -> 0 | V41: =-SUMIFS('P&L'!U:U,'P&L'!$A:$A,$C41)/1000 -> 0 | W41: =-SUMIFS('P&L'!V:V,'P&L'!$A:$A,$C41)/1000 -> 0 | X41: =-SUMIFS('P&L'!W:W,'P&L'!$A:$A,$C41)/1000 -> 0 | Y41: =-SUMIFS('P&L'!X:X,'P&L'!$A:$A,$C41)/1000 -> 0 | Z41: =-SUMIFS('P&L'!Y:Y,'P&L'!$A:$A,$C41)/1000 -> 0 | AA41: =-SUMIFS('P&L'!Z:Z,'P&L'!$A:$A,$C41)/1000 -> 0 | AB41: =-SUMIFS('P&L'!AA:AA,'P&L'!$A:$A,$C41)/1000 -> 0 | AC41: =-SUMIFS('P&L'!AB:AB,'P&L'!$A:$A,$C41)/1000 -> 0 | AD41: =-SUMIFS('P&L'!AC:AC,'P&L'!$A:$A,$C41)/1000 -> 0 | AE41: =-SUMIFS('P&L'!AD:AD,'P&L'!$A:$A,$C41)/1000 -> 0 | AF41: =-SUMIFS('P&L'!AE:AE,'P&L'!$A:$A,$C41)/1000 -> 0 | AG41: =-SUMIFS('P&L'!AF:AF,'P&L'!$A:$A,$C41)/1000 -> 0 | AH41: =-SUMIFS('P&L'!AG:AG,'P&L'!$A:$A,$C41)/1000 -> 0 | AK41: =SUMIFS($CC41:$CE41,$CC$1:$CE$1,AK$3)*AK$24 -> 0 | AL41: =SUMIFS($CC41:$CE41,$CC$1:$CE$1,AL$3)*AL$24 -> 0 | AM41: =SUMIFS($CC41:$CE41,$CC$1:$CE$1,AM$3)*AM$24 -> 0 | AN41: =SUMIFS($CC41:$CE41,$CC$1:$CE$1,AN$3)*AN$24 -> 0 | AO41: =SUMIFS($CC41:$CE41,$CC$1:$CE$1,AO$3)*AO$24 -> 0 | AP41: =SUMIFS($CC41:$CE41,$CC$1:$CE$1,AP$3)*AP$24 -> 0 | AQ41: =SUMIFS($CC41:$CE41,$CC$1:$CE$1,AQ$3)*AQ$24 -> 0 | AR41: =SUMIFS($CC41:$CE41,$CC$1:$CE$1,AR$3)*AR$24 -> 0 | ... BT41: =SUMIFS($CC41:$CE41,$CC$1:$CE$1,BT$3)*BT$24 -> -5.018836 | BU41: =BI41 -> -6.6917813 | BV41: =BJ41 -> -7.528254 | BW41: =BK41 -> -6.6917813 | BX41: =BL41 -> -5.018836 | BZ41: =SUMIFS($D41:$AJ41,$D$1:$AJ$1,BZ$9) -> 0 | CA41: =SUMIFS($D41:$AJ41,$D$1:$AJ$1,CA$9) -> 0 | CB41: =SUMIFS($D41:$AJ41,$D$3:$AJ$3,"LTM") -> 0 | CC41: =CC28*CG41 -> 0 | CD41: =CD28*CH41 -> -26.767125 | CE41: =CE28*CI41 -> -66.917813 | CG41: =$CN41 -> -0.16556167 | CH41: =$CN41 -> -0.16556167 | CI41: =$CN41 -> -0.16556167 | CK41: =IFERROR(CB41/CB28,0) -> 0 | CM41: =-SUMIFS('FY25 By Venue Financials'!$N:$N,'FY25 By Venue Financials'!$A:$A,$C41) -> -286.71546 | CN41: =IFERROR(CM41/CM28,0) -> -0.16556167 | CP41: % Food Rev | CQ41: % of Total Events
C42: Ancillary COGS | D42: =-SUMIFS('P&L'!C:C,'P&L'!$A:$A,$C42)/1000 -> 0 | E42: =-SUMIFS('P&L'!D:D,'P&L'!$A:$A,$C42)/1000 -> 0 | F42: =-SUMIFS('P&L'!E:E,'P&L'!$A:$A,$C42)/1000 -> 0 | G42: =-SUMIFS('P&L'!F:F,'P&L'!$A:$A,$C42)/1000 -> 0 | H42: =-SUMIFS('P&L'!G:G,'P&L'!$A:$A,$C42)/1000 -> 0 | I42: =-SUMIFS('P&L'!H:H,'P&L'!$A:$A,$C42)/1000 -> 0 | J42: =-SUMIFS('P&L'!I:I,'P&L'!$A:$A,$C42)/1000 -> 0 | K42: =-SUMIFS('P&L'!J:J,'P&L'!$A:$A,$C42)/1000 -> 0 | L42: =-SUMIFS('P&L'!K:K,'P&L'!$A:$A,$C42)/1000 -> 0 | M42: =-SUMIFS('P&L'!L:L,'P&L'!$A:$A,$C42)/1000 -> 0 | N42: =-SUMIFS('P&L'!M:M,'P&L'!$A:$A,$C42)/1000 -> 0 | O42: =-SUMIFS('P&L'!N:N,'P&L'!$A:$A,$C42)/1000 -> 0 | P42: =-SUMIFS('P&L'!O:O,'P&L'!$A:$A,$C42)/1000 -> 0 | Q42: =-SUMIFS('P&L'!P:P,'P&L'!$A:$A,$C42)/1000 -> 0 | R42: =-SUMIFS('P&L'!Q:Q,'P&L'!$A:$A,$C42)/1000 -> 0 | S42: =-SUMIFS('P&L'!R:R,'P&L'!$A:$A,$C42)/1000 -> 0 | T42: =-SUMIFS('P&L'!S:S,'P&L'!$A:$A,$C42)/1000 -> 0 | U42: =-SUMIFS('P&L'!T:T,'P&L'!$A:$A,$C42)/1000 -> 0 | V42: =-SUMIFS('P&L'!U:U,'P&L'!$A:$A,$C42)/1000 -> 0 | W42: =-SUMIFS('P&L'!V:V,'P&L'!$A:$A,$C42)/1000 -> 0 | X42: =-SUMIFS('P&L'!W:W,'P&L'!$A:$A,$C42)/1000 -> 0 | Y42: =-SUMIFS('P&L'!X:X,'P&L'!$A:$A,$C42)/1000 -> 0 | Z42: =-SUMIFS('P&L'!Y:Y,'P&L'!$A:$A,$C42)/1000 -> 0 | AA42: =-SUMIFS('P&L'!Z:Z,'P&L'!$A:$A,$C42)/1000 -> 0 | AB42: =-SUMIFS('P&L'!AA:AA,'P&L'!$A:$A,$C42)/1000 -> 0 | AC42: =-SUMIFS('P&L'!AB:AB,'P&L'!$A:$A,$C42)/1000 -> 0 | AD42: =-SUMIFS('P&L'!AC:AC,'P&L'!$A:$A,$C42)/1000 -> 0 | AE42: =-SUMIFS('P&L'!AD:AD,'P&L'!$A:$A,$C42)/1000 -> 0 | AF42: =-SUMIFS('P&L'!AE:AE,'P&L'!$A:$A,$C42)/1000 -> 0 | AG42: =-SUMIFS('P&L'!AF:AF,'P&L'!$A:$A,$C42)/1000 -> 0 | AH42: =-SUMIFS('P&L'!AG:AG,'P&L'!$A:$A,$C42)/1000 -> 0 | AK42: =SUMIFS($CC42:$CE42,$CC$1:$CE$1,AK$3)*AK$24 -> -0.61162324 | AL42: =SUMIFS($CC42:$CE42,$CC$1:$CE$1,AL$3)*AL$24 -> -0.61162324 | AM42: =SUMIFS($CC42:$CE42,$CC$1:$CE$1,AM$3)*AM$24 -> -0.20387441 | AN42: =SUMIFS($CC42:$CE42,$CC$1:$CE$1,AN$3)*AN$24 -> -0.20387441 | AO42: =SUMIFS($CC42:$CE42,$CC$1:$CE$1,AO$3)*AO$24 -> 0 | AP42: =SUMIFS($CC42:$CE42,$CC$1:$CE$1,AP$3)*AP$24 -> 0 | AQ42: =SUMIFS($CC42:$CE42,$CC$1:$CE$1,AQ$3)*AQ$24 -> -0.10193721 | AR42: =SUMIFS($CC42:$CE42,$CC$1:$CE$1,AR$3)*AR$24 -> -0.40774883 | ... BT42: =SUMIFS($CC42:$CE42,$CC$1:$CE$1,BT$3)*BT$24 -> -5.1906047 | BU42: =BI42 -> -6.9208063 | BV42: =BJ42 -> -7.7859071 | BW42: =BK42 -> -6.9208063 | BX42: =BL42 -> -5.1906047 | BZ42: =SUMIFS($D42:$AJ42,$D$1:$AJ$1,BZ$9) -> 0 | CA42: =SUMIFS($D42:$AJ42,$D$1:$AJ$1,CA$9) -> 0 | CB42: =SUMIFS($D42:$AJ42,$D$3:$AJ$3,"LTM") -> 0 | CC42: =CC$31*CG42 -> -4.0774883 | CD42: =CD$31*CH42 -> -30.80201 | CE42: =CE$31*CI42 -> -69.208063 | CG42: =$CN42 -> -0.20786193 | CH42: =$CN42 -> -0.20786193 | CI42: =$CN42 -> -0.20786193 | CK42: =IFERROR(CB42/CB31,0) -> 0 | CM42: =-SUMIFS('FY25 By Venue Financials'!$N:$N,'FY25 By Venue Financials'!$A:$A,$C42) -> -315.48199 | CN42: =IFERROR(CM42/CM$31,0) -> -0.20786193 | CP42: % Ancillary Rev | CQ42: % of Total Events
C43: Alcohol COGS | D43: =-SUMIFS('P&L'!C:C,'P&L'!$A:$A,$C43)/1000 -> 0 | E43: =-SUMIFS('P&L'!D:D,'P&L'!$A:$A,$C43)/1000 -> 0 | F43: =-SUMIFS('P&L'!E:E,'P&L'!$A:$A,$C43)/1000 -> 0 | G43: =-SUMIFS('P&L'!F:F,'P&L'!$A:$A,$C43)/1000 -> 0 | H43: =-SUMIFS('P&L'!G:G,'P&L'!$A:$A,$C43)/1000 -> 0 | I43: =-SUMIFS('P&L'!H:H,'P&L'!$A:$A,$C43)/1000 -> 0 | J43: =-SUMIFS('P&L'!I:I,'P&L'!$A:$A,$C43)/1000 -> 0 | K43: =-SUMIFS('P&L'!J:J,'P&L'!$A:$A,$C43)/1000 -> 0 | L43: =-SUMIFS('P&L'!K:K,'P&L'!$A:$A,$C43)/1000 -> 0 | M43: =-SUMIFS('P&L'!L:L,'P&L'!$A:$A,$C43)/1000 -> 0 | N43: =-SUMIFS('P&L'!M:M,'P&L'!$A:$A,$C43)/1000 -> 0 | O43: =-SUMIFS('P&L'!N:N,'P&L'!$A:$A,$C43)/1000 -> 0 | P43: =-SUMIFS('P&L'!O:O,'P&L'!$A:$A,$C43)/1000 -> 0 | Q43: =-SUMIFS('P&L'!P:P,'P&L'!$A:$A,$C43)/1000 -> 0 | R43: =-SUMIFS('P&L'!Q:Q,'P&L'!$A:$A,$C43)/1000 -> 0 | S43: =-SUMIFS('P&L'!R:R,'P&L'!$A:$A,$C43)/1000 -> 0 | T43: =-SUMIFS('P&L'!S:S,'P&L'!$A:$A,$C43)/1000 -> 0 | U43: =-SUMIFS('P&L'!T:T,'P&L'!$A:$A,$C43)/1000 -> 0 | V43: =-SUMIFS('P&L'!U:U,'P&L'!$A:$A,$C43)/1000 -> 0 | W43: =-SUMIFS('P&L'!V:V,'P&L'!$A:$A,$C43)/1000 -> 0 | X43: =-SUMIFS('P&L'!W:W,'P&L'!$A:$A,$C43)/1000 -> 0 | Y43: =-SUMIFS('P&L'!X:X,'P&L'!$A:$A,$C43)/1000 -> 0 | Z43: =-SUMIFS('P&L'!Y:Y,'P&L'!$A:$A,$C43)/1000 -> 0 | AA43: =-SUMIFS('P&L'!Z:Z,'P&L'!$A:$A,$C43)/1000 -> 0 | AB43: =-SUMIFS('P&L'!AA:AA,'P&L'!$A:$A,$C43)/1000 -> 0 | AC43: =-SUMIFS('P&L'!AB:AB,'P&L'!$A:$A,$C43)/1000 -> 0 | AD43: =-SUMIFS('P&L'!AC:AC,'P&L'!$A:$A,$C43)/1000 -> 0 | AE43: =-SUMIFS('P&L'!AD:AD,'P&L'!$A:$A,$C43)/1000 -> 0 | AF43: =-SUMIFS('P&L'!AE:AE,'P&L'!$A:$A,$C43)/1000 -> 0 | AG43: =-SUMIFS('P&L'!AF:AF,'P&L'!$A:$A,$C43)/1000 -> 0 | AH43: =-SUMIFS('P&L'!AG:AG,'P&L'!$A:$A,$C43)/1000 -> 0 | AK43: =SUMIFS($CC43:$CE43,$CC$1:$CE$1,AK$3)*AK$24 -> -0.062654706 | AL43: =SUMIFS($CC43:$CE43,$CC$1:$CE$1,AL$3)*AL$24 -> -0.062654706 | AM43: =SUMIFS($CC43:$CE43,$CC$1:$CE$1,AM$3)*AM$24 -> -0.020884902 | AN43: =SUMIFS($CC43:$CE43,$CC$1:$CE$1,AN$3)*AN$24 -> -0.020884902 | AO43: =SUMIFS($CC43:$CE43,$CC$1:$CE$1,AO$3)*AO$24 -> 0 | AP43: =SUMIFS($CC43:$CE43,$CC$1:$CE$1,AP$3)*AP$24 -> 0 | AQ43: =SUMIFS($CC43:$CE43,$CC$1:$CE$1,AQ$3)*AQ$24 -> -0.010442451 | AR43: =SUMIFS($CC43:$CE43,$CC$1:$CE$1,AR$3)*AR$24 -> -0.041769804 | ... BT43: =SUMIFS($CC43:$CE43,$CC$1:$CE$1,BT$3)*BT$24 -> -0.31327353 | BU43: =BI43 -> -0.41769804 | BV43: =BJ43 -> -0.46991029 | BW43: =BK43 -> -0.41769804 | BX43: =BL43 -> -0.31327353 | BZ43: =SUMIFS($D43:$AJ43,$D$1:$AJ$1,BZ$9) -> 0 | CA43: =SUMIFS($D43:$AJ43,$D$1:$AJ$1,CA$9) -> 0 | CB43: =SUMIFS($D43:$AJ43,$D$3:$AJ$3,"LTM") -> 0 | CC43: =CC29*CG43 -> -0.41769804 | CD43: =CD29*CH43 -> -2.5061882 | CE43: =CE29*CI43 -> -4.1769804 | CG43: =$CN43 -> -0.06961634 | CH43: =$CN43 -> -0.06961634 | CI43: =$CN43 -> -0.06961634 | CK43: =IFERROR(CB43/CB29,0) -> 0 | CM43: =-SUMIFS('FY25 By Venue Financials'!$N:$N,'FY25 By Venue Financials'!$A:$A,$C43) -> -68.25809 | CN43: =IFERROR(CM43/CM29,0) -> -0.06961634 | CP43: % Alcohol Rev | CQ43: % of Total Events
C44: Other COGS | D44: =-SUMIFS('P&L'!C:C,'P&L'!$A:$A,$C44)/1000 -> -13.22447 | E44: =-SUMIFS('P&L'!D:D,'P&L'!$A:$A,$C44)/1000 -> -16.90425 | F44: =-SUMIFS('P&L'!E:E,'P&L'!$A:$A,$C44)/1000 -> -6.92204 | G44: =-SUMIFS('P&L'!F:F,'P&L'!$A:$A,$C44)/1000 -> -5.68561 | H44: =-SUMIFS('P&L'!G:G,'P&L'!$A:$A,$C44)/1000 -> -20.64956 | I44: =-SUMIFS('P&L'!H:H,'P&L'!$A:$A,$C44)/1000 -> -15.13228 | J44: =-SUMIFS('P&L'!I:I,'P&L'!$A:$A,$C44)/1000 -> -6.60258 | K44: =-SUMIFS('P&L'!J:J,'P&L'!$A:$A,$C44)/1000 -> -1.70385 | L44: =-SUMIFS('P&L'!K:K,'P&L'!$A:$A,$C44)/1000 -> -1.65507 | M44: =-SUMIFS('P&L'!L:L,'P&L'!$A:$A,$C44)/1000 -> -0.78576 | N44: =-SUMIFS('P&L'!M:M,'P&L'!$A:$A,$C44)/1000 -> -4.49531 | O44: =-SUMIFS('P&L'!N:N,'P&L'!$A:$A,$C44)/1000 -> 7.33563 | P44: =-SUMIFS('P&L'!O:O,'P&L'!$A:$A,$C44)/1000 -> -5.91342 | Q44: =-SUMIFS('P&L'!P:P,'P&L'!$A:$A,$C44)/1000 -> -4.23246 | R44: =-SUMIFS('P&L'!Q:Q,'P&L'!$A:$A,$C44)/1000 -> -2.91899 | S44: =-SUMIFS('P&L'!R:R,'P&L'!$A:$A,$C44)/1000 -> -5.85358 | T44: =-SUMIFS('P&L'!S:S,'P&L'!$A:$A,$C44)/1000 -> -5.04119 | U44: =-SUMIFS('P&L'!T:T,'P&L'!$A:$A,$C44)/1000 -> -6.14997 | V44: =-SUMIFS('P&L'!U:U,'P&L'!$A:$A,$C44)/1000 -> -0.93362 | W44: =-SUMIFS('P&L'!V:V,'P&L'!$A:$A,$C44)/1000 -> -1.76676 | X44: =-SUMIFS('P&L'!W:W,'P&L'!$A:$A,$C44)/1000 -> -0.90708 | Y44: =-SUMIFS('P&L'!X:X,'P&L'!$A:$A,$C44)/1000 -> -1.77226 | Z44: =-SUMIFS('P&L'!Y:Y,'P&L'!$A:$A,$C44)/1000 -> -6.35034 | AA44: =-SUMIFS('P&L'!Z:Z,'P&L'!$A:$A,$C44)/1000 -> -0.65108 | AB44: =-SUMIFS('P&L'!AA:AA,'P&L'!$A:$A,$C44)/1000 -> -11.74306 | AC44: =-SUMIFS('P&L'!AB:AB,'P&L'!$A:$A,$C44)/1000 -> 0 | AD44: =-SUMIFS('P&L'!AC:AC,'P&L'!$A:$A,$C44)/1000 -> -3.6575 | AE44: =-SUMIFS('P&L'!AD:AD,'P&L'!$A:$A,$C44)/1000 -> -4.13734 | AF44: =-SUMIFS('P&L'!AE:AE,'P&L'!$A:$A,$C44)/1000 -> -13.55008 | AG44: =-SUMIFS('P&L'!AF:AF,'P&L'!$A:$A,$C44)/1000 -> -3.93788 | AH44: =-SUMIFS('P&L'!AG:AG,'P&L'!$A:$A,$C44)/1000 -> -0.56763 | AK44: =SUMIFS($CC44:$CE44,$CC$1:$CE$1,AK$3)*AK$24 -> -1.6722018 | AL44: =SUMIFS($CC44:$CE44,$CC$1:$CE$1,AL$3)*AL$24 -> -1.6722018 | AM44: =SUMIFS($CC44:$CE44,$CC$1:$CE$1,AM$3)*AM$24 -> -0.55740061 | AN44: =SUMIFS($CC44:$CE44,$CC$1:$CE$1,AN$3)*AN$24 -> -0.55740061 | AO44: =SUMIFS($CC44:$CE44,$CC$1:$CE$1,AO$3)*AO$24 -> 0 | AP44: =SUMIFS($CC44:$CE44,$CC$1:$CE$1,AP$3)*AP$24 -> 0 | AQ44: =SUMIFS($CC44:$CE44,$CC$1:$CE$1,AQ$3)*AQ$24 -> -0.27870031 | AR44: =SUMIFS($CC44:$CE44,$CC$1:$CE$1,AR$3)*AR$24 -> -1.1148012 | ... BT44: =SUMIFS($CC44:$CE44,$CC$1:$CE$1,BT$3)*BT$24 -> -2.4003213 | BU44: =BI44 -> -3.2004284 | BV44: =BJ44 -> -3.6004819 | BW44: =BK44 -> -3.2004284 | BX44: =BL44 -> -2.4003213 | BZ44: =SUMIFS($D44:$AJ44,$D$1:$AJ$1,BZ$9) -> -86.42515 | CA44: =SUMIFS($D44:$AJ44,$D$1:$AJ$1,CA$9) -> -42.49075 | CB44: =SUMIFS($D44:$AJ44,$D$3:$AJ$3,"LTM") -> -49.04101 | CC44: =CC$38*CG44 -> -11.148012 | CD44: =CD$38*CH44 -> -21.519824 | CE44: =CE$38*CI44 -> -32.004284 | CG44: =$CN44 -> -0.012299518 | CH44: =$CN44 -> -0.012299518 | CI44: =$CN44 -> -0.012299518 | CK44: =IFERROR(CB44/CB$38,0) -> -0.087440544 | CM44: =-SUMIFS('FY25 By Venue Financials'!$N:$N,'FY25 By Venue Financials'!$A:$A,$C44) -> -86.75385 | CN44: =IFERROR(CM44/CM$38,0) -> -0.012299518 | CP44: % Total Rev | CQ44: % of Total Events
C45: Room COGS | D45: =-SUMIFS('P&L'!C:C,'P&L'!$A:$A,$C45)/1000 -> 0 | E45: =-SUMIFS('P&L'!D:D,'P&L'!$A:$A,$C45)/1000 -> 0 | F45: =-SUMIFS('P&L'!E:E,'P&L'!$A:$A,$C45)/1000 -> 0 | G45: =-SUMIFS('P&L'!F:F,'P&L'!$A:$A,$C45)/1000 -> 0 | H45: =-SUMIFS('P&L'!G:G,'P&L'!$A:$A,$C45)/1000 -> 0 | I45: =-SUMIFS('P&L'!H:H,'P&L'!$A:$A,$C45)/1000 -> 0 | J45: =-SUMIFS('P&L'!I:I,'P&L'!$A:$A,$C45)/1000 -> 0 | K45: =-SUMIFS('P&L'!J:J,'P&L'!$A:$A,$C45)/1000 -> 0 | L45: =-SUMIFS('P&L'!K:K,'P&L'!$A:$A,$C45)/1000 -> 0 | M45: =-SUMIFS('P&L'!L:L,'P&L'!$A:$A,$C45)/1000 -> 0 | N45: =-SUMIFS('P&L'!M:M,'P&L'!$A:$A,$C45)/1000 -> 0 | O45: =-SUMIFS('P&L'!N:N,'P&L'!$A:$A,$C45)/1000 -> 0 | P45: =-SUMIFS('P&L'!O:O,'P&L'!$A:$A,$C45)/1000 -> 0 | Q45: =-SUMIFS('P&L'!P:P,'P&L'!$A:$A,$C45)/1000 -> 0 | R45: =-SUMIFS('P&L'!Q:Q,'P&L'!$A:$A,$C45)/1000 -> 0 | S45: =-SUMIFS('P&L'!R:R,'P&L'!$A:$A,$C45)/1000 -> 0 | T45: =-SUMIFS('P&L'!S:S,'P&L'!$A:$A,$C45)/1000 -> 0 | U45: =-SUMIFS('P&L'!T:T,'P&L'!$A:$A,$C45)/1000 -> 0 | V45: =-SUMIFS('P&L'!U:U,'P&L'!$A:$A,$C45)/1000 -> 0 | W45: =-SUMIFS('P&L'!V:V,'P&L'!$A:$A,$C45)/1000 -> 0 | X45: =-SUMIFS('P&L'!W:W,'P&L'!$A:$A,$C45)/1000 -> 0 | Y45: =-SUMIFS('P&L'!X:X,'P&L'!$A:$A,$C45)/1000 -> 0 | Z45: =-SUMIFS('P&L'!Y:Y,'P&L'!$A:$A,$C45)/1000 -> 0 | AA45: =-SUMIFS('P&L'!Z:Z,'P&L'!$A:$A,$C45)/1000 -> 0 | AB45: =-SUMIFS('P&L'!AA:AA,'P&L'!$A:$A,$C45)/1000 -> 0 | AC45: =-SUMIFS('P&L'!AB:AB,'P&L'!$A:$A,$C45)/1000 -> 0 | AD45: =-SUMIFS('P&L'!AC:AC,'P&L'!$A:$A,$C45)/1000 -> 0 | AE45: =-SUMIFS('P&L'!AD:AD,'P&L'!$A:$A,$C45)/1000 -> 0 | AF45: =-SUMIFS('P&L'!AE:AE,'P&L'!$A:$A,$C45)/1000 -> 0 | AG45: =-SUMIFS('P&L'!AF:AF,'P&L'!$A:$A,$C45)/1000 -> 0 | AH45: =-SUMIFS('P&L'!AG:AG,'P&L'!$A:$A,$C45)/1000 -> 0 | AK45: =SUMIFS($CC45:$CE45,$CC$1:$CE$1,AK$3)*AK$24 -> 0 | AL45: =SUMIFS($CC45:$CE45,$CC$1:$CE$1,AL$3)*AL$24 -> 0 | AM45: =SUMIFS($CC45:$CE45,$CC$1:$CE$1,AM$3)*AM$24 -> 0 | AN45: =SUMIFS($CC45:$CE45,$CC$1:$CE$1,AN$3)*AN$24 -> 0 | AO45: =SUMIFS($CC45:$CE45,$CC$1:$CE$1,AO$3)*AO$24 -> 0 | AP45: =SUMIFS($CC45:$CE45,$CC$1:$CE$1,AP$3)*AP$24 -> 0 | AQ45: =SUMIFS($CC45:$CE45,$CC$1:$CE$1,AQ$3)*AQ$24 -> 0 | AR45: =SUMIFS($CC45:$CE45,$CC$1:$CE$1,AR$3)*AR$24 -> 0 | ... BT45: =SUMIFS($CC45:$CE45,$CC$1:$CE$1,BT$3)*BT$24 -> 0 | BU45: =BI45 -> 0 | BV45: =BJ45 -> 0 | BW45: =BK45 -> 0 | BX45: =BL45 -> 0 | BZ45: =SUMIFS($D45:$AJ45,$D$1:$AJ$1,BZ$9) -> 0 | CA45: =SUMIFS($D45:$AJ45,$D$1:$AJ$1,CA$9) -> 0 | CB45: =SUMIFS($D45:$AJ45,$D$3:$AJ$3,"LTM") -> 0 | CC45: =CC30*CG45 -> 0 | CD45: =CD30*CH45 -> 0 | CE45: =CE30*CI45 -> 0 | CG45: =$CN45 -> 0 | CH45: =$CN45 -> 0 | CI45: =$CN45 -> 0 | CK45: =IFERROR(CB45/CB27,0) -> 0 | CM45: =-SUMIFS('FY25 By Venue Financials'!$N:$N,'FY25 By Venue Financials'!$A:$A,$C45) -> 0 | CN45: =IFERROR(CM45/CM30,0) -> 0 | CP45: % Lodging Rev | CQ45: % of Total Events
C47: Total COGS | D47: =SUM(D41:D46) -> -13.22447 | E47: =SUM(E41:E46) -> -16.90425 | F47: =SUM(F41:F46) -> -6.92204 | G47: =SUM(G41:G46) -> -5.68561 | H47: =SUM(H41:H46) -> -20.64956 | I47: =SUM(I41:I46) -> -15.13228 | J47: =SUM(J41:J46) -> -6.60258 | K47: =SUM(K41:K46) -> -1.70385 | ... AH47: =SUM(AH41:AH46) -> -0.56763 | AK47: =SUM(AK41:AK46) -> -2.3464798 | AL47: =SUM(AL41:AL46) -> -2.3464798 | AM47: =SUM(AM41:AM46) -> -0.78215993 | AN47: =SUM(AN41:AN46) -> -0.78215993 | AO47: =SUM(AO41:AO46) -> 0 | AP47: =SUM(AP41:AP46) -> 0 | AQ47: =SUM(AQ41:AQ46) -> -0.39107996 | AR47: =SUM(AR41:AR46) -> -1.5643199 | ... BX47: =SUM(BX41:BX46) -> -12.923036 | BZ47: =SUM(BZ41:BZ46) -> -86.42515 | CA47: =SUM(CA41:CA46) -> -42.49075 | CB47: =SUM(CB41:CB46) -> -49.04101 | CC47: =SUM(CC41:CC46) -> -15.643199 | CD47: =SUM(CD41:CD46) -> -81.595148 | CE47: =SUM(CE41:CE46) -> -172.30714 | CG47: =IFERROR(CC47/CC$38,0) -> -0.017259023 | CH47: =IFERROR(CD47/CD$38,0) -> -0.046635185 | CI47: =IFERROR(CE47/CE$38,0) -> -0.066219097 | CK47: =IFERROR(CB47/CB$38,0) -> -0.087440544 | CM47: =SUM(CM41:CM46) -> -757.20939 | CN47: =IFERROR(CM47/CM$38,0) -> -0.10735328 | CP47: % Total Rev
C49: Gross Margin | D49: =D38+D47 -> -12.84202 | E49: =E38+E47 -> 1.0224 | F49: =F38+F47 -> 43.27796 | G49: =G38+G47 -> 70.90499 | H49: =H38+H47 -> 52.23224 | I49: =I38+I47 -> 95.31391 | J49: =J38+J47 -> 16.66809 | K49: =K38+K47 -> -0.86785 | ... AH49: =AH38+AH47 -> 25.01403 | AK49: =AK38+AK47 -> 133.61022 | AL49: =AL38+AL47 -> 133.61022 | AM49: =AM38+AM47 -> 44.536739 | AN49: =AN38+AN47 -> 44.536739 | AO49: =AO38+AO47 -> 0 | AP49: =AP38+AP47 -> 0 | AQ49: =AQ38+AQ47 -> 22.26837 | AR49: =AR38+AR47 -> 89.073478 | ... BX49: =BX38+BX47 -> 182.23268 | BZ49: =BZ38+BZ47 -> 380.03921 | CA49: =CA38+CA47 -> 395.19447 | CB49: =CB38+CB47 -> 511.80877 | CC49: =CC38+CC47 -> 890.73478 | CD49: =CD38+CD47 -> 1668.0526 | CE49: =CE38+CE47 -> 2429.7691 | CG49: =IFERROR(CC49/CC$38,0) -> 0.98274098 | CH49: =IFERROR(CD49/CD$38,0) -> 0.95336482 | CI49: =IFERROR(CE49/CE$38,0) -> 0.9337809 | CK49: =IFERROR(CB49/CB$38,0) -> 0.91255946 | CM49: =CM38+CM47 -> 6296.2256 | CN49: =IFERROR(CM49/CM$38,0) -> 0.89264672 | CP49: % Total Rev
C51: Payroll
C52: Sales Team Payroll | D52: =-SUMIFS('P&L'!C:C,'P&L'!$A:$A,$C52)/1000 -> 0 | E52: =-SUMIFS('P&L'!D:D,'P&L'!$A:$A,$C52)/1000 -> 0 | F52: =-SUMIFS('P&L'!E:E,'P&L'!$A:$A,$C52)/1000 -> 0 | G52: =-SUMIFS('P&L'!F:F,'P&L'!$A:$A,$C52)/1000 -> 0 | H52: =-SUMIFS('P&L'!G:G,'P&L'!$A:$A,$C52)/1000 -> 0 | I52: =-SUMIFS('P&L'!H:H,'P&L'!$A:$A,$C52)/1000 -> 0 | J52: =-SUMIFS('P&L'!I:I,'P&L'!$A:$A,$C52)/1000 -> 0 | K52: =-SUMIFS('P&L'!J:J,'P&L'!$A:$A,$C52)/1000 -> 0 | L52: =-SUMIFS('P&L'!K:K,'P&L'!$A:$A,$C52)/1000 -> 0 | M52: =-SUMIFS('P&L'!L:L,'P&L'!$A:$A,$C52)/1000 -> 0 | N52: =-SUMIFS('P&L'!M:M,'P&L'!$A:$A,$C52)/1000 -> 0 | O52: =-SUMIFS('P&L'!N:N,'P&L'!$A:$A,$C52)/1000 -> 0 | P52: =-SUMIFS('P&L'!O:O,'P&L'!$A:$A,$C52)/1000 -> 0 | Q52: =-SUMIFS('P&L'!P:P,'P&L'!$A:$A,$C52)/1000 -> 0 | R52: =-SUMIFS('P&L'!Q:Q,'P&L'!$A:$A,$C52)/1000 -> 0 | S52: =-SUMIFS('P&L'!R:R,'P&L'!$A:$A,$C52)/1000 -> 0 | T52: =-SUMIFS('P&L'!S:S,'P&L'!$A:$A,$C52)/1000 -> 0 | U52: =-SUMIFS('P&L'!T:T,'P&L'!$A:$A,$C52)/1000 -> 0 | V52: =-SUMIFS('P&L'!U:U,'P&L'!$A:$A,$C52)/1000 -> 0 | W52: =-SUMIFS('P&L'!V:V,'P&L'!$A:$A,$C52)/1000 -> 0 | X52: =-SUMIFS('P&L'!W:W,'P&L'!$A:$A,$C52)/1000 -> 0 | Y52: =-SUMIFS('P&L'!X:X,'P&L'!$A:$A,$C52)/1000 -> 0 | Z52: =-SUMIFS('P&L'!Y:Y,'P&L'!$A:$A,$C52)/1000 -> 0 | AA52: =-SUMIFS('P&L'!Z:Z,'P&L'!$A:$A,$C52)/1000 -> 0 | AB52: =-SUMIFS('P&L'!AA:AA,'P&L'!$A:$A,$C52)/1000 -> 0 | AC52: =-SUMIFS('P&L'!AB:AB,'P&L'!$A:$A,$C52)/1000 -> 0 | AD52: =-SUMIFS('P&L'!AC:AC,'P&L'!$A:$A,$C52)/1000 -> 0 | AE52: =-SUMIFS('P&L'!AD:AD,'P&L'!$A:$A,$C52)/1000 -> 0 | AF52: =-SUMIFS('P&L'!AE:AE,'P&L'!$A:$A,$C52)/1000 -> 0 | AG52: =-SUMIFS('P&L'!AF:AF,'P&L'!$A:$A,$C52)/1000 -> 0 | AH52: =-SUMIFS('P&L'!AG:AG,'P&L'!$A:$A,$C52)/1000 -> 0 | AK52: =SUMIFS($CC52:$CE52,$CC$1:$CE$1,AK$3)/12 -> -6.25 | AL52: =SUMIFS($CC52:$CE52,$CC$1:$CE$1,AL$3)/12 -> -6.25 | AM52: =SUMIFS($CC52:$CE52,$CC$1:$CE$1,AM$3)/12 -> -6.25 | AN52: =SUMIFS($CC52:$CE52,$CC$1:$CE$1,AN$3)/12 -> -6.25 | AO52: =SUMIFS($CC52:$CE52,$CC$1:$CE$1,AO$3)/12 -> -6.25 | AP52: =SUMIFS($CC52:$CE52,$CC$1:$CE$1,AP$3)/12 -> -6.25 | AQ52: =SUMIFS($CC52:$CE52,$CC$1:$CE$1,AQ$3)/12 -> -6.25 | AR52: =SUMIFS($CC52:$CE52,$CC$1:$CE$1,AR$3)/12 -> -6.25 | ... BT52: =SUMIFS($CC52:$CE52,$CC$1:$CE$1,BT$3)/12 -> -6.630625 | BU52: =BI52 -> -6.630625 | BV52: =BJ52 -> -6.630625 | BW52: =BK52 -> -6.630625 | BX52: =BL52 -> -6.630625 | BZ52: =SUMIFS($D52:$AJ52,$D$1:$AJ$1,BZ$9) -> 0 | CA52: =SUMIFS($D52:$AJ52,$D$1:$AJ$1,CA$9) -> 0 | CB52: =SUMIFS($D52:$AJ52,$D$3:$AJ$3,"LTM") -> 0 | CC52: =CG52*1 -> -75 | CD52: =CH52*1 -> -77.25 | CE52: =CI52*1 -> -79.5675 | CG52: =-Payroll!$E$11/1000 -> -75 | CH52: =CG52*1.03 -> -77.25 | CI52: =CH52*1.03 -> -79.5675 | CK52: =IFERROR(CB52/CB$38,0) -> 0 | CM52: =-SUMIFS('FY25 By Venue Financials'!$N:$N,'FY25 By Venue Financials'!$A:$A,$C52) -> -210.42054 | CP52: $/team member | CQ52: Split evently | CR52: Kathy (5% YoY)
C53: Planning Team Payroll | D53: =-SUMIFS('P&L'!C:C,'P&L'!$A:$A,$C53)/1000 -> 0 | E53: =-SUMIFS('P&L'!D:D,'P&L'!$A:$A,$C53)/1000 -> 0 | F53: =-SUMIFS('P&L'!E:E,'P&L'!$A:$A,$C53)/1000 -> 0 | G53: =-SUMIFS('P&L'!F:F,'P&L'!$A:$A,$C53)/1000 -> 0 | H53: =-SUMIFS('P&L'!G:G,'P&L'!$A:$A,$C53)/1000 -> 0 | I53: =-SUMIFS('P&L'!H:H,'P&L'!$A:$A,$C53)/1000 -> 0 | J53: =-SUMIFS('P&L'!I:I,'P&L'!$A:$A,$C53)/1000 -> 0 | K53: =-SUMIFS('P&L'!J:J,'P&L'!$A:$A,$C53)/1000 -> 0 | L53: =-SUMIFS('P&L'!K:K,'P&L'!$A:$A,$C53)/1000 -> 0 | M53: =-SUMIFS('P&L'!L:L,'P&L'!$A:$A,$C53)/1000 -> 0 | N53: =-SUMIFS('P&L'!M:M,'P&L'!$A:$A,$C53)/1000 -> 0 | O53: =-SUMIFS('P&L'!N:N,'P&L'!$A:$A,$C53)/1000 -> 0 | P53: =-SUMIFS('P&L'!O:O,'P&L'!$A:$A,$C53)/1000 -> 0 | Q53: =-SUMIFS('P&L'!P:P,'P&L'!$A:$A,$C53)/1000 -> 0 | R53: =-SUMIFS('P&L'!Q:Q,'P&L'!$A:$A,$C53)/1000 -> 0 | S53: =-SUMIFS('P&L'!R:R,'P&L'!$A:$A,$C53)/1000 -> 0 | T53: =-SUMIFS('P&L'!S:S,'P&L'!$A:$A,$C53)/1000 -> 0 | U53: =-SUMIFS('P&L'!T:T,'P&L'!$A:$A,$C53)/1000 -> 0 | V53: =-SUMIFS('P&L'!U:U,'P&L'!$A:$A,$C53)/1000 -> 0 | W53: =-SUMIFS('P&L'!V:V,'P&L'!$A:$A,$C53)/1000 -> 0 | X53: =-SUMIFS('P&L'!W:W,'P&L'!$A:$A,$C53)/1000 -> 0 | Y53: =-SUMIFS('P&L'!X:X,'P&L'!$A:$A,$C53)/1000 -> 0 | Z53: =-SUMIFS('P&L'!Y:Y,'P&L'!$A:$A,$C53)/1000 -> 0 | AA53: =-SUMIFS('P&L'!Z:Z,'P&L'!$A:$A,$C53)/1000 -> 0 | AB53: =-SUMIFS('P&L'!AA:AA,'P&L'!$A:$A,$C53)/1000 -> 0 | AC53: =-SUMIFS('P&L'!AB:AB,'P&L'!$A:$A,$C53)/1000 -> 0 | AD53: =-SUMIFS('P&L'!AC:AC,'P&L'!$A:$A,$C53)/1000 -> 0 | AE53: =-SUMIFS('P&L'!AD:AD,'P&L'!$A:$A,$C53)/1000 -> 0 | AF53: =-SUMIFS('P&L'!AE:AE,'P&L'!$A:$A,$C53)/1000 -> 0 | AG53: =-SUMIFS('P&L'!AF:AF,'P&L'!$A:$A,$C53)/1000 -> 0 | AH53: =-SUMIFS('P&L'!AG:AG,'P&L'!$A:$A,$C53)/1000 -> 0 | AK53: =SUMIFS($CC53:$CE53,$CC$1:$CE$1,AK$3)/12 -> -12.153333 | AL53: =SUMIFS($CC53:$CE53,$CC$1:$CE$1,AL$3)/12 -> -12.153333 | AM53: =SUMIFS($CC53:$CE53,$CC$1:$CE$1,AM$3)/12 -> -12.153333 | AN53: =SUMIFS($CC53:$CE53,$CC$1:$CE$1,AN$3)/12 -> -12.153333 | AO53: =SUMIFS($CC53:$CE53,$CC$1:$CE$1,AO$3)/12 -> -12.153333 | AP53: =SUMIFS($CC53:$CE53,$CC$1:$CE$1,AP$3)/12 -> -12.153333 | AQ53: =SUMIFS($CC53:$CE53,$CC$1:$CE$1,AQ$3)/12 -> -12.153333 | AR53: =SUMIFS($CC53:$CE53,$CC$1:$CE$1,AR$3)/12 -> -12.153333 | ... BT53: =SUMIFS($CC53:$CE53,$CC$1:$CE$1,BT$3)/12 -> -12.893471 | BU53: =BI53 -> -12.893471 | BV53: =BJ53 -> -12.893471 | BW53: =BK53 -> -12.893471 | BX53: =BL53 -> -12.893471 | BZ53: =SUMIFS($D53:$AJ53,$D$1:$AJ$1,BZ$9) -> 0 | CA53: =SUMIFS($D53:$AJ53,$D$1:$AJ$1,CA$9) -> 0 | CB53: =SUMIFS($D53:$AJ53,$D$3:$AJ$3,"LTM") -> 0 | CC53: =CG53*1 -> -145.84 | CD53: =CH53*1 -> -150.2152 | CE53: =CI53*1 -> -154.72166 | CG53: =-Payroll!$E$7/1000-Payroll!$E$8/1000 -> -145.84 | CH53: =CG53*1.03 -> -150.2152 | CI53: =CH53*1.03 -> -154.72166 | CK53: =IFERROR(CB53/CB$38,0) -> 0 | CM53: =-SUMIFS('FY25 By Venue Financials'!$N:$N,'FY25 By Venue Financials'!$A:$A,$C53) -> -332.84058 | CP53: $/team member | CQ53: Split evently | CR53: Danielle and Yami (5% YoY)
C54: Operations Team Payroll | D54: =-SUMIFS('P&L'!C:C,'P&L'!$A:$A,$C54)/1000 -> -10.7971 | E54: =-SUMIFS('P&L'!D:D,'P&L'!$A:$A,$C54)/1000 -> -11.45475 | F54: =-SUMIFS('P&L'!E:E,'P&L'!$A:$A,$C54)/1000 -> -18.41805 | G54: =-SUMIFS('P&L'!F:F,'P&L'!$A:$A,$C54)/1000 -> -15.69802 | H54: =-SUMIFS('P&L'!G:G,'P&L'!$A:$A,$C54)/1000 -> -19.06351 | I54: =-SUMIFS('P&L'!H:H,'P&L'!$A:$A,$C54)/1000 -> -20.56165 | J54: =-SUMIFS('P&L'!I:I,'P&L'!$A:$A,$C54)/1000 -> -15.3939 | K54: =-SUMIFS('P&L'!J:J,'P&L'!$A:$A,$C54)/1000 -> -9.09785 | L54: =-SUMIFS('P&L'!K:K,'P&L'!$A:$A,$C54)/1000 -> -18.01144 | M54: =-SUMIFS('P&L'!L:L,'P&L'!$A:$A,$C54)/1000 -> -13.28815 | N54: =-SUMIFS('P&L'!M:M,'P&L'!$A:$A,$C54)/1000 -> -16.0353 | O54: =-SUMIFS('P&L'!N:N,'P&L'!$A:$A,$C54)/1000 -> -3.75948 | P54: =-SUMIFS('P&L'!O:O,'P&L'!$A:$A,$C54)/1000 -> -14.2979 | Q54: =-SUMIFS('P&L'!P:P,'P&L'!$A:$A,$C54)/1000 -> -13.76059 | R54: =-SUMIFS('P&L'!Q:Q,'P&L'!$A:$A,$C54)/1000 -> -13.81246 | S54: =-SUMIFS('P&L'!R:R,'P&L'!$A:$A,$C54)/1000 -> -15.07122 | T54: =-SUMIFS('P&L'!S:S,'P&L'!$A:$A,$C54)/1000 -> -22.5305 | U54: =-SUMIFS('P&L'!T:T,'P&L'!$A:$A,$C54)/1000 -> -20.48729 | V54: =-SUMIFS('P&L'!U:U,'P&L'!$A:$A,$C54)/1000 -> -16.35836 | W54: =-SUMIFS('P&L'!V:V,'P&L'!$A:$A,$C54)/1000 -> -21.2416 | X54: =-SUMIFS('P&L'!W:W,'P&L'!$A:$A,$C54)/1000 -> -13.16678 | Y54: =-SUMIFS('P&L'!X:X,'P&L'!$A:$A,$C54)/1000 -> -21.32926 | Z54: =-SUMIFS('P&L'!Y:Y,'P&L'!$A:$A,$C54)/1000 -> -15.27442 | AA54: =-SUMIFS('P&L'!Z:Z,'P&L'!$A:$A,$C54)/1000 -> -14.2261 | AB54: =-SUMIFS('P&L'!AA:AA,'P&L'!$A:$A,$C54)/1000 -> -18.85747 | AC54: =-SUMIFS('P&L'!AB:AB,'P&L'!$A:$A,$C54)/1000 -> -18.50131 | AD54: =-SUMIFS('P&L'!AC:AC,'P&L'!$A:$A,$C54)/1000 -> -22.55881 | AE54: =-SUMIFS('P&L'!AD:AD,'P&L'!$A:$A,$C54)/1000 -> -25.36483 | AF54: =-SUMIFS('P&L'!AE:AE,'P&L'!$A:$A,$C54)/1000 -> -26.42849 | AG54: =-SUMIFS('P&L'!AF:AF,'P&L'!$A:$A,$C54)/1000 -> -32.36422 | AH54: =-SUMIFS('P&L'!AG:AG,'P&L'!$A:$A,$C54)/1000 -> -26.31843 | AK54: =SUMIFS($CC54:$CE54,$CC$1:$CE$1,AK$3)*AK$24 -> -9.54 | AL54: =SUMIFS($CC54:$CE54,$CC$1:$CE$1,AL$3)*AL$24 -> -9.54 | AM54: =SUMIFS($CC54:$CE54,$CC$1:$CE$1,AM$3)*AM$24 -> -3.18 | AN54: =SUMIFS($CC54:$CE54,$CC$1:$CE$1,AN$3)*AN$24 -> -3.18 | AO54: =SUMIFS($CC54:$CE54,$CC$1:$CE$1,AO$3)*AO$24 -> 0 | AP54: =SUMIFS($CC54:$CE54,$CC$1:$CE$1,AP$3)*AP$24 -> 0 | AQ54: =SUMIFS($CC54:$CE54,$CC$1:$CE$1,AQ$3)*AQ$24 -> -1.59 | AR54: =SUMIFS($CC54:$CE54,$CC$1:$CE$1,AR$3)*AR$24 -> -6.36 | ... BT54: =SUMIFS($CC54:$CE54,$CC$1:$CE$1,BT$3)*BT$24 -> -5.060493 | BU54: =BI54 -> -6.747324 | BV54: =BJ54 -> -7.5907395 | BW54: =BK54 -> -6.747324 | BX54: =BL54 -> -5.060493 | BZ54: =SUMIFS($D54:$AJ54,$D$1:$AJ$1,BZ$9) -> -171.5792 | CA54: =SUMIFS($D54:$AJ54,$D$1:$AJ$1,CA$9) -> -201.55648 | CB54: =SUMIFS($D54:$AJ54,$D$3:$AJ$3,"LTM") -> -255.63172 | CC54: =CG54*1 -> -63.6 | CD54: =CH54*1 -> -65.508 | CE54: =CI54*1 -> -67.47324 | CG54: =-SUM(Payroll!$E$8:$E$9)/1000 -> -63.6 | CH54: =CG54*1.03 -> -65.508 | CI54: =CH54*1.03 -> -67.47324 | CK54: =IFERROR(CB54/CB$38,0) -> -0.45579356 | CM54: =-SUMIFS('FY25 By Venue Financials'!$N:$N,'FY25 By Venue Financials'!$A:$A,$C54) -> -126.76002 | CN54: =IFERROR(CM54/CM$38,0) -> -0.017971388 | CP54: % Total Rev | CQ54: % of Total Events | CR54: Josh & Adi (5% YoY)
C55: Ancillary Payroll | D55: =-SUMIFS('P&L'!C:C,'P&L'!$A:$A,$C55)/1000 -> 0 | E55: =-SUMIFS('P&L'!D:D,'P&L'!$A:$A,$C55)/1000 -> 0 | F55: =-SUMIFS('P&L'!E:E,'P&L'!$A:$A,$C55)/1000 -> 0 | G55: =-SUMIFS('P&L'!F:F,'P&L'!$A:$A,$C55)/1000 -> 0 | H55: =-SUMIFS('P&L'!G:G,'P&L'!$A:$A,$C55)/1000 -> 0 | I55: =-SUMIFS('P&L'!H:H,'P&L'!$A:$A,$C55)/1000 -> 0 | J55: =-SUMIFS('P&L'!I:I,'P&L'!$A:$A,$C55)/1000 -> 0 | K55: =-SUMIFS('P&L'!J:J,'P&L'!$A:$A,$C55)/1000 -> 0 | L55: =-SUMIFS('P&L'!K:K,'P&L'!$A:$A,$C55)/1000 -> 0 | M55: =-SUMIFS('P&L'!L:L,'P&L'!$A:$A,$C55)/1000 -> 0 | N55: =-SUMIFS('P&L'!M:M,'P&L'!$A:$A,$C55)/1000 -> 0 | O55: =-SUMIFS('P&L'!N:N,'P&L'!$A:$A,$C55)/1000 -> 0 | P55: =-SUMIFS('P&L'!O:O,'P&L'!$A:$A,$C55)/1000 -> 0 | Q55: =-SUMIFS('P&L'!P:P,'P&L'!$A:$A,$C55)/1000 -> 0 | R55: =-SUMIFS('P&L'!Q:Q,'P&L'!$A:$A,$C55)/1000 -> 0 | S55: =-SUMIFS('P&L'!R:R,'P&L'!$A:$A,$C55)/1000 -> 0 | T55: =-SUMIFS('P&L'!S:S,'P&L'!$A:$A,$C55)/1000 -> 0 | U55: =-SUMIFS('P&L'!T:T,'P&L'!$A:$A,$C55)/1000 -> 0 | V55: =-SUMIFS('P&L'!U:U,'P&L'!$A:$A,$C55)/1000 -> 0 | W55: =-SUMIFS('P&L'!V:V,'P&L'!$A:$A,$C55)/1000 -> 0 | X55: =-SUMIFS('P&L'!W:W,'P&L'!$A:$A,$C55)/1000 -> 0 | Y55: =-SUMIFS('P&L'!X:X,'P&L'!$A:$A,$C55)/1000 -> 0 | Z55: =-SUMIFS('P&L'!Y:Y,'P&L'!$A:$A,$C55)/1000 -> 0 | AA55: =-SUMIFS('P&L'!Z:Z,'P&L'!$A:$A,$C55)/1000 -> 0 | AB55: =-SUMIFS('P&L'!AA:AA,'P&L'!$A:$A,$C55)/1000 -> 0 | AC55: =-SUMIFS('P&L'!AB:AB,'P&L'!$A:$A,$C55)/1000 -> 0 | AD55: =-SUMIFS('P&L'!AC:AC,'P&L'!$A:$A,$C55)/1000 -> 0 | AE55: =-SUMIFS('P&L'!AD:AD,'P&L'!$A:$A,$C55)/1000 -> 0 | AF55: =-SUMIFS('P&L'!AE:AE,'P&L'!$A:$A,$C55)/1000 -> 0 | AG55: =-SUMIFS('P&L'!AF:AF,'P&L'!$A:$A,$C55)/1000 -> 0 | AH55: =-SUMIFS('P&L'!AG:AG,'P&L'!$A:$A,$C55)/1000 -> 0 | AK55: =SUMIFS($CC55:$CE55,$CC$1:$CE$1,AK$3)*AK$24 -> -0.88753468 | AL55: =SUMIFS($CC55:$CE55,$CC$1:$CE$1,AL$3)*AL$24 -> -0.88753468 | AM55: =SUMIFS($CC55:$CE55,$CC$1:$CE$1,AM$3)*AM$24 -> -0.29584489 | AN55: =SUMIFS($CC55:$CE55,$CC$1:$CE$1,AN$3)*AN$24 -> -0.29584489 | AO55: =SUMIFS($CC55:$CE55,$CC$1:$CE$1,AO$3)*AO$24 -> 0 | AP55: =SUMIFS($CC55:$CE55,$CC$1:$CE$1,AP$3)*AP$24 -> 0 | AQ55: =SUMIFS($CC55:$CE55,$CC$1:$CE$1,AQ$3)*AQ$24 -> -0.14792245 | AR55: =SUMIFS($CC55:$CE55,$CC$1:$CE$1,AR$3)*AR$24 -> -0.59168978 | ... BT55: =SUMIFS($CC55:$CE55,$CC$1:$CE$1,BT$3)*BT$24 -> -7.532156 | BU55: =BI55 -> -10.042875 | BV55: =BJ55 -> -11.298234 | BW55: =BK55 -> -10.042875 | BX55: =BL55 -> -7.532156 | BZ55: =SUMIFS($D55:$AJ55,$D$1:$AJ$1,BZ$9) -> 0 | CA55: =SUMIFS($D55:$AJ55,$D$1:$AJ$1,CA$9) -> 0 | CB55: =SUMIFS($D55:$AJ55,$D$3:$AJ$3,"LTM") -> 0 | CC55: =CC$31*CG55 -> -5.9168978 | CD55: =CD$31*CH55 -> -44.697209 | CE55: =CE$31*CI55 -> -100.42875 | CG55: =$CN55 -> -0.30163123 | CH55: =$CN55 -> -0.30163123 | CI55: =$CN55 -> -0.30163123 | CK55: =IFERROR(CB55/CB44,0) -> 0 | CM55: =-SUMIFS('FY25 By Venue Financials'!$N:$N,'FY25 By Venue Financials'!$A:$A,$C55) -> -457.80014 | CN55: =IFERROR(CM55/CM$31,0) -> -0.30163123 | CP55: % Ancillary Rev | CQ55: % of Total Events
C56: F&B Team Payroll | D56: =-SUMIFS('P&L'!C:C,'P&L'!$A:$A,$C56)/1000 -> 0 | E56: =-SUMIFS('P&L'!D:D,'P&L'!$A:$A,$C56)/1000 -> 0 | F56: =-SUMIFS('P&L'!E:E,'P&L'!$A:$A,$C56)/1000 -> 0 | G56: =-SUMIFS('P&L'!F:F,'P&L'!$A:$A,$C56)/1000 -> 0 | H56: =-SUMIFS('P&L'!G:G,'P&L'!$A:$A,$C56)/1000 -> 0 | I56: =-SUMIFS('P&L'!H:H,'P&L'!$A:$A,$C56)/1000 -> 0 | J56: =-SUMIFS('P&L'!I:I,'P&L'!$A:$A,$C56)/1000 -> 0 | K56: =-SUMIFS('P&L'!J:J,'P&L'!$A:$A,$C56)/1000 -> 0 | L56: =-SUMIFS('P&L'!K:K,'P&L'!$A:$A,$C56)/1000 -> 0 | M56: =-SUMIFS('P&L'!L:L,'P&L'!$A:$A,$C56)/1000 -> 0 | N56: =-SUMIFS('P&L'!M:M,'P&L'!$A:$A,$C56)/1000 -> 0 | O56: =-SUMIFS('P&L'!N:N,'P&L'!$A:$A,$C56)/1000 -> 0 | P56: =-SUMIFS('P&L'!O:O,'P&L'!$A:$A,$C56)/1000 -> 0 | Q56: =-SUMIFS('P&L'!P:P,'P&L'!$A:$A,$C56)/1000 -> 0 | R56: =-SUMIFS('P&L'!Q:Q,'P&L'!$A:$A,$C56)/1000 -> 0 | S56: =-SUMIFS('P&L'!R:R,'P&L'!$A:$A,$C56)/1000 -> 0 | T56: =-SUMIFS('P&L'!S:S,'P&L'!$A:$A,$C56)/1000 -> 0 | U56: =-SUMIFS('P&L'!T:T,'P&L'!$A:$A,$C56)/1000 -> 0 | V56: =-SUMIFS('P&L'!U:U,'P&L'!$A:$A,$C56)/1000 -> 0 | W56: =-SUMIFS('P&L'!V:V,'P&L'!$A:$A,$C56)/1000 -> 0 | X56: =-SUMIFS('P&L'!W:W,'P&L'!$A:$A,$C56)/1000 -> 0 | Y56: =-SUMIFS('P&L'!X:X,'P&L'!$A:$A,$C56)/1000 -> 0 | Z56: =-SUMIFS('P&L'!Y:Y,'P&L'!$A:$A,$C56)/1000 -> 0 | AA56: =-SUMIFS('P&L'!Z:Z,'P&L'!$A:$A,$C56)/1000 -> 0 | AB56: =-SUMIFS('P&L'!AA:AA,'P&L'!$A:$A,$C56)/1000 -> 0 | AC56: =-SUMIFS('P&L'!AB:AB,'P&L'!$A:$A,$C56)/1000 -> 0 | AD56: =-SUMIFS('P&L'!AC:AC,'P&L'!$A:$A,$C56)/1000 -> 0 | AE56: =-SUMIFS('P&L'!AD:AD,'P&L'!$A:$A,$C56)/1000 -> 0 | AF56: =-SUMIFS('P&L'!AE:AE,'P&L'!$A:$A,$C56)/1000 -> 0 | AG56: =-SUMIFS('P&L'!AF:AF,'P&L'!$A:$A,$C56)/1000 -> 0 | AH56: =-SUMIFS('P&L'!AG:AG,'P&L'!$A:$A,$C56)/1000 -> 0 | AK56: =SUMIFS($CC56:$CE56,$CC$1:$CE$1,AK$3)*AK$24 -> -0.13588374 | AL56: =SUMIFS($CC56:$CE56,$CC$1:$CE$1,AL$3)*AL$24 -> -0.13588374 | AM56: =SUMIFS($CC56:$CE56,$CC$1:$CE$1,AM$3)*AM$24 -> -0.04529458 | AN56: =SUMIFS($CC56:$CE56,$CC$1:$CE$1,AN$3)*AN$24 -> -0.04529458 | AO56: =SUMIFS($CC56:$CE56,$CC$1:$CE$1,AO$3)*AO$24 -> 0 | AP56: =SUMIFS($CC56:$CE56,$CC$1:$CE$1,AP$3)*AP$24 -> 0 | AQ56: =SUMIFS($CC56:$CE56,$CC$1:$CE$1,AQ$3)*AQ$24 -> -0.02264729 | AR56: =SUMIFS($CC56:$CE56,$CC$1:$CE$1,AR$3)*AR$24 -> -0.09058916 | ... BT56: =SUMIFS($CC56:$CE56,$CC$1:$CE$1,BT$3)*BT$24 -> -5.2562845 | BU56: =BI56 -> -7.0083793 | BV56: =BJ56 -> -7.8844267 | BW56: =BK56 -> -7.0083793 | BX56: =BL56 -> -5.2562845 | BZ56: =SUMIFS($D56:$AJ56,$D$1:$AJ$1,BZ$9) -> 0 | CA56: =SUMIFS($D56:$AJ56,$D$1:$AJ$1,CA$9) -> 0 | CB56: =SUMIFS($D56:$AJ56,$D$3:$AJ$3,"LTM") -> 0 | CC56: =SUM(CC28:CC29)*CG56 -> -0.9058916 | CD56: =SUM(CD28:CD29)*CH56 -> -29.845301 | CE56: =SUM(CE28:CE29)*CI56 -> -70.083793 | CG56: =$CN56 -> -0.15098193 | CH56: =$CN56 -> -0.15098193 | CI56: =$CN56 -> -0.15098193 | CK56: =IFERROR(CB56/CB$38,0) -> 0 | CM56: =-SUMIFS('FY25 By Venue Financials'!$N:$N,'FY25 By Venue Financials'!$A:$A,$C56) -> -409.50284 | CN56: =CM56/SUM(CM28:CM29) -> -0.15098193 | CP56: % F&B Rev | CQ56: % of Total Events
C57: Owner Salaries | D57: =-SUMIFS('P&L'!C:C,'P&L'!$A:$A,$C57)/1000 -> 0 | E57: =-SUMIFS('P&L'!D:D,'P&L'!$A:$A,$C57)/1000 -> 0 | F57: =-SUMIFS('P&L'!E:E,'P&L'!$A:$A,$C57)/1000 -> -0.5 | G57: =-SUMIFS('P&L'!F:F,'P&L'!$A:$A,$C57)/1000 -> -1 | H57: =-SUMIFS('P&L'!G:G,'P&L'!$A:$A,$C57)/1000 -> -1.25 | I57: =-SUMIFS('P&L'!H:H,'P&L'!$A:$A,$C57)/1000 -> -1 | J57: =-SUMIFS('P&L'!I:I,'P&L'!$A:$A,$C57)/1000 -> -1 | K57: =-SUMIFS('P&L'!J:J,'P&L'!$A:$A,$C57)/1000 -> -1.25 | L57: =-SUMIFS('P&L'!K:K,'P&L'!$A:$A,$C57)/1000 -> -1 | M57: =-SUMIFS('P&L'!L:L,'P&L'!$A:$A,$C57)/1000 -> -1 | N57: =-SUMIFS('P&L'!M:M,'P&L'!$A:$A,$C57)/1000 -> -1.25 | O57: =-SUMIFS('P&L'!N:N,'P&L'!$A:$A,$C57)/1000 -> -3.75 | P57: =-SUMIFS('P&L'!O:O,'P&L'!$A:$A,$C57)/1000 -> -1.25 | Q57: =-SUMIFS('P&L'!P:P,'P&L'!$A:$A,$C57)/1000 -> -1 | R57: =-SUMIFS('P&L'!Q:Q,'P&L'!$A:$A,$C57)/1000 -> -1 | S57: =-SUMIFS('P&L'!R:R,'P&L'!$A:$A,$C57)/1000 -> -1 | T57: =-SUMIFS('P&L'!S:S,'P&L'!$A:$A,$C57)/1000 -> -1.25 | U57: =-SUMIFS('P&L'!T:T,'P&L'!$A:$A,$C57)/1000 -> -1 | V57: =-SUMIFS('P&L'!U:U,'P&L'!$A:$A,$C57)/1000 -> -1 | W57: =-SUMIFS('P&L'!V:V,'P&L'!$A:$A,$C57)/1000 -> -1.25 | X57: =-SUMIFS('P&L'!W:W,'P&L'!$A:$A,$C57)/1000 -> -1 | Y57: =-SUMIFS('P&L'!X:X,'P&L'!$A:$A,$C57)/1000 -> -1.25 | Z57: =-SUMIFS('P&L'!Y:Y,'P&L'!$A:$A,$C57)/1000 -> -1 | AA57: =-SUMIFS('P&L'!Z:Z,'P&L'!$A:$A,$C57)/1000 -> -0.75 | AB57: =-SUMIFS('P&L'!AA:AA,'P&L'!$A:$A,$C57)/1000 -> -0.25 | AC57: =-SUMIFS('P&L'!AB:AB,'P&L'!$A:$A,$C57)/1000 -> 0 | AD57: =-SUMIFS('P&L'!AC:AC,'P&L'!$A:$A,$C57)/1000 -> 0 | AE57: =-SUMIFS('P&L'!AD:AD,'P&L'!$A:$A,$C57)/1000 -> 0 | AF57: =-SUMIFS('P&L'!AE:AE,'P&L'!$A:$A,$C57)/1000 -> 0 | AG57: =-SUMIFS('P&L'!AF:AF,'P&L'!$A:$A,$C57)/1000 -> 0 | AH57: =-SUMIFS('P&L'!AG:AG,'P&L'!$A:$A,$C57)/1000 -> 0 | AK57: =SUMIFS($CC57:$CE57,$CC$1:$CE$1,AK$3)*AK$24 -> 0 | AL57: =SUMIFS($CC57:$CE57,$CC$1:$CE$1,AL$3)*AL$24 -> 0 | AM57: =SUMIFS($CC57:$CE57,$CC$1:$CE$1,AM$3)*AM$24 -> 0 | AN57: =SUMIFS($CC57:$CE57,$CC$1:$CE$1,AN$3)*AN$24 -> 0 | AO57: =SUMIFS($CC57:$CE57,$CC$1:$CE$1,AO$3)*AO$24 -> 0 | AP57: =SUMIFS($CC57:$CE57,$CC$1:$CE$1,AP$3)*AP$24 -> 0 | AQ57: =SUMIFS($CC57:$CE57,$CC$1:$CE$1,AQ$3)*AQ$24 -> 0 | AR57: =SUMIFS($CC57:$CE57,$CC$1:$CE$1,AR$3)*AR$24 -> 0 | ... BT57: =SUMIFS($CC57:$CE57,$CC$1:$CE$1,BT$3)*BT$24 -> 0 | BU57: =BI57 -> 0 | BV57: =BJ57 -> 0 | BW57: =BK57 -> 0 | BX57: =BL57 -> 0 | BZ57: =SUMIFS($D57:$AJ57,$D$1:$AJ$1,BZ$9) -> -13 | CA57: =SUMIFS($D57:$AJ57,$D$1:$AJ$1,CA$9) -> -12.75 | CB57: =SUMIFS($D57:$AJ57,$D$3:$AJ$3,"LTM") -> -5.5 | CC57: =CC$38*CG57 -> 0 | CD57: =CD$38*CH57 -> 0 | CE57: =CE$38*CI57 -> 0 | CG57: =$CN57 -> 0 | CH57: =$CN57 -> 0 | CI57: =$CN57 -> 0 | CK57: =IFERROR(CB57/CB$38,0) -> -0.0098065475 | CM57: =-SUMIFS('FY25 By Venue Financials'!$N:$N,'FY25 By Venue Financials'!$A:$A,$C57) -> 0 | CN57: =IFERROR(CM57/CM$38,0) -> 0 | CP57: % Total Rev | CQ57: % of Total Events
C58: Payroll Admin & Benefit Expenses | D58: =-SUMIFS('P&L'!C:C,'P&L'!$A:$A,$C58)/1000 -> -0.63485 | E58: =-SUMIFS('P&L'!D:D,'P&L'!$A:$A,$C58)/1000 -> -0.72874 | F58: =-SUMIFS('P&L'!E:E,'P&L'!$A:$A,$C58)/1000 -> -1.33903 | G58: =-SUMIFS('P&L'!F:F,'P&L'!$A:$A,$C58)/1000 -> -1.07979 | H58: =-SUMIFS('P&L'!G:G,'P&L'!$A:$A,$C58)/1000 -> -1.17756 | I58: =-SUMIFS('P&L'!H:H,'P&L'!$A:$A,$C58)/1000 -> -1.18112 | J58: =-SUMIFS('P&L'!I:I,'P&L'!$A:$A,$C58)/1000 -> -0.87632 | K58: =-SUMIFS('P&L'!J:J,'P&L'!$A:$A,$C58)/1000 -> -0.33328 | L58: =-SUMIFS('P&L'!K:K,'P&L'!$A:$A,$C58)/1000 -> -0.79241 | M58: =-SUMIFS('P&L'!L:L,'P&L'!$A:$A,$C58)/1000 -> -0.74154 | N58: =-SUMIFS('P&L'!M:M,'P&L'!$A:$A,$C58)/1000 -> -0.96838 | O58: =-SUMIFS('P&L'!N:N,'P&L'!$A:$A,$C58)/1000 -> -0.61969 | P58: =-SUMIFS('P&L'!O:O,'P&L'!$A:$A,$C58)/1000 -> -1.11731 | Q58: =-SUMIFS('P&L'!P:P,'P&L'!$A:$A,$C58)/1000 -> -1.24297 | R58: =-SUMIFS('P&L'!Q:Q,'P&L'!$A:$A,$C58)/1000 -> -1.13747 | S58: =-SUMIFS('P&L'!R:R,'P&L'!$A:$A,$C58)/1000 -> -1.54918 | T58: =-SUMIFS('P&L'!S:S,'P&L'!$A:$A,$C58)/1000 -> -1.64141 | U58: =-SUMIFS('P&L'!T:T,'P&L'!$A:$A,$C58)/1000 -> -1.67364 | V58: =-SUMIFS('P&L'!U:U,'P&L'!$A:$A,$C58)/1000 -> -1.21819 | W58: =-SUMIFS('P&L'!V:V,'P&L'!$A:$A,$C58)/1000 -> -1.53357 | X58: =-SUMIFS('P&L'!W:W,'P&L'!$A:$A,$C58)/1000 -> -0.97523 | Y58: =-SUMIFS('P&L'!X:X,'P&L'!$A:$A,$C58)/1000 -> -1.50072 | Z58: =-SUMIFS('P&L'!Y:Y,'P&L'!$A:$A,$C58)/1000 -> -0.86448 | AA58: =-SUMIFS('P&L'!Z:Z,'P&L'!$A:$A,$C58)/1000 -> -0.84474 | AB58: =-SUMIFS('P&L'!AA:AA,'P&L'!$A:$A,$C58)/1000 -> -1.22239 | AC58: =-SUMIFS('P&L'!AB:AB,'P&L'!$A:$A,$C58)/1000 -> -1.24925 | AD58: =-SUMIFS('P&L'!AC:AC,'P&L'!$A:$A,$C58)/1000 -> -1.16911 | AE58: =-SUMIFS('P&L'!AD:AD,'P&L'!$A:$A,$C58)/1000 -> -0.66938 | AF58: =-SUMIFS('P&L'!AE:AE,'P&L'!$A:$A,$C58)/1000 -> -1.29408 | AG58: =-SUMIFS('P&L'!AF:AF,'P&L'!$A:$A,$C58)/1000 -> -1.46802 | AH58: =-SUMIFS('P&L'!AG:AG,'P&L'!$A:$A,$C58)/1000 -> -1.48142 | AK58: =SUMIFS($CC58:$CE58,$CC$1:$CE$1,AK$3)*AK$24 -> -3.8479987 | AL58: =SUMIFS($CC58:$CE58,$CC$1:$CE$1,AL$3)*AL$24 -> -3.8479987 | AM58: =SUMIFS($CC58:$CE58,$CC$1:$CE$1,AM$3)*AM$24 -> -1.2826662 | AN58: =SUMIFS($CC58:$CE58,$CC$1:$CE$1,AN$3)*AN$24 -> -1.2826662 | AO58: =SUMIFS($CC58:$CE58,$CC$1:$CE$1,AO$3)*AO$24 -> 0 | AP58: =SUMIFS($CC58:$CE58,$CC$1:$CE$1,AP$3)*AP$24 -> 0 | AQ58: =SUMIFS($CC58:$CE58,$CC$1:$CE$1,AQ$3)*AQ$24 -> -0.64133312 | AR58: =SUMIFS($CC58:$CE58,$CC$1:$CE$1,AR$3)*AR$24 -> -2.5653325 | ... BT58: =SUMIFS($CC58:$CE58,$CC$1:$CE$1,BT$3)*BT$24 -> -2.6446144 | BU58: =BI58 -> -3.5261526 | BV58: =BJ58 -> -3.9669216 | BW58: =BK58 -> -3.5261526 | BX58: =BL58 -> -2.6446144 | BZ58: =SUMIFS($D58:$AJ58,$D$1:$AJ$1,BZ$9) -> -10.47271 | CA58: =SUMIFS($D58:$AJ58,$D$1:$AJ$1,CA$9) -> -15.29891 | CB58: =SUMIFS($D58:$AJ58,$D$3:$AJ$3,"LTM") -> -14.27239 | CC58: =SUM(CC52:CC53,CC56:CC57,CC59)*CG58 -> -25.653325 | CD58: =SUM(CD52:CD53,CD56:CD57,CD59)*CH58 -> -29.793031 | CE58: =SUM(CE52:CE53,CE56:CE57,CE59)*CI58 -> -35.261526 | CG58: =$CN58 -> 0.11553971 | CH58: =$CN58 -> 0.11553971 | CI58: =$CN58 -> 0.11553971 | CK58: =IFERROR(CB58/SUM(CB52:CB55,CB56:CB57,CB59),0) -> 0.054655903 | CM58: =-SUMIFS('FY25 By Venue Financials'!$N:$N,'FY25 By Venue Financials'!$A:$A,$C58) -> -177.87777 | CN58: =CM58/SUM(CM52:CM55,CM56:CM57,CM59) -> 0.11553971 | CP58: % Total Other Payroll | CQ58: NA
C59: Other Payroll | D59: =-SUMIFS('P&L'!C:C,'P&L'!$A:$A,$C59)/1000 -> 0 | E59: =-SUMIFS('P&L'!D:D,'P&L'!$A:$A,$C59)/1000 -> 0 | F59: =-SUMIFS('P&L'!E:E,'P&L'!$A:$A,$C59)/1000 -> 0 | G59: =-SUMIFS('P&L'!F:F,'P&L'!$A:$A,$C59)/1000 -> 0 | H59: =-SUMIFS('P&L'!G:G,'P&L'!$A:$A,$C59)/1000 -> 0 | I59: =-SUMIFS('P&L'!H:H,'P&L'!$A:$A,$C59)/1000 -> 0 | J59: =-SUMIFS('P&L'!I:I,'P&L'!$A:$A,$C59)/1000 -> 0 | K59: =-SUMIFS('P&L'!J:J,'P&L'!$A:$A,$C59)/1000 -> 0 | L59: =-SUMIFS('P&L'!K:K,'P&L'!$A:$A,$C59)/1000 -> 0 | M59: =-SUMIFS('P&L'!L:L,'P&L'!$A:$A,$C59)/1000 -> 0 | N59: =-SUMIFS('P&L'!M:M,'P&L'!$A:$A,$C59)/1000 -> 0 | O59: =-SUMIFS('P&L'!N:N,'P&L'!$A:$A,$C59)/1000 -> 0 | P59: =-SUMIFS('P&L'!O:O,'P&L'!$A:$A,$C59)/1000 -> 0 | Q59: =-SUMIFS('P&L'!P:P,'P&L'!$A:$A,$C59)/1000 -> 0 | R59: =-SUMIFS('P&L'!Q:Q,'P&L'!$A:$A,$C59)/1000 -> 0 | S59: =-SUMIFS('P&L'!R:R,'P&L'!$A:$A,$C59)/1000 -> 0 | T59: =-SUMIFS('P&L'!S:S,'P&L'!$A:$A,$C59)/1000 -> 0 | U59: =-SUMIFS('P&L'!T:T,'P&L'!$A:$A,$C59)/1000 -> 0 | V59: =-SUMIFS('P&L'!U:U,'P&L'!$A:$A,$C59)/1000 -> 0 | W59: =-SUMIFS('P&L'!V:V,'P&L'!$A:$A,$C59)/1000 -> 0 | X59: =-SUMIFS('P&L'!W:W,'P&L'!$A:$A,$C59)/1000 -> 0 | Y59: =-SUMIFS('P&L'!X:X,'P&L'!$A:$A,$C59)/1000 -> 0 | Z59: =-SUMIFS('P&L'!Y:Y,'P&L'!$A:$A,$C59)/1000 -> 0 | AA59: =-SUMIFS('P&L'!Z:Z,'P&L'!$A:$A,$C59)/1000 -> 0 | AB59: =-SUMIFS('P&L'!AA:AA,'P&L'!$A:$A,$C59)/1000 -> 0 | AC59: =-SUMIFS('P&L'!AB:AB,'P&L'!$A:$A,$C59)/1000 -> 0 | AD59: =-SUMIFS('P&L'!AC:AC,'P&L'!$A:$A,$C59)/1000 -> 0 | AE59: =-SUMIFS('P&L'!AD:AD,'P&L'!$A:$A,$C59)/1000 -> 0 | AF59: =-SUMIFS('P&L'!AE:AE,'P&L'!$A:$A,$C59)/1000 -> 0 | AG59: =-SUMIFS('P&L'!AF:AF,'P&L'!$A:$A,$C59)/1000 -> 0 | AH59: =-SUMIFS('P&L'!AG:AG,'P&L'!$A:$A,$C59)/1000 -> 0 | AK59: =SUMIFS($CC59:$CE59,$CC$1:$CE$1,AK$3)*AK$24 -> -0.042673468 | AL59: =SUMIFS($CC59:$CE59,$CC$1:$CE$1,AL$3)*AL$24 -> -0.042673468 | AM59: =SUMIFS($CC59:$CE59,$CC$1:$CE$1,AM$3)*AM$24 -> -0.014224489 | AN59: =SUMIFS($CC59:$CE59,$CC$1:$CE$1,AN$3)*AN$24 -> -0.014224489 | AO59: =SUMIFS($CC59:$CE59,$CC$1:$CE$1,AO$3)*AO$24 -> 0 | AP59: =SUMIFS($CC59:$CE59,$CC$1:$CE$1,AP$3)*AP$24 -> 0 | AQ59: =SUMIFS($CC59:$CE59,$CC$1:$CE$1,AQ$3)*AQ$24 -> -0.0071122447 | AR59: =SUMIFS($CC59:$CE59,$CC$1:$CE$1,AR$3)*AR$24 -> -0.028448979 | ... BT59: =SUMIFS($CC59:$CE59,$CC$1:$CE$1,BT$3)*BT$24 -> -0.061254587 | BU59: =BI59 -> -0.081672783 | BV59: =BJ59 -> -0.091881881 | BW59: =BK59 -> -0.081672783 | BX59: =BL59 -> -0.061254587 | BZ59: =SUMIFS($D59:$AJ59,$D$1:$AJ$1,BZ$9) -> 0 | CA59: =SUMIFS($D59:$AJ59,$D$1:$AJ$1,CA$9) -> 0 | CB59: =SUMIFS($D59:$AJ59,$D$3:$AJ$3,"LTM") -> 0 | CC59: =CC$38*CG59 -> -0.28448979 | CD59: =CD$38*CH59 -> -0.54917146 | CE59: =CE$38*CI59 -> -0.81672783 | CG59: =$CN59 -> -0.00031387544 | CH59: =$CN59 -> -0.00031387544 | CI59: =$CN59 -> -0.00031387544 | CK59: =IFERROR(CB59/CB$38,0) -> 0 | CM59: =-SUMIFS('FY25 By Venue Financials'!$N:$N,'FY25 By Venue Financials'!$A:$A,$C59) -> -2.2139 | CN59: =IFERROR(CM59/CM$38,0) -> -0.00031387544 | CP59: % Total Rev | CQ59: % of Total Events
C61: Total Payroll | D61: =SUM(D52:D60) -> -11.43195 | E61: =SUM(E52:E60) -> -12.18349 | F61: =SUM(F52:F60) -> -20.25708 | G61: =SUM(G52:G60) -> -17.77781 | H61: =SUM(H52:H60) -> -21.49107 | I61: =SUM(I52:I60) -> -22.74277 | J61: =SUM(J52:J60) -> -17.27022 | K61: =SUM(K52:K60) -> -10.68113 | ... AH61: =SUM(AH52:AH60) -> -27.79985 | AK61: =SUM(AK52:AK60) -> -32.857424 | AL61: =SUM(AL52:AL60) -> -32.857424 | AM61: =SUM(AM52:AM60) -> -23.221364 | AN61: =SUM(AN52:AN60) -> -23.221364 | AO61: =SUM(AO52:AO60) -> -18.403333 | AP61: =SUM(AP52:AP60) -> -18.403333 | AQ61: =SUM(AQ52:AQ60) -> -20.812348 | AR61: =SUM(AR52:AR60) -> -28.039394 | ... BX61: =SUM(BX52:BX60) -> -40.078899 | BZ61: =SUM(BZ52:BZ60) -> -195.05191 | CA61: =SUM(CA52:CA60) -> -229.60539 | CB61: =SUM(CB52:CB60) -> -275.40411 | CC61: =SUM(CC52:CC60) -> -317.2006 | CD61: =SUM(CD52:CD60) -> -397.85791 | CE61: =SUM(CE52:CE60) -> -508.35319 | CG61: =IFERROR(CC61/CC$38,0) -> -0.34996504 | CH61: =IFERROR(CD61/CD$38,0) -> -0.22739315 | CI61: =IFERROR(CE61/CE$38,0) -> -0.19536445 | CK61: =IFERROR(CB61/CB$38,0) -> -0.49104791 | CM61: =SUM(CM52:CM60) -> -1717.4158 | CN61: =IFERROR(CM61/CM$38,0) -> -0.24348644 | CP61: % Total Rev
C63: Operating Expenses
C64: Marketing Expense | D64: =-SUMIFS('P&L'!C:C,'P&L'!$A:$A,$C64)/1000 -> -0.215 | E64: =-SUMIFS('P&L'!D:D,'P&L'!$A:$A,$C64)/1000 -> -0.765 | F64: =-SUMIFS('P&L'!E:E,'P&L'!$A:$A,$C64)/1000 -> -1.23625 | G64: =-SUMIFS('P&L'!F:F,'P&L'!$A:$A,$C64)/1000 -> -1.78272 | H64: =-SUMIFS('P&L'!G:G,'P&L'!$A:$A,$C64)/1000 -> -0.31053 | I64: =-SUMIFS('P&L'!H:H,'P&L'!$A:$A,$C64)/1000 -> -1.66 | J64: =-SUMIFS('P&L'!I:I,'P&L'!$A:$A,$C64)/1000 -> -6.215 | K64: =-SUMIFS('P&L'!J:J,'P&L'!$A:$A,$C64)/1000 -> -0.215 | L64: =-SUMIFS('P&L'!K:K,'P&L'!$A:$A,$C64)/1000 -> -3.2825 | M64: =-SUMIFS('P&L'!L:L,'P&L'!$A:$A,$C64)/1000 -> -1.4375 | N64: =-SUMIFS('P&L'!M:M,'P&L'!$A:$A,$C64)/1000 -> -0.06 | O64: =-SUMIFS('P&L'!N:N,'P&L'!$A:$A,$C64)/1000 -> -0.73969 | P64: =-SUMIFS('P&L'!O:O,'P&L'!$A:$A,$C64)/1000 -> -5.1778 | Q64: =-SUMIFS('P&L'!P:P,'P&L'!$A:$A,$C64)/1000 -> -0.82486 | R64: =-SUMIFS('P&L'!Q:Q,'P&L'!$A:$A,$C64)/1000 -> -5.45871 | S64: =-SUMIFS('P&L'!R:R,'P&L'!$A:$A,$C64)/1000 -> -3.38727 | T64: =-SUMIFS('P&L'!S:S,'P&L'!$A:$A,$C64)/1000 -> -3.84306 | U64: =-SUMIFS('P&L'!T:T,'P&L'!$A:$A,$C64)/1000 -> -3.30805 | V64: =-SUMIFS('P&L'!U:U,'P&L'!$A:$A,$C64)/1000 -> -3.02144 | W64: =-SUMIFS('P&L'!V:V,'P&L'!$A:$A,$C64)/1000 -> -3.02165 | X64: =-SUMIFS('P&L'!W:W,'P&L'!$A:$A,$C64)/1000 -> -3.01644 | Y64: =-SUMIFS('P&L'!X:X,'P&L'!$A:$A,$C64)/1000 -> -3.47602 | Z64: =-SUMIFS('P&L'!Y:Y,'P&L'!$A:$A,$C64)/1000 -> -3.06401 | AA64: =-SUMIFS('P&L'!Z:Z,'P&L'!$A:$A,$C64)/1000 -> -5.26402 | AB64: =-SUMIFS('P&L'!AA:AA,'P&L'!$A:$A,$C64)/1000 -> -0.85562 | AC64: =-SUMIFS('P&L'!AB:AB,'P&L'!$A:$A,$C64)/1000 -> 0 | AD64: =-SUMIFS('P&L'!AC:AC,'P&L'!$A:$A,$C64)/1000 -> -2.95 | AE64: =-SUMIFS('P&L'!AD:AD,'P&L'!$A:$A,$C64)/1000 -> 0 | AF64: =-SUMIFS('P&L'!AE:AE,'P&L'!$A:$A,$C64)/1000 -> 0 | AG64: =-SUMIFS('P&L'!AF:AF,'P&L'!$A:$A,$C64)/1000 -> -0.29905 | AH64: =-SUMIFS('P&L'!AG:AG,'P&L'!$A:$A,$C64)/1000 -> 0 | AK64: =SUMIFS($CC64:$CE64,$CC$1:$CE$1,AK$3)/12 -> -5.5600229 | AL64: =SUMIFS($CC64:$CE64,$CC$1:$CE$1,AL$3)/12 -> -5.5600229 | AM64: =SUMIFS($CC64:$CE64,$CC$1:$CE$1,AM$3)/12 -> -5.5600229 | AN64: =SUMIFS($CC64:$CE64,$CC$1:$CE$1,AN$3)/12 -> -5.5600229 | AO64: =SUMIFS($CC64:$CE64,$CC$1:$CE$1,AO$3)/12 -> -5.5600229 | AP64: =SUMIFS($CC64:$CE64,$CC$1:$CE$1,AP$3)/12 -> -5.5600229 | AQ64: =SUMIFS($CC64:$CE64,$CC$1:$CE$1,AQ$3)/12 -> -5.5600229 | AR64: =SUMIFS($CC64:$CE64,$CC$1:$CE$1,AR$3)/12 -> -5.5600229 | ... BT64: =SUMIFS($CC64:$CE64,$CC$1:$CE$1,BT$3)/12 -> -6.1299253 | BU64: =BI64 -> -6.1299253 | BV64: =BJ64 -> -6.1299253 | BW64: =BK64 -> -6.1299253 | BX64: =BL64 -> -6.1299253 | BZ64: =SUMIFS($D64:$AJ64,$D$1:$AJ$1,BZ$9) -> -17.91919 | CA64: =SUMIFS($D64:$AJ64,$D$1:$AJ$1,CA$9) -> -42.86333 | CB64: =SUMIFS($D64:$AJ64,$D$3:$AJ$3,"LTM") -> -21.94681 | CC64: =CM64/2 -> -66.720275 | CD64: =CC64*(1+CH64) -> -70.056289 | CE64: =CD64*(1+CI64) -> -73.559103 | CG64: 0 | CH64: 0.05 | CI64: 0.05 | CM64: =-SUMIFS('FY25 By Venue Financials'!$N:$N,'FY25 By Venue Financials'!$A:$A,$C64) -> -133.44055 | CN64: =IFERROR(CM64/CM$38,0) -> -0.01891852 | CP64: 1/2 ATL spend today - 5% YoY growth | CQ64: Split evently
C65: Maintenance Expense | D65: =-SUMIFS('P&L'!C:C,'P&L'!$A:$A,$C65)/1000 -> -24.08154 | E65: =-SUMIFS('P&L'!D:D,'P&L'!$A:$A,$C65)/1000 -> -8.98599 | F65: =-SUMIFS('P&L'!E:E,'P&L'!$A:$A,$C65)/1000 -> -11.15525 | G65: =-SUMIFS('P&L'!F:F,'P&L'!$A:$A,$C65)/1000 -> -13.01789 | H65: =-SUMIFS('P&L'!G:G,'P&L'!$A:$A,$C65)/1000 -> -2.62663 | I65: =-SUMIFS('P&L'!H:H,'P&L'!$A:$A,$C65)/1000 -> -2.96629 | J65: =-SUMIFS('P&L'!I:I,'P&L'!$A:$A,$C65)/1000 -> -6.72996 | K65: =-SUMIFS('P&L'!J:J,'P&L'!$A:$A,$C65)/1000 -> -21.1848 | L65: =-SUMIFS('P&L'!K:K,'P&L'!$A:$A,$C65)/1000 -> -19.67063 | M65: =-SUMIFS('P&L'!L:L,'P&L'!$A:$A,$C65)/1000 -> -7.57105 | N65: =-SUMIFS('P&L'!M:M,'P&L'!$A:$A,$C65)/1000 -> -6.51699 | O65: =-SUMIFS('P&L'!N:N,'P&L'!$A:$A,$C65)/1000 -> -3.16774 | P65: =-SUMIFS('P&L'!O:O,'P&L'!$A:$A,$C65)/1000 -> -4.46213 | Q65: =-SUMIFS('P&L'!P:P,'P&L'!$A:$A,$C65)/1000 -> -2.97769 | R65: =-SUMIFS('P&L'!Q:Q,'P&L'!$A:$A,$C65)/1000 -> -10.95413 | S65: =-SUMIFS('P&L'!R:R,'P&L'!$A:$A,$C65)/1000 -> -7.29879 | T65: =-SUMIFS('P&L'!S:S,'P&L'!$A:$A,$C65)/1000 -> -11.85417 | U65: =-SUMIFS('P&L'!T:T,'P&L'!$A:$A,$C65)/1000 -> -5.35186 | V65: =-SUMIFS('P&L'!U:U,'P&L'!$A:$A,$C65)/1000 -> -12.68029 | W65: =-SUMIFS('P&L'!V:V,'P&L'!$A:$A,$C65)/1000 -> -6.42021 | X65: =-SUMIFS('P&L'!W:W,'P&L'!$A:$A,$C65)/1000 -> -2.42899 | Y65: =-SUMIFS('P&L'!X:X,'P&L'!$A:$A,$C65)/1000 -> -3.2615 | Z65: =-SUMIFS('P&L'!Y:Y,'P&L'!$A:$A,$C65)/1000 -> -10.65582 | AA65: =-SUMIFS('P&L'!Z:Z,'P&L'!$A:$A,$C65)/1000 -> -16.94357 | AB65: =-SUMIFS('P&L'!AA:AA,'P&L'!$A:$A,$C65)/1000 -> -6.47993 | AC65: =-SUMIFS('P&L'!AB:AB,'P&L'!$A:$A,$C65)/1000 -> -12.02461 | AD65: =-SUMIFS('P&L'!AC:AC,'P&L'!$A:$A,$C65)/1000 -> -4.63376 | AE65: =-SUMIFS('P&L'!AD:AD,'P&L'!$A:$A,$C65)/1000 -> 2.56751 | AF65: =-SUMIFS('P&L'!AE:AE,'P&L'!$A:$A,$C65)/1000 -> -1.9365 | AG65: =-SUMIFS('P&L'!AF:AF,'P&L'!$A:$A,$C65)/1000 -> -6.23343 | AH65: =-SUMIFS('P&L'!AG:AG,'P&L'!$A:$A,$C65)/1000 -> -4.60474 | AK65: =SUMIFS($CC65:$CE65,$CC$1:$CE$1,AK$3)/12 -> -6.2440641 | AL65: =SUMIFS($CC65:$CE65,$CC$1:$CE$1,AL$3)/12 -> -6.2440641 | AM65: =SUMIFS($CC65:$CE65,$CC$1:$CE$1,AM$3)/12 -> -6.2440641 | AN65: =SUMIFS($CC65:$CE65,$CC$1:$CE$1,AN$3)/12 -> -6.2440641 | AO65: =SUMIFS($CC65:$CE65,$CC$1:$CE$1,AO$3)/12 -> -6.2440641 | AP65: =SUMIFS($CC65:$CE65,$CC$1:$CE$1,AP$3)/12 -> -6.2440641 | AQ65: =SUMIFS($CC65:$CE65,$CC$1:$CE$1,AQ$3)/12 -> -6.2440641 | AR65: =SUMIFS($CC65:$CE65,$CC$1:$CE$1,AR$3)/12 -> -6.2440641 | ... BT65: =SUMIFS($CC65:$CE65,$CC$1:$CE$1,BT$3)/12 -> -12.488128 | BU65: =BI65 -> -12.488128 | BV65: =BJ65 -> -12.488128 | BW65: =BK65 -> -12.488128 | BX65: =BL65 -> -12.488128 | BZ65: =SUMIFS($D65:$AJ65,$D$1:$AJ$1,BZ$9) -> -127.67476 | CA65: =SUMIFS($D65:$AJ65,$D$1:$AJ$1,CA$9) -> -95.28915 | CB65: =SUMIFS($D65:$AJ65,$D$3:$AJ$3,"LTM") -> -73.05555 | CC65: =CG65*CC$23 -> -74.928769 | CD65: =CH65*CD$23 -> -121.75925 | CE65: =CI65*CE$23 -> -149.85754 | CG65: =$CK65 -> -1.8732192 | CH65: =$CK65 -> -1.8732192 | CI65: =$CK65 -> -1.8732192 | CK65: =IFERROR(CB65/CK$23,0) -> -1.8732192 | CM65: =-SUMIFS('FY25 By Venue Financials'!$N:$N,'FY25 By Venue Financials'!$A:$A,$C65) -> -79.4758 | CN65: =CM65/CM$23 -> -0.32439102 | CP65: $ / Event | CQ65: Split evently
C66: Utilities Expense | D66: =-SUMIFS('P&L'!C:C,'P&L'!$A:$A,$C66)/1000 -> -4.3143 | E66: =-SUMIFS('P&L'!D:D,'P&L'!$A:$A,$C66)/1000 -> -3.7412 | F66: =-SUMIFS('P&L'!E:E,'P&L'!$A:$A,$C66)/1000 -> -3.67048 | G66: =-SUMIFS('P&L'!F:F,'P&L'!$A:$A,$C66)/1000 -> -2.76034 | H66: =-SUMIFS('P&L'!G:G,'P&L'!$A:$A,$C66)/1000 -> -2.84584 | I66: =-SUMIFS('P&L'!H:H,'P&L'!$A:$A,$C66)/1000 -> -3.52263 | J66: =-SUMIFS('P&L'!I:I,'P&L'!$A:$A,$C66)/1000 -> -4.39437 | K66: =-SUMIFS('P&L'!J:J,'P&L'!$A:$A,$C66)/1000 -> -4.86317 | L66: =-SUMIFS('P&L'!K:K,'P&L'!$A:$A,$C66)/1000 -> -3.85886 | M66: =-SUMIFS('P&L'!L:L,'P&L'!$A:$A,$C66)/1000 -> -5.42427 | N66: =-SUMIFS('P&L'!M:M,'P&L'!$A:$A,$C66)/1000 -> -0.75307 | O66: =-SUMIFS('P&L'!N:N,'P&L'!$A:$A,$C66)/1000 -> -2.91408 | P66: =-SUMIFS('P&L'!O:O,'P&L'!$A:$A,$C66)/1000 -> -2.86137 | Q66: =-SUMIFS('P&L'!P:P,'P&L'!$A:$A,$C66)/1000 -> -3.24229 | R66: =-SUMIFS('P&L'!Q:Q,'P&L'!$A:$A,$C66)/1000 -> -4.52307 | S66: =-SUMIFS('P&L'!R:R,'P&L'!$A:$A,$C66)/1000 -> -5.31037 | T66: =-SUMIFS('P&L'!S:S,'P&L'!$A:$A,$C66)/1000 -> -1.76649 | U66: =-SUMIFS('P&L'!T:T,'P&L'!$A:$A,$C66)/1000 -> -4.48901 | V66: =-SUMIFS('P&L'!U:U,'P&L'!$A:$A,$C66)/1000 -> -3.62304 | W66: =-SUMIFS('P&L'!V:V,'P&L'!$A:$A,$C66)/1000 -> -3.77751 | X66: =-SUMIFS('P&L'!W:W,'P&L'!$A:$A,$C66)/1000 -> -3.92138 | Y66: =-SUMIFS('P&L'!X:X,'P&L'!$A:$A,$C66)/1000 -> -3.10076 | Z66: =-SUMIFS('P&L'!Y:Y,'P&L'!$A:$A,$C66)/1000 -> -2.85336 | AA66: =-SUMIFS('P&L'!Z:Z,'P&L'!$A:$A,$C66)/1000 -> -3.45182 | AB66: =-SUMIFS('P&L'!AA:AA,'P&L'!$A:$A,$C66)/1000 -> -2.75384 | AC66: =-SUMIFS('P&L'!AB:AB,'P&L'!$A:$A,$C66)/1000 -> -2.64049 | AD66: =-SUMIFS('P&L'!AC:AC,'P&L'!$A:$A,$C66)/1000 -> -3.08671 | AE66: =-SUMIFS('P&L'!AD:AD,'P&L'!$A:$A,$C66)/1000 -> -2.39174 | AF66: =-SUMIFS('P&L'!AE:AE,'P&L'!$A:$A,$C66)/1000 -> -2.64114 | AG66: =-SUMIFS('P&L'!AF:AF,'P&L'!$A:$A,$C66)/1000 -> -2.6137 | AH66: =-SUMIFS('P&L'!AG:AG,'P&L'!$A:$A,$C66)/1000 -> -5.2922 | AK66: =SUMIFS($CC66:$CE66,$CC$1:$CE$1,AK$3)*AK$24 -> -5.9268692 | AL66: =SUMIFS($CC66:$CE66,$CC$1:$CE$1,AL$3)*AL$24 -> -5.9268692 | AM66: =SUMIFS($CC66:$CE66,$CC$1:$CE$1,AM$3)*AM$24 -> -1.9756231 | AN66: =SUMIFS($CC66:$CE66,$CC$1:$CE$1,AN$3)*AN$24 -> -1.9756231 | AO66: =SUMIFS($CC66:$CE66,$CC$1:$CE$1,AO$3)*AO$24 -> 0 | AP66: =SUMIFS($CC66:$CE66,$CC$1:$CE$1,AP$3)*AP$24 -> 0 | AQ66: =SUMIFS($CC66:$CE66,$CC$1:$CE$1,AQ$3)*AQ$24 -> -0.98781154 | AR66: =SUMIFS($CC66:$CE66,$CC$1:$CE$1,AR$3)*AR$24 -> -3.9512462 | ... BT66: =SUMIFS($CC66:$CE66,$CC$1:$CE$1,BT$3)*BT$24 -> -5.9268692 | BU66: =BI66 -> -7.9024923 | BV66: =BJ66 -> -8.8903038 | BW66: =BK66 -> -7.9024923 | BX66: =BL66 -> -5.9268692 | BZ66: =SUMIFS($D66:$AJ66,$D$1:$AJ$1,BZ$9) -> -43.06261 | CA66: =SUMIFS($D66:$AJ66,$D$1:$AJ$1,CA$9) -> -42.92047 | CB66: =SUMIFS($D66:$AJ66,$D$3:$AJ$3,"LTM") -> -38.52465 | CC66: =CG66*CC$23 -> -39.512462 | CD66: =CH66*CD$23 -> -64.20775 | CE66: =CI66*CE$23 -> -79.024923 | CG66: =$CK66 -> -0.98781154 | CH66: =$CK66 -> -0.98781154 | CI66: =$CK66 -> -0.98781154 | CK66: =IFERROR(CB66/CK$23,0) -> -0.98781154 | CM66: =-SUMIFS('FY25 By Venue Financials'!$N:$N,'FY25 By Venue Financials'!$A:$A,$C66) -> -114.89324 | CN66: =CM66/CM$23 -> -0.468952 | CP66: $ / Event | CQ66: % of Total Events
C67: Office Expense | D67: =-SUMIFS('P&L'!C:C,'P&L'!$A:$A,$C67)/1000 -> -0.50577 | E67: =-SUMIFS('P&L'!D:D,'P&L'!$A:$A,$C67)/1000 -> -0.98901 | F67: =-SUMIFS('P&L'!E:E,'P&L'!$A:$A,$C67)/1000 -> -2.25833 | G67: =-SUMIFS('P&L'!F:F,'P&L'!$A:$A,$C67)/1000 -> -0.80603 | H67: =-SUMIFS('P&L'!G:G,'P&L'!$A:$A,$C67)/1000 -> -0.16303 | I67: =-SUMIFS('P&L'!H:H,'P&L'!$A:$A,$C67)/1000 -> 0 | J67: =-SUMIFS('P&L'!I:I,'P&L'!$A:$A,$C67)/1000 -> -0.0688 | K67: =-SUMIFS('P&L'!J:J,'P&L'!$A:$A,$C67)/1000 -> -0.005 | L67: =-SUMIFS('P&L'!K:K,'P&L'!$A:$A,$C67)/1000 -> -0.18792 | M67: =-SUMIFS('P&L'!L:L,'P&L'!$A:$A,$C67)/1000 -> -0.07986 | N67: =-SUMIFS('P&L'!M:M,'P&L'!$A:$A,$C67)/1000 -> -0.01969 | O67: =-SUMIFS('P&L'!N:N,'P&L'!$A:$A,$C67)/1000 -> -0.45348 | P67: =-SUMIFS('P&L'!O:O,'P&L'!$A:$A,$C67)/1000 -> -0.26663 | Q67: =-SUMIFS('P&L'!P:P,'P&L'!$A:$A,$C67)/1000 -> -0.11664 | R67: =-SUMIFS('P&L'!Q:Q,'P&L'!$A:$A,$C67)/1000 -> 0 | S67: =-SUMIFS('P&L'!R:R,'P&L'!$A:$A,$C67)/1000 -> 0 | T67: =-SUMIFS('P&L'!S:S,'P&L'!$A:$A,$C67)/1000 -> 0 | U67: =-SUMIFS('P&L'!T:T,'P&L'!$A:$A,$C67)/1000 -> -0.12802 | V67: =-SUMIFS('P&L'!U:U,'P&L'!$A:$A,$C67)/1000 -> 0 | W67: =-SUMIFS('P&L'!V:V,'P&L'!$A:$A,$C67)/1000 -> 0 | X67: =-SUMIFS('P&L'!W:W,'P&L'!$A:$A,$C67)/1000 -> 0 | Y67: =-SUMIFS('P&L'!X:X,'P&L'!$A:$A,$C67)/1000 -> 0 | Z67: =-SUMIFS('P&L'!Y:Y,'P&L'!$A:$A,$C67)/1000 -> 0 | AA67: =-SUMIFS('P&L'!Z:Z,'P&L'!$A:$A,$C67)/1000 -> -0.17999 | AB67: =-SUMIFS('P&L'!AA:AA,'P&L'!$A:$A,$C67)/1000 -> -0.31798 | AC67: =-SUMIFS('P&L'!AB:AB,'P&L'!$A:$A,$C67)/1000 -> -0.14103 | AD67: =-SUMIFS('P&L'!AC:AC,'P&L'!$A:$A,$C67)/1000 -> -0.17168 | AE67: =-SUMIFS('P&L'!AD:AD,'P&L'!$A:$A,$C67)/1000 -> 0 | AF67: =-SUMIFS('P&L'!AE:AE,'P&L'!$A:$A,$C67)/1000 -> 0 | AG67: =-SUMIFS('P&L'!AF:AF,'P&L'!$A:$A,$C67)/1000 -> 0 | AH67: =-SUMIFS('P&L'!AG:AG,'P&L'!$A:$A,$C67)/1000 -> -0.09498 | AK67: =SUMIFS($CC67:$CE67,$CC$1:$CE$1,AK$3)/12 -> -0.52124111 | AL67: =SUMIFS($CC67:$CE67,$CC$1:$CE$1,AL$3)/12 -> -0.52124111 | AM67: =SUMIFS($CC67:$CE67,$CC$1:$CE$1,AM$3)/12 -> -0.52124111 | AN67: =SUMIFS($CC67:$CE67,$CC$1:$CE$1,AN$3)/12 -> -0.52124111 | AO67: =SUMIFS($CC67:$CE67,$CC$1:$CE$1,AO$3)/12 -> -0.52124111 | AP67: =SUMIFS($CC67:$CE67,$CC$1:$CE$1,AP$3)/12 -> -0.52124111 | AQ67: =SUMIFS($CC67:$CE67,$CC$1:$CE$1,AQ$3)/12 -> -0.52124111 | AR67: =SUMIFS($CC67:$CE67,$CC$1:$CE$1,AR$3)/12 -> -0.52124111 | ... BT67: =SUMIFS($CC67:$CE67,$CC$1:$CE$1,BT$3)/12 -> -1.4964056 | BU67: =BI67 -> -1.4964056 | BV67: =BJ67 -> -1.4964056 | BW67: =BK67 -> -1.4964056 | BX67: =BL67 -> -1.4964056 | BZ67: =SUMIFS($D67:$AJ67,$D$1:$AJ$1,BZ$9) -> -5.53692 | CA67: =SUMIFS($D67:$AJ67,$D$1:$AJ$1,CA$9) -> -0.69128 | CB67: =SUMIFS($D67:$AJ67,$D$3:$AJ$3,"LTM") -> -0.90566 | CC67: =CC$38*CG67 -> -6.2548933 | CD67: =CD$38*CH67 -> -12.074278 | CE67: =CE$38*CI67 -> -17.956867 | CG67: =$CN67 -> -0.0069009766 | CH67: =$CN67 -> -0.0069009766 | CI67: =$CN67 -> -0.0069009766 | CK67: =IFERROR(CB67/CB$38,0) -> -0.0016147996 | CM67: =-SUMIFS('FY25 By Venue Financials'!$N:$N,'FY25 By Venue Financials'!$A:$A,$C67) -> -48.67559 | CN67: =IFERROR(CM67/CM$38,0) -> -0.0069009766 | CP67: % Total Rev | CQ67: Split evently
C68: Computer Expense | D68: =-SUMIFS('P&L'!C:C,'P&L'!$A:$A,$C68)/1000 -> -0.2509 | E68: =-SUMIFS('P&L'!D:D,'P&L'!$A:$A,$C68)/1000 -> -0.17361 | F68: =-SUMIFS('P&L'!E:E,'P&L'!$A:$A,$C68)/1000 -> -1.195 | G68: =-SUMIFS('P&L'!F:F,'P&L'!$A:$A,$C68)/1000 -> -0.37749 | H68: =-SUMIFS('P&L'!G:G,'P&L'!$A:$A,$C68)/1000 -> -0.2519 | I68: =-SUMIFS('P&L'!H:H,'P&L'!$A:$A,$C68)/1000 -> -0.3847 | J68: =-SUMIFS('P&L'!I:I,'P&L'!$A:$A,$C68)/1000 -> -0.18682 | K68: =-SUMIFS('P&L'!J:J,'P&L'!$A:$A,$C68)/1000 -> -2.61204 | L68: =-SUMIFS('P&L'!K:K,'P&L'!$A:$A,$C68)/1000 -> -0.52725 | M68: =-SUMIFS('P&L'!L:L,'P&L'!$A:$A,$C68)/1000 -> -1.19323 | N68: =-SUMIFS('P&L'!M:M,'P&L'!$A:$A,$C68)/1000 -> -1.0731 | O68: =-SUMIFS('P&L'!N:N,'P&L'!$A:$A,$C68)/1000 -> -8.2014 | P68: =-SUMIFS('P&L'!O:O,'P&L'!$A:$A,$C68)/1000 -> -0.24642 | Q68: =-SUMIFS('P&L'!P:P,'P&L'!$A:$A,$C68)/1000 -> -0.83756 | R68: =-SUMIFS('P&L'!Q:Q,'P&L'!$A:$A,$C68)/1000 -> -1.47705 | S68: =-SUMIFS('P&L'!R:R,'P&L'!$A:$A,$C68)/1000 -> -0.39637 | T68: =-SUMIFS('P&L'!S:S,'P&L'!$A:$A,$C68)/1000 -> -0.42069 | U68: =-SUMIFS('P&L'!T:T,'P&L'!$A:$A,$C68)/1000 -> -0.50201 | V68: =-SUMIFS('P&L'!U:U,'P&L'!$A:$A,$C68)/1000 -> -0.39173 | W68: =-SUMIFS('P&L'!V:V,'P&L'!$A:$A,$C68)/1000 -> -0.28337 | X68: =-SUMIFS('P&L'!W:W,'P&L'!$A:$A,$C68)/1000 -> -0.19038 | Y68: =-SUMIFS('P&L'!X:X,'P&L'!$A:$A,$C68)/1000 -> -0.07688 | Z68: =-SUMIFS('P&L'!Y:Y,'P&L'!$A:$A,$C68)/1000 -> -0.30017 | AA68: =-SUMIFS('P&L'!Z:Z,'P&L'!$A:$A,$C68)/1000 -> -0.28169 | AB68: =-SUMIFS('P&L'!AA:AA,'P&L'!$A:$A,$C68)/1000 -> -1.28668 | AC68: =-SUMIFS('P&L'!AB:AB,'P&L'!$A:$A,$C68)/1000 -> -1.12588 | AD68: =-SUMIFS('P&L'!AC:AC,'P&L'!$A:$A,$C68)/1000 -> -2.31342 | AE68: =-SUMIFS('P&L'!AD:AD,'P&L'!$A:$A,$C68)/1000 -> -0.21718 | AF68: =-SUMIFS('P&L'!AE:AE,'P&L'!$A:$A,$C68)/1000 -> -0.70244 | AG68: =-SUMIFS('P&L'!AF:AF,'P&L'!$A:$A,$C68)/1000 -> -0.21718 | AH68: =-SUMIFS('P&L'!AG:AG,'P&L'!$A:$A,$C68)/1000 -> -0.13 | AK68: =SUMIFS($CC68:$CE68,$CC$1:$CE$1,AK$3)/12 -> -0.079848672 | AL68: =SUMIFS($CC68:$CE68,$CC$1:$CE$1,AL$3)/12 -> -0.079848672 | AM68: =SUMIFS($CC68:$CE68,$CC$1:$CE$1,AM$3)/12 -> -0.079848672 | AN68: =SUMIFS($CC68:$CE68,$CC$1:$CE$1,AN$3)/12 -> -0.079848672 | AO68: =SUMIFS($CC68:$CE68,$CC$1:$CE$1,AO$3)/12 -> -0.079848672 | AP68: =SUMIFS($CC68:$CE68,$CC$1:$CE$1,AP$3)/12 -> -0.079848672 | AQ68: =SUMIFS($CC68:$CE68,$CC$1:$CE$1,AQ$3)/12 -> -0.079848672 | AR68: =SUMIFS($CC68:$CE68,$CC$1:$CE$1,AR$3)/12 -> -0.079848672 | ... BT68: =SUMIFS($CC68:$CE68,$CC$1:$CE$1,BT$3)/12 -> -0.22923365 | BU68: =BI68 -> -0.22923365 | BV68: =BJ68 -> -0.22923365 | BW68: =BK68 -> -0.22923365 | BX68: =BL68 -> -0.22923365 | BZ68: =SUMIFS($D68:$AJ68,$D$1:$AJ$1,BZ$9) -> -16.42744 | CA68: =SUMIFS($D68:$AJ68,$D$1:$AJ$1,CA$9) -> -5.40432 | CB68: =SUMIFS($D68:$AJ68,$D$3:$AJ$3,"LTM") -> -7.12527 | CC68: =CC$38*CG68 -> -0.95818406 | CD68: =CD$38*CH68 -> -1.8496528 | CE68: =CE$38*CI68 -> -2.7508038 | CG68: =$CN68 -> -0.0010571573 | CH68: =$CN68 -> -0.0010571573 | CI68: =$CN68 -> -0.0010571573 | CK68: =IFERROR(CB68/CB$38,0) -> -0.012704418 | CM68: =-SUMIFS('FY25 By Venue Financials'!$N:$N,'FY25 By Venue Financials'!$A:$A,$C68) -> -7.45659 | CN68: =IFERROR(CM68/CM$38,0) -> -0.0010571573 | CP68: % Total Rev | CQ68: Split evently
C69: Automobile Expenses | D69: =-SUMIFS('P&L'!C:C,'P&L'!$A:$A,$C69)/1000 -> -0.26554 | E69: =-SUMIFS('P&L'!D:D,'P&L'!$A:$A,$C69)/1000 -> -2.15084 | F69: =-SUMIFS('P&L'!E:E,'P&L'!$A:$A,$C69)/1000 -> -0.64377 | G69: =-SUMIFS('P&L'!F:F,'P&L'!$A:$A,$C69)/1000 -> -0.61104 | H69: =-SUMIFS('P&L'!G:G,'P&L'!$A:$A,$C69)/1000 -> -0.54609 | I69: =-SUMIFS('P&L'!H:H,'P&L'!$A:$A,$C69)/1000 -> -1.04621 | J69: =-SUMIFS('P&L'!I:I,'P&L'!$A:$A,$C69)/1000 -> -0.39597 | K69: =-SUMIFS('P&L'!J:J,'P&L'!$A:$A,$C69)/1000 -> 0 | L69: =-SUMIFS('P&L'!K:K,'P&L'!$A:$A,$C69)/1000 -> 0 | M69: =-SUMIFS('P&L'!L:L,'P&L'!$A:$A,$C69)/1000 -> 0 | N69: =-SUMIFS('P&L'!M:M,'P&L'!$A:$A,$C69)/1000 -> 0 | O69: =-SUMIFS('P&L'!N:N,'P&L'!$A:$A,$C69)/1000 -> 0 | P69: =-SUMIFS('P&L'!O:O,'P&L'!$A:$A,$C69)/1000 -> -1.95599 | Q69: =-SUMIFS('P&L'!P:P,'P&L'!$A:$A,$C69)/1000 -> 0 | R69: =-SUMIFS('P&L'!Q:Q,'P&L'!$A:$A,$C69)/1000 -> 0 | S69: =-SUMIFS('P&L'!R:R,'P&L'!$A:$A,$C69)/1000 -> 0 | T69: =-SUMIFS('P&L'!S:S,'P&L'!$A:$A,$C69)/1000 -> 0 | U69: =-SUMIFS('P&L'!T:T,'P&L'!$A:$A,$C69)/1000 -> 0 | V69: =-SUMIFS('P&L'!U:U,'P&L'!$A:$A,$C69)/1000 -> 0 | W69: =-SUMIFS('P&L'!V:V,'P&L'!$A:$A,$C69)/1000 -> 0 | X69: =-SUMIFS('P&L'!W:W,'P&L'!$A:$A,$C69)/1000 -> -1.7199 | Y69: =-SUMIFS('P&L'!X:X,'P&L'!$A:$A,$C69)/1000 -> 0 | Z69: =-SUMIFS('P&L'!Y:Y,'P&L'!$A:$A,$C69)/1000 -> 0 | AA69: =-SUMIFS('P&L'!Z:Z,'P&L'!$A:$A,$C69)/1000 -> 0 | AB69: =-SUMIFS('P&L'!AA:AA,'P&L'!$A:$A,$C69)/1000 -> 0 | AC69: =-SUMIFS('P&L'!AB:AB,'P&L'!$A:$A,$C69)/1000 -> 0 | AD69: =-SUMIFS('P&L'!AC:AC,'P&L'!$A:$A,$C69)/1000 -> 0 | AE69: =-SUMIFS('P&L'!AD:AD,'P&L'!$A:$A,$C69)/1000 -> -0.02044 | AF69: =-SUMIFS('P&L'!AE:AE,'P&L'!$A:$A,$C69)/1000 -> 0 | AG69: =-SUMIFS('P&L'!AF:AF,'P&L'!$A:$A,$C69)/1000 -> 0 | AH69: =-SUMIFS('P&L'!AG:AG,'P&L'!$A:$A,$C69)/1000 -> -2.65504 | AK69: =SUMIFS($CC69:$CE69,$CC$1:$CE$1,AK$3)/12 -> -0.025501794 | AL69: =SUMIFS($CC69:$CE69,$CC$1:$CE$1,AL$3)/12 -> -0.025501794 | AM69: =SUMIFS($CC69:$CE69,$CC$1:$CE$1,AM$3)/12 -> -0.025501794 | AN69: =SUMIFS($CC69:$CE69,$CC$1:$CE$1,AN$3)/12 -> -0.025501794 | AO69: =SUMIFS($CC69:$CE69,$CC$1:$CE$1,AO$3)/12 -> -0.025501794 | AP69: =SUMIFS($CC69:$CE69,$CC$1:$CE$1,AP$3)/12 -> -0.025501794 | AQ69: =SUMIFS($CC69:$CE69,$CC$1:$CE$1,AQ$3)/12 -> -0.025501794 | AR69: =SUMIFS($CC69:$CE69,$CC$1:$CE$1,AR$3)/12 -> -0.025501794 | ... BT69: =SUMIFS($CC69:$CE69,$CC$1:$CE$1,BT$3)/12 -> -0.073211853 | BU69: =BI69 -> -0.073211853 | BV69: =BJ69 -> -0.073211853 | BW69: =BK69 -> -0.073211853 | BX69: =BL69 -> -0.073211853 | BZ69: =SUMIFS($D69:$AJ69,$D$1:$AJ$1,BZ$9) -> -5.65946 | CA69: =SUMIFS($D69:$AJ69,$D$1:$AJ$1,CA$9) -> -3.67589 | CB69: =SUMIFS($D69:$AJ69,$D$3:$AJ$3,"LTM") -> -4.39538 | CC69: =CC$38*CG69 -> -0.30602152 | CD69: =CD$38*CH69 -> -0.59073575 | CE69: =CE$38*CI69 -> -0.87854224 | CG69: =$CN69 -> -0.00033763124 | CH69: =$CN69 -> -0.00033763124 | CI69: =$CN69 -> -0.00033763124 | CK69: =IFERROR(CB69/CB$38,0) -> -0.0078370005 | CM69: =-SUMIFS('FY25 By Venue Financials'!$N:$N,'FY25 By Venue Financials'!$A:$A,$C69) -> -2.38146 | CN69: =IFERROR(CM69/CM$38,0) -> -0.00033763124 | CP69: % Total Rev | CQ69: Split evently
C70: Training & Development Expense | D70: =-SUMIFS('P&L'!C:C,'P&L'!$A:$A,$C70)/1000 -> 0 | E70: =-SUMIFS('P&L'!D:D,'P&L'!$A:$A,$C70)/1000 -> 0 | F70: =-SUMIFS('P&L'!E:E,'P&L'!$A:$A,$C70)/1000 -> 0 | G70: =-SUMIFS('P&L'!F:F,'P&L'!$A:$A,$C70)/1000 -> 0 | H70: =-SUMIFS('P&L'!G:G,'P&L'!$A:$A,$C70)/1000 -> 0 | I70: =-SUMIFS('P&L'!H:H,'P&L'!$A:$A,$C70)/1000 -> 0 | J70: =-SUMIFS('P&L'!I:I,'P&L'!$A:$A,$C70)/1000 -> 0 | K70: =-SUMIFS('P&L'!J:J,'P&L'!$A:$A,$C70)/1000 -> 0 | L70: =-SUMIFS('P&L'!K:K,'P&L'!$A:$A,$C70)/1000 -> 0 | M70: =-SUMIFS('P&L'!L:L,'P&L'!$A:$A,$C70)/1000 -> 0 | N70: =-SUMIFS('P&L'!M:M,'P&L'!$A:$A,$C70)/1000 -> 0 | O70: =-SUMIFS('P&L'!N:N,'P&L'!$A:$A,$C70)/1000 -> 0 | P70: =-SUMIFS('P&L'!O:O,'P&L'!$A:$A,$C70)/1000 -> 0 | Q70: =-SUMIFS('P&L'!P:P,'P&L'!$A:$A,$C70)/1000 -> 0 | R70: =-SUMIFS('P&L'!Q:Q,'P&L'!$A:$A,$C70)/1000 -> 0 | S70: =-SUMIFS('P&L'!R:R,'P&L'!$A:$A,$C70)/1000 -> 0 | T70: =-SUMIFS('P&L'!S:S,'P&L'!$A:$A,$C70)/1000 -> 0 | U70: =-SUMIFS('P&L'!T:T,'P&L'!$A:$A,$C70)/1000 -> 0 | V70: =-SUMIFS('P&L'!U:U,'P&L'!$A:$A,$C70)/1000 -> 0 | W70: =-SUMIFS('P&L'!V:V,'P&L'!$A:$A,$C70)/1000 -> 0 | X70: =-SUMIFS('P&L'!W:W,'P&L'!$A:$A,$C70)/1000 -> 0 | Y70: =-SUMIFS('P&L'!X:X,'P&L'!$A:$A,$C70)/1000 -> 0 | Z70: =-SUMIFS('P&L'!Y:Y,'P&L'!$A:$A,$C70)/1000 -> 0 | AA70: =-SUMIFS('P&L'!Z:Z,'P&L'!$A:$A,$C70)/1000 -> 0 | AB70: =-SUMIFS('P&L'!AA:AA,'P&L'!$A:$A,$C70)/1000 -> 0 | AC70: =-SUMIFS('P&L'!AB:AB,'P&L'!$A:$A,$C70)/1000 -> 0 | AD70: =-SUMIFS('P&L'!AC:AC,'P&L'!$A:$A,$C70)/1000 -> 0 | AE70: =-SUMIFS('P&L'!AD:AD,'P&L'!$A:$A,$C70)/1000 -> 0 | AF70: =-SUMIFS('P&L'!AE:AE,'P&L'!$A:$A,$C70)/1000 -> 0 | AG70: =-SUMIFS('P&L'!AF:AF,'P&L'!$A:$A,$C70)/1000 -> 0 | AH70: =-SUMIFS('P&L'!AG:AG,'P&L'!$A:$A,$C70)/1000 -> 0 | AK70: =SUMIFS($CC70:$CE70,$CC$1:$CE$1,AK$3)/12 -> -0.0021159937 | AL70: =SUMIFS($CC70:$CE70,$CC$1:$CE$1,AL$3)/12 -> -0.0021159937 | AM70: =SUMIFS($CC70:$CE70,$CC$1:$CE$1,AM$3)/12 -> -0.0021159937 | AN70: =SUMIFS($CC70:$CE70,$CC$1:$CE$1,AN$3)/12 -> -0.0021159937 | AO70: =SUMIFS($CC70:$CE70,$CC$1:$CE$1,AO$3)/12 -> -0.0021159937 | AP70: =SUMIFS($CC70:$CE70,$CC$1:$CE$1,AP$3)/12 -> -0.0021159937 | AQ70: =SUMIFS($CC70:$CE70,$CC$1:$CE$1,AQ$3)/12 -> -0.0021159937 | AR70: =SUMIFS($CC70:$CE70,$CC$1:$CE$1,AR$3)/12 -> -0.0021159937 | ... BT70: =SUMIFS($CC70:$CE70,$CC$1:$CE$1,BT$3)/12 -> -0.006074703 | BU70: =BI70 -> -0.006074703 | BV70: =BJ70 -> -0.006074703 | BW70: =BK70 -> -0.006074703 | BX70: =BL70 -> -0.006074703 | BZ70: =SUMIFS($D70:$AJ70,$D$1:$AJ$1,BZ$9) -> 0 | CA70: =SUMIFS($D70:$AJ70,$D$1:$AJ$1,CA$9) -> 0 | CB70: =SUMIFS($D70:$AJ70,$D$3:$AJ$3,"LTM") -> 0 | CC70: =CC$38*CG70 -> -0.025391925 | CD70: =CD$38*CH70 -> -0.049015891 | CE70: =CE$38*CI70 -> -0.072896436 | CG70: =$CN70 -> -2.8014719e-05 | CH70: =$CN70 -> -2.8014719e-05 | CI70: =$CN70 -> -2.8014719e-05 | CK70: =IFERROR(CB70/CB$38,0) -> 0 | CM70: =-SUMIFS('FY25 By Venue Financials'!$N:$N,'FY25 By Venue Financials'!$A:$A,$C70) -> -0.1976 | CN70: =IFERROR(CM70/CM$38,0) -> -2.8014719e-05 | CP70: % Total Rev | CQ70: Split evently
C71: Tax Expense | D71: =-SUMIFS('P&L'!C:C,'P&L'!$A:$A,$C71)/1000 -> -0.07215 | E71: =-SUMIFS('P&L'!D:D,'P&L'!$A:$A,$C71)/1000 -> 0 | F71: =-SUMIFS('P&L'!E:E,'P&L'!$A:$A,$C71)/1000 -> 0 | G71: =-SUMIFS('P&L'!F:F,'P&L'!$A:$A,$C71)/1000 -> 0 | H71: =-SUMIFS('P&L'!G:G,'P&L'!$A:$A,$C71)/1000 -> 0 | I71: =-SUMIFS('P&L'!H:H,'P&L'!$A:$A,$C71)/1000 -> 0 | J71: =-SUMIFS('P&L'!I:I,'P&L'!$A:$A,$C71)/1000 -> 0 | K71: =-SUMIFS('P&L'!J:J,'P&L'!$A:$A,$C71)/1000 -> 0 | L71: =-SUMIFS('P&L'!K:K,'P&L'!$A:$A,$C71)/1000 -> -0.056 | M71: =-SUMIFS('P&L'!L:L,'P&L'!$A:$A,$C71)/1000 -> -9.85141 | N71: =-SUMIFS('P&L'!M:M,'P&L'!$A:$A,$C71)/1000 -> 0 | O71: =-SUMIFS('P&L'!N:N,'P&L'!$A:$A,$C71)/1000 -> 0 | P71: =-SUMIFS('P&L'!O:O,'P&L'!$A:$A,$C71)/1000 -> 0 | Q71: =-SUMIFS('P&L'!P:P,'P&L'!$A:$A,$C71)/1000 -> 0 | R71: =-SUMIFS('P&L'!Q:Q,'P&L'!$A:$A,$C71)/1000 -> 0 | S71: =-SUMIFS('P&L'!R:R,'P&L'!$A:$A,$C71)/1000 -> 0 | T71: =-SUMIFS('P&L'!S:S,'P&L'!$A:$A,$C71)/1000 -> 0 | U71: =-SUMIFS('P&L'!T:T,'P&L'!$A:$A,$C71)/1000 -> 0 | V71: =-SUMIFS('P&L'!U:U,'P&L'!$A:$A,$C71)/1000 -> 0 | W71: =-SUMIFS('P&L'!V:V,'P&L'!$A:$A,$C71)/1000 -> 0 | X71: =-SUMIFS('P&L'!W:W,'P&L'!$A:$A,$C71)/1000 -> 0 | Y71: =-SUMIFS('P&L'!X:X,'P&L'!$A:$A,$C71)/1000 -> -29.06877 | Z71: =-SUMIFS('P&L'!Y:Y,'P&L'!$A:$A,$C71)/1000 -> 0 | AA71: =-SUMIFS('P&L'!Z:Z,'P&L'!$A:$A,$C71)/1000 -> 0 | AB71: =-SUMIFS('P&L'!AA:AA,'P&L'!$A:$A,$C71)/1000 -> -5.21347 | AC71: =-SUMIFS('P&L'!AB:AB,'P&L'!$A:$A,$C71)/1000 -> -2.59865 | AD71: =-SUMIFS('P&L'!AC:AC,'P&L'!$A:$A,$C71)/1000 -> -2.59865 | AE71: =-SUMIFS('P&L'!AD:AD,'P&L'!$A:$A,$C71)/1000 -> -2.59865 | AF71: =-SUMIFS('P&L'!AE:AE,'P&L'!$A:$A,$C71)/1000 -> -2.59865 | AG71: =-SUMIFS('P&L'!AF:AF,'P&L'!$A:$A,$C71)/1000 -> -2.59865 | AH71: =-SUMIFS('P&L'!AG:AG,'P&L'!$A:$A,$C71)/1000 -> 0 | AK71: =SUMIFS($CC71:$CE71,$CC$1:$CE$1,AK$3)/12 -> -2.9166667 | AL71: =SUMIFS($CC71:$CE71,$CC$1:$CE$1,AL$3)/12 -> -2.9166667 | AM71: =SUMIFS($CC71:$CE71,$CC$1:$CE$1,AM$3)/12 -> -2.9166667 | AN71: =SUMIFS($CC71:$CE71,$CC$1:$CE$1,AN$3)/12 -> -2.9166667 | AO71: =SUMIFS($CC71:$CE71,$CC$1:$CE$1,AO$3)/12 -> -2.9166667 | AP71: =SUMIFS($CC71:$CE71,$CC$1:$CE$1,AP$3)/12 -> -2.9166667 | AQ71: =SUMIFS($CC71:$CE71,$CC$1:$CE$1,AQ$3)/12 -> -2.9166667 | AR71: =SUMIFS($CC71:$CE71,$CC$1:$CE$1,AR$3)/12 -> -2.9166667 | ... BT71: =SUMIFS($CC71:$CE71,$CC$1:$CE$1,BT$3)/12 -> -2.9166667 | BU71: =BI71 -> -2.9166667 | BV71: =BJ71 -> -2.9166667 | BW71: =BK71 -> -2.9166667 | BX71: =BL71 -> -2.9166667 | BZ71: =SUMIFS($D71:$AJ71,$D$1:$AJ$1,BZ$9) -> -9.97956 | CA71: =SUMIFS($D71:$AJ71,$D$1:$AJ$1,CA$9) -> -29.06877 | CB71: =SUMIFS($D71:$AJ71,$D$3:$AJ$3,"LTM") -> -47.27549 | CC71: -35 | CD71: -35 | CE71: -35 | CK71: =CB71 -> -47.27549 | CM71: =-SUMIFS('FY25 By Venue Financials'!$N:$N,'FY25 By Venue Financials'!$A:$A,$C71) -> -62.51545 | CN71: =IFERROR(CM71/CM$38,0) -> -0.0088631213 | CP71: Fixed | CQ71: Split evently | CR71: LTM double counts property taxes, 2025 was ~30k, adding 10%+
C72: Travel Expense | D72: =-SUMIFS('P&L'!C:C,'P&L'!$A:$A,$C72)/1000 -> -0.02235 | E72: =-SUMIFS('P&L'!D:D,'P&L'!$A:$A,$C72)/1000 -> -0.53 | F72: =-SUMIFS('P&L'!E:E,'P&L'!$A:$A,$C72)/1000 -> 0 | G72: =-SUMIFS('P&L'!F:F,'P&L'!$A:$A,$C72)/1000 -> -0.035 | H72: =-SUMIFS('P&L'!G:G,'P&L'!$A:$A,$C72)/1000 -> 0 | I72: =-SUMIFS('P&L'!H:H,'P&L'!$A:$A,$C72)/1000 -> 0.53 | J72: =-SUMIFS('P&L'!I:I,'P&L'!$A:$A,$C72)/1000 -> -1.58504 | K72: =-SUMIFS('P&L'!J:J,'P&L'!$A:$A,$C72)/1000 -> 0 | L72: =-SUMIFS('P&L'!K:K,'P&L'!$A:$A,$C72)/1000 -> 0 | M72: =-SUMIFS('P&L'!L:L,'P&L'!$A:$A,$C72)/1000 -> 0 | N72: =-SUMIFS('P&L'!M:M,'P&L'!$A:$A,$C72)/1000 -> 0 | O72: =-SUMIFS('P&L'!N:N,'P&L'!$A:$A,$C72)/1000 -> 0 | P72: =-SUMIFS('P&L'!O:O,'P&L'!$A:$A,$C72)/1000 -> 0 | Q72: =-SUMIFS('P&L'!P:P,'P&L'!$A:$A,$C72)/1000 -> 0 | R72: =-SUMIFS('P&L'!Q:Q,'P&L'!$A:$A,$C72)/1000 -> 0 | S72: =-SUMIFS('P&L'!R:R,'P&L'!$A:$A,$C72)/1000 -> 0 | T72: =-SUMIFS('P&L'!S:S,'P&L'!$A:$A,$C72)/1000 -> 0 | U72: =-SUMIFS('P&L'!T:T,'P&L'!$A:$A,$C72)/1000 -> 0 | V72: =-SUMIFS('P&L'!U:U,'P&L'!$A:$A,$C72)/1000 -> 0 | W72: =-SUMIFS('P&L'!V:V,'P&L'!$A:$A,$C72)/1000 -> 0 | X72: =-SUMIFS('P&L'!W:W,'P&L'!$A:$A,$C72)/1000 -> 0 | Y72: =-SUMIFS('P&L'!X:X,'P&L'!$A:$A,$C72)/1000 -> 0 | Z72: =-SUMIFS('P&L'!Y:Y,'P&L'!$A:$A,$C72)/1000 -> 0 | AA72: =-SUMIFS('P&L'!Z:Z,'P&L'!$A:$A,$C72)/1000 -> 0 | AB72: =-SUMIFS('P&L'!AA:AA,'P&L'!$A:$A,$C72)/1000 -> 0 | AC72: =-SUMIFS('P&L'!AB:AB,'P&L'!$A:$A,$C72)/1000 -> 0 | AD72: =-SUMIFS('P&L'!AC:AC,'P&L'!$A:$A,$C72)/1000 -> -0.04337 | AE72: =-SUMIFS('P&L'!AD:AD,'P&L'!$A:$A,$C72)/1000 -> 0 | AF72: =-SUMIFS('P&L'!AE:AE,'P&L'!$A:$A,$C72)/1000 -> 0 | AG72: =-SUMIFS('P&L'!AF:AF,'P&L'!$A:$A,$C72)/1000 -> -0.0462 | AH72: =-SUMIFS('P&L'!AG:AG,'P&L'!$A:$A,$C72)/1000 -> 0 | AK72: =SUMIFS($CC72:$CE72,$CC$1:$CE$1,AK$3)/12 -> -0.022905525 | AL72: =SUMIFS($CC72:$CE72,$CC$1:$CE$1,AL$3)/12 -> -0.022905525 | AM72: =SUMIFS($CC72:$CE72,$CC$1:$CE$1,AM$3)/12 -> -0.022905525 | AN72: =SUMIFS($CC72:$CE72,$CC$1:$CE$1,AN$3)/12 -> -0.022905525 | AO72: =SUMIFS($CC72:$CE72,$CC$1:$CE$1,AO$3)/12 -> -0.022905525 | AP72: =SUMIFS($CC72:$CE72,$CC$1:$CE$1,AP$3)/12 -> -0.022905525 | AQ72: =SUMIFS($CC72:$CE72,$CC$1:$CE$1,AQ$3)/12 -> -0.022905525 | AR72: =SUMIFS($CC72:$CE72,$CC$1:$CE$1,AR$3)/12 -> -0.022905525 | ... BT72: =SUMIFS($CC72:$CE72,$CC$1:$CE$1,BT$3)/12 -> -0.065758352 | BU72: =BI72 -> -0.065758352 | BV72: =BJ72 -> -0.065758352 | BW72: =BK72 -> -0.065758352 | BX72: =BL72 -> -0.065758352 | BZ72: =SUMIFS($D72:$AJ72,$D$1:$AJ$1,BZ$9) -> -1.64239 | CA72: =SUMIFS($D72:$AJ72,$D$1:$AJ$1,CA$9) -> 0 | CB72: =SUMIFS($D72:$AJ72,$D$3:$AJ$3,"LTM") -> -0.08957 | CC72: =CC$38*CG72 -> -0.2748663 | CD72: =CD$38*CH72 -> -0.53059454 | CE72: =CE$38*CI72 -> -0.78910023 | CG72: =$CN72 -> -0.00030325792 | CH72: =$CN72 -> -0.00030325792 | CI72: =$CN72 -> -0.00030325792 | CK72: =IFERROR(CB72/CB$38,0) -> -0.00015970408 | CM72: =-SUMIFS('FY25 By Venue Financials'!$N:$N,'FY25 By Venue Financials'!$A:$A,$C72) -> -2.13901 | CN72: =IFERROR(CM72/CM$38,0) -> -0.00030325792 | CP72: % Total Rev | CQ72: Split evently
C73: Professional Expenses | D73: =-SUMIFS('P&L'!C:C,'P&L'!$A:$A,$C73)/1000 -> 0 | E73: =-SUMIFS('P&L'!D:D,'P&L'!$A:$A,$C73)/1000 -> 0 | F73: =-SUMIFS('P&L'!E:E,'P&L'!$A:$A,$C73)/1000 -> 0 | G73: =-SUMIFS('P&L'!F:F,'P&L'!$A:$A,$C73)/1000 -> 0 | H73: =-SUMIFS('P&L'!G:G,'P&L'!$A:$A,$C73)/1000 -> 0 | I73: =-SUMIFS('P&L'!H:H,'P&L'!$A:$A,$C73)/1000 -> -0.53 | J73: =-SUMIFS('P&L'!I:I,'P&L'!$A:$A,$C73)/1000 -> -3.507 | K73: =-SUMIFS('P&L'!J:J,'P&L'!$A:$A,$C73)/1000 -> -1.1 | L73: =-SUMIFS('P&L'!K:K,'P&L'!$A:$A,$C73)/1000 -> 0 | M73: =-SUMIFS('P&L'!L:L,'P&L'!$A:$A,$C73)/1000 -> 0 | N73: =-SUMIFS('P&L'!M:M,'P&L'!$A:$A,$C73)/1000 -> 0 | O73: =-SUMIFS('P&L'!N:N,'P&L'!$A:$A,$C73)/1000 -> -4.75 | P73: =-SUMIFS('P&L'!O:O,'P&L'!$A:$A,$C73)/1000 -> -0.314 | Q73: =-SUMIFS('P&L'!P:P,'P&L'!$A:$A,$C73)/1000 -> 0 | R73: =-SUMIFS('P&L'!Q:Q,'P&L'!$A:$A,$C73)/1000 -> -0.1 | S73: =-SUMIFS('P&L'!R:R,'P&L'!$A:$A,$C73)/1000 -> -1.275 | T73: =-SUMIFS('P&L'!S:S,'P&L'!$A:$A,$C73)/1000 -> 0 | U73: =-SUMIFS('P&L'!T:T,'P&L'!$A:$A,$C73)/1000 -> 0 | V73: =-SUMIFS('P&L'!U:U,'P&L'!$A:$A,$C73)/1000 -> 0 | W73: =-SUMIFS('P&L'!V:V,'P&L'!$A:$A,$C73)/1000 -> 0 | X73: =-SUMIFS('P&L'!W:W,'P&L'!$A:$A,$C73)/1000 -> 0 | Y73: =-SUMIFS('P&L'!X:X,'P&L'!$A:$A,$C73)/1000 -> 0 | Z73: =-SUMIFS('P&L'!Y:Y,'P&L'!$A:$A,$C73)/1000 -> 0 | AA73: =-SUMIFS('P&L'!Z:Z,'P&L'!$A:$A,$C73)/1000 -> 0 | AB73: =-SUMIFS('P&L'!AA:AA,'P&L'!$A:$A,$C73)/1000 -> 0 | AC73: =-SUMIFS('P&L'!AB:AB,'P&L'!$A:$A,$C73)/1000 -> 0 | AD73: =-SUMIFS('P&L'!AC:AC,'P&L'!$A:$A,$C73)/1000 -> 0 | AE73: =-SUMIFS('P&L'!AD:AD,'P&L'!$A:$A,$C73)/1000 -> -1.275 | AF73: =-SUMIFS('P&L'!AE:AE,'P&L'!$A:$A,$C73)/1000 -> 0 | AG73: =-SUMIFS('P&L'!AF:AF,'P&L'!$A:$A,$C73)/1000 -> 0 | AH73: =-SUMIFS('P&L'!AG:AG,'P&L'!$A:$A,$C73)/1000 -> 0 | AK73: =SUMIFS($CC73:$CE73,$CC$1:$CE$1,AK$3)/12 -> -0.016069773 | AL73: =SUMIFS($CC73:$CE73,$CC$1:$CE$1,AL$3)/12 -> -0.016069773 | AM73: =SUMIFS($CC73:$CE73,$CC$1:$CE$1,AM$3)/12 -> -0.016069773 | AN73: =SUMIFS($CC73:$CE73,$CC$1:$CE$1,AN$3)/12 -> -0.016069773 | AO73: =SUMIFS($CC73:$CE73,$CC$1:$CE$1,AO$3)/12 -> -0.016069773 | AP73: =SUMIFS($CC73:$CE73,$CC$1:$CE$1,AP$3)/12 -> -0.016069773 | AQ73: =SUMIFS($CC73:$CE73,$CC$1:$CE$1,AQ$3)/12 -> -0.016069773 | AR73: =SUMIFS($CC73:$CE73,$CC$1:$CE$1,AR$3)/12 -> -0.016069773 | ... BT73: =SUMIFS($CC73:$CE73,$CC$1:$CE$1,BT$3)/12 -> -0.046133926 | BU73: =BI73 -> -0.046133926 | BV73: =BJ73 -> -0.046133926 | BW73: =BK73 -> -0.046133926 | BX73: =BL73 -> -0.046133926 | BZ73: =SUMIFS($D73:$AJ73,$D$1:$AJ$1,BZ$9) -> -9.887 | CA73: =SUMIFS($D73:$AJ73,$D$1:$AJ$1,CA$9) -> -1.689 | CB73: =SUMIFS($D73:$AJ73,$D$3:$AJ$3,"LTM") -> -1.275 | CC73: =CC$38*CG73 -> -0.19283728 | CD73: =CD$38*CH73 -> -0.37224791 | CE73: =CE$38*CI73 -> -0.55360711 | CG73: =$CN73 -> -0.00021275591 | CH73: =$CN73 -> -0.00021275591 | CI73: =$CN73 -> -0.00021275591 | CK73: =IFERROR(CB73/CB$38,0) -> -0.002273336 | CM73: =-SUMIFS('FY25 By Venue Financials'!$N:$N,'FY25 By Venue Financials'!$A:$A,$C73) -> -1.50066 | CN73: =IFERROR(CM73/CM$38,0) -> -0.00021275591 | CP73: % Total Rev | CQ73: Split evently
C74: Rent Expense | D74: =-SUMIFS('P&L'!C:C,'P&L'!$A:$A,$C74)/1000 -> 0 | E74: =-SUMIFS('P&L'!D:D,'P&L'!$A:$A,$C74)/1000 -> 0 | F74: =-SUMIFS('P&L'!E:E,'P&L'!$A:$A,$C74)/1000 -> 0 | G74: =-SUMIFS('P&L'!F:F,'P&L'!$A:$A,$C74)/1000 -> 0 | H74: =-SUMIFS('P&L'!G:G,'P&L'!$A:$A,$C74)/1000 -> 0 | I74: =-SUMIFS('P&L'!H:H,'P&L'!$A:$A,$C74)/1000 -> 0 | J74: =-SUMIFS('P&L'!I:I,'P&L'!$A:$A,$C74)/1000 -> 0 | K74: =-SUMIFS('P&L'!J:J,'P&L'!$A:$A,$C74)/1000 -> 0 | L74: =-SUMIFS('P&L'!K:K,'P&L'!$A:$A,$C74)/1000 -> 0 | M74: =-SUMIFS('P&L'!L:L,'P&L'!$A:$A,$C74)/1000 -> 0 | N74: =-SUMIFS('P&L'!M:M,'P&L'!$A:$A,$C74)/1000 -> 0 | O74: =-SUMIFS('P&L'!N:N,'P&L'!$A:$A,$C74)/1000 -> 0 | P74: =-SUMIFS('P&L'!O:O,'P&L'!$A:$A,$C74)/1000 -> 0 | Q74: =-SUMIFS('P&L'!P:P,'P&L'!$A:$A,$C74)/1000 -> 0 | R74: =-SUMIFS('P&L'!Q:Q,'P&L'!$A:$A,$C74)/1000 -> 0 | S74: =-SUMIFS('P&L'!R:R,'P&L'!$A:$A,$C74)/1000 -> 0 | T74: =-SUMIFS('P&L'!S:S,'P&L'!$A:$A,$C74)/1000 -> 0 | U74: =-SUMIFS('P&L'!T:T,'P&L'!$A:$A,$C74)/1000 -> 0 | V74: =-SUMIFS('P&L'!U:U,'P&L'!$A:$A,$C74)/1000 -> 0 | W74: =-SUMIFS('P&L'!V:V,'P&L'!$A:$A,$C74)/1000 -> 0 | X74: =-SUMIFS('P&L'!W:W,'P&L'!$A:$A,$C74)/1000 -> 0 | Y74: =-SUMIFS('P&L'!X:X,'P&L'!$A:$A,$C74)/1000 -> 0 | Z74: =-SUMIFS('P&L'!Y:Y,'P&L'!$A:$A,$C74)/1000 -> 0 | AA74: =-SUMIFS('P&L'!Z:Z,'P&L'!$A:$A,$C74)/1000 -> 0 | AB74: =-SUMIFS('P&L'!AA:AA,'P&L'!$A:$A,$C74)/1000 -> 0 | AC74: =-SUMIFS('P&L'!AB:AB,'P&L'!$A:$A,$C74)/1000 -> 0 | AD74: =-SUMIFS('P&L'!AC:AC,'P&L'!$A:$A,$C74)/1000 -> 0 | AE74: =-SUMIFS('P&L'!AD:AD,'P&L'!$A:$A,$C74)/1000 -> 0 | AF74: =-SUMIFS('P&L'!AE:AE,'P&L'!$A:$A,$C74)/1000 -> 0 | AG74: =-SUMIFS('P&L'!AF:AF,'P&L'!$A:$A,$C74)/1000 -> 0 | AH74: =-SUMIFS('P&L'!AG:AG,'P&L'!$A:$A,$C74)/1000 -> 0 | AK74: =SUMIFS($CC74:$CE74,$CC$1:$CE$1,AK$3)/12 -> 0 | AL74: =SUMIFS($CC74:$CE74,$CC$1:$CE$1,AL$3)/12 -> 0 | AM74: =SUMIFS($CC74:$CE74,$CC$1:$CE$1,AM$3)/12 -> 0 | AN74: =SUMIFS($CC74:$CE74,$CC$1:$CE$1,AN$3)/12 -> 0 | AO74: =SUMIFS($CC74:$CE74,$CC$1:$CE$1,AO$3)/12 -> 0 | AP74: =SUMIFS($CC74:$CE74,$CC$1:$CE$1,AP$3)/12 -> 0 | AQ74: =SUMIFS($CC74:$CE74,$CC$1:$CE$1,AQ$3)/12 -> 0 | AR74: =SUMIFS($CC74:$CE74,$CC$1:$CE$1,AR$3)/12 -> 0 | ... BT74: =SUMIFS($CC74:$CE74,$CC$1:$CE$1,BT$3)/12 -> 0 | BU74: =BI74 -> 0 | BV74: =BJ74 -> 0 | BW74: =BK74 -> 0 | BX74: =BL74 -> 0 | BZ74: =SUMIFS($D74:$AJ74,$D$1:$AJ$1,BZ$9) -> 0 | CA74: =SUMIFS($D74:$AJ74,$D$1:$AJ$1,CA$9) -> 0 | CB74: =SUMIFS($D74:$AJ74,$D$3:$AJ$3,"LTM") -> 0 | CC74: =CC$38*CG74 -> 0 | CD74: =CD$38*CH74 -> 0 | CE74: =CE$38*CI74 -> 0 | CG74: 0 | CH74: 0 | CI74: 0 | CK74: =IFERROR(CB74/CB$38,0) -> 0 | CM74: =-SUMIFS('FY25 By Venue Financials'!$N:$N,'FY25 By Venue Financials'!$A:$A,$C74) -> -14.46209 | CN74: =IFERROR(CM74/CM$38,0) -> -0.0020503613 | CP74: % Total Rev | CQ74: Split evently
C75: Insurance | D75: =-SUMIFS('P&L'!C:C,'P&L'!$A:$A,$C75)/1000 -> -0.241 | E75: =-SUMIFS('P&L'!D:D,'P&L'!$A:$A,$C75)/1000 -> -8.33495 | F75: =-SUMIFS('P&L'!E:E,'P&L'!$A:$A,$C75)/1000 -> -0.734 | G75: =-SUMIFS('P&L'!F:F,'P&L'!$A:$A,$C75)/1000 -> -20.014 | H75: =-SUMIFS('P&L'!G:G,'P&L'!$A:$A,$C75)/1000 -> -0.756 | I75: =-SUMIFS('P&L'!H:H,'P&L'!$A:$A,$C75)/1000 -> -0.771 | J75: =-SUMIFS('P&L'!I:I,'P&L'!$A:$A,$C75)/1000 -> -0.272 | K75: =-SUMIFS('P&L'!J:J,'P&L'!$A:$A,$C75)/1000 -> -0.257 | L75: =-SUMIFS('P&L'!K:K,'P&L'!$A:$A,$C75)/1000 -> 0 | M75: =-SUMIFS('P&L'!L:L,'P&L'!$A:$A,$C75)/1000 -> 0 | N75: =-SUMIFS('P&L'!M:M,'P&L'!$A:$A,$C75)/1000 -> 0 | O75: =-SUMIFS('P&L'!N:N,'P&L'!$A:$A,$C75)/1000 -> 0 | P75: =-SUMIFS('P&L'!O:O,'P&L'!$A:$A,$C75)/1000 -> -0.84116 | Q75: =-SUMIFS('P&L'!P:P,'P&L'!$A:$A,$C75)/1000 -> 0 | R75: =-SUMIFS('P&L'!Q:Q,'P&L'!$A:$A,$C75)/1000 -> 0 | S75: =-SUMIFS('P&L'!R:R,'P&L'!$A:$A,$C75)/1000 -> -2.55413 | T75: =-SUMIFS('P&L'!S:S,'P&L'!$A:$A,$C75)/1000 -> -0.34034 | U75: =-SUMIFS('P&L'!T:T,'P&L'!$A:$A,$C75)/1000 -> -4.12256 | V75: =-SUMIFS('P&L'!U:U,'P&L'!$A:$A,$C75)/1000 -> -2.13983 | W75: =-SUMIFS('P&L'!V:V,'P&L'!$A:$A,$C75)/1000 -> -5.01783 | X75: =-SUMIFS('P&L'!W:W,'P&L'!$A:$A,$C75)/1000 -> -2.71273 | Y75: =-SUMIFS('P&L'!X:X,'P&L'!$A:$A,$C75)/1000 -> -5.69736 | Z75: =-SUMIFS('P&L'!Y:Y,'P&L'!$A:$A,$C75)/1000 -> 0 | AA75: =-SUMIFS('P&L'!Z:Z,'P&L'!$A:$A,$C75)/1000 -> -2.70868 | AB75: =-SUMIFS('P&L'!AA:AA,'P&L'!$A:$A,$C75)/1000 -> -6.03562 | AC75: =-SUMIFS('P&L'!AB:AB,'P&L'!$A:$A,$C75)/1000 -> -4.53555 | AD75: =-SUMIFS('P&L'!AC:AC,'P&L'!$A:$A,$C75)/1000 -> -5.81655 | AE75: =-SUMIFS('P&L'!AD:AD,'P&L'!$A:$A,$C75)/1000 -> -5.41037 | AF75: =-SUMIFS('P&L'!AE:AE,'P&L'!$A:$A,$C75)/1000 -> -2.97491 | AG75: =-SUMIFS('P&L'!AF:AF,'P&L'!$A:$A,$C75)/1000 -> -4.11282 | AH75: =-SUMIFS('P&L'!AG:AG,'P&L'!$A:$A,$C75)/1000 -> -1.61782 | AK75: =SUMIFS($CC75:$CE75,$CC$1:$CE$1,AK$3)/12 -> -2.5 | AL75: =SUMIFS($CC75:$CE75,$CC$1:$CE$1,AL$3)/12 -> -2.5 | AM75: =SUMIFS($CC75:$CE75,$CC$1:$CE$1,AM$3)/12 -> -2.5 | AN75: =SUMIFS($CC75:$CE75,$CC$1:$CE$1,AN$3)/12 -> -2.5 | AO75: =SUMIFS($CC75:$CE75,$CC$1:$CE$1,AO$3)/12 -> -2.5 | AP75: =SUMIFS($CC75:$CE75,$CC$1:$CE$1,AP$3)/12 -> -2.5 | AQ75: =SUMIFS($CC75:$CE75,$CC$1:$CE$1,AQ$3)/12 -> -2.5 | AR75: =SUMIFS($CC75:$CE75,$CC$1:$CE$1,AR$3)/12 -> -2.5 | ... BT75: =SUMIFS($CC75:$CE75,$CC$1:$CE$1,BT$3)/12 -> -2.5 | BU75: =BI75 -> -2.5 | BV75: =BJ75 -> -2.5 | BW75: =BK75 -> -2.5 | BX75: =BL75 -> -2.5 | BZ75: =SUMIFS($D75:$AJ75,$D$1:$AJ$1,BZ$9) -> -31.37995 | CA75: =SUMIFS($D75:$AJ75,$D$1:$AJ$1,CA$9) -> -26.13462 | CB75: =SUMIFS($D75:$AJ75,$D$3:$AJ$3,"LTM") -> -46.64024 | CC75: =CG75 -> -30 | CD75: =CH75 -> -30 | CE75: =CI75 -> -30 | CG75: -30 | CH75: -30 | CI75: -30 | CK75: =IFERROR(CB75/CB$38,0) -> -0.083159951 | CM75: =-SUMIFS('FY25 By Venue Financials'!$N:$N,'FY25 By Venue Financials'!$A:$A,$C75) -> -39.1794 | CN75: =IFERROR(CM75/CM$38,0) -> -0.0055546553 | CP75: % Total Rev | CQ75: Split evently | CR75: Actual premiums ~$28k currently
C76: Finance Expenses | D76: =-SUMIFS('P&L'!C:C,'P&L'!$A:$A,$C76)/1000 -> -0.43197 | E76: =-SUMIFS('P&L'!D:D,'P&L'!$A:$A,$C76)/1000 -> -0.11822 | F76: =-SUMIFS('P&L'!E:E,'P&L'!$A:$A,$C76)/1000 -> -0.0257 | G76: =-SUMIFS('P&L'!F:F,'P&L'!$A:$A,$C76)/1000 -> -0.40469 | H76: =-SUMIFS('P&L'!G:G,'P&L'!$A:$A,$C76)/1000 -> -0.24377 | I76: =-SUMIFS('P&L'!H:H,'P&L'!$A:$A,$C76)/1000 -> -2.62804 | J76: =-SUMIFS('P&L'!I:I,'P&L'!$A:$A,$C76)/1000 -> -0.98248 | K76: =-SUMIFS('P&L'!J:J,'P&L'!$A:$A,$C76)/1000 -> -0.58545 | L76: =-SUMIFS('P&L'!K:K,'P&L'!$A:$A,$C76)/1000 -> -0.33234 | M76: =-SUMIFS('P&L'!L:L,'P&L'!$A:$A,$C76)/1000 -> -0.36359 | N76: =-SUMIFS('P&L'!M:M,'P&L'!$A:$A,$C76)/1000 -> -0.54867 | O76: =-SUMIFS('P&L'!N:N,'P&L'!$A:$A,$C76)/1000 -> -0.36566 | P76: =-SUMIFS('P&L'!O:O,'P&L'!$A:$A,$C76)/1000 -> -0.45162 | Q76: =-SUMIFS('P&L'!P:P,'P&L'!$A:$A,$C76)/1000 -> -0.65022 | R76: =-SUMIFS('P&L'!Q:Q,'P&L'!$A:$A,$C76)/1000 -> -0.37832 | S76: =-SUMIFS('P&L'!R:R,'P&L'!$A:$A,$C76)/1000 -> -0.45733 | T76: =-SUMIFS('P&L'!S:S,'P&L'!$A:$A,$C76)/1000 -> -0.38872 | U76: =-SUMIFS('P&L'!T:T,'P&L'!$A:$A,$C76)/1000 -> -0.55158 | V76: =-SUMIFS('P&L'!U:U,'P&L'!$A:$A,$C76)/1000 -> -0.98136 | W76: =-SUMIFS('P&L'!V:V,'P&L'!$A:$A,$C76)/1000 -> -0.89076 | X76: =-SUMIFS('P&L'!W:W,'P&L'!$A:$A,$C76)/1000 -> -1.09866 | Y76: =-SUMIFS('P&L'!X:X,'P&L'!$A:$A,$C76)/1000 -> -0.55147 | Z76: =-SUMIFS('P&L'!Y:Y,'P&L'!$A:$A,$C76)/1000 -> -0.59313 | AA76: =-SUMIFS('P&L'!Z:Z,'P&L'!$A:$A,$C76)/1000 -> -0.53603 | AB76: =-SUMIFS('P&L'!AA:AA,'P&L'!$A:$A,$C76)/1000 -> -0.70318 | AC76: =-SUMIFS('P&L'!AB:AB,'P&L'!$A:$A,$C76)/1000 -> -1.18722 | AD76: =-SUMIFS('P&L'!AC:AC,'P&L'!$A:$A,$C76)/1000 -> -0.86026 | AE76: =-SUMIFS('P&L'!AD:AD,'P&L'!$A:$A,$C76)/1000 -> -0.70817 | AF76: =-SUMIFS('P&L'!AE:AE,'P&L'!$A:$A,$C76)/1000 -> -0.65815 | AG76: =-SUMIFS('P&L'!AF:AF,'P&L'!$A:$A,$C76)/1000 -> -0.46112 | AH76: =-SUMIFS('P&L'!AG:AG,'P&L'!$A:$A,$C76)/1000 -> -0.62546 | AK76: =SUMIFS($CC76:$CE76,$CC$1:$CE$1,AK$3)/12 -> -0.57756241 | AL76: =SUMIFS($CC76:$CE76,$CC$1:$CE$1,AL$3)/12 -> -0.57756241 | AM76: =SUMIFS($CC76:$CE76,$CC$1:$CE$1,AM$3)/12 -> -0.57756241 | AN76: =SUMIFS($CC76:$CE76,$CC$1:$CE$1,AN$3)/12 -> -0.57756241 | AO76: =SUMIFS($CC76:$CE76,$CC$1:$CE$1,AO$3)/12 -> -0.57756241 | AP76: =SUMIFS($CC76:$CE76,$CC$1:$CE$1,AP$3)/12 -> -0.57756241 | AQ76: =SUMIFS($CC76:$CE76,$CC$1:$CE$1,AQ$3)/12 -> -0.57756241 | AR76: =SUMIFS($CC76:$CE76,$CC$1:$CE$1,AR$3)/12 -> -0.57756241 | ... BT76: =SUMIFS($CC76:$CE76,$CC$1:$CE$1,BT$3)/12 -> -1.6580957 | BU76: =BI76 -> -1.6580957 | BV76: =BJ76 -> -1.6580957 | BW76: =BK76 -> -1.6580957 | BX76: =BL76 -> -1.6580957 | BZ76: =SUMIFS($D76:$AJ76,$D$1:$AJ$1,BZ$9) -> -7.03058 | CA76: =SUMIFS($D76:$AJ76,$D$1:$AJ$1,CA$9) -> -7.5292 | CB76: =SUMIFS($D76:$AJ76,$D$3:$AJ$3,"LTM") -> -8.87361 | CC76: =CC$38*CG76 -> -6.9307489 | CD76: =CD$38*CH76 -> -13.378932 | CE76: =CE$38*CI76 -> -19.897149 | CG76: =$CN76 -> -0.0076466431 | CH76: =$CN76 -> -0.0076466431 | CI76: =$CN76 -> -0.0076466431 | CK76: =IFERROR(CB76/CB$38,0) -> -0.015821723 | CM76: =-SUMIFS('FY25 By Venue Financials'!$N:$N,'FY25 By Venue Financials'!$A:$A,$C76) -> -53.9351 | CN76: =IFERROR(CM76/CM$38,0) -> -0.0076466431 | CP76: % Total Rev | CQ76: Split evently
C77: Personal Expenses | D77: =-SUMIFS('P&L'!C:C,'P&L'!$A:$A,$C77)/1000 -> 0 | E77: =-SUMIFS('P&L'!D:D,'P&L'!$A:$A,$C77)/1000 -> 0 | F77: =-SUMIFS('P&L'!E:E,'P&L'!$A:$A,$C77)/1000 -> 0 | G77: =-SUMIFS('P&L'!F:F,'P&L'!$A:$A,$C77)/1000 -> 0 | H77: =-SUMIFS('P&L'!G:G,'P&L'!$A:$A,$C77)/1000 -> 0 | I77: =-SUMIFS('P&L'!H:H,'P&L'!$A:$A,$C77)/1000 -> 0 | J77: =-SUMIFS('P&L'!I:I,'P&L'!$A:$A,$C77)/1000 -> 0 | K77: =-SUMIFS('P&L'!J:J,'P&L'!$A:$A,$C77)/1000 -> 0 | L77: =-SUMIFS('P&L'!K:K,'P&L'!$A:$A,$C77)/1000 -> 0 | M77: =-SUMIFS('P&L'!L:L,'P&L'!$A:$A,$C77)/1000 -> 0 | N77: =-SUMIFS('P&L'!M:M,'P&L'!$A:$A,$C77)/1000 -> 0 | O77: =-SUMIFS('P&L'!N:N,'P&L'!$A:$A,$C77)/1000 -> 0 | P77: =-SUMIFS('P&L'!O:O,'P&L'!$A:$A,$C77)/1000 -> 0 | Q77: =-SUMIFS('P&L'!P:P,'P&L'!$A:$A,$C77)/1000 -> 0 | R77: =-SUMIFS('P&L'!Q:Q,'P&L'!$A:$A,$C77)/1000 -> 0 | S77: =-SUMIFS('P&L'!R:R,'P&L'!$A:$A,$C77)/1000 -> 0 | T77: =-SUMIFS('P&L'!S:S,'P&L'!$A:$A,$C77)/1000 -> 0 | U77: =-SUMIFS('P&L'!T:T,'P&L'!$A:$A,$C77)/1000 -> 0 | V77: =-SUMIFS('P&L'!U:U,'P&L'!$A:$A,$C77)/1000 -> 0 | W77: =-SUMIFS('P&L'!V:V,'P&L'!$A:$A,$C77)/1000 -> 0 | X77: =-SUMIFS('P&L'!W:W,'P&L'!$A:$A,$C77)/1000 -> 0 | Y77: =-SUMIFS('P&L'!X:X,'P&L'!$A:$A,$C77)/1000 -> 0 | Z77: =-SUMIFS('P&L'!Y:Y,'P&L'!$A:$A,$C77)/1000 -> 0 | AA77: =-SUMIFS('P&L'!Z:Z,'P&L'!$A:$A,$C77)/1000 -> 0 | AB77: =-SUMIFS('P&L'!AA:AA,'P&L'!$A:$A,$C77)/1000 -> 0 | AC77: =-SUMIFS('P&L'!AB:AB,'P&L'!$A:$A,$C77)/1000 -> 0 | AD77: =-SUMIFS('P&L'!AC:AC,'P&L'!$A:$A,$C77)/1000 -> 0 | AE77: =-SUMIFS('P&L'!AD:AD,'P&L'!$A:$A,$C77)/1000 -> 0 | AF77: =-SUMIFS('P&L'!AE:AE,'P&L'!$A:$A,$C77)/1000 -> 0 | AG77: =-SUMIFS('P&L'!AF:AF,'P&L'!$A:$A,$C77)/1000 -> 0 | AH77: =-SUMIFS('P&L'!AG:AG,'P&L'!$A:$A,$C77)/1000 -> 0 | AK77: =SUMIFS($CC77:$CE77,$CC$1:$CE$1,AK$3)/12 -> 0 | AL77: =SUMIFS($CC77:$CE77,$CC$1:$CE$1,AL$3)/12 -> 0 | AM77: =SUMIFS($CC77:$CE77,$CC$1:$CE$1,AM$3)/12 -> 0 | AN77: =SUMIFS($CC77:$CE77,$CC$1:$CE$1,AN$3)/12 -> 0 | AO77: =SUMIFS($CC77:$CE77,$CC$1:$CE$1,AO$3)/12 -> 0 | AP77: =SUMIFS($CC77:$CE77,$CC$1:$CE$1,AP$3)/12 -> 0 | AQ77: =SUMIFS($CC77:$CE77,$CC$1:$CE$1,AQ$3)/12 -> 0 | AR77: =SUMIFS($CC77:$CE77,$CC$1:$CE$1,AR$3)/12 -> 0 | ... BT77: =SUMIFS($CC77:$CE77,$CC$1:$CE$1,BT$3)/12 -> 0 | BU77: =BI77 -> 0 | BV77: =BJ77 -> 0 | BW77: =BK77 -> 0 | BX77: =BL77 -> 0 | BZ77: =SUMIFS($D77:$AJ77,$D$1:$AJ$1,BZ$9) -> 0 | CA77: =SUMIFS($D77:$AJ77,$D$1:$AJ$1,CA$9) -> 0 | CB77: =SUMIFS($D77:$AJ77,$D$3:$AJ$3,"LTM") -> 0 | CC77: =CC$38*CG77 -> 0 | CD77: =CD$38*CH77 -> 0 | CE77: =CE$38*CI77 -> 0 | CG77: 0 | CH77: 0 | CI77: 0 | CK77: =IFERROR(CB77/CB$38,0) -> 0 | CM77: =-SUMIFS('FY25 By Venue Financials'!$N:$N,'FY25 By Venue Financials'!$A:$A,$C77) -> 0 | CN77: =IFERROR(CM77/CM$38,0) -> 0 | CP77: % Total Rev | CQ77: NA
C78: Other Operating Expenses | D78: =-SUMIFS('P&L'!C:C,'P&L'!$A:$A,$C78)/1000 -> -0.25 | E78: =-SUMIFS('P&L'!D:D,'P&L'!$A:$A,$C78)/1000 -> -0.1 | F78: =-SUMIFS('P&L'!E:E,'P&L'!$A:$A,$C78)/1000 -> -1.01726 | G78: =-SUMIFS('P&L'!F:F,'P&L'!$A:$A,$C78)/1000 -> -1.20043 | H78: =-SUMIFS('P&L'!G:G,'P&L'!$A:$A,$C78)/1000 -> -0.245 | I78: =-SUMIFS('P&L'!H:H,'P&L'!$A:$A,$C78)/1000 -> 0.45 | J78: =-SUMIFS('P&L'!I:I,'P&L'!$A:$A,$C78)/1000 -> 0 | K78: =-SUMIFS('P&L'!J:J,'P&L'!$A:$A,$C78)/1000 -> 0 | L78: =-SUMIFS('P&L'!K:K,'P&L'!$A:$A,$C78)/1000 -> 0 | M78: =-SUMIFS('P&L'!L:L,'P&L'!$A:$A,$C78)/1000 -> -0.69177 | N78: =-SUMIFS('P&L'!M:M,'P&L'!$A:$A,$C78)/1000 -> -0.21331 | O78: =-SUMIFS('P&L'!N:N,'P&L'!$A:$A,$C78)/1000 -> -1.61646 | P78: =-SUMIFS('P&L'!O:O,'P&L'!$A:$A,$C78)/1000 -> -0.25 | Q78: =-SUMIFS('P&L'!P:P,'P&L'!$A:$A,$C78)/1000 -> -0.56221 | R78: =-SUMIFS('P&L'!Q:Q,'P&L'!$A:$A,$C78)/1000 -> -0.15629 | S78: =-SUMIFS('P&L'!R:R,'P&L'!$A:$A,$C78)/1000 -> -1.41511 | T78: =-SUMIFS('P&L'!S:S,'P&L'!$A:$A,$C78)/1000 -> -0.77926 | U78: =-SUMIFS('P&L'!T:T,'P&L'!$A:$A,$C78)/1000 -> -0.8167 | V78: =-SUMIFS('P&L'!U:U,'P&L'!$A:$A,$C78)/1000 -> -0.31426 | W78: =-SUMIFS('P&L'!V:V,'P&L'!$A:$A,$C78)/1000 -> 0 | X78: =-SUMIFS('P&L'!W:W,'P&L'!$A:$A,$C78)/1000 -> -0.79795 | Y78: =-SUMIFS('P&L'!X:X,'P&L'!$A:$A,$C78)/1000 -> -0.30862 | Z78: =-SUMIFS('P&L'!Y:Y,'P&L'!$A:$A,$C78)/1000 -> 0 | AA78: =-SUMIFS('P&L'!Z:Z,'P&L'!$A:$A,$C78)/1000 -> -2.45 | AB78: =-SUMIFS('P&L'!AA:AA,'P&L'!$A:$A,$C78)/1000 -> -0.06 | AC78: =-SUMIFS('P&L'!AB:AB,'P&L'!$A:$A,$C78)/1000 -> 0 | AD78: =-SUMIFS('P&L'!AC:AC,'P&L'!$A:$A,$C78)/1000 -> -2.45 | AE78: =-SUMIFS('P&L'!AD:AD,'P&L'!$A:$A,$C78)/1000 -> 0 | AF78: =-SUMIFS('P&L'!AE:AE,'P&L'!$A:$A,$C78)/1000 -> -2.45 | AG78: =-SUMIFS('P&L'!AF:AF,'P&L'!$A:$A,$C78)/1000 -> 0 | AH78: =-SUMIFS('P&L'!AG:AG,'P&L'!$A:$A,$C78)/1000 -> -1.5242 | AK78: =SUMIFS($CC78:$CE78,$CC$1:$CE$1,AK$3)/12 -> -1.3522238 | AL78: =SUMIFS($CC78:$CE78,$CC$1:$CE$1,AL$3)/12 -> -1.3522238 | AM78: =SUMIFS($CC78:$CE78,$CC$1:$CE$1,AM$3)/12 -> -1.3522238 | AN78: =SUMIFS($CC78:$CE78,$CC$1:$CE$1,AN$3)/12 -> -1.3522238 | AO78: =SUMIFS($CC78:$CE78,$CC$1:$CE$1,AO$3)/12 -> -1.3522238 | AP78: =SUMIFS($CC78:$CE78,$CC$1:$CE$1,AP$3)/12 -> -1.3522238 | AQ78: =SUMIFS($CC78:$CE78,$CC$1:$CE$1,AQ$3)/12 -> -1.3522238 | AR78: =SUMIFS($CC78:$CE78,$CC$1:$CE$1,AR$3)/12 -> -1.3522238 | ... BT78: =SUMIFS($CC78:$CE78,$CC$1:$CE$1,BT$3)/12 -> -3.8820332 | BU78: =BI78 -> -3.8820332 | BV78: =BJ78 -> -3.8820332 | BW78: =BK78 -> -3.8820332 | BX78: =BL78 -> -3.8820332 | BZ78: =SUMIFS($D78:$AJ78,$D$1:$AJ$1,BZ$9) -> -4.88423 | CA78: =SUMIFS($D78:$AJ78,$D$1:$AJ$1,CA$9) -> -7.8504 | CB78: =SUMIFS($D78:$AJ78,$D$3:$AJ$3,"LTM") -> -10.04077 | CC78: =CC$38*CG78 -> -16.226685 | CD78: =CD$38*CH78 -> -31.323559 | CE78: =CE$38*CI78 -> -46.584398 | CG78: =$CK78 -> -0.01790278 | CH78: =$CK78 -> -0.01790278 | CI78: =$CK78 -> -0.01790278 | CK78: =IFERROR(CB78/CB$38,0) -> -0.01790278 | CM78: =-SUMIFS('FY25 By Venue Financials'!$N:$N,'FY25 By Venue Financials'!$A:$A,$C78) -> -31.20662 | CN78: =IFERROR(CM78/CM$38,0) -> -0.0044243153 | CP78: % Total Rev | CQ78: Split evently
C80: Total Operating Expenses | D80: =SUM(D64:D79) -> -30.65052 | E80: =SUM(E64:E79) -> -25.88882 | F80: =SUM(F64:F79) -> -21.93604 | G80: =SUM(G64:G79) -> -41.00963 | H80: =SUM(H64:H79) -> -7.98879 | I80: =SUM(I64:I79) -> -12.52887 | J80: =SUM(J64:J79) -> -24.33744 | K80: =SUM(K64:K79) -> -30.82246 | ... AH80: =SUM(AH64:AH79) -> -16.54444 | AK80: =SUM(AK64:AK79) -> -25.745092 | AL80: =SUM(AL64:AL79) -> -25.745092 | AM80: =SUM(AM64:AM79) -> -21.793846 | AN80: =SUM(AN64:AN79) -> -21.793846 | AO80: =SUM(AO64:AO79) -> -19.818223 | AP80: =SUM(AP64:AP79) -> -19.818223 | AQ80: =SUM(AQ64:AQ79) -> -20.806034 | AR80: =SUM(AR64:AR79) -> -23.769469 | ... BX80: =SUM(BX64:BX79) -> -37.418536 | BZ80: =SUM(BZ64:BZ79) -> -281.08409 | CA80: =SUM(CA64:CA79) -> -263.11643 | CB80: =SUM(CB64:CB79) -> -260.148 | CC80: =SUM(CC64:CC79) -> -277.33113 | CD80: =SUM(CD64:CD79) -> -381.1923 | CE80: =SUM(CE64:CE79) -> -456.92493 | CG80: =IFERROR(CC80/CC$38,0) -> -0.30597735 | CH80: =IFERROR(CD80/CD$38,0) -> -0.21786802 | CI80: =IFERROR(CE80/CE$38,0) -> -0.17560013 | CM80: =SUM(CM64:CM79) -> -591.45916 | CN80: =IFERROR(CM80/CM$38,0) -> -0.08385406
C82: EBITDAR | D82: =D49+D61+D80 -> -54.92449 | E82: =E49+E61+E80 -> -37.04991 | F82: =F49+F61+F80 -> 1.08484 | G82: =G49+G61+G80 -> 12.11755 | H82: =H49+H61+H80 -> 22.75238 | I82: =I49+I61+I80 -> 60.04227 | J82: =J49+J61+J80 -> -24.93957 | K82: =K49+K61+K80 -> -42.37144 | ... AH82: =AH49+AH61+AH80 -> -19.33026 | AK82: =AK49+AK61+AK80 -> 75.007702 | AL82: =AL49+AL61+AL80 -> 75.007702 | AM82: =AM49+AM61+AM80 -> -0.47847014 | AN82: =AN49+AN61+AN80 -> -0.47847014 | AO82: =AO49+AO61+AO80 -> -38.221556 | AP82: =AP49+AP61+AP80 -> -38.221556 | AQ82: =AQ49+AQ61+AQ80 -> -19.350013 | AR82: =AR49+AR61+AR80 -> 37.264616 | ... BX82: =BX49+BX61+BX80 -> 104.73525 | BZ82: =BZ49+BZ61+BZ80 -> -96.09679 | CA82: =CA49+CA61+CA80 -> -97.52735 | CB82: =CB49+CB61+CB80 -> -23.74334 | CC82: =CC49+CC61+CC80 -> 296.20305 | CD82: =CD49+CD61+CD80 -> 889.00241 | CE82: =CE49+CE61+CE80 -> 1464.491 | CG82: =IFERROR(CC82/CC$38,0) -> 0.32679859 | CH82: =IFERROR(CD82/CD$38,0) -> 0.50810365 | CI82: =IFERROR(CE82/CE$38,0) -> 0.56281633 | CK82: =IFERROR(CB82/CB$38,0) -> -0.04233458 | CM82: =CM49+CM61+CM80 -> 3987.3506 | CN82: =IFERROR(CM82/CM$38,0) -> 0.56530622 | CP82: % Total Rev
C84: Rent | AK84: -23.75 | AL84: =AK84 -> -23.75 | AM84: =AL84 -> -23.75 | AN84: =AM84 -> -23.75 | AO84: =AN84 -> -23.75 | AP84: =AO84 -> -23.75 | AQ84: =AP84 -> -23.75 | AR84: =AQ84 -> -23.75 | AS84: =AR84 -> -23.75 | ... AV84: =AU84 -> -23.75 | AW84: -23.75 | AX84: =AW84 -> -23.75 | AY84: =AX84 -> -23.75 | AZ84: =AY84 -> -23.75 | BA84: =AZ84 -> -23.75 | BB84: =BA84 -> -23.75 | BC84: =BB84 -> -23.75 | BD84: =BC84 -> -23.75 | BE84: =BD84 -> -23.75 | ... BH84: =BG84 -> -23.75 | BI84: -24.7 | BJ84: =BI84 -> -24.7 | BK84: =BJ84 -> -24.7 | BL84: =BK84 -> -24.7 | BM84: =BL84 -> -24.7 | BN84: =BM84 -> -24.7 | BO84: =BN84 -> -24.7 | BP84: =BO84 -> -24.7 | BQ84: =BP84 -> -24.7 | ... BT84: =BS84 -> -24.7 | BU84: -25.688 | BV84: =BU84 -> -25.688 | BW84: =BV84 -> -25.688 | BX84: =BW84 -> -25.688 | CC84: =SUMIFS($AK$84:$BX$84,$AK$3:$BX$3,CC$1) -> -285 | CD84: =SUMIFS($AK$84:$BX$84,$AK$3:$BX$3,CD$1) -> -285 | CE84: =SUMIFS($AK$84:$BX$84,$AK$3:$BX$3,CE$1) -> -296.4
C86: EBITDA | D86: =D82+D84 -> -54.92449 | E86: =E82+E84 -> -37.04991 | F86: =F82+F84 -> 1.08484 | G86: =G82+G84 -> 12.11755 | H86: =H82+H84 -> 22.75238 | I86: =I82+I84 -> 60.04227 | J86: =J82+J84 -> -24.93957 | K86: =K82+K84 -> -42.37144 | ... AH86: =AH82+AH84 -> -19.33026 | AK86: =AK82+AK84 -> 51.257702 | AL86: =AL82+AL84 -> 51.257702 | AM86: =AM82+AM84 -> -24.22847 | AN86: =AN82+AN84 -> -24.22847 | AO86: =AO82+AO84 -> -61.971556 | AP86: =AP82+AP84 -> -61.971556 | AQ86: =AQ82+AQ84 -> -43.100013 | AR86: =AR82+AR84 -> 13.514616 | ... BX86: =BX82+BX84 -> 79.047249 | BZ86: =BZ82+BZ84 -> -96.09679 | CA86: =CA82+CA84 -> -97.52735 | CB86: =CB82+CB84 -> -23.74334 | CC86: =CC82+CC84 -> 11.203046 | CD86: =CD82+CD84 -> 604.00241 | CE86: =CE82+CE84 -> 1168.091 | CG86: =IFERROR(CC86/CC$38,0) -> 0.012360236 | CH86: =IFERROR(CD86/CD$38,0) -> 0.34521372 | CI86: =IFERROR(CE86/CE$38,0) -> 0.44890729 | CK86: =CK82+CK84 -> -0.04233458 | CM86: =CM82+CM84 -> 3987.3506 | CN86: =CN82+CN84 -> 0.56530622
C88: Checks | D88: =D47+D61+D80+'P&L'!C92/1000 -> 0 | E88: =E47+E61+E80+'P&L'!D92/1000 -> 0 | F88: =F47+F61+F80+'P&L'!E92/1000 -> 0 | G88: =G47+G61+G80+'P&L'!F92/1000 -> 0 | H88: =H47+H61+H80+'P&L'!G92/1000 -> 0 | I88: =I47+I61+I80+'P&L'!H92/1000 -> 0 | J88: =J47+J61+J80+'P&L'!I92/1000 -> 0 | K88: =K47+K61+K80+'P&L'!J92/1000 -> 0 | ... AH88: =AH47+AH61+AH80+'P&L'!AG92/1000 -> 0 | BZ88: =SUMIFS($D86:$AJ86,$D$1:$AJ$1,BZ$9)-$BZ$86 -> 0 | CA88: =SUMIFS($D86:$AJ86,$D$1:$AJ$1,CA$9)-CA86 -> 0 | CB88: =SUMIFS($D86:$AJ86,$D$3:$AJ$3,"LTM")-CB86 -> 0
C90: Seasonality
C91: Leads | AK91: 0.08 | AL91: 0.08 | AM91: 0.07 | AN91: 0.07 | AO91: 0.13 | AP91: 0.09 | AQ91: 0.08 | AR91: 0.08 | AS91: 0.08 | AT91: 0.08 | AU91: 0.08 | AV91: 0.08 | AW91: =AK91 -> 0.08 | AX91: =AL91 -> 0.08 | AY91: =AM91 -> 0.07 | AZ91: =AN91 -> 0.07 | BA91: =AO91 -> 0.13 | BB91: =AP91 -> 0.09 | BC91: =AQ91 -> 0.08 | BD91: =AR91 -> 0.08 | ... BX91: =BL91 -> 0.07
C92: Tours | D92: =INDEX(AGA!$U:$U,MATCH(D$2,AGA!$S:$S,0)) -> 0.1176952 | E92: =INDEX(AGA!$U:$U,MATCH(E$2,AGA!$S:$S,0)) -> 0.081462444 | F92: =INDEX(AGA!$U:$U,MATCH(F$2,AGA!$S:$S,0)) -> 0.076562199 | G92: =INDEX(AGA!$U:$U,MATCH(G$2,AGA!$S:$S,0)) -> 0.068624346 | H92: =INDEX(AGA!$U:$U,MATCH(H$2,AGA!$S:$S,0)) -> 0.061739285 | I92: =INDEX(AGA!$U:$U,MATCH(I$2,AGA!$S:$S,0)) -> 0.070612147 | J92: =INDEX(AGA!$U:$U,MATCH(J$2,AGA!$S:$S,0)) -> 0.084810706 | K92: =INDEX(AGA!$U:$U,MATCH(K$2,AGA!$S:$S,0)) -> 0.074281315 | ... AI92: =INDEX(AGA!$U:$U,MATCH(AI$2,AGA!$S:$S,0)) -> 0.074281315 | AK92: =INDEX(AGA!$U:$U,MATCH(AK$2,AGA!$S:$S,0)) -> 0.084583843 | AL92: =INDEX(AGA!$U:$U,MATCH(AL$2,AGA!$S:$S,0)) -> 0.084539487 | AM92: =INDEX(AGA!$U:$U,MATCH(AM$2,AGA!$S:$S,0)) -> 0.094860298 | AN92: =INDEX(AGA!$U:$U,MATCH(AN$2,AGA!$S:$S,0)) -> 0.10022873 | AO92: =INDEX(AGA!$U:$U,MATCH(AO$2,AGA!$S:$S,0)) -> 0.1176952 | AP92: =INDEX(AGA!$U:$U,MATCH(AP$2,AGA!$S:$S,0)) -> 0.081462444 | AQ92: =INDEX(AGA!$U:$U,MATCH(AQ$2,AGA!$S:$S,0)) -> 0.076562199 | AR92: =INDEX(AGA!$U:$U,MATCH(AR$2,AGA!$S:$S,0)) -> 0.068624346 | ... BX92: =INDEX(AGA!$U:$U,MATCH(BX$2,AGA!$S:$S,0)) -> 0.10022873
C93: Contracts | D93: =INDEX(AGA!$V:$V,MATCH(D$2,AGA!$S:$S,0)) -> 0.12478042 | E93: =INDEX(AGA!$V:$V,MATCH(E$2,AGA!$S:$S,0)) -> 0.098680213 | F93: =INDEX(AGA!$V:$V,MATCH(F$2,AGA!$S:$S,0)) -> 0.083554084 | G93: =INDEX(AGA!$V:$V,MATCH(G$2,AGA!$S:$S,0)) -> 0.078806163 | H93: =INDEX(AGA!$V:$V,MATCH(H$2,AGA!$S:$S,0)) -> 0.063719465 | I93: =INDEX(AGA!$V:$V,MATCH(I$2,AGA!$S:$S,0)) -> 0.073509107 | J93: =INDEX(AGA!$V:$V,MATCH(J$2,AGA!$S:$S,0)) -> 0.074655073 | K93: =INDEX(AGA!$V:$V,MATCH(K$2,AGA!$S:$S,0)) -> 0.079430014 | ... AI93: =INDEX(AGA!$V:$V,MATCH(AI$2,AGA!$S:$S,0)) -> 0.079430014 | AK93: =INDEX(AGA!$V:$V,MATCH(AK$2,AGA!$S:$S,0)) -> 0.071257575 | AL93: =INDEX(AGA!$V:$V,MATCH(AL$2,AGA!$S:$S,0)) -> 0.085240904 | AM93: =INDEX(AGA!$V:$V,MATCH(AM$2,AGA!$S:$S,0)) -> 0.070327512 | AN93: =INDEX(AGA!$V:$V,MATCH(AN$2,AGA!$S:$S,0)) -> 0.096039473 | AO93: =INDEX(AGA!$V:$V,MATCH(AO$2,AGA!$S:$S,0)) -> 0.12478042 | AP93: =INDEX(AGA!$V:$V,MATCH(AP$2,AGA!$S:$S,0)) -> 0.098680213 | AQ93: =INDEX(AGA!$V:$V,MATCH(AQ$2,AGA!$S:$S,0)) -> 0.083554084 | AR93: =INDEX(AGA!$V:$V,MATCH(AR$2,AGA!$S:$S,0)) -> 0.078806163 | ... BX93: =INDEX(AGA!$V:$V,MATCH(BX$2,AGA!$S:$S,0)) -> 0.096039473
C94: Events | D94: =INDEX(AGA!$W:$W,MATCH(D$2,AGA!$S:$S,0)) -> 0.044982847 | E94: =INDEX(AGA!$W:$W,MATCH(E$2,AGA!$S:$S,0)) -> 0.058016636 | F94: =INDEX(AGA!$W:$W,MATCH(F$2,AGA!$S:$S,0)) -> 0.078703584 | G94: =INDEX(AGA!$W:$W,MATCH(G$2,AGA!$S:$S,0)) -> 0.078777127 | H94: =INDEX(AGA!$W:$W,MATCH(H$2,AGA!$S:$S,0)) -> 0.092623931 | I94: =INDEX(AGA!$W:$W,MATCH(I$2,AGA!$S:$S,0)) -> 0.097320638 | J94: =INDEX(AGA!$W:$W,MATCH(J$2,AGA!$S:$S,0)) -> 0.079423627 | K94: =INDEX(AGA!$W:$W,MATCH(K$2,AGA!$S:$S,0)) -> 0.080631087 | ... AI94: =INDEX(AGA!$W:$W,MATCH(AI$2,AGA!$S:$S,0)) -> 0.080631087 | AK94: =INDEX(AGA!$W:$W,MATCH(AK$2,AGA!$S:$S,0)) -> 0.097389487 | AL94: =INDEX(AGA!$W:$W,MATCH(AL$2,AGA!$S:$S,0)) -> 0.11295986 | AM94: =INDEX(AGA!$W:$W,MATCH(AM$2,AGA!$S:$S,0)) -> 0.099464075 | AN94: =INDEX(AGA!$W:$W,MATCH(AN$2,AGA!$S:$S,0)) -> 0.079707106 | AO94: =INDEX(AGA!$W:$W,MATCH(AO$2,AGA!$S:$S,0)) -> 0.044982847 | AP94: =INDEX(AGA!$W:$W,MATCH(AP$2,AGA!$S:$S,0)) -> 0.058016636 | AQ94: =INDEX(AGA!$W:$W,MATCH(AQ$2,AGA!$S:$S,0)) -> 0.078703584 | AR94: =INDEX(AGA!$W:$W,MATCH(AR$2,AGA!$S:$S,0)) -> 0.078777127 | ... BX94: =INDEX(AGA!$W:$W,MATCH(BX$2,AGA!$S:$S,0)) -> 0.079707106

Sheet Revenue Analysis
C3: =Summary!$C$3 -> Hadden Estate
C4: Revenue Analysis
C6: $ in thousands | D6: =$C$3 -> Hadden Estate | K6: Drivers | O6: To Compare
D7: Historical | G7: PF | P7: WH Venue | Q7: WH Region
D8: =Summary!$D$11 -> 2024 | E8: =Summary!$D$12 -> 2025 | F8: =Summary!$D$13 -> LTM Jul-26 | G8: Y1 | H8: Y2 | I8: Y3 | K8: Y1 | L8: Y2 | M8: Y3 | O8: =C3 -> Hadden Estate | P8: ATL | Q8: ATL | R8: WH Average
C10: Events
C11: OC | D11: ='Events Summary'!$P$10 -> 42 | E11: ='Events Summary'!$P$11 -> 43 | F11: ='Events Summary'!$P$12 -> 39 | G11: ='Events Summary'!$P$14 -> 24 | H11: ='Events Summary'!$P$15 -> 1 | I11: 0
C12: New | G12: =G13-G11 -> 16 | H12: =H13-H11 -> 64 | I12: =I13-I11 -> 80
C13: Total | D13: =SUM(D11:D12) -> 42 | E13: =SUM(E11:E12) -> 43 | F13: =SUM(F11:F12) -> 39 | G13: 40 | H13: 65 | I13: 80 | P13: =INDEX('WH Rev & Events Data'!13:13,MATCH(P$8,'WH Rev & Events Data'!$8:$8,0)) -> 245 | Q13: =INDEX('WH Rev & Events Data'!13:13,MATCH(Q$8,'WH Rev & Events Data'!$8:$8,0)) -> 245 | R13: =INDEX('WH Rev & Events Data'!13:13,MATCH(R$8,'WH Rev & Events Data'!$8:$8,0)) -> 3035
C15: Revenue
C16: OC | D16: =('Events Summary'!$Q$10)/1000 -> 405.27832 | E16: =('Events Summary'!$Q$11)/1000 -> 403.06514 | F16: =('Events Summary'!$Q$12)/1000 -> 545.81013 | G16: =('Events Summary'!$Q$14)/1000 -> 546.4 | H16: =('Events Summary'!$Q$15)/1000 -> 19.5 | I16: 0
C17: OC New Rev | G17: =G71-G16 -> 0 | H17: =H71-H16 -> 0 | I17: =I71-I16 -> 0
C18: New Contracts | G18: =G87 -> 349.02892 | H18: =H87 -> 1723.0687 | I18: =I87 -> 2598.9092
C19: Total | D19: =SUM(D16:D18) -> 405.27832 | E19: =SUM(E16:E18) -> 403.06514 | F19: =SUM(F16:F18) -> 545.81013 | G19: =SUM(G16:G18) -> 895.42892 | H19: =SUM(H16:H18) -> 1742.5687 | I19: =SUM(I16:I18) -> 2598.9092
C21: $ / Event
C22: OC | D22: =IFERROR(D16/D11,0) -> 9.6494838 | E22: =IFERROR(E16/E11,0) -> 9.3736079 | F22: =IFERROR(F16/F11,0) -> 13.995132 | G22: =IFERROR(G16/G11,0) -> 22.766667 | H22: =IFERROR(H16/H11,0) -> 19.5 | I22: =IFERROR(I16/I11,0) -> 0
C23: OC New Rev | G23: =IFERROR(G17/G11,0) -> 0 | H23: =IFERROR(H17/H11,0) -> 0 | I23: =IFERROR(I17/I11,0) -> 0
C24: New Contracts | G24: =IFERROR(G18/G12,0) -> 21.814308 | H24: =IFERROR(H18/H12,0) -> 26.922949 | I24: =IFERROR(I18/I12,0) -> 32.486365
C25: Total | D25: =IFERROR(D19/D13,0) -> 9.6494838 | E25: =IFERROR(E19/E13,0) -> 9.3736079 | F25: =IFERROR(F19/F13,0) -> 13.995132 | G25: =IFERROR(G19/G13,0) -> 22.385723 | H25: =IFERROR(H19/H13,0) -> 26.808749 | I25: =IFERROR(I19/I13,0) -> 32.486365
C27: EVENTS | K27: % of Total Events
C28: Events - OC
C29: Room Rental | D29: ='Events Summary'!$D$10 -> 42 | E29: ='Events Summary'!$D$11 -> 43 | F29: ='Events Summary'!$D$12 -> 39 | G29: ='Events Summary'!$D$14 -> 24 | H29: ='Events Summary'!$D$15 -> 1 | I29: ='Events Summary'!$D$16 -> 0 | K29: 1 | L29: 1 | M29: 1
C30: Food | G30: =ROUND(G$11*K30,0) -> 0 | H30: =ROUND(H$11*L30,0) -> 0 | I30: =ROUND(I$11*M30,0) -> 0 | K30: 0 | L30: 0 | M30: 0 | O30: 0 | P30: 0 | Q30: 0 | R30: 0 | T30: <- not assuming any additional attachment given Danielle is working with most of these
C31: Beverage | G31: =ROUND(G$11*K31,0) -> 0 | H31: =ROUND(H$11*L31,0) -> 0 | I31: =ROUND(I$11*M31,0) -> 0 | K31: 0 | L31: 0 | M31: 0 | O31: 0 | P31: 0 | Q31: 0 | R31: 0
C32: Lodgings | D32: ='Events Summary'!$H$10 -> 9 | E32: ='Events Summary'!$H$11 -> 13 | F32: ='Events Summary'!$H$12 -> 15 | G32: ='Events Summary'!$H$14 -> 12 | H32: ='Events Summary'!$H$15 -> 0 | I32: ='Events Summary'!$H$16 -> 0 | K32: =G32/G$29 -> 0.5 | L32: =H32/H$29 -> 0 | M32: 0 | O32: =G32/G$29 -> 0.5 | P32: 0 | Q32: 0 | R32: 0 | T32: <- historical, not assuming additional
C33: DJ | G33: =ROUND(G$11*K33,0) -> 0 | H33: =ROUND(H$11*L33,0) -> 0 | I33: =ROUND(I$11*M33,0) -> 0 | K33: 0 | L33: 0 | M33: 0 | O33: 0 | P33: =INDEX('WH Rev & Events Data'!27:27,MATCH(P$8,'WH Rev & Events Data'!$8:$8,0)) -> 0.76734694 | Q33: =INDEX('WH Rev & Events Data'!27:27,MATCH(Q$8,'WH Rev & Events Data'!$8:$8,0)) -> 0.76734694 | R33: =INDEX('WH Rev & Events Data'!27:27,MATCH(R$8,'WH Rev & Events Data'!$8:$8,0)) -> 0.69028007
C34: Floral | G34: =ROUND(G$11*K34,0) -> 0 | H34: =ROUND(H$11*L34,0) -> 0 | I34: =ROUND(I$11*M34,0) -> 0 | K34: 0 | L34: 0 | M34: 0 | O34: 0 | P34: =INDEX('WH Rev & Events Data'!28:28,MATCH(P$8,'WH Rev & Events Data'!$8:$8,0)) -> 0.47755102 | Q34: =INDEX('WH Rev & Events Data'!28:28,MATCH(Q$8,'WH Rev & Events Data'!$8:$8,0)) -> 0.47755102 | R34: =INDEX('WH Rev & Events Data'!28:28,MATCH(R$8,'WH Rev & Events Data'!$8:$8,0)) -> 0.53937397
C35: Bakery | G35: =ROUND(G$11*K35,0) -> 0 | H35: =ROUND(H$11*L35,0) -> 0 | I35: =ROUND(I$11*M35,0) -> 0 | K35: 0 | L35: 0 | M35: 0 | O35: 0 | P35: =INDEX('WH Rev & Events Data'!29:29,MATCH(P$8,'WH Rev & Events Data'!$8:$8,0)) -> 0.32244898 | Q35: =INDEX('WH Rev & Events Data'!29:29,MATCH(Q$8,'WH Rev & Events Data'!$8:$8,0)) -> 0.32244898 | R35: =INDEX('WH Rev & Events Data'!29:29,MATCH(R$8,'WH Rev & Events Data'!$8:$8,0)) -> 0.44250412
C36: Stationery | G36: =ROUND(G$11*K36,0) -> 0 | H36: =ROUND(H$11*L36,0) -> 0 | I36: =ROUND(I$11*M36,0) -> 0 | K36: 0 | L36: 0 | M36: 0 | O36: 0 | P36: =INDEX('WH Rev & Events Data'!30:30,MATCH(P$8,'WH Rev & Events Data'!$8:$8,0)) -> 0.77959184 | Q36: =INDEX('WH Rev & Events Data'!30:30,MATCH(Q$8,'WH Rev & Events Data'!$8:$8,0)) -> 0.77959184 | R36: =INDEX('WH Rev & Events Data'!30:30,MATCH(R$8,'WH Rev & Events Data'!$8:$8,0)) -> 0.5937397
C37: Photography | G37: =ROUND(G$11*K37,0) -> 0 | H37: =ROUND(H$11*L37,0) -> 0 | I37: =ROUND(I$11*M37,0) -> 0 | K37: 0 | L37: 0 | M37: 0 | O37: 0 | P37: =INDEX('WH Rev & Events Data'!31:31,MATCH(P$8,'WH Rev & Events Data'!$8:$8,0)) -> 0.34285714 | Q37: =INDEX('WH Rev & Events Data'!31:31,MATCH(Q$8,'WH Rev & Events Data'!$8:$8,0)) -> 0.34285714 | R37: =INDEX('WH Rev & Events Data'!31:31,MATCH(R$8,'WH Rev & Events Data'!$8:$8,0)) -> 0.44975288
C38: Other Ancillary | D38: ='Events Summary'!$L$10 -> 10 | E38: ='Events Summary'!$L$11 -> 9 | F38: ='Events Summary'!$L$12 -> 17 | G38: ='Events Summary'!$L$14 -> 8 | H38: ='Events Summary'!$L$15 -> 0 | I38: ='Events Summary'!$L$16 -> 0 | K38: =G38/G$29 -> 0.33333333 | L38: =H38/H$29 -> 0 | M38: 0 | O38: =G38/G$29 -> 0.33333333
C40: Total OC Events | D40: =D11 -> 42 | E40: =E11 -> 43 | F40: =F11 -> 39 | G40: =G11 -> 24 | H40: =H11 -> 1 | I40: =I11 -> 0
C42: Events - NEW CONTRACT
C43: Room Rental | G43: =G$12*K43 -> 16 | H43: =H$12*L43 -> 64 | I43: =I$12*M43 -> 80 | K43: 1 | L43: 1 | M43: 1
C44: Food | G44: =G$12*K44 -> 0 | H44: =H$12*L44 -> 32 | I44: =I$12*M44 -> 80 | K44: 0 | L44: 0.5 | M44: 1 | O44: 0 | P44: 0 | Q44: 0 | R44: 0 | T44: <- will need to build out their catering kitchen, assume we can do that in the next 6mo to start selling / attaching by beginning of Y2, assuming ~50% ramp up from then to 75% in Y3
C45: Beverage | G45: =G$12*K45 -> 8 | H45: =H$12*L45 -> 48 | I45: =I$12*M45 -> 80 | K45: 0.5 | L45: 0.75 | M45: 1 | O45: 0 | P45: 0 | Q45: 0 | R45: 0 | T45: <- Assuming we can start selling now for 2027 events, so assuming 50% of Y2 then 75% of Y3 as it likely won't be required
C46: Lodgings | G46: =G$12*K46 -> 8 | H46: =H$12*L46 -> 32 | I46: =I$12*M46 -> 40 | K46: 0.5 | L46: 0.5 | M46: 0.5 | O46: =O32 -> 0.5 | P46: 0 | Q46: 0 | R46: 0 | T46: <- ~50% LTM, team thinks this will increase as we're starting to include in all packages so assuming 75%
C47: DJ | G47: =G$12*K47 -> 1.8416327 | H47: =H$12*L47 -> 24.555102 | I47: =I$12*M47 -> 49.110204 | K47: =$Q47*0.15 -> 0.11510204 | L47: =$Q47*0.5 -> 0.38367347 | M47: =$Q47*0.8 -> 0.61387755 | O47: =O33 -> 0 | P47: =P33 -> 0.76734694 | Q47: =Q33 -> 0.76734694 | R47: =R33 -> 0.69028007 | T47: <- start selling in September for events to occur in November 2026+ - 15% // 50% // 80% of ATL Average - people want bands more here so not hitting 100%
C48: Floral | G48: =G$12*K48 -> 1.1461224 | H48: =H$12*L48 -> 15.281633 | I48: =I$12*M48 -> 38.204082 | K48: =$Q48*0.15 -> 0.071632653 | L48: =$Q48*0.5 -> 0.23877551 | M48: =$Q48*1 -> 0.47755102 | O48: =O34 -> 0 | P48: =P34 -> 0.47755102 | Q48: =Q34 -> 0.47755102 | R48: =R34 -> 0.53937397 | T48: <- start selling in September for events to occur as soon as we have packaging - assuming November 2026+ - 15% // 50% // 100% of ATL Average
C49: Bakery | G49: =G$12*K49 -> 0.77387755 | H49: =H$12*L49 -> 10.318367 | I49: =I$12*M49 -> 25.795918 | K49: =$Q49*0.15 -> 0.048367347 | L49: =$Q49*0.5 -> 0.16122449 | M49: =$Q49*1 -> 0.32244898 | O49: =O35 -> 0 | P49: =P35 -> 0.32244898 | Q49: =Q35 -> 0.32244898 | R49: =R35 -> 0.44250412 | T49: <- start selling in September for events to occur as soon as we have packaging - assuming November 2026+ - 15% // 50% // 100% of ATL Average
C50: Stationery | G50: =G$12*K50 -> 1.8710204 | H50: =H$12*L50 -> 24.946939 | I50: =I$12*M50 -> 62.367347 | K50: =$Q50*0.15 -> 0.11693878 | L50: =$Q50*0.5 -> 0.38979592 | M50: =$Q50*1 -> 0.77959184 | O50: =O36 -> 0 | P50: =P36 -> 0.77959184 | Q50: =Q36 -> 0.77959184 | R50: =R36 -> 0.5937397 | T50: <- start selling in September for events to occur in November 2026+ - 15% // 50% // 100% of ATL Average
C51: Photography | G51: =G$12*K51 -> 0.82285714 | H51: =H$12*L51 -> 10.971429 | I51: =I$12*M51 -> 27.428571 | K51: =$Q51*0.15 -> 0.051428571 | L51: =$Q51*0.5 -> 0.17142857 | M51: =$Q51*1 -> 0.34285714 | O51: =O37 -> 0 | P51: =P37 -> 0.34285714 | Q51: =Q37 -> 0.34285714 | R51: =R37 -> 0.44975288 | T51: <- start selling in September for events to occur in November 2026+ - 15% // 50% // 100% of ATL Average
C52: Other Ancillary | G52: =G$12*K52 -> 5.3333333 | H52: =H$12*L52 -> 21.333333 | I52: =I$12*M52 -> 26.666667 | K52: =$O52 -> 0.33333333 | L52: =$O52 -> 0.33333333 | M52: =$O52 -> 0.33333333 | O52: =O38 -> 0.33333333 | T52: <- ~33% LTM, discuss if we think this will be higher
C54: Total NEW CONTRACT Events | D54: =D12 -> 0 | E54: =E12 -> 0 | F54: =F12 -> 0 | G54: =G12 -> 16 | H54: =H12 -> 64 | I54: =I12 -> 80
C56: Total Events | D56: =D40+D54 -> 42 | E56: =E40+E54 -> 43 | F56: =F40+F54 -> 39 | G56: =G40+G54 -> 40 | H56: =H40+H54 -> 65 | I56: =I40+I54 -> 80
C58: REVENUE | K58: Avg. $ / Event
C59: Revenue OC
C60: Room Rental | D60: ='Events Summary'!$E$10/1000 -> 352.75965 | E60: ='Events Summary'!$E$11/1000 -> 319.97463 | F60: ='Events Summary'!$E$12/1000 -> 452.64363 | G60: ='Events Summary'!$E$14/1000 -> 485.35 | H60: ='Events Summary'!$E$15/1000 -> 19.5 | I60: ='Events Summary'!$E$16/1000 -> 0 | K60: =G22 -> 22.766667 | L60: =H22 -> 19.5 | M60: =I22 -> 0 | O60: 0 | P60: =INDEX('WH Rev & Events Data'!42:42,MATCH(P$8,'WH Rev & Events Data'!$8:$8,0)) -> 6.7207593 | Q60: =INDEX('WH Rev & Events Data'!42:42,MATCH(Q$8,'WH Rev & Events Data'!$8:$8,0)) -> 6.7207593 | R60: =INDEX('WH Rev & Events Data'!42:42,MATCH(R$8,'WH Rev & Events Data'!$8:$8,0)) -> 5.1467523
C61: Food | G61: =G30*K61 -> 0 | H61: =H30*L61 -> 0 | I61: =I30*M61 -> 0 | O61: 0 | P61: =INDEX('WH Rev & Events Data'!43:43,MATCH(P$8,'WH Rev & Events Data'!$8:$8,0)) -> 7.0684667 | Q61: =INDEX('WH Rev & Events Data'!43:43,MATCH(Q$8,'WH Rev & Events Data'!$8:$8,0)) -> 7.0684667 | R61: =INDEX('WH Rev & Events Data'!43:43,MATCH(R$8,'WH Rev & Events Data'!$8:$8,0)) -> 5.0523327
C62: Beverage | G62: =G31*K62 -> 0 | H62: =H31*L62 -> 0 | I62: =I31*M62 -> 0 | O62: 0 | P62: =INDEX('WH Rev & Events Data'!44:44,MATCH(P$8,'WH Rev & Events Data'!$8:$8,0)) -> 4.001998 | Q62: =INDEX('WH Rev & Events Data'!44:44,MATCH(Q$8,'WH Rev & Events Data'!$8:$8,0)) -> 4.001998 | R62: =INDEX('WH Rev & Events Data'!44:44,MATCH(R$8,'WH Rev & Events Data'!$8:$8,0)) -> 3.0830681
C63: Lodgings | D63: ='Events Summary'!$I$10/1000 -> 41.26 | E63: ='Events Summary'!$I$11/1000 -> 67.8 | F63: ='Events Summary'!$I$12/1000 -> 69.8 | G63: ='Events Summary'!$I$14/1000 -> 54.9 | H63: ='Events Summary'!$I$15/1000 -> 0 | I63: ='Events Summary'!$I$16/1000 -> 0 | K63: =G63/G32 -> 4.575 | L63: 0 | M63: 0 | O63: 0
C64: DJ | G64: =G33*K64 -> 0 | H64: =H33*L64 -> 0 | I64: =I33*M64 -> 0 | O64: 0 | P64: =INDEX('WH Rev & Events Data'!34:34,MATCH(P$8,'WH Rev & Events Data'!$8:$8,0)) -> 2.5192819 | Q64: =INDEX('WH Rev & Events Data'!34:34,MATCH(Q$8,'WH Rev & Events Data'!$8:$8,0)) -> 2.5192819 | R64: =INDEX('WH Rev & Events Data'!34:34,MATCH(R$8,'WH Rev & Events Data'!$8:$8,0)) -> 1.6865752
C65: Floral | G65: =G34*K65 -> 0 | H65: =H34*L65 -> 0 | I65: =I34*M65 -> 0 | O65: 0 | P65: =INDEX('WH Rev & Events Data'!35:35,MATCH(P$8,'WH Rev & Events Data'!$8:$8,0)) -> 3.0809578 | Q65: =INDEX('WH Rev & Events Data'!35:35,MATCH(Q$8,'WH Rev & Events Data'!$8:$8,0)) -> 3.0809578 | R65: =INDEX('WH Rev & Events Data'!35:35,MATCH(R$8,'WH Rev & Events Data'!$8:$8,0)) -> 3.2563306
C66: Bakery | G66: =G35*K66 -> 0 | H66: =H35*L66 -> 0 | I66: =I35*M66 -> 0 | O66: 0 | P66: =INDEX('WH Rev & Events Data'!36:36,MATCH(P$8,'WH Rev & Events Data'!$8:$8,0)) -> 1.252557 | Q66: =INDEX('WH Rev & Events Data'!36:36,MATCH(Q$8,'WH Rev & Events Data'!$8:$8,0)) -> 1.252557 | R66: =INDEX('WH Rev & Events Data'!36:36,MATCH(R$8,'WH Rev & Events Data'!$8:$8,0)) -> 1.1287598
C67: Stationery | G67: =G36*K67 -> 0 | H67: =H36*L67 -> 0 | I67: =I36*M67 -> 0 | O67: 0 | P67: =INDEX('WH Rev & Events Data'!37:37,MATCH(P$8,'WH Rev & Events Data'!$8:$8,0)) -> 0.81256937 | Q67: =INDEX('WH Rev & Events Data'!37:37,MATCH(Q$8,'WH Rev & Events Data'!$8:$8,0)) -> 0.81256937 | R67: =INDEX('WH Rev & Events Data'!37:37,MATCH(R$8,'WH Rev & Events Data'!$8:$8,0)) -> 0.79107037
C68: Photography | G68: =G37*K68 -> 0 | H68: =H37*L68 -> 0 | I68: =I37*M68 -> 0 | O68: 0 | P68: =INDEX('WH Rev & Events Data'!38:38,MATCH(P$8,'WH Rev & Events Data'!$8:$8,0)) -> 1.178 | Q68: =INDEX('WH Rev & Events Data'!38:38,MATCH(Q$8,'WH Rev & Events Data'!$8:$8,0)) -> 1.178 | R68: =INDEX('WH Rev & Events Data'!38:38,MATCH(R$8,'WH Rev & Events Data'!$8:$8,0)) -> 1.1105674
C69: Other Ancillary | D69: ='Events Summary'!M$10/1000 -> 11.25867 | E69: ='Events Summary'!M$11/1000 -> 15.29051 | F69: ='Events Summary'!M$12/1000 -> 23.3665 | G69: ='Events Summary'!M$14/1000 -> 6.15 | H69: ='Events Summary'!M$15/1000 -> 0 | I69: ='Events Summary'!M$16/1000 -> 0 | K69: =$O69 -> 0.63012295 | L69: =$O69 -> 0.63012295 | M69: =$O69 -> 0.63012295 | O69: ='Events Summary'!N14/1000/(1+$K$85) -> 0.63012295 | P69: =INDEX('WH Rev & Events Data'!39:39,MATCH(P$8,'WH Rev & Events Data'!$8:$8,0)) -> 0.46774694 | Q69: =INDEX('WH Rev & Events Data'!39:39,MATCH(Q$8,'WH Rev & Events Data'!$8:$8,0)) -> 0.46774694 | R69: =INDEX('WH Rev & Events Data'!39:39,MATCH(R$8,'WH Rev & Events Data'!$8:$8,0)) -> 0.66640874
C71: Total OC Revenue | D71: =SUM(D60:D70) -> 405.27832 | E71: =SUM(E60:E70) -> 403.06514 | F71: =SUM(F60:F70) -> 545.81013 | G71: =SUM(G60:G70) -> 546.4 | H71: =SUM(H60:H70) -> 19.5 | I71: =SUM(I60:I70) -> 0
C72: Average $ / OC Event | D72: =IFERROR(D71/D40,0) -> 9.6494838 | E72: =IFERROR(E71/E40,0) -> 9.3736079 | F72: =IFERROR(F71/F40,0) -> 13.995132 | G72: =IFERROR(G71/G40,0) -> 22.766667 | H72: =IFERROR(H71/H40,0) -> 19.5 | I72: =IFERROR(I71/I40,0) -> 0
C74: Revenue NEW CONTRACT
C75: Room Rental | G75: =G43*K75 -> 242.62295 | H75: =H43*L75 -> 970.4918 | I75: =I43*M75 -> 1213.1148 | K75: =(18.5)/(1+K85) -> 15.163934 | L75: =(18.5)/(1+L85) -> 15.163934 | M75: =L75 -> 15.163934 | O75: 0 | P75: =P60 -> 6.7207593 | Q75: =Q60 -> 6.7207593 | R75: =R60 -> 5.1467523 | T75: <- $18.5k venue rental fee on average, less 22% service charge
C76: Food | G76: =G44*K76 -> 0 | H76: =H44*L76 -> 161.67465 | I76: =I44*M76 -> 404.18662 | K76: =K61 -> 0 | L76: =$R76 -> 5.0523327 | M76: =$R76 -> 5.0523327 | O76: 0 | P76: =P61 -> 7.0684667 | Q76: =Q61 -> 7.0684667 | R76: =R61 -> 5.0523327 | T76: <- WH Average conservatively vs ATL Average
C77: Beverage | G77: =G45*K77 -> 6 | H77: =H45*L77 -> 36 | I77: =I45*M77 -> 60 | K77: =$O77 -> 0.75 | L77: =$O77 -> 0.75 | M77: =$O77 -> 0.75 | O77: 0.75 | P77: =P62 -> 4.001998 | Q77: =Q62 -> 4.001998 | R77: =R62 -> 3.0830681 | T77: <- Assuming we can start selling now for 2027 events, so assuming 50% of Y2 then 75% of Y3 as it likely won't be required
C78: Lodgings | G78: =G46*K78 -> 24 | H78: =H46*L78 -> 96 | I78: =I46*M78 -> 120 | K78: =$O78 -> 3 | L78: =$O78 -> 3 | M78: =$O78 -> 3 | O78: 3
C79: DJ | G79: =G47*K79 -> 3.1060519 | H79: =H47*L79 -> 41.414026 | I79: =I47*M79 -> 82.828051 | K79: =$R79 -> 1.6865752 | L79: =$R79 -> 1.6865752 | M79: =$R79 -> 1.6865752 | O79: 0 | P79: =P64 -> 2.5192819 | Q79: =Q64 -> 2.5192819 | R79: =R64 -> 1.6865752 | T79: <- WH Average conservatively vs ATL Average
C80: Floral | G80: =G48*K80 -> 3.7321536 | H80: =H48*L80 -> 49.762048 | I80: =I48*M80 -> 124.40512 | K80: =$R80 -> 3.2563306 | L80: =$R80 -> 3.2563306 | M80: =$R80 -> 3.2563306 | O80: 0 | P80: =P65 -> 3.0809578 | Q80: =Q65 -> 3.0809578 | R80: =R65 -> 3.2563306 | T80: <- WH Average conservatively vs ATL Average
C81: Bakery | G81: =G49*K81 -> 0.8735219 | H81: =H49*L81 -> 11.646959 | I81: =I49*M81 -> 29.117397 | K81: =$R81 -> 1.1287598 | L81: =$R81 -> 1.1287598 | M81: =$R81 -> 1.1287598 | O81: 0 | P81: =P66 -> 1.252557 | Q81: =Q66 -> 1.252557 | R81: =R66 -> 1.1287598 | T81: <- WH Average conservatively vs ATL Average
C82: Stationery | G82: =G50*K82 -> 1.4801088 | H82: =H50*L82 -> 19.734784 | I82: =I50*M82 -> 49.33696 | K82: =$R82 -> 0.79107037 | L82: =$R82 -> 0.79107037 | M82: =$R82 -> 0.79107037 | O82: 0 | P82: =P67 -> 0.81256937 | Q82: =Q67 -> 0.81256937 | R82: =R67 -> 0.79107037 | T82: <- WH Average conservatively vs ATL Average
C83: Photography | G83: =G51*K83 -> 0.91383829 | H83: =H51*L83 -> 12.184511 | I83: =I51*M83 -> 30.461276 | K83: =$R83 -> 1.1105674 | L83: =$R83 -> 1.1105674 | M83: =$R83 -> 1.1105674 | O83: 0 | P83: =P68 -> 1.178 | Q83: =Q68 -> 1.178 | R83: =R68 -> 1.1105674 | T83: <- WH Average conservatively vs ATL Average
C84: Other Ancillary | G84: =G52*K84 -> 3.3606557 | H84: =H52*L84 -> 13.442623 | I84: =I52*M84 -> 16.803279 | K84: =K69 -> 0.63012295 | L84: =L69 -> 0.63012295 | M84: =M69 -> 0.63012295 | O84: =O69 -> 0.63012295 | P84: =P69 -> 0.46774694 | Q84: =Q69 -> 0.46774694 | R84: =R69 -> 0.66640874 | T84: <- current average for add-on events less 22%
C85: Service Charge | G85: =K85*G93 -> 62.939642 | H85: =L85*H93 -> 310.71731 | I85: =M85*I93 -> 468.65576 | K85: 0.22 | L85: 0.22 | M85: 0.22 | O85: 0 | P85: =INDEX('WH Rev & Events Data'!45:45,MATCH(P$8,'WH Rev & Events Data'!$8:$8,0)) -> 4.9355404 | Q85: =INDEX('WH Rev & Events Data'!45:45,MATCH(Q$8,'WH Rev & Events Data'!$8:$8,0)) -> 4.9355404 | R85: =INDEX('WH Rev & Events Data'!45:45,MATCH(R$8,'WH Rev & Events Data'!$8:$8,0)) -> 3.7751451
C87: Total NEW CONTRACT Revenue | D87: =SUM(D75:D86) -> 0 | E87: =SUM(E75:E86) -> 0 | F87: =SUM(F75:F86) -> 0 | G87: =SUM(G75:G86) -> 349.02892 | H87: =SUM(H75:H86) -> 1723.0687 | I87: =SUM(I75:I86) -> 2598.9092
C88: Average $ / NEW CONTRACT Event | D88: =IFERROR(D87/D54,0) -> 0 | E88: =IFERROR(E87/E54,0) -> 0 | F88: =IFERROR(F87/F54,0) -> 0 | G88: =IFERROR(G87/G54,0) -> 21.814308 | H88: =IFERROR(H87/H54,0) -> 26.922949 | I88: =IFERROR(I87/I54,0) -> 32.486365
C90: Total Events | D90: =D71+D87 -> 405.27832 | E90: =E71+E87 -> 403.06514 | F90: =F71+F87 -> 545.81013 | G90: =G71+G87 -> 895.42892 | H90: =H71+H87 -> 1742.5687 | I90: =I71+I87 -> 2598.9092
C92: OC Revenue | G92: =G16 -> 546.4 | H92: =H16 -> 19.5 | I92: =I16 -> 0
C93: ALL New Revenue (OC and NC) | G93: =SUM(G$75:G$84)+(G71-G16) -> 286.08928 | H93: =SUM(H$75:H$84)+(H71-H16) -> 1412.3514 | I93: =SUM(I$75:I$84)+(I71-I16) -> 2130.2535
C96: CHECKS
C97: Revenue | D97: =D19-D90 -> 0 | E97: =E19-E90 -> 0 | F97: =F19-F90 -> 0 | G97: =G19-G90 -> 0 | H97: =H19-H90 -> 0 | I97: =I19-I90 -> 0
C98: Events | D98: =D13-D56 -> 0 | E98: =E13-E56 -> 0 | F98: =F13-F56 -> 0 | G98: =G13-G56 -> 0 | H98: =H13-H56 -> 0 | I98: =I13-I56 -> 0

Sheet Events Summary
C1: Jul | D1: {=INDEX($C:$C,MATCH($V$12,$U:$U,0)+11)} -> 46234
C3: =Summary!$C$3 -> Hadden Estate
C4: Booked Events Summary
D6: Venue Fee | H6: Lodging | L6: Other | P6: Total
C7: Item | D7: Events | E7: Revenue | F7: $ / Event | H7: Events | I7: Revenue | J7: $ / Event | L7: Events | M7: Revenue | N7: $ / Event | P7: Events | Q7: Revenue | R7: $ / Event | T7: Year | U7: LTM
C9: Summary
C10: =Summary!D11 -> 2024 | D10: =SUMIFS(D$19:D$66,$T$19:$T$66,$C10) -> 42 | E10: =SUMIFS(E$19:E$66,$T$19:$T$66,$C10) -> 352759.65 | F10: =IFERROR(E10/D10,0) -> 8399.0393 | H10: =SUMIFS(H$19:H$66,$T$19:$T$66,$C10) -> 9 | I10: =SUMIFS(I$19:I$66,$T$19:$T$66,$C10) -> 41260 | J10: =IFERROR(I10/H10,0) -> 4584.4444 | L10: =SUMIFS(L$19:L$66,$T$19:$T$66,$C10) -> 10 | M10: =SUMIFS(M$19:M$66,$T$19:$T$66,$C10) -> 11258.67 | N10: =IFERROR(M10/L10,0) -> 1125.867 | P10: =SUMIFS(P$19:P$66,$T$19:$T$66,$C10) -> 42 | Q10: =SUMIFS(Q$19:Q$66,$T$19:$T$66,$C10) -> 405278.32 | R10: =IFERROR(Q10/P10,0) -> 9649.4838
C11: =Summary!D12 -> 2025 | D11: =SUMIFS(D$19:D$66,$T$19:$T$66,$C11) -> 43 | E11: =SUMIFS(E$19:E$66,$T$19:$T$66,$C11) -> 319974.63 | F11: =IFERROR(E11/D11,0) -> 7441.2705 | H11: =SUMIFS(H$19:H$66,$T$19:$T$66,$C11) -> 13 | I11: =SUMIFS(I$19:I$66,$T$19:$T$66,$C11) -> 67800 | J11: =IFERROR(I11/H11,0) -> 5215.3846 | L11: =SUMIFS(L$19:L$66,$T$19:$T$66,$C11) -> 9 | M11: =SUMIFS(M$19:M$66,$T$19:$T$66,$C11) -> 15290.51 | N11: =IFERROR(M11/L11,0) -> 1698.9456 | P11: =SUMIFS(P$19:P$66,$T$19:$T$66,$C11) -> 43 | Q11: =SUMIFS(Q$19:Q$66,$T$19:$T$66,$C11) -> 403065.14 | R11: =IFERROR(Q11/P11,0) -> 9373.6079
C12: =Summary!D13 -> LTM Jul-26 | D12: =SUMIFS(D$19:D$66,$U$19:$U$66,$V12) -> 39 | E12: =SUMIFS(E$19:E$66,$U$19:$U$66,$V12) -> 452643.63 | F12: =IFERROR(E12/D12,0) -> 11606.247 | H12: =SUMIFS(H$19:H$66,$U$19:$U$66,$V12) -> 15 | I12: =SUMIFS(I$19:I$66,$U$19:$U$66,$V12) -> 69800 | J12: =IFERROR(I12/H12,0) -> 4653.3333 | L12: =SUMIFS(L$19:L$66,$U$19:$U$66,$V12) -> 17 | M12: =SUMIFS(M$19:M$66,$U$19:$U$66,$V12) -> 23366.5 | N12: =IFERROR(M12/L12,0) -> 1374.5 | P12: =SUMIFS(P$19:P$66,$U$19:$U$66,$V12) -> 39 | Q12: =SUMIFS(Q$19:Q$66,$U$19:$U$66,$V12) -> 545810.13 | R12: =IFERROR(Q12/P12,0) -> 13995.132 | V12: LTM 26 | W12: =COUNTIFS($U:$U,V12) -> 12
C14: =Summary!D14 -> LTM Aug-27 | D14: =SUMIFS(D$19:D$66,$U$19:$U$66,$V14) -> 24 | E14: =SUMIFS(E$19:E$66,$U$19:$U$66,$V14) -> 485350 | F14: =IFERROR(E14/D14,0) -> 20222.917 | H14: =SUMIFS(H$19:H$66,$U$19:$U$66,$V14) -> 12 | I14: =SUMIFS(I$19:I$66,$U$19:$U$66,$V14) -> 54900 | J14: =IFERROR(I14/H14,0) -> 4575 | L14: =SUMIFS(L$19:L$66,$U$19:$U$66,$V14) -> 8 | M14: =SUMIFS(M$19:M$66,$U$19:$U$66,$V14) -> 6150 | N14: =IFERROR(M14/L14,0) -> 768.75 | P14: =SUMIFS(P$19:P$66,$U$19:$U$66,$V14) -> 24 | Q14: =SUMIFS(Q$19:Q$66,$U$19:$U$66,$V14) -> 546400 | R14: =IFERROR(Q14/P14,0) -> 22766.667 | V14: LTM 27 | W14: =COUNTIFS($U:$U,V14) -> 12
C15: =Summary!D15 -> LTM Aug-28 | D15: =SUMIFS(D$19:D$66,$U$19:$U$66,$V15) -> 1 | E15: =SUMIFS(E$19:E$66,$U$19:$U$66,$V15) -> 19500 | F15: =IFERROR(E15/D15,0) -> 19500 | H15: =SUMIFS(H$19:H$66,$U$19:$U$66,$V15) -> 0 | I15: =SUMIFS(I$19:I$66,$U$19:$U$66,$V15) -> 0 | J15: =IFERROR(I15/H15,0) -> 0 | L15: =SUMIFS(L$19:L$66,$U$19:$U$66,$V15) -> 0 | M15: =SUMIFS(M$19:M$66,$U$19:$U$66,$V15) -> 0 | N15: =IFERROR(M15/L15,0) -> 0 | P15: =SUMIFS(P$19:P$66,$U$19:$U$66,$V15) -> 1 | Q15: =SUMIFS(Q$19:Q$66,$U$19:$U$66,$V15) -> 19500 | R15: =IFERROR(Q15/P15,0) -> 19500 | V15: LTM 28 | W15: =COUNTIFS($U:$U,V15) -> 12 | Y15: Seasonality
C16: =Summary!D16 -> LTM Aug-29 | D16: =SUMIFS(D$19:D$66,$U$19:$U$66,$V16) -> 0 | E16: =SUMIFS(E$19:E$66,$U$19:$U$66,$V16) -> 0 | F16: =IFERROR(E16/D16,0) -> 0 | H16: =SUMIFS(H$19:H$66,$U$19:$U$66,$V16) -> 0 | I16: =SUMIFS(I$19:I$66,$U$19:$U$66,$V16) -> 0 | J16: =IFERROR(I16/H16,0) -> 0 | L16: =SUMIFS(L$19:L$66,$U$19:$U$66,$V16) -> 0 | M16: =SUMIFS(M$19:M$66,$U$19:$U$66,$V16) -> 0 | N16: =IFERROR(M16/L16,0) -> 0 | P16: =SUMIFS(P$19:P$66,$U$19:$U$66,$V16) -> 0 | Q16: =SUMIFS(Q$19:Q$66,$U$19:$U$66,$V16) -> 0 | R16: =IFERROR(Q16/P16,0) -> 0 | V16: LTM 29 | W16: =COUNTIFS($U:$U,V16) -> 12 | Y16: % of CY | Z16: Month | AB16: Month | AC16: % Use
C18: Monthly
C19: 45322 | D19: =COUNTIFS('Full Events Detail'!$C:$C,$C19) -> 0 | E19: =SUMIFS('Full Events Detail'!$F:$F,'Full Events Detail'!$C:$C,$C19) -> 0 | F19: =IFERROR(E19/D19,0) -> 0 | H19: =COUNTIFS('Full Events Detail'!$C:$C,$C19,'Full Events Detail'!$G:$G,">"&0) -> 0 | I19: =SUMIFS('Full Events Detail'!$G:$G,'Full Events Detail'!$C:$C,$C19) -> 0 | J19: =IFERROR(I19/H19,0) -> 0 | L19: =COUNTIFS('Full Events Detail'!$C:$C,$C19,'Full Events Detail'!$H:$H,">"&0) -> 0 | M19: =SUMIFS('Full Events Detail'!$H:$H,'Full Events Detail'!$C:$C,$C19) -> 0 | N19: =IFERROR(M19/L19,0) -> 0 | P19: =D19 -> 0 | Q19: =E19+I19+M19 -> 0 | R19: =IFERROR(Q19/P19,0) -> 0 | T19: =YEAR(C19) -> 2024 | V19: =INDEX('Detailed P&L'!$3:$3,MATCH($C19,'Detailed P&L'!$9:$9,0)) -> 0 | Y19: =IFERROR(P19/SUMIFS($P$19:$P$78,$T$19:$T$78,T19),"-") -> 0 | Z19: 1 | AB19: 1 | AC19: =ROUND(AVERAGEIFS($Y$19:$Y$78,$Z$19:$Z$78,AB19),2) -> 0
C20: =EOMONTH(C19,1) -> 45351 | D20: =COUNTIFS('Full Events Detail'!$C:$C,$C20) -> 3 | E20: =SUMIFS('Full Events Detail'!$F:$F,'Full Events Detail'!$C:$C,$C20) -> 12126.65 | F20: =IFERROR(E20/D20,0) -> 4042.2167 | H20: =COUNTIFS('Full Events Detail'!$C:$C,$C20,'Full Events Detail'!$G:$G,">"&0) -> 1 | I20: =SUMIFS('Full Events Detail'!$G:$G,'Full Events Detail'!$C:$C,$C20) -> 4800 | J20: =IFERROR(I20/H20,0) -> 4800 | L20: =COUNTIFS('Full Events Detail'!$C:$C,$C20,'Full Events Detail'!$H:$H,">"&0) -> 1 | M20: =SUMIFS('Full Events Detail'!$H:$H,'Full Events Detail'!$C:$C,$C20) -> 1000 | N20: =IFERROR(M20/L20,0) -> 1000 | P20: =D20 -> 3 | Q20: =E20+I20+M20 -> 17926.65 | R20: =IFERROR(Q20/P20,0) -> 5975.55 | T20: =YEAR(C20) -> 2024 | V20: =INDEX('Detailed P&L'!$3:$3,MATCH($C20,'Detailed P&L'!$9:$9,0)) -> 0 | Y20: =IFERROR(P20/SUMIFS($P$19:$P$78,$T$19:$T$78,T20),"-") -> 0.071428571 | Z20: =Z19+1 -> 2 | AB20: =AB19+1 -> 2 | AC20: =ROUND(AVERAGEIFS($Y$19:$Y$78,$Z$19:$Z$78,AB20),2) -> 0.05
C21: =EOMONTH(C20,1) -> 45382 | D21: =COUNTIFS('Full Events Detail'!$C:$C,$C21) -> 5 | E21: =SUMIFS('Full Events Detail'!$F:$F,'Full Events Detail'!$C:$C,$C21) -> 50200 | F21: =IFERROR(E21/D21,0) -> 10040 | H21: =COUNTIFS('Full Events Detail'!$C:$C,$C21,'Full Events Detail'!$G:$G,">"&0) -> 0 | I21: =SUMIFS('Full Events Detail'!$G:$G,'Full Events Detail'!$C:$C,$C21) -> 0 | J21: =IFERROR(I21/H21,0) -> 0 | L21: =COUNTIFS('Full Events Detail'!$C:$C,$C21,'Full Events Detail'!$H:$H,">"&0) -> 0 | M21: =SUMIFS('Full Events Detail'!$H:$H,'Full Events Detail'!$C:$C,$C21) -> 0 | N21: =IFERROR(M21/L21,0) -> 0 | P21: =D21 -> 5 | Q21: =E21+I21+M21 -> 50200 | R21: =IFERROR(Q21/P21,0) -> 10040 | T21: =YEAR(C21) -> 2024 | V21: =INDEX('Detailed P&L'!$3:$3,MATCH($C21,'Detailed P&L'!$9:$9,0)) -> 0 | Y21: =IFERROR(P21/SUMIFS($P$19:$P$78,$T$19:$T$78,T21),"-") -> 0.11904762 | Z21: =Z20+1 -> 3 | AB21: =AB20+1 -> 3 | AC21: =ROUND(AVERAGEIFS($Y$19:$Y$78,$Z$19:$Z$78,AB21),2) -> 0.13
C22: =EOMONTH(C21,1) -> 45412 | D22: =COUNTIFS('Full Events Detail'!$C:$C,$C22) -> 4 | E22: =SUMIFS('Full Events Detail'!$F:$F,'Full Events Detail'!$C:$C,$C22) -> 58600 | F22: =IFERROR(E22/D22,0) -> 14650 | H22: =COUNTIFS('Full Events Detail'!$C:$C,$C22,'Full Events Detail'!$G:$G,">"&0) -> 2 | I22: =SUMIFS('Full Events Detail'!$G:$G,'Full Events Detail'!$C:$C,$C22) -> 10300 | J22: =IFERROR(I22/H22,0) -> 5150 | L22: =COUNTIFS('Full Events Detail'!$C:$C,$C22,'Full Events Detail'!$H:$H,">"&0) -> 3 | M22: =SUMIFS('Full Events Detail'!$H:$H,'Full Events Detail'!$C:$C,$C22) -> 3929 | N22: =IFERROR(M22/L22,0) -> 1309.6667 | P22: =D22 -> 4 | Q22: =E22+I22+M22 -> 72829 | R22: =IFERROR(Q22/P22,0) -> 18207.25 | T22: =YEAR(C22) -> 2024 | V22: =INDEX('Detailed P&L'!$3:$3,MATCH($C22,'Detailed P&L'!$9:$9,0)) -> 0 | Y22: =IFERROR(P22/SUMIFS($P$19:$P$78,$T$19:$T$78,T22),"-") -> 0.095238095 | Z22: =Z21+1 -> 4 | AB22: =AB21+1 -> 4 | AC22: =ROUND(AVERAGEIFS($Y$19:$Y$78,$Z$19:$Z$78,AB22),2) -> 0.11
C23: =EOMONTH(C22,1) -> 45443 | D23: =COUNTIFS('Full Events Detail'!$C:$C,$C23) -> 8 | E23: =SUMIFS('Full Events Detail'!$F:$F,'Full Events Detail'!$C:$C,$C23) -> 52982 | F23: =IFERROR(E23/D23,0) -> 6622.75 | H23: =COUNTIFS('Full Events Detail'!$C:$C,$C23,'Full Events Detail'!$G:$G,">"&0) -> 1 | I23: =SUMIFS('Full Events Detail'!$G:$G,'Full Events Detail'!$C:$C,$C23) -> 4700 | J23: =IFERROR(I23/H23,0) -> 4700 | L23: =COUNTIFS('Full Events Detail'!$C:$C,$C23,'Full Events Detail'!$H:$H,">"&0) -> 1 | M23: =SUMIFS('Full Events Detail'!$H:$H,'Full Events Detail'!$C:$C,$C23) -> 520 | N23: =IFERROR(M23/L23,0) -> 520 | P23: =D23 -> 8 | Q23: =E23+I23+M23 -> 58202 | R23: =IFERROR(Q23/P23,0) -> 7275.25 | T23: =YEAR(C23) -> 2024 | V23: =INDEX('Detailed P&L'!$3:$3,MATCH($C23,'Detailed P&L'!$9:$9,0)) -> 0 | Y23: =IFERROR(P23/SUMIFS($P$19:$P$78,$T$19:$T$78,T23),"-") -> 0.19047619 | Z23: =Z22+1 -> 5 | AB23: =AB22+1 -> 5 | AC23: =ROUND(AVERAGEIFS($Y$19:$Y$78,$Z$19:$Z$78,AB23),2) -> 0.23
C24: =EOMONTH(C23,1) -> 45473 | D24: =COUNTIFS('Full Events Detail'!$C:$C,$C24) -> 6 | E24: =SUMIFS('Full Events Detail'!$F:$F,'Full Events Detail'!$C:$C,$C24) -> 82000 | F24: =IFERROR(E24/D24,0) -> 13666.667 | H24: =COUNTIFS('Full Events Detail'!$C:$C,$C24,'Full Events Detail'!$G:$G,">"&0) -> 1 | I24: =SUMIFS('Full Events Detail'!$G:$G,'Full Events Detail'!$C:$C,$C24) -> 3800 | J24: =IFERROR(I24/H24,0) -> 3800 | L24: =COUNTIFS('Full Events Detail'!$C:$C,$C24,'Full Events Detail'!$H:$H,">"&0) -> 1 | M24: =SUMIFS('Full Events Detail'!$H:$H,'Full Events Detail'!$C:$C,$C24) -> 1248 | N24: =IFERROR(M24/L24,0) -> 1248 | P24: =D24 -> 6 | Q24: =E24+I24+M24 -> 87048 | R24: =IFERROR(Q24/P24,0) -> 14508 | T24: =YEAR(C24) -> 2024 | V24: =INDEX('Detailed P&L'!$3:$3,MATCH($C24,'Detailed P&L'!$9:$9,0)) -> 0 | Y24: =IFERROR(P24/SUMIFS($P$19:$P$78,$T$19:$T$78,T24),"-") -> 0.14285714 | Z24: =Z23+1 -> 6 | AB24: =AB23+1 -> 6 | AC24: =ROUND(AVERAGEIFS($Y$19:$Y$78,$Z$19:$Z$78,AB24),2) -> 0.13
C25: =EOMONTH(C24,1) -> 45504 | D25: =COUNTIFS('Full Events Detail'!$C:$C,$C25) -> 1 | E25: =SUMIFS('Full Events Detail'!$F:$F,'Full Events Detail'!$C:$C,$C25) -> 14000 | F25: =IFERROR(E25/D25,0) -> 14000 | H25: =COUNTIFS('Full Events Detail'!$C:$C,$C25,'Full Events Detail'!$G:$G,">"&0) -> 1 | I25: =SUMIFS('Full Events Detail'!$G:$G,'Full Events Detail'!$C:$C,$C25) -> 5100 | J25: =IFERROR(I25/H25,0) -> 5100 | L25: =COUNTIFS('Full Events Detail'!$C:$C,$C25,'Full Events Detail'!$H:$H,">"&0) -> 1 | M25: =SUMIFS('Full Events Detail'!$H:$H,'Full Events Detail'!$C:$C,$C25) -> 1079.67 | N25: =IFERROR(M25/L25,0) -> 1079.67 | P25: =D25 -> 1 | Q25: =E25+I25+M25 -> 20179.67 | R25: =IFERROR(Q25/P25,0) -> 20179.67 | T25: =YEAR(C25) -> 2024 | V25: =INDEX('Detailed P&L'!$3:$3,MATCH($C25,'Detailed P&L'!$9:$9,0)) -> 0 | Y25: =IFERROR(P25/SUMIFS($P$19:$P$78,$T$19:$T$78,T25),"-") -> 0.023809524 | Z25: =Z24+1 -> 7 | AB25: =AB24+1 -> 7 | AC25: =ROUND(AVERAGEIFS($Y$19:$Y$78,$Z$19:$Z$78,AB25),2) -> 0.05
C26: =EOMONTH(C25,1) -> 45535 | D26: =COUNTIFS('Full Events Detail'!$C:$C,$C26) -> 0 | E26: =SUMIFS('Full Events Detail'!$F:$F,'Full Events Detail'!$C:$C,$C26) -> 0 | F26: =IFERROR(E26/D26,0) -> 0 | H26: =COUNTIFS('Full Events Detail'!$C:$C,$C26,'Full Events Detail'!$G:$G,">"&0) -> 0 | I26: =SUMIFS('Full Events Detail'!$G:$G,'Full Events Detail'!$C:$C,$C26) -> 0 | J26: =IFERROR(I26/H26,0) -> 0 | L26: =COUNTIFS('Full Events Detail'!$C:$C,$C26,'Full Events Detail'!$H:$H,">"&0) -> 0 | M26: =SUMIFS('Full Events Detail'!$H:$H,'Full Events Detail'!$C:$C,$C26) -> 0 | N26: =IFERROR(M26/L26,0) -> 0 | P26: =D26 -> 0 | Q26: =E26+I26+M26 -> 0 | R26: =IFERROR(Q26/P26,0) -> 0 | T26: =YEAR(C26) -> 2024 | V26: =INDEX('Detailed P&L'!$3:$3,MATCH($C26,'Detailed P&L'!$9:$9,0)) -> 0 | Y26: =IFERROR(P26/SUMIFS($P$19:$P$78,$T$19:$T$78,T26),"-") -> 0 | Z26: =Z25+1 -> 8 | AB26: =AB25+1 -> 8 | AC26: =ROUND(AVERAGEIFS($Y$19:$Y$78,$Z$19:$Z$78,AB26),2) -> 0.02
C27: =EOMONTH(C26,1) -> 45565 | D27: =COUNTIFS('Full Events Detail'!$C:$C,$C27) -> 2 | E27: =SUMIFS('Full Events Detail'!$F:$F,'Full Events Detail'!$C:$C,$C27) -> 28000 | F27: =IFERROR(E27/D27,0) -> 14000 | H27: =COUNTIFS('Full Events Detail'!$C:$C,$C27,'Full Events Detail'!$G:$G,">"&0) -> 1 | I27: =SUMIFS('Full Events Detail'!$G:$G,'Full Events Detail'!$C:$C,$C27) -> 2184 | J27: =IFERROR(I27/H27,0) -> 2184 | L27: =COUNTIFS('Full Events Detail'!$C:$C,$C27,'Full Events Detail'!$H:$H,">"&0) -> 1 | M27: =SUMIFS('Full Events Detail'!$H:$H,'Full Events Detail'!$C:$C,$C27) -> 1450 | N27: =IFERROR(M27/L27,0) -> 1450 | P27: =D27 -> 2 | Q27: =E27+I27+M27 -> 31634 | R27: =IFERROR(Q27/P27,0) -> 15817 | T27: =YEAR(C27) -> 2024 | V27: =INDEX('Detailed P&L'!$3:$3,MATCH($C27,'Detailed P&L'!$9:$9,0)) -> 0 | Y27: =IFERROR(P27/SUMIFS($P$19:$P$78,$T$19:$T$78,T27),"-") -> 0.047619048 | Z27: =Z26+1 -> 9 | AB27: =AB26+1 -> 9 | AC27: =ROUND(AVERAGEIFS($Y$19:$Y$78,$Z$19:$Z$78,AB27),2) -> 0.05
C28: =EOMONTH(C27,1) -> 45596 | D28: =COUNTIFS('Full Events Detail'!$C:$C,$C28) -> 6 | E28: =SUMIFS('Full Events Detail'!$F:$F,'Full Events Detail'!$C:$C,$C28) -> 44356 | F28: =IFERROR(E28/D28,0) -> 7392.6667 | H28: =COUNTIFS('Full Events Detail'!$C:$C,$C28,'Full Events Detail'!$G:$G,">"&0) -> 2 | I28: =SUMIFS('Full Events Detail'!$G:$G,'Full Events Detail'!$C:$C,$C28) -> 10376 | J28: =IFERROR(I28/H28,0) -> 5188 | L28: =COUNTIFS('Full Events Detail'!$C:$C,$C28,'Full Events Detail'!$H:$H,">"&0) -> 2 | M28: =SUMIFS('Full Events Detail'!$H:$H,'Full Events Detail'!$C:$C,$C28) -> 2032 | N28: =IFERROR(M28/L28,0) -> 1016 | P28: =D28 -> 6 | Q28: =E28+I28+M28 -> 56764 | R28: =IFERROR(Q28/P28,0) -> 9460.6667 | T28: =YEAR(C28) -> 2024 | V28: =INDEX('Detailed P&L'!$3:$3,MATCH($C28,'Detailed P&L'!$9:$9,0)) -> 0 | Y28: =IFERROR(P28/SUMIFS($P$19:$P$78,$T$19:$T$78,T28),"-") -> 0.14285714 | Z28: =Z27+1 -> 10 | AB28: =AB27+1 -> 10 | AC28: =ROUND(AVERAGEIFS($Y$19:$Y$78,$Z$19:$Z$78,AB28),2) -> 0.12
C29: =EOMONTH(C28,1) -> 45626 | D29: =COUNTIFS('Full Events Detail'!$C:$C,$C29) -> 1 | E29: =SUMIFS('Full Events Detail'!$F:$F,'Full Events Detail'!$C:$C,$C29) -> 600 | F29: =IFERROR(E29/D29,0) -> 600 | H29: =COUNTIFS('Full Events Detail'!$C:$C,$C29,'Full Events Detail'!$G:$G,">"&0) -> 0 | I29: =SUMIFS('Full Events Detail'!$G:$G,'Full Events Detail'!$C:$C,$C29) -> 0 | J29: =IFERROR(I29/H29,0) -> 0 | L29: =COUNTIFS('Full Events Detail'!$C:$C,$C29,'Full Events Detail'!$H:$H,">"&0) -> 0 | M29: =SUMIFS('Full Events Detail'!$H:$H,'Full Events Detail'!$C:$C,$C29) -> 0 | N29: =IFERROR(M29/L29,0) -> 0 | P29: =D29 -> 1 | Q29: =E29+I29+M29 -> 600 | R29: =IFERROR(Q29/P29,0) -> 600 | T29: =YEAR(C29) -> 2024 | V29: =INDEX('Detailed P&L'!$3:$3,MATCH($C29,'Detailed P&L'!$9:$9,0)) -> 0 | Y29: =IFERROR(P29/SUMIFS($P$19:$P$78,$T$19:$T$78,T29),"-") -> 0.023809524 | Z29: =Z28+1 -> 11 | AB29: =AB28+1 -> 11 | AC29: =ROUND(AVERAGEIFS($Y$19:$Y$78,$Z$19:$Z$78,AB29),2) -> 0.05
C30: =EOMONTH(C29,1) -> 45657 | D30: =COUNTIFS('Full Events Detail'!$C:$C,$C30) -> 6 | E30: =SUMIFS('Full Events Detail'!$F:$F,'Full Events Detail'!$C:$C,$C30) -> 9895 | F30: =IFERROR(E30/D30,0) -> 1649.1667 | H30: =COUNTIFS('Full Events Detail'!$C:$C,$C30,'Full Events Detail'!$G:$G,">"&0) -> 0 | I30: =SUMIFS('Full Events Detail'!$G:$G,'Full Events Detail'!$C:$C,$C30) -> 0 | J30: =IFERROR(I30/H30,0) -> 0 | L30: =COUNTIFS('Full Events Detail'!$C:$C,$C30,'Full Events Detail'!$H:$H,">"&0) -> 0 | M30: =SUMIFS('Full Events Detail'!$H:$H,'Full Events Detail'!$C:$C,$C30) -> 0 | N30: =IFERROR(M30/L30,0) -> 0 | P30: =D30 -> 6 | Q30: =E30+I30+M30 -> 9895 | R30: =IFERROR(Q30/P30,0) -> 1649.1667 | T30: =YEAR(C30) -> 2024 | V30: =INDEX('Detailed P&L'!$3:$3,MATCH($C30,'Detailed P&L'!$9:$9,0)) -> 0 | Y30: =IFERROR(P30/SUMIFS($P$19:$P$78,$T$19:$T$78,T30),"-") -> 0.14285714 | Z30: =Z29+1 -> 12 | AB30: =AB29+1 -> 12 | AC30: =ROUND(AVERAGEIFS($Y$19:$Y$78,$Z$19:$Z$78,AB30),2) -> 0.07
C31: =EOMONTH(C30,1) -> 45688 | D31: =COUNTIFS('Full Events Detail'!$C:$C,$C31) -> 0 | E31: =SUMIFS('Full Events Detail'!$F:$F,'Full Events Detail'!$C:$C,$C31) -> 0 | F31: =IFERROR(E31/D31,0) -> 0 | H31: =COUNTIFS('Full Events Detail'!$C:$C,$C31,'Full Events Detail'!$G:$G,">"&0) -> 0 | I31: =SUMIFS('Full Events Detail'!$G:$G,'Full Events Detail'!$C:$C,$C31) -> 0 | J31: =IFERROR(I31/H31,0) -> 0 | L31: =COUNTIFS('Full Events Detail'!$C:$C,$C31,'Full Events Detail'!$H:$H,">"&0) -> 0 | M31: =SUMIFS('Full Events Detail'!$H:$H,'Full Events Detail'!$C:$C,$C31) -> 0 | N31: =IFERROR(M31/L31,0) -> 0 | P31: =D31 -> 0 | Q31: =E31+I31+M31 -> 0 | R31: =IFERROR(Q31/P31,0) -> 0 | T31: =YEAR(C31) -> 2025 | V31: =INDEX('Detailed P&L'!$3:$3,MATCH($C31,'Detailed P&L'!$9:$9,0)) -> 0 | Y31: =IFERROR(P31/SUMIFS($P$19:$P$78,$T$19:$T$78,T31),"-") -> 0 | Z31: =Z19 -> 1
C32: =EOMONTH(C31,1) -> 45716 | D32: =COUNTIFS('Full Events Detail'!$C:$C,$C32) -> 1 | E32: =SUMIFS('Full Events Detail'!$F:$F,'Full Events Detail'!$C:$C,$C32) -> 2415 | F32: =IFERROR(E32/D32,0) -> 2415 | H32: =COUNTIFS('Full Events Detail'!$C:$C,$C32,'Full Events Detail'!$G:$G,">"&0) -> 0 | I32: =SUMIFS('Full Events Detail'!$G:$G,'Full Events Detail'!$C:$C,$C32) -> 0 | J32: =IFERROR(I32/H32,0) -> 0 | L32: =COUNTIFS('Full Events Detail'!$C:$C,$C32,'Full Events Detail'!$H:$H,">"&0) -> 0 | M32: =SUMIFS('Full Events Detail'!$H:$H,'Full Events Detail'!$C:$C,$C32) -> 0 | N32: =IFERROR(M32/L32,0) -> 0 | P32: =D32 -> 1 | Q32: =E32+I32+M32 -> 2415 | R32: =IFERROR(Q32/P32,0) -> 2415 | T32: =YEAR(C32) -> 2025 | V32: =INDEX('Detailed P&L'!$3:$3,MATCH($C32,'Detailed P&L'!$9:$9,0)) -> 0 | Y32: =IFERROR(P32/SUMIFS($P$19:$P$78,$T$19:$T$78,T32),"-") -> 0.023255814 | Z32: =Z20 -> 2
C33: =EOMONTH(C32,1) -> 45747 | D33: =COUNTIFS('Full Events Detail'!$C:$C,$C33) -> 6 | E33: =SUMIFS('Full Events Detail'!$F:$F,'Full Events Detail'!$C:$C,$C33) -> 26850 | F33: =IFERROR(E33/D33,0) -> 4475 | H33: =COUNTIFS('Full Events Detail'!$C:$C,$C33,'Full Events Detail'!$G:$G,">"&0) -> 1 | I33: =SUMIFS('Full Events Detail'!$G:$G,'Full Events Detail'!$C:$C,$C33) -> 5000 | J33: =IFERROR(I33/H33,0) -> 5000 | L33: =COUNTIFS('Full Events Detail'!$C:$C,$C33,'Full Events Detail'!$H:$H,">"&0) -> 0 | M33: =SUMIFS('Full Events Detail'!$H:$H,'Full Events Detail'!$C:$C,$C33) -> 0 | N33: =IFERROR(M33/L33,0) -> 0 | P33: =D33 -> 6 | Q33: =E33+I33+M33 -> 31850 | R33: =IFERROR(Q33/P33,0) -> 5308.3333 | T33: =YEAR(C33) -> 2025 | V33: =INDEX('Detailed P&L'!$3:$3,MATCH($C33,'Detailed P&L'!$9:$9,0)) -> 0 | Y33: =IFERROR(P33/SUMIFS($P$19:$P$78,$T$19:$T$78,T33),"-") -> 0.13953488 | Z33: =Z21 -> 3
C34: =EOMONTH(C33,1) -> 45777 | D34: =COUNTIFS('Full Events Detail'!$C:$C,$C34) -> 5 | E34: =SUMIFS('Full Events Detail'!$F:$F,'Full Events Detail'!$C:$C,$C34) -> 56200 | F34: =IFERROR(E34/D34,0) -> 11240 | H34: =COUNTIFS('Full Events Detail'!$C:$C,$C34,'Full Events Detail'!$G:$G,">"&0) -> 3 | I34: =SUMIFS('Full Events Detail'!$G:$G,'Full Events Detail'!$C:$C,$C34) -> 16100 | J34: =IFERROR(I34/H34,0) -> 5366.6667 | L34: =COUNTIFS('Full Events Detail'!$C:$C,$C34,'Full Events Detail'!$H:$H,">"&0) -> 1 | M34: =SUMIFS('Full Events Detail'!$H:$H,'Full Events Detail'!$C:$C,$C34) -> 1248 | N34: =IFERROR(M34/L34,0) -> 1248 | P34: =D34 -> 5 | Q34: =E34+I34+M34 -> 73548 | R34: =IFERROR(Q34/P34,0) -> 14709.6 | T34: =YEAR(C34) -> 2025 | V34: =INDEX('Detailed P&L'!$3:$3,MATCH($C34,'Detailed P&L'!$9:$9,0)) -> 0 | Y34: =IFERROR(P34/SUMIFS($P$19:$P$78,$T$19:$T$78,T34),"-") -> 0.11627907 | Z34: =Z22 -> 4
C35: =EOMONTH(C34,1) -> 45808 | D35: =COUNTIFS('Full Events Detail'!$C:$C,$C35) -> 12 | E35: =SUMIFS('Full Events Detail'!$F:$F,'Full Events Detail'!$C:$C,$C35) -> 86466 | F35: =IFERROR(E35/D35,0) -> 7205.5 | H35: =COUNTIFS('Full Events Detail'!$C:$C,$C35,'Full Events Detail'!$G:$G,">"&0) -> 3 | I35: =SUMIFS('Full Events Detail'!$G:$G,'Full Events Detail'!$C:$C,$C35) -> 22350 | J35: =IFERROR(I35/H35,0) -> 7450 | L35: =COUNTIFS('Full Events Detail'!$C:$C,$C35,'Full Events Detail'!$H:$H,">"&0) -> 3 | M35: =SUMIFS('Full Events Detail'!$H:$H,'Full Events Detail'!$C:$C,$C35) -> 4412.01 | N35: =IFERROR(M35/L35,0) -> 1470.67 | P35: =D35 -> 12 | Q35: =E35+I35+M35 -> 113228.01 | R35: =IFERROR(Q35/P35,0) -> 9435.6675 | T35: =YEAR(C35) -> 2025 | V35: =INDEX('Detailed P&L'!$3:$3,MATCH($C35,'Detailed P&L'!$9:$9,0)) -> 0 | Y35: =IFERROR(P35/SUMIFS($P$19:$P$78,$T$19:$T$78,T35),"-") -> 0.27906977 | Z35: =Z23 -> 5
C36: =EOMONTH(C35,1) -> 45838 | D36: =COUNTIFS('Full Events Detail'!$C:$C,$C36) -> 5 | E36: =SUMIFS('Full Events Detail'!$F:$F,'Full Events Detail'!$C:$C,$C36) -> 72150 | F36: =IFERROR(E36/D36,0) -> 14430 | H36: =COUNTIFS('Full Events Detail'!$C:$C,$C36,'Full Events Detail'!$G:$G,">"&0) -> 3 | I36: =SUMIFS('Full Events Detail'!$G:$G,'Full Events Detail'!$C:$C,$C36) -> 15050 | J36: =IFERROR(I36/H36,0) -> 5016.6667 | L36: =COUNTIFS('Full Events Detail'!$C:$C,$C36,'Full Events Detail'!$H:$H,">"&0) -> 1 | M36: =SUMIFS('Full Events Detail'!$H:$H,'Full Events Detail'!$C:$C,$C36) -> 3114 | N36: =IFERROR(M36/L36,0) -> 3114 | P36: =D36 -> 5 | Q36: =E36+I36+M36 -> 90314 | R36: =IFERROR(Q36/P36,0) -> 18062.8 | T36: =YEAR(C36) -> 2025 | V36: =INDEX('Detailed P&L'!$3:$3,MATCH($C36,'Detailed P&L'!$9:$9,0)) -> 0 | Y36: =IFERROR(P36/SUMIFS($P$19:$P$78,$T$19:$T$78,T36),"-") -> 0.11627907 | Z36: =Z24 -> 6
C37: =EOMONTH(C36,1) -> 45869 | D37: =COUNTIFS('Full Events Detail'!$C:$C,$C37) -> 3 | E37: =SUMIFS('Full Events Detail'!$F:$F,'Full Events Detail'!$C:$C,$C37) -> 3800 | F37: =IFERROR(E37/D37,0) -> 1266.6667 | H37: =COUNTIFS('Full Events Detail'!$C:$C,$C37,'Full Events Detail'!$G:$G,">"&0) -> 0 | I37: =SUMIFS('Full Events Detail'!$G:$G,'Full Events Detail'!$C:$C,$C37) -> 0 | J37: =IFERROR(I37/H37,0) -> 0 | L37: =COUNTIFS('Full Events Detail'!$C:$C,$C37,'Full Events Detail'!$H:$H,">"&0) -> 0 | M37: =SUMIFS('Full Events Detail'!$H:$H,'Full Events Detail'!$C:$C,$C37) -> 0 | N37: =IFERROR(M37/L37,0) -> 0 | P37: =D37 -> 3 | Q37: =E37+I37+M37 -> 3800 | R37: =IFERROR(Q37/P37,0) -> 1266.6667 | T37: =YEAR(C37) -> 2025 | V37: =INDEX('Detailed P&L'!$3:$3,MATCH($C37,'Detailed P&L'!$9:$9,0)) -> 0 | Y37: =IFERROR(P37/SUMIFS($P$19:$P$78,$T$19:$T$78,T37),"-") -> 0.069767442 | Z37: =Z25 -> 7
C38: =EOMONTH(C37,1) -> 45900 | D38: =COUNTIFS('Full Events Detail'!$C:$C,$C38) -> 2 | E38: =SUMIFS('Full Events Detail'!$F:$F,'Full Events Detail'!$C:$C,$C38) -> 1800 | F38: =IFERROR(E38/D38,0) -> 900 | H38: =COUNTIFS('Full Events Detail'!$C:$C,$C38,'Full Events Detail'!$G:$G,">"&0) -> 0 | I38: =SUMIFS('Full Events Detail'!$G:$G,'Full Events Detail'!$C:$C,$C38) -> 0 | J38: =IFERROR(I38/H38,0) -> 0 | L38: =COUNTIFS('Full Events Detail'!$C:$C,$C38,'Full Events Detail'!$H:$H,">"&0) -> 0 | M38: =SUMIFS('Full Events Detail'!$H:$H,'Full Events Detail'!$C:$C,$C38) -> 0 | N38: =IFERROR(M38/L38,0) -> 0 | P38: =D38 -> 2 | Q38: =E38+I38+M38 -> 1800 | R38: =IFERROR(Q38/P38,0) -> 900 | T38: =YEAR(C38) -> 2025 | U38: LTM 26 | V38: =INDEX('Detailed P&L'!$3:$3,MATCH($C38,'Detailed P&L'!$9:$9,0)) -> LTM | Y38: =IFERROR(P38/SUMIFS($P$19:$P$78,$T$19:$T$78,T38),"-") -> 0.046511628 | Z38: =Z26 -> 8
C39: =EOMONTH(C38,1) -> 45930 | D39: =COUNTIFS('Full Events Detail'!$C:$C,$C39) -> 2 | E39: =SUMIFS('Full Events Detail'!$F:$F,'Full Events Detail'!$C:$C,$C39) -> 2200 | F39: =IFERROR(E39/D39,0) -> 1100 | H39: =COUNTIFS('Full Events Detail'!$C:$C,$C39,'Full Events Detail'!$G:$G,">"&0) -> 0 | I39: =SUMIFS('Full Events Detail'!$G:$G,'Full Events Detail'!$C:$C,$C39) -> 0 | J39: =IFERROR(I39/H39,0) -> 0 | L39: =COUNTIFS('Full Events Detail'!$C:$C,$C39,'Full Events Detail'!$H:$H,">"&0) -> 0 | M39: =SUMIFS('Full Events Detail'!$H:$H,'Full Events Detail'!$C:$C,$C39) -> 0 | N39: =IFERROR(M39/L39,0) -> 0 | P39: =D39 -> 2 | Q39: =E39+I39+M39 -> 2200 | R39: =IFERROR(Q39/P39,0) -> 1100 | T39: =YEAR(C39) -> 2025 | U39: LTM 26 | V39: =INDEX('Detailed P&L'!$3:$3,MATCH($C39,'Detailed P&L'!$9:$9,0)) -> LTM | Y39: =IFERROR(P39/SUMIFS($P$19:$P$78,$T$19:$T$78,T39),"-") -> 0.046511628 | Z39: =Z27 -> 9
C40: =EOMONTH(C39,1) -> 45961 | D40: =COUNTIFS('Full Events Detail'!$C:$C,$C40) -> 4 | E40: =SUMIFS('Full Events Detail'!$F:$F,'Full Events Detail'!$C:$C,$C40) -> 45630 | F40: =IFERROR(E40/D40,0) -> 11407.5 | H40: =COUNTIFS('Full Events Detail'!$C:$C,$C40,'Full Events Detail'!$G:$G,">"&0) -> 2 | I40: =SUMIFS('Full Events Detail'!$G:$G,'Full Events Detail'!$C:$C,$C40) -> 5100 | J40: =IFERROR(I40/H40,0) -> 2550 | L40: =COUNTIFS('Full Events Detail'!$C:$C,$C40,'Full Events Detail'!$H:$H,">"&0) -> 3 | M40: =SUMIFS('Full Events Detail'!$H:$H,'Full Events Detail'!$C:$C,$C40) -> 4516.5 | N40: =IFERROR(M40/L40,0) -> 1505.5 | P40: =D40 -> 4 | Q40: =E40+I40+M40 -> 55246.5 | R40: =IFERROR(Q40/P40,0) -> 13811.625 | T40: =YEAR(C40) -> 2025 | U40: LTM 26 | V40: =INDEX('Detailed P&L'!$3:$3,MATCH($C40,'Detailed P&L'!$9:$9,0)) -> LTM | Y40: =IFERROR(P40/SUMIFS($P$19:$P$78,$T$19:$T$78,T40),"-") -> 0.093023256 | Z40: =Z28 -> 10
C41: =EOMONTH(C40,1) -> 45991 | D41: =COUNTIFS('Full Events Detail'!$C:$C,$C41) -> 3 | E41: =SUMIFS('Full Events Detail'!$F:$F,'Full Events Detail'!$C:$C,$C41) -> 22463.63 | F41: =IFERROR(E41/D41,0) -> 7487.8767 | H41: =COUNTIFS('Full Events Detail'!$C:$C,$C41,'Full Events Detail'!$G:$G,">"&0) -> 1 | I41: =SUMIFS('Full Events Detail'!$G:$G,'Full Events Detail'!$C:$C,$C41) -> 4200 | J41: =IFERROR(I41/H41,0) -> 4200 | L41: =COUNTIFS('Full Events Detail'!$C:$C,$C41,'Full Events Detail'!$H:$H,">"&0) -> 1 | M41: =SUMIFS('Full Events Detail'!$H:$H,'Full Events Detail'!$C:$C,$C41) -> 2000 | N41: =IFERROR(M41/L41,0) -> 2000 | P41: =D41 -> 3 | Q41: =E41+I41+M41 -> 28663.63 | R41: =IFERROR(Q41/P41,0) -> 9554.5433 | T41: =YEAR(C41) -> 2025 | U41: LTM 26 | V41: =INDEX('Detailed P&L'!$3:$3,MATCH($C41,'Detailed P&L'!$9:$9,0)) -> LTM | Y41: =IFERROR(P41/SUMIFS($P$19:$P$78,$T$19:$T$78,T41),"-") -> 0.069767442 | Z41: =Z29 -> 11
C42: =EOMONTH(C41,1) -> 46022 | D42: =COUNTIFS('Full Events Detail'!$C:$C,$C42) -> 0 | E42: =SUMIFS('Full Events Detail'!$F:$F,'Full Events Detail'!$C:$C,$C42) -> 0 | F42: =IFERROR(E42/D42,0) -> 0 | H42: =COUNTIFS('Full Events Detail'!$C:$C,$C42,'Full Events Detail'!$G:$G,">"&0) -> 0 | I42: =SUMIFS('Full Events Detail'!$G:$G,'Full Events Detail'!$C:$C,$C42) -> 0 | J42: =IFERROR(I42/H42,0) -> 0 | L42: =COUNTIFS('Full Events Detail'!$C:$C,$C42,'Full Events Detail'!$H:$H,">"&0) -> 0 | M42: =SUMIFS('Full Events Detail'!$H:$H,'Full Events Detail'!$C:$C,$C42) -> 0 | N42: =IFERROR(M42/L42,0) -> 0 | P42: =D42 -> 0 | Q42: =E42+I42+M42 -> 0 | R42: =IFERROR(Q42/P42,0) -> 0 | T42: =YEAR(C42) -> 2025 | U42: LTM 26 | V42: =INDEX('Detailed P&L'!$3:$3,MATCH($C42,'Detailed P&L'!$9:$9,0)) -> LTM | Y42: =IFERROR(P42/SUMIFS($P$19:$P$78,$T$19:$T$78,T42),"-") -> 0 | Z42: =Z30 -> 12
C43: =EOMONTH(C42,1) -> 46053 | D43: =COUNTIFS('Full Events Detail'!$C:$C,$C43) -> 1 | E43: =SUMIFS('Full Events Detail'!$F:$F,'Full Events Detail'!$C:$C,$C43) -> 16000 | F43: =IFERROR(E43/D43,0) -> 16000 | H43: =COUNTIFS('Full Events Detail'!$C:$C,$C43,'Full Events Detail'!$G:$G,">"&0) -> 1 | I43: =SUMIFS('Full Events Detail'!$G:$G,'Full Events Detail'!$C:$C,$C43) -> 5900 | J43: =IFERROR(I43/H43,0) -> 5900 | L43: =COUNTIFS('Full Events Detail'!$C:$C,$C43,'Full Events Detail'!$H:$H,">"&0) -> 0 | M43: =SUMIFS('Full Events Detail'!$H:$H,'Full Events Detail'!$C:$C,$C43) -> 0 | N43: =IFERROR(M43/L43,0) -> 0 | P43: =D43 -> 1 | Q43: =E43+I43+M43 -> 21900 | R43: =IFERROR(Q43/P43,0) -> 21900 | T43: =YEAR(C43) -> 2026 | U43: LTM 26 | V43: =INDEX('Detailed P&L'!$3:$3,MATCH($C43,'Detailed P&L'!$9:$9,0)) -> LTM
C44: =EOMONTH(C43,1) -> 46081 | D44: =COUNTIFS('Full Events Detail'!$C:$C,$C44) -> 1 | E44: =SUMIFS('Full Events Detail'!$F:$F,'Full Events Detail'!$C:$C,$C44) -> 600 | F44: =IFERROR(E44/D44,0) -> 600 | H44: =COUNTIFS('Full Events Detail'!$C:$C,$C44,'Full Events Detail'!$G:$G,">"&0) -> 0 | I44: =SUMIFS('Full Events Detail'!$G:$G,'Full Events Detail'!$C:$C,$C44) -> 0 | J44: =IFERROR(I44/H44,0) -> 0 | L44: =COUNTIFS('Full Events Detail'!$C:$C,$C44,'Full Events Detail'!$H:$H,">"&0) -> 0 | M44: =SUMIFS('Full Events Detail'!$H:$H,'Full Events Detail'!$C:$C,$C44) -> 0 | N44: =IFERROR(M44/L44,0) -> 0 | P44: =D44 -> 1 | Q44: =E44+I44+M44 -> 600 | R44: =IFERROR(Q44/P44,0) -> 600 | T44: =YEAR(C44) -> 2026 | U44: LTM 26 | V44: =INDEX('Detailed P&L'!$3:$3,MATCH($C44,'Detailed P&L'!$9:$9,0)) -> LTM
C45: =EOMONTH(C44,1) -> 46112 | D45: =COUNTIFS('Full Events Detail'!$C:$C,$C45) -> 4 | E45: =SUMIFS('Full Events Detail'!$F:$F,'Full Events Detail'!$C:$C,$C45) -> 55700 | F45: =IFERROR(E45/D45,0) -> 13925 | H45: =COUNTIFS('Full Events Detail'!$C:$C,$C45,'Full Events Detail'!$G:$G,">"&0) -> 1 | I45: =SUMIFS('Full Events Detail'!$G:$G,'Full Events Detail'!$C:$C,$C45) -> 4100 | J45: =IFERROR(I45/H45,0) -> 4100 | L45: =COUNTIFS('Full Events Detail'!$C:$C,$C45,'Full Events Detail'!$H:$H,">"&0) -> 1 | M45: =SUMIFS('Full Events Detail'!$H:$H,'Full Events Detail'!$C:$C,$C45) -> 1700 | N45: =IFERROR(M45/L45,0) -> 1700 | P45: =D45 -> 4 | Q45: =E45+I45+M45 -> 61500 | R45: =IFERROR(Q45/P45,0) -> 15375 | T45: =YEAR(C45) -> 2026 | U45: LTM 26 | V45: =INDEX('Detailed P&L'!$3:$3,MATCH($C45,'Detailed P&L'!$9:$9,0)) -> LTM
C46: =EOMONTH(C45,1) -> 46142 | D46: =COUNTIFS('Full Events Detail'!$C:$C,$C46) -> 5 | E46: =SUMIFS('Full Events Detail'!$F:$F,'Full Events Detail'!$C:$C,$C46) -> 78000 | F46: =IFERROR(E46/D46,0) -> 15600 | H46: =COUNTIFS('Full Events Detail'!$C:$C,$C46,'Full Events Detail'!$G:$G,">"&0) -> 2 | I46: =SUMIFS('Full Events Detail'!$G:$G,'Full Events Detail'!$C:$C,$C46) -> 10900 | J46: =IFERROR(I46/H46,0) -> 5450 | L46: =COUNTIFS('Full Events Detail'!$C:$C,$C46,'Full Events Detail'!$H:$H,">"&0) -> 3 | M46: =SUMIFS('Full Events Detail'!$H:$H,'Full Events Detail'!$C:$C,$C46) -> 4400 | N46: =IFERROR(M46/L46,0) -> 1466.6667 | P46: =D46 -> 5 | Q46: =E46+I46+M46 -> 93300 | R46: =IFERROR(Q46/P46,0) -> 18660 | T46: =YEAR(C46) -> 2026 | U46: LTM 26 | V46: =INDEX('Detailed P&L'!$3:$3,MATCH($C46,'Detailed P&L'!$9:$9,0)) -> LTM
C47: =EOMONTH(C46,1) -> 46173 | D47: =COUNTIFS('Full Events Detail'!$C:$C,$C47) -> 9 | E47: =SUMIFS('Full Events Detail'!$F:$F,'Full Events Detail'!$C:$C,$C47) -> 107100 | F47: =IFERROR(E47/D47,0) -> 11900 | H47: =COUNTIFS('Full Events Detail'!$C:$C,$C47,'Full Events Detail'!$G:$G,">"&0) -> 4 | I47: =SUMIFS('Full Events Detail'!$G:$G,'Full Events Detail'!$C:$C,$C47) -> 18500 | J47: =IFERROR(I47/H47,0) -> 4625 | L47: =COUNTIFS('Full Events Detail'!$C:$C,$C47,'Full Events Detail'!$H:$H,">"&0) -> 5 | M47: =SUMIFS('Full Events Detail'!$H:$H,'Full Events Detail'!$C:$C,$C47) -> 7000 | N47: =IFERROR(M47/L47,0) -> 1400 | P47: =D47 -> 9 | Q47: =E47+I47+M47 -> 132600 | R47: =IFERROR(Q47/P47,0) -> 14733.333 | T47: =YEAR(C47) -> 2026 | U47: LTM 26 | V47: =INDEX('Detailed P&L'!$3:$3,MATCH($C47,'Detailed P&L'!$9:$9,0)) -> LTM
C48: =EOMONTH(C47,1) -> 46203 | D48: =COUNTIFS('Full Events Detail'!$C:$C,$C48) -> 6 | E48: =SUMIFS('Full Events Detail'!$F:$F,'Full Events Detail'!$C:$C,$C48) -> 105150 | F48: =IFERROR(E48/D48,0) -> 17525 | H48: =COUNTIFS('Full Events Detail'!$C:$C,$C48,'Full Events Detail'!$G:$G,">"&0) -> 3 | I48: =SUMIFS('Full Events Detail'!$G:$G,'Full Events Detail'!$C:$C,$C48) -> 15900 | J48: =IFERROR(I48/H48,0) -> 5300 | L48: =COUNTIFS('Full Events Detail'!$C:$C,$C48,'Full Events Detail'!$H:$H,">"&0) -> 4 | M48: =SUMIFS('Full Events Detail'!$H:$H,'Full Events Detail'!$C:$C,$C48) -> 3750 | N48: =IFERROR(M48/L48,0) -> 937.5 | P48: =D48 -> 6 | Q48: =E48+I48+M48 -> 124800 | R48: =IFERROR(Q48/P48,0) -> 20800 | T48: =YEAR(C48) -> 2026 | U48: LTM 26 | V48: =INDEX('Detailed P&L'!$3:$3,MATCH($C48,'Detailed P&L'!$9:$9,0)) -> LTM
C49: =EOMONTH(C48,1) -> 46234 | D49: =COUNTIFS('Full Events Detail'!$C:$C,$C49) -> 2 | E49: =SUMIFS('Full Events Detail'!$F:$F,'Full Events Detail'!$C:$C,$C49) -> 18000 | F49: =IFERROR(E49/D49,0) -> 9000 | H49: =COUNTIFS('Full Events Detail'!$C:$C,$C49,'Full Events Detail'!$G:$G,">"&0) -> 1 | I49: =SUMIFS('Full Events Detail'!$G:$G,'Full Events Detail'!$C:$C,$C49) -> 5200 | J49: =IFERROR(I49/H49,0) -> 5200 | L49: =COUNTIFS('Full Events Detail'!$C:$C,$C49,'Full Events Detail'!$H:$H,">"&0) -> 0 | M49: =SUMIFS('Full Events Detail'!$H:$H,'Full Events Detail'!$C:$C,$C49) -> 0 | N49: =IFERROR(M49/L49,0) -> 0 | P49: =D49 -> 2 | Q49: =E49+I49+M49 -> 23200 | R49: =IFERROR(Q49/P49,0) -> 11600 | T49: =YEAR(C49) -> 2026 | U49: LTM 26 | V49: =INDEX('Detailed P&L'!$3:$3,MATCH($C49,'Detailed P&L'!$9:$9,0)) -> LTM
C50: =EOMONTH(C49,1) -> 46265 | D50: =COUNTIFS('Full Events Detail'!$C:$C,$C50) -> 7 | E50: =SUMIFS('Full Events Detail'!$F:$F,'Full Events Detail'!$C:$C,$C50) -> 82700 | F50: =IFERROR(E50/D50,0) -> 11814.286 | H50: =COUNTIFS('Full Events Detail'!$C:$C,$C50,'Full Events Detail'!$G:$G,">"&0) -> 4 | I50: =SUMIFS('Full Events Detail'!$G:$G,'Full Events Detail'!$C:$C,$C50) -> 15800 | J50: =IFERROR(I50/H50,0) -> 3950 | L50: =COUNTIFS('Full Events Detail'!$C:$C,$C50,'Full Events Detail'!$H:$H,">"&0) -> 3 | M50: =SUMIFS('Full Events Detail'!$H:$H,'Full Events Detail'!$C:$C,$C50) -> 1250 | N50: =IFERROR(M50/L50,0) -> 416.66667 | P50: =D50 -> 7 | Q50: =E50+I50+M50 -> 99750 | R50: =IFERROR(Q50/P50,0) -> 14250 | T50: =YEAR(C50) -> 2026 | V50: =INDEX('Detailed P&L'!$3:$3,MATCH($C50,'Detailed P&L'!$9:$9,0)) -> 0
C51: =EOMONTH(C50,1) -> 46295 | D51: =COUNTIFS('Full Events Detail'!$C:$C,$C51) -> 6 | E51: =SUMIFS('Full Events Detail'!$F:$F,'Full Events Detail'!$C:$C,$C51) -> 107000 | F51: =IFERROR(E51/D51,0) -> 17833.333 | H51: =COUNTIFS('Full Events Detail'!$C:$C,$C51,'Full Events Detail'!$G:$G,">"&0) -> 5 | I51: =SUMIFS('Full Events Detail'!$G:$G,'Full Events Detail'!$C:$C,$C51) -> 21700 | J51: =IFERROR(I51/H51,0) -> 4340 | L51: =COUNTIFS('Full Events Detail'!$C:$C,$C51,'Full Events Detail'!$H:$H,">"&0) -> 2 | M51: =SUMIFS('Full Events Detail'!$H:$H,'Full Events Detail'!$C:$C,$C51) -> 3500 | N51: =IFERROR(M51/L51,0) -> 1750 | P51: =D51 -> 6 | Q51: =E51+I51+M51 -> 132200 | R51: =IFERROR(Q51/P51,0) -> 22033.333 | T51: =YEAR(C51) -> 2026 | U51: LTM 27 | V51: =INDEX('Detailed P&L'!$3:$3,MATCH($C51,'Detailed P&L'!$9:$9,0)) -> 1
C52: =EOMONTH(C51,1) -> 46326 | D52: =COUNTIFS('Full Events Detail'!$C:$C,$C52) -> 6 | E52: =SUMIFS('Full Events Detail'!$F:$F,'Full Events Detail'!$C:$C,$C52) -> 105150 | F52: =IFERROR(E52/D52,0) -> 17525 | H52: =COUNTIFS('Full Events Detail'!$C:$C,$C52,'Full Events Detail'!$G:$G,">"&0) -> 5 | I52: =SUMIFS('Full Events Detail'!$G:$G,'Full Events Detail'!$C:$C,$C52) -> 24400 | J52: =IFERROR(I52/H52,0) -> 4880 | L52: =COUNTIFS('Full Events Detail'!$C:$C,$C52,'Full Events Detail'!$H:$H,">"&0) -> 2 | M52: =SUMIFS('Full Events Detail'!$H:$H,'Full Events Detail'!$C:$C,$C52) -> 1450 | N52: =IFERROR(M52/L52,0) -> 725 | P52: =D52 -> 6 | Q52: =E52+I52+M52 -> 131000 | R52: =IFERROR(Q52/P52,0) -> 21833.333 | T52: =YEAR(C52) -> 2026 | U52: LTM 27 | V52: =INDEX('Detailed P&L'!$3:$3,MATCH($C52,'Detailed P&L'!$9:$9,0)) -> 1
C53: =EOMONTH(C52,1) -> 46356 | D53: =COUNTIFS('Full Events Detail'!$C:$C,$C53) -> 2 | E53: =SUMIFS('Full Events Detail'!$F:$F,'Full Events Detail'!$C:$C,$C53) -> 18200 | F53: =IFERROR(E53/D53,0) -> 9100 | H53: =COUNTIFS('Full Events Detail'!$C:$C,$C53,'Full Events Detail'!$G:$G,">"&0) -> 1 | I53: =SUMIFS('Full Events Detail'!$G:$G,'Full Events Detail'!$C:$C,$C53) -> 3600 | J53: =IFERROR(I53/H53,0) -> 3600 | L53: =COUNTIFS('Full Events Detail'!$C:$C,$C53,'Full Events Detail'!$H:$H,">"&0) -> 1 | M53: =SUMIFS('Full Events Detail'!$H:$H,'Full Events Detail'!$C:$C,$C53) -> 1e-06 | N53: =IFERROR(M53/L53,0) -> 1e-06 | P53: =D53 -> 2 | Q53: =E53+I53+M53 -> 21800 | R53: =IFERROR(Q53/P53,0) -> 10900 | T53: =YEAR(C53) -> 2026 | U53: LTM 27 | V53: =INDEX('Detailed P&L'!$3:$3,MATCH($C53,'Detailed P&L'!$9:$9,0)) -> 1
C54: =EOMONTH(C53,1) -> 46387 | D54: =COUNTIFS('Full Events Detail'!$C:$C,$C54) -> 0 | E54: =SUMIFS('Full Events Detail'!$F:$F,'Full Events Detail'!$C:$C,$C54) -> 0 | F54: =IFERROR(E54/D54,0) -> 0 | H54: =COUNTIFS('Full Events Detail'!$C:$C,$C54,'Full Events Detail'!$G:$G,">"&0) -> 0 | I54: =SUMIFS('Full Events Detail'!$G:$G,'Full Events Detail'!$C:$C,$C54) -> 0 | J54: =IFERROR(I54/H54,0) -> 0 | L54: =COUNTIFS('Full Events Detail'!$C:$C,$C54,'Full Events Detail'!$H:$H,">"&0) -> 0 | M54: =SUMIFS('Full Events Detail'!$H:$H,'Full Events Detail'!$C:$C,$C54) -> 0 | N54: =IFERROR(M54/L54,0) -> 0 | P54: =D54 -> 0 | Q54: =E54+I54+M54 -> 0 | R54: =IFERROR(Q54/P54,0) -> 0 | T54: =YEAR(C54) -> 2026 | U54: LTM 27 | V54: =INDEX('Detailed P&L'!$3:$3,MATCH($C54,'Detailed P&L'!$9:$9,0)) -> 1
C55: =EOMONTH(C54,1) -> 46418 | D55: =COUNTIFS('Full Events Detail'!$C:$C,$C55) -> 0 | E55: =SUMIFS('Full Events Detail'!$F:$F,'Full Events Detail'!$C:$C,$C55) -> 0 | F55: =IFERROR(E55/D55,0) -> 0 | H55: =COUNTIFS('Full Events Detail'!$C:$C,$C55,'Full Events Detail'!$G:$G,">"&0) -> 0 | I55: =SUMIFS('Full Events Detail'!$G:$G,'Full Events Detail'!$C:$C,$C55) -> 0 | J55: =IFERROR(I55/H55,0) -> 0 | L55: =COUNTIFS('Full Events Detail'!$C:$C,$C55,'Full Events Detail'!$H:$H,">"&0) -> 0 | M55: =SUMIFS('Full Events Detail'!$H:$H,'Full Events Detail'!$C:$C,$C55) -> 0 | N55: =IFERROR(M55/L55,0) -> 0 | P55: =D55 -> 0 | Q55: =E55+I55+M55 -> 0 | R55: =IFERROR(Q55/P55,0) -> 0 | T55: =YEAR(C55) -> 2027 | U55: LTM 27 | V55: =INDEX('Detailed P&L'!$3:$3,MATCH($C55,'Detailed P&L'!$9:$9,0)) -> 1
C56: =EOMONTH(C55,1) -> 46446 | D56: =COUNTIFS('Full Events Detail'!$C:$C,$C56) -> 0 | E56: =SUMIFS('Full Events Detail'!$F:$F,'Full Events Detail'!$C:$C,$C56) -> 0 | F56: =IFERROR(E56/D56,0) -> 0 | H56: =COUNTIFS('Full Events Detail'!$C:$C,$C56,'Full Events Detail'!$G:$G,">"&0) -> 0 | I56: =SUMIFS('Full Events Detail'!$G:$G,'Full Events Detail'!$C:$C,$C56) -> 0 | J56: =IFERROR(I56/H56,0) -> 0 | L56: =COUNTIFS('Full Events Detail'!$C:$C,$C56,'Full Events Detail'!$H:$H,">"&0) -> 0 | M56: =SUMIFS('Full Events Detail'!$H:$H,'Full Events Detail'!$C:$C,$C56) -> 0 | N56: =IFERROR(M56/L56,0) -> 0 | P56: =D56 -> 0 | Q56: =E56+I56+M56 -> 0 | R56: =IFERROR(Q56/P56,0) -> 0 | T56: =YEAR(C56) -> 2027 | U56: LTM 27 | V56: =INDEX('Detailed P&L'!$3:$3,MATCH($C56,'Detailed P&L'!$9:$9,0)) -> 1
C57: =EOMONTH(C56,1) -> 46477 | D57: =COUNTIFS('Full Events Detail'!$C:$C,$C57) -> 1 | E57: =SUMIFS('Full Events Detail'!$F:$F,'Full Events Detail'!$C:$C,$C57) -> 19500 | F57: =IFERROR(E57/D57,0) -> 19500 | H57: =COUNTIFS('Full Events Detail'!$C:$C,$C57,'Full Events Detail'!$G:$G,">"&0) -> 0 | I57: =SUMIFS('Full Events Detail'!$G:$G,'Full Events Detail'!$C:$C,$C57) -> 0 | J57: =IFERROR(I57/H57,0) -> 0 | L57: =COUNTIFS('Full Events Detail'!$C:$C,$C57,'Full Events Detail'!$H:$H,">"&0) -> 0 | M57: =SUMIFS('Full Events Detail'!$H:$H,'Full Events Detail'!$C:$C,$C57) -> 0 | N57: =IFERROR(M57/L57,0) -> 0 | P57: =D57 -> 1 | Q57: =E57+I57+M57 -> 19500 | R57: =IFERROR(Q57/P57,0) -> 19500 | T57: =YEAR(C57) -> 2027 | U57: LTM 27 | V57: =INDEX('Detailed P&L'!$3:$3,MATCH($C57,'Detailed P&L'!$9:$9,0)) -> 1
C58: =EOMONTH(C57,1) -> 46507 | D58: =COUNTIFS('Full Events Detail'!$C:$C,$C58) -> 2 | E58: =SUMIFS('Full Events Detail'!$F:$F,'Full Events Detail'!$C:$C,$C58) -> 39000 | F58: =IFERROR(E58/D58,0) -> 19500 | H58: =COUNTIFS('Full Events Detail'!$C:$C,$C58,'Full Events Detail'!$G:$G,">"&0) -> 0 | I58: =SUMIFS('Full Events Detail'!$G:$G,'Full Events Detail'!$C:$C,$C58) -> 0 | J58: =IFERROR(I58/H58,0) -> 0 | L58: =COUNTIFS('Full Events Detail'!$C:$C,$C58,'Full Events Detail'!$H:$H,">"&0) -> 0 | M58: =SUMIFS('Full Events Detail'!$H:$H,'Full Events Detail'!$C:$C,$C58) -> 0 | N58: =IFERROR(M58/L58,0) -> 0 | P58: =D58 -> 2 | Q58: =E58+I58+M58 -> 39000 | R58: =IFERROR(Q58/P58,0) -> 19500 | T58: =YEAR(C58) -> 2027 | U58: LTM 27 | V58: =INDEX('Detailed P&L'!$3:$3,MATCH($C58,'Detailed P&L'!$9:$9,0)) -> 1
C59: =EOMONTH(C58,1) -> 46538 | D59: =COUNTIFS('Full Events Detail'!$C:$C,$C59) -> 4 | E59: =SUMIFS('Full Events Detail'!$F:$F,'Full Events Detail'!$C:$C,$C59) -> 107500 | F59: =IFERROR(E59/D59,0) -> 26875 | H59: =COUNTIFS('Full Events Detail'!$C:$C,$C59,'Full Events Detail'!$G:$G,">"&0) -> 0 | I59: =SUMIFS('Full Events Detail'!$G:$G,'Full Events Detail'!$C:$C,$C59) -> 0 | J59: =IFERROR(I59/H59,0) -> 0 | L59: =COUNTIFS('Full Events Detail'!$C:$C,$C59,'Full Events Detail'!$H:$H,">"&0) -> 1 | M59: =SUMIFS('Full Events Detail'!$H:$H,'Full Events Detail'!$C:$C,$C59) -> 1e-06 | N59: =IFERROR(M59/L59,0) -> 1e-06 | P59: =D59 -> 4 | Q59: =E59+I59+M59 -> 107500 | R59: =IFERROR(Q59/P59,0) -> 26875 | T59: =YEAR(C59) -> 2027 | U59: LTM 27 | V59: =INDEX('Detailed P&L'!$3:$3,MATCH($C59,'Detailed P&L'!$9:$9,0)) -> 1
C60: =EOMONTH(C59,1) -> 46568 | D60: =COUNTIFS('Full Events Detail'!$C:$C,$C60) -> 3 | E60: =SUMIFS('Full Events Detail'!$F:$F,'Full Events Detail'!$C:$C,$C60) -> 89000 | F60: =IFERROR(E60/D60,0) -> 29666.667 | H60: =COUNTIFS('Full Events Detail'!$C:$C,$C60,'Full Events Detail'!$G:$G,">"&0) -> 1 | I60: =SUMIFS('Full Events Detail'!$G:$G,'Full Events Detail'!$C:$C,$C60) -> 5200 | J60: =IFERROR(I60/H60,0) -> 5200 | L60: =COUNTIFS('Full Events Detail'!$C:$C,$C60,'Full Events Detail'!$H:$H,">"&0) -> 2 | M60: =SUMIFS('Full Events Detail'!$H:$H,'Full Events Detail'!$C:$C,$C60) -> 1200 | N60: =IFERROR(M60/L60,0) -> 600 | P60: =D60 -> 3 | Q60: =E60+I60+M60 -> 95400 | R60: =IFERROR(Q60/P60,0) -> 31800 | T60: =YEAR(C60) -> 2027 | U60: LTM 27 | V60: =INDEX('Detailed P&L'!$3:$3,MATCH($C60,'Detailed P&L'!$9:$9,0)) -> 1
C61: =EOMONTH(C60,1) -> 46599 | D61: =COUNTIFS('Full Events Detail'!$C:$C,$C61) -> 0 | E61: =SUMIFS('Full Events Detail'!$F:$F,'Full Events Detail'!$C:$C,$C61) -> 0 | F61: =IFERROR(E61/D61,0) -> 0 | H61: =COUNTIFS('Full Events Detail'!$C:$C,$C61,'Full Events Detail'!$G:$G,">"&0) -> 0 | I61: =SUMIFS('Full Events Detail'!$G:$G,'Full Events Detail'!$C:$C,$C61) -> 0 | J61: =IFERROR(I61/H61,0) -> 0 | L61: =COUNTIFS('Full Events Detail'!$C:$C,$C61,'Full Events Detail'!$H:$H,">"&0) -> 0 | M61: =SUMIFS('Full Events Detail'!$H:$H,'Full Events Detail'!$C:$C,$C61) -> 0 | N61: =IFERROR(M61/L61,0) -> 0 | P61: =D61 -> 0 | Q61: =E61+I61+M61 -> 0 | R61: =IFERROR(Q61/P61,0) -> 0 | T61: =YEAR(C61) -> 2027 | U61: LTM 27 | V61: =INDEX('Detailed P&L'!$3:$3,MATCH($C61,'Detailed P&L'!$9:$9,0)) -> 1
C62: =EOMONTH(C61,1) -> 46630 | D62: =COUNTIFS('Full Events Detail'!$C:$C,$C62) -> 0 | E62: =SUMIFS('Full Events Detail'!$F:$F,'Full Events Detail'!$C:$C,$C62) -> 0 | F62: =IFERROR(E62/D62,0) -> 0 | H62: =COUNTIFS('Full Events Detail'!$C:$C,$C62,'Full Events Detail'!$G:$G,">"&0) -> 0 | I62: =SUMIFS('Full Events Detail'!$G:$G,'Full Events Detail'!$C:$C,$C62) -> 0 | J62: =IFERROR(I62/H62,0) -> 0 | L62: =COUNTIFS('Full Events Detail'!$C:$C,$C62,'Full Events Detail'!$H:$H,">"&0) -> 0 | M62: =SUMIFS('Full Events Detail'!$H:$H,'Full Events Detail'!$C:$C,$C62) -> 0 | N62: =IFERROR(M62/L62,0) -> 0 | P62: =D62 -> 0 | Q62: =E62+I62+M62 -> 0 | R62: =IFERROR(Q62/P62,0) -> 0 | T62: =YEAR(C62) -> 2027 | U62: LTM 27 | V62: =INDEX('Detailed P&L'!$3:$3,MATCH($C62,'Detailed P&L'!$9:$9,0)) -> 1
... C86: =EOMONTH(C85,1) -> 47361 | D86: =COUNTIFS('Full Events Detail'!$C:$C,$C86) -> 0 | E86: =SUMIFS('Full Events Detail'!$F:$F,'Full Events Detail'!$C:$C,$C86) -> 0 | F86: =IFERROR(E86/D86,0) -> 0 | H86: =COUNTIFS('Full Events Detail'!$C:$C,$C86,'Full Events Detail'!$G:$G,">"&0) -> 0 | I86: =SUMIFS('Full Events Detail'!$G:$G,'Full Events Detail'!$C:$C,$C86) -> 0 | J86: =IFERROR(I86/H86,0) -> 0 | L86: =COUNTIFS('Full Events Detail'!$C:$C,$C86,'Full Events Detail'!$H:$H,">"&0) -> 0 | M86: =SUMIFS('Full Events Detail'!$H:$H,'Full Events Detail'!$C:$C,$C86) -> 0 | N86: =IFERROR(M86/L86,0) -> 0 | P86: =D86 -> 0 | Q86: =E86+I86+M86 -> 0 | R86: =IFERROR(Q86/P86,0) -> 0 | T86: =YEAR(C86) -> 2029 | U86: LTM 29 | V86: =INDEX('Detailed P&L'!$3:$3,MATCH($C86,'Detailed P&L'!$9:$9,0)) -> 3

Sheet Inputs-->

Sheet Payroll
C3: =Summary!$C$3 -> Hadden Estate
C4: Payroll
C6: Person | D6: Category | E6: Annual $ | F6: $ / Hour | G6: Weekly Hr
C7: Danielle | D7: Planner | E7: 85000
C8: Yami | D8: Coordinator | E8: =F8*G8*52 -> 60840 | F8: 39 | G8: 30 | H8: <- 39hr * 52 weeks
C9: Josh | D9: Maintenance | E9: =F9*G9*12 -> 2760 | F9: 23 | G9: 10 | H9: <- 20 hrs * through end of November
C10: Adi | D10: Maintenance | E10: 75000
C11: Kathy | D11: Sales | E11: 75000

Sheet P&L
B1: Damn Good Dawg Farms
B2: Profit and Loss by Month
B3: January 1, 2024-August 5, 2026
C5: Jan 2024 | D5: Feb 2024 | E5: Mar 2024 | F5: Apr 2024 | G5: May 2024 | H5: Jun 2024 | I5: Jul 2024 | J5: Aug 2024 | K5: Sep 2024 | L5: Oct 2024 | M5: Nov 2024 | N5: Dec 2024 | O5: Jan 2025 | P5: Feb 2025 | Q5: Mar 2025 | R5: Apr 2025 | S5: May 2025 | T5: Jun 2025 | U5: Jul 2025 | V5: Aug 2025 | W5: Sep 2025 | X5: Oct 2025 | Y5: Nov 2025 | Z5: Dec 2025 | AA5: Jan 2026 | AB5: Feb 2026 | AC5: Mar 2026 | AD5: Apr 2026 | AE5: May 2026 | AF5: Jun 2026 | AG5: Jul 2026 | AH5: Aug 1-5 2026 | AI5: Total | AK5: 2024 | AL5: 2025 | AM5: LTM Jul-26
B6: Income
